Workbook

Sheet Deal_Master_Wide
A1: AUDIT & ELIGIBILITY | O1: DEAL CHARACTERISTICS | AJ1: FIRM, CLASSIFICATION & SOURCE STATUS | BI1: EVENT-YEAR MAP | BP1: FINANCIAL DATA — ENTER VALUES IN REPORTED CURRENCY, MILLIONS | EA1: PATENT DATA — UNIQUE FAMILIES / CITATION-WEIGHTED OUTPUT | EO1: PATENT MODERATORS | EU1: DERIVED DiD CHECKS
A2: Deal_ID | B2: Source_Row | C2: Initial_Group | D2: Initial_Treatment_Indicator | E2: Source_File | F2: Cross_File_Key | G2: Overlap_Flag | H2: Duplicate_Flag | I2: Multiple_Deal_Acquirer | J2: Acquirer_Deal_Count_in_File | K2: Manual_Review_Status | L2: Initial_Control_Transfer_Status | M2: Main_DiD_Decision | N2: Exclusion_Reason | O2: Announced_Date | P2: Completion_Date | Q2: Completion_Year | R2: Completion_Quarter | S2: Deal_Status | T2: Deal_Headline | U2: Deal_Type_Level_1 | V2: Deal_Subtype_Level_2 | W2: Deal_Subtype_Level_3 | X2: Deal_Country_s | Y2: Deal_Subcategory | Z2: Financial_Advisors | AA2: Legal_Advisors | AB2: Acquirer_Raw | AC2: Acquirer_Normalized | AD2: Target_Raw | AE2: Target_Normalized | AF2: Deal_Value_USD_m | AG2: Deal_Value_Raw | AH2: Description | AI2: Deal_Rationale | AJ2: Acquirer_Country | AK2: Target_Country | AL2: Cross_Border_Flag | AM2: Acquirer_Listed | AN2: Bloomberg_Ticker | AO2: ISIN | AP2: LEI | AQ2: Acquirer_Parent_Mapping | AR2: Target_Parent_Mapping | AS2: Patent_Search_Acquirer_Names | AT2: Patent_Search_Target_Names | AU2: Final_Classification | AV2: Classification_Confidence | AW2: Patent_Evidence | AX2: Pipeline_Evidence | AY2: Platform_Evidence | AZ2: R_and_D_Evidence | BA2: Commercial_or_Geographic_Evidence | BB2: Mixed_Motive_Flag | BC2: Classification_Notes | BD2: Deal_Validation_Source_URL | BE2: Financial_Currency | BF2: Financial_Data_Status | BG2: Patent_Data_Status | BH2: Patent_Entity_Scope | BI2: Calendar_Year_t-3 | BJ2: Calendar_Year_t-2 | BK2: Calendar_Year_t-1 | BL2: Calendar_Year_t0 | BM2: Calendar_Year_t+1 | BN2: Calendar_Year_t+2 | BO2: Calendar_Year_t+3 | BP2: Revenue_m_t-3 | BQ2: Revenue_m_t-2 | BR2: Revenue_m_t-1 | BS2: Revenue_m_t0 | BT2: Revenue_m_t+1 | BU2: Revenue_m_t+2 | BV2: Revenue_m_t+3 | BW2: Operating_Income_m_t-3 | BX2: Operating_Income_m_t-2 | BY2: Operating_Income_m_t-1 | BZ2: Operating_Income_m_t0 | CA2: Operating_Income_m_t+1 | CB2: Operating_Income_m_t+2 | CC2: Operating_Income_m_t+3 | CD2: Net_Income_m_t-3 | CE2: Net_Income_m_t-2 | CF2: Net_Income_m_t-1 | CG2: Net_Income_m_t0 | CH2: Net_Income_m_t+1 | CI2: Net_Income_m_t+2 | CJ2: Net_Income_m_t+3 | CK2: Total_Assets_m_t-3 | CL2: Total_Assets_m_t-2 | CM2: Total_Assets_m_t-1 | CN2: Total_Assets_m_t0 | CO2: Total_Assets_m_t+1 | CP2: Total_Assets_m_t+2 | CQ2: Total_Assets_m_t+3 | CR2: Total_Debt_m_t-3 | CS2: Total_Debt_m_t-2 | CT2: Total_Debt_m_t-1 | CU2: Total_Debt_m_t0 | CV2: Total_Debt_m_t+1 | CW2: Total_Debt_m_t+2 | CX2: Total_Debt_m_t+3 | CY2: R_and_D_Expense_m_t-3 | CZ2: R_and_D_Expense_m_t-2 | DA2: R_and_D_Expense_m_t-1 | DB2: R_and_D_Expense_m_t0 | DC2: R_and_D_Expense_m_t+1 | DD2: R_and_D_Expense_m_t+2 | DE2: R_and_D_Expense_m_t+3 | DF2: ROA_pct_t-3 | DG2: ROA_pct_t-2 | DH2: ROA_pct_t-1 | DI2: ROA_pct_t0 | DJ2: ROA_pct_t+1 | DK2: ROA_pct_t+2 | DL2: ROA_pct_t+3 | DM2: Operating_Margin_pct_t-3 | DN2: Operating_Margin_pct_t-2 | DO2: Operating_Margin_pct_t-1 | DP2: Operating_Margin_pct_t0 | DQ2: Operating_Margin_pct_t+1 | DR2: Operating_Margin_pct_t+2 | DS2: Operating_Margin_pct_t+3 | DT2: Leverage_pct_t-3 | DU2: Leverage_pct_t-2 | DV2: Leverage_pct_t-1 | DW2: Leverage_pct_t0 | DX2: Leverage_pct_t+1 | DY2: Leverage_pct_t+2 | DZ2: Leverage_pct_t+3 | EA2: Patent_Family_Count_t-3 | EB2: Patent_Family_Count_t-2 | EC2: Patent_Family_Count_t-1 | ED2: Patent_Family_Count_t0 | EE2: Patent_Family_Count_t+1 | EF2: Patent_Family_Count_t+2 | EG2: Patent_Family_Count_t+3 | EH2: Citation_Weighted_Output_t-3 | EI2: Citation_Weighted_Output_t-2 | EJ2: Citation_Weighted_Output_t-1 | EK2: Citation_Weighted_Output_t0 | EL2: Citation_Weighted_Output_t+1 | EM2: Citation_Weighted_Output_t+2 | EN2: Citation_Weighted_Output_t+3 | EO2: Acquirer_PreDeal_Patent_Stock | EP2: Target_PreDeal_Patent_Stock | EQ2: Relative_Knowledge_Base_Size | ER2: Technological_Relatedness_Cosine | ES2: Inventor_Location_Available | ET2: Cross_Border_Relocation_Testable | EU2: Pre_Avg_ROA | EV2: Post_Avg_ROA | EW2: Delta_ROA | EX2: Pre_Avg_Operating_Margin | EY2: Post_Avg_Operating_Margin | EZ2: Delta_Operating_Margin | FA2: Pre_Avg_Patent_Families | FB2: Post_Avg_Patent_Families | FC2: Delta_Patent_Families | FD2: Pre_Avg_Citation_Weighted | FE2: Post_Avg_Citation_Weighted | FF2: Delta_Citation_Weighted | FG2: Complete_Financial_Window | FH2: Complete_Patent_Window | FI2: Data_Ready_Flag
A3: CTL-0001 | B3: 12 | C3: Candidate alternative-rationale group | D3: 0 | E3: DATA non-innovation deals.xlsx | F3: emmes acquires neox | G3: No | H3: No | I3: No | J3: 1 | K3: Not started | L3: Eligible - 100% | M3: Review | O3: 44195 | P3: 44195 | Q3: 2020 | R3: Q4 2020 | S3: Completed | T3: Emmes Acquires Neox | U3: Mergers & Acquisitions | V3: Acquisition | W3: 100% Acquisition | X3: Czech Republic | Y3: 100% Acquisition | AB3: Emmes Corp | AC3: emmes | AD3: Neox sro | AE3: neox sro | AG3: n/a | AH3: The Emmes Corp, a contract research organization, has acquired Neox sro, a contract research organization. The transaction will allow to expand its biopharma effort and international presence. | AI3: The transaction will allow to expand its biopharma effort and international presence. | AL3: Unknown | AM3: Unknown | AS3: Emmes Corp | AT3: Neox sro | AU3: Not reviewed | AV3: Not assessed | AW3: Unknown | AX3: Unknown | AY3: Unknown | AZ3: Unknown | BA3: Unknown | BB3: Unknown | BF3: Not collected | BG3: Not collected | BH3: Not defined | BI3: =IF($Q3="","",$Q3-3) -> 2017 | BJ3: =IF($Q3="","",$Q3-2) -> 2018 | BK3: =IF($Q3="","",$Q3-1) -> 2019 | BL3: =IF($Q3="","",$Q3+0) -> 2020 | BM3: =IF($Q3="","",$Q3+1) -> 2021 | BN3: =IF($Q3="","",$Q3+2) -> 2022 | BO3: =IF($Q3="","",$Q3+3) -> 2023 | EQ3: =IF(OR($EO3="",$EP3="",$EO3=0),"",$EP3/$EO3) | ES3: Unknown | ET3: Unknown | EU3: =IF(COUNT($DF3,$DG3,$DH3)=0,"",AVERAGE($DF3,$DG3,$DH3)) | EV3: =IF(COUNT($DJ3,$DK3,$DL3)=0,"",AVERAGE($DJ3,$DK3,$DL3)) | EW3: =IF(OR($EU3="",$EV3=""),"",$EV3-$EU3) | EX3: =IF(COUNT($DM3,$DN3,$DO3)=0,"",AVERAGE($DM3,$DN3,$DO3)) | EY3: =IF(COUNT($DQ3,$DR3,$DS3)=0,"",AVERAGE($DQ3,$DR3,$DS3)) | EZ3: =IF(OR($EX3="",$EY3=""),"",$EY3-$EX3) | FA3: =IF(COUNT($EA3,$EB3,$EC3)=0,"",AVERAGE($EA3,$EB3,$EC3)) | FB3: =IF(COUNT($EE3,$EF3,$EG3)=0,"",AVERAGE($EE3,$EF3,$EG3)) | FC3: =IF(OR($FA3="",$FB3=""),"",$FB3-$FA3) | FD3: =IF(COUNT($EH3,$EI3,$EJ3)=0,"",AVERAGE($EH3,$EI3,$EJ3)) | FE3: =IF(COUNT($EL3,$EM3,$EN3)=0,"",AVERAGE($EL3,$EM3,$EN3)) | FF3: =IF(OR($FD3="",$FE3=""),"",$FE3-$FD3) | FG3: =IF(COUNT($DF3,$DG3,$DH3,$DJ3,$DK3,$DL3,$DM3,$DN3,$DO3,$DQ3,$DR3,$DS3)=12,"Yes","No") -> No | FH3: =IF(COUNT($EA3,$EB3,$EC3,$EE3,$EF3,$EG3,$EH3,$EI3,$EJ3,$EL3,$EM3,$EN3)=12,"Yes","No") -> No | FI3: =IF(AND($M3="Include",OR($FG3="Yes",$FH3="Yes")),"Ready","Not ready") -> Not ready
A4: CTL-0002 | B4: 13 | C4: Candidate alternative-rationale group | D4: 0 | E4: DATA non-innovation deals.xlsx | F4: veraxa biotech acquires araxa biosciences and velabs therapeutics | G4: No | H4: No | I4: No | J4: 1 | K4: Not started | L4: Eligible - 100% | M4: Review | O4: 44188 | P4: 44188 | Q4: 2020 | R4: Q4 2020 | S4: Completed | T4: Veraxa Biotech Acquires Araxa Biosciences and Velabs Therapeutics | U4: Mergers & Acquisitions | V4: Acquisition | W4: 100% Acquisition | X4: Germany | Y4: 100% Acquisition | AB4: VERAXA Biotech GmbH | AC4: veraxa biotech | AD4: Velabs Therapeutics GmbH (Inactive); Araxa Biosciences GmbH (Inactive) | AE4: velabs therapeutics araxa biosciences | AG4: n/a | AH4: VERAXA Biotech GmbH, a company that identifies and develops functional therapeutic antibodies and antibody-drug conjugates (ADCs) for the bio and pharmaceutical industries, has acquired life science company Araxa Biosciences GmbH and Velabs Therapeutics GmbH from Xlife Sciences. In 2021, Araxa Biosciences GmbH and Velabs Therapeutics GmbH merged to become Veraxa Biotech GmbH, which is fully owned by the Swiss entity Veraxa Biotech AG. Veraxa Biotech AG operates through Veraxa Biotech GmbH. With the acquisition of Araxa Biosciences GmbH and Velabs Therapeutics GmbH (merged into Veraxa GmbH) Veraxa Biotech AG combines two technologies with the goal to solve major challenges in antibody drug development in the fields of screening for functional therapeutic antibodies and aims to develop one of the next generation antibody drug conjugation (antibody-drug conjugates, " ADCs ") technologies to expand its preclinical antibody capacities from early screening to later stage antibody engineering and to sharpen its profile in personalized medicine and precision oncology. | AI4: The transaction will allow Veraxa Biotech to positioned as a leading provider in the identification and development of functional antibodies and drug conjugates. | AL4: Unknown | AM4: Unknown | AS4: VERAXA Biotech GmbH | AT4: Velabs Therapeutics GmbH (Inactive); Araxa Biosciences GmbH (Inactive) | AU4: Not reviewed | AV4: Not assessed | AW4: Unknown | AX4: Unknown | AY4: Unknown | AZ4: Unknown | BA4: Unknown | BB4: Unknown | BF4: Not collected | BG4: Not collected | BH4: Not defined | BI4: =IF($Q4="","",$Q4-3) -> 2017 | BJ4: =IF($Q4="","",$Q4-2) -> 2018 | BK4: =IF($Q4="","",$Q4-1) -> 2019 | BL4: =IF($Q4="","",$Q4+0) -> 2020 | BM4: =IF($Q4="","",$Q4+1) -> 2021 | BN4: =IF($Q4="","",$Q4+2) -> 2022 | BO4: =IF($Q4="","",$Q4+3) -> 2023 | EQ4: =IF(OR($EO4="",$EP4="",$EO4=0),"",$EP4/$EO4) | ES4: Unknown | ET4: Unknown | EU4: =IF(COUNT($DF4,$DG4,$DH4)=0,"",AVERAGE($DF4,$DG4,$DH4)) | EV4: =IF(COUNT($DJ4,$DK4,$DL4)=0,"",AVERAGE($DJ4,$DK4,$DL4)) | EW4: =IF(OR($EU4="",$EV4=""),"",$EV4-$EU4) | EX4: =IF(COUNT($DM4,$DN4,$DO4)=0,"",AVERAGE($DM4,$DN4,$DO4)) | EY4: =IF(COUNT($DQ4,$DR4,$DS4)=0,"",AVERAGE($DQ4,$DR4,$DS4)) | EZ4: =IF(OR($EX4="",$EY4=""),"",$EY4-$EX4) | FA4: =IF(COUNT($EA4,$EB4,$EC4)=0,"",AVERAGE($EA4,$EB4,$EC4)) | FB4: =IF(COUNT($EE4,$EF4,$EG4)=0,"",AVERAGE($EE4,$EF4,$EG4)) | FC4: =IF(OR($FA4="",$FB4=""),"",$FB4-$FA4) | FD4: =IF(COUNT($EH4,$EI4,$EJ4)=0,"",AVERAGE($EH4,$EI4,$EJ4)) | FE4: =IF(COUNT($EL4,$EM4,$EN4)=0,"",AVERAGE($EL4,$EM4,$EN4)) | FF4: =IF(OR($FD4="",$FE4=""),"",$FE4-$FD4) | FG4: =IF(COUNT($DF4,$DG4,$DH4,$DJ4,$DK4,$DL4,$DM4,$DN4,$DO4,$DQ4,$DR4,$DS4)=12,"Yes","No") -> No | FH4: =IF(COUNT($EA4,$EB4,$EC4,$EE4,$EF4,$EG4,$EH4,$EI4,$EJ4,$EL4,$EM4,$EN4)=12,"Yes","No") -> No | FI4: =IF(AND($M4="Include",OR($FG4="Yes",$FH4="Yes")),"Ready","Not ready") -> Not ready
A5: CTL-0003 | B5: 14 | C5: Candidate alternative-rationale group | D5: 0 | E5: DATA non-innovation deals.xlsx | F5: link medical research acquires irw consulting | G5: No | H5: No | I5: No | J5: 1 | K5: Not started | L5: Eligible - 100% | M5: Review | O5: 44169 | P5: 44169 | Q5: 2020 | R5: Q4 2020 | S5: Completed | T5: Link Medical Research Acquires IRW Consulting | U5: Mergers & Acquisitions | V5: Acquisition | W5: 100% Acquisition | X5: Sweden | Y5: 100% Acquisition | AB5: Link Medical Research AS | AC5: link medical research | AD5: IRW Consulting AB | AE5: irw consulting ab | AG5: n/a | AH5: Link Medical Research AS, a full-service contract research organization (CRO) providing product development services for the pharmaceutical and medical device industries, has acquired IRW Consulting AB, a clinical research organization. With this acquisition LINK Medical will continue growing and strengthening its position in the Nordics while improving its already strong offerings and increasing its clinical operations capabilities in the region. | AI5: The transaction enables LINK Medical to continue growing and strengthen its position in the Nordics while improving its already strong offerings and increasing its clinical operations capabilities in the region. | AL5: Unknown | AM5: Unknown | AS5: Link Medical Research AS | AT5: IRW Consulting AB | AU5: Not reviewed | AV5: Not assessed | AW5: Unknown | AX5: Unknown | AY5: Unknown | AZ5: Unknown | BA5: Unknown | BB5: Unknown | BF5: Not collected | BG5: Not collected | BH5: Not defined | BI5: =IF($Q5="","",$Q5-3) -> 2017 | BJ5: =IF($Q5="","",$Q5-2) -> 2018 | BK5: =IF($Q5="","",$Q5-1) -> 2019 | BL5: =IF($Q5="","",$Q5+0) -> 2020 | BM5: =IF($Q5="","",$Q5+1) -> 2021 | BN5: =IF($Q5="","",$Q5+2) -> 2022 | BO5: =IF($Q5="","",$Q5+3) -> 2023 | EQ5: =IF(OR($EO5="",$EP5="",$EO5=0),"",$EP5/$EO5) | ES5: Unknown | ET5: Unknown | EU5: =IF(COUNT($DF5,$DG5,$DH5)=0,"",AVERAGE($DF5,$DG5,$DH5)) | EV5: =IF(COUNT($DJ5,$DK5,$DL5)=0,"",AVERAGE($DJ5,$DK5,$DL5)) | EW5: =IF(OR($EU5="",$EV5=""),"",$EV5-$EU5) | EX5: =IF(COUNT($DM5,$DN5,$DO5)=0,"",AVERAGE($DM5,$DN5,$DO5)) | EY5: =IF(COUNT($DQ5,$DR5,$DS5)=0,"",AVERAGE($DQ5,$DR5,$DS5)) | EZ5: =IF(OR($EX5="",$EY5=""),"",$EY5-$EX5) | FA5: =IF(COUNT($EA5,$EB5,$EC5)=0,"",AVERAGE($EA5,$EB5,$EC5)) | FB5: =IF(COUNT($EE5,$EF5,$EG5)=0,"",AVERAGE($EE5,$EF5,$EG5)) | FC5: =IF(OR($FA5="",$FB5=""),"",$FB5-$FA5) | FD5: =IF(COUNT($EH5,$EI5,$EJ5)=0,"",AVERAGE($EH5,$EI5,$EJ5)) | FE5: =IF(COUNT($EL5,$EM5,$EN5)=0,"",AVERAGE($EL5,$EM5,$EN5)) | FF5: =IF(OR($FD5="",$FE5=""),"",$FE5-$FD5) | FG5: =IF(COUNT($DF5,$DG5,$DH5,$DJ5,$DK5,$DL5,$DM5,$DN5,$DO5,$DQ5,$DR5,$DS5)=12,"Yes","No") -> No | FH5: =IF(COUNT($EA5,$EB5,$EC5,$EE5,$EF5,$EG5,$EH5,$EI5,$EJ5,$EL5,$EM5,$EN5)=12,"Yes","No") -> No | FI5: =IF(AND($M5="Include",OR($FG5="Yes",$FH5="Yes")),"Ready","Not ready") -> Not ready
A6: CTL-0004 | B6: 15 | C6: Candidate alternative-rationale group | D6: 0 | E6: DATA non-innovation deals.xlsx | F6: immunicum acquire dcprime | G6: No | H6: No | I6: No | J6: 1 | K6: Not started | L6: Eligible - 100% | M6: Review | O6: 44153 | P6: 44186 | Q6: 2020 | R6: Q4 2020 | S6: Completed | T6: Immunicum Acquire DCprime | U6: Mergers & Acquisitions | V6: Acquisition | W6: 100% Acquisition | X6: The Netherlands | Y6: 100% Acquisition | Z6: Erik Penser Bankaktiebolag , Advokatfirman Cederquist KB , Kempen & Co NV | AA6: Allen Overy Shearman Sterling LLP , Advokatfirman Delphi AB | AB6: Mendus AB | AC6: mendus ab | AD6: DC Prime BV | AE6: dc prime | AG6: n/a | AH6: Immunicum AB, a developer of therapeutic cancer vaccines, has completed the acquisition of the shares in DCprime BV, a clinical stage biotechnology company developing cancer relapse vaccines aimed to reduce tumor recurrence, from Van Herk Investments B.V., a private equity firm. Further, prior to the closing of the transaction, Van Herk will acquire the minority shareholders’ shares in DCprime and such minority shareholders will consequently partly be paid in cash and partly in Immunicum shares. As a result of the Transaction, Van Herk will be the largest shareholder in Immunicum, holding approximately 43% of the total outstanding shares after the transaction. Customary lock-up provisions covering a period of twelve months have been put in place between Immunicum, Van Herk and DCprime minority shareholders receiving issued shares. The purchase price for all outstanding shares in DCprime will be paid through the issuance of 73,909,635 shares (Consideration Shares) in Immunicum, representing a dilution of 44.48% (44% on a fully diluted basis considering outstanding warrants). Based on the closing price of Immunicum’s shares on November 17, 2020, SEK 8.10, the consideration for the capital contributed in-kind corresponds to a total of SEK 598,668,043.50. Through issuance of the Consideration Shares, the number of shares in Immunicum will increase to a total of 166,167,166. The share capital will increase by SEK 3,695,481.75, from SEK 4,612,876.55 to a total of SEK 8,308,358.3. The dilution has been calculated as the number of issued new shares, divided by the total number of shares following the new issue. The issuance of the shares is subject to approval by an Extraordinary General Meeting (EGM) to be held on December 18, 2020. The newly combined company will maintain its corporate headquarters in Stockholm, Sweden and consolidate research, process development and future manufacturing efforts at the location in Leiden, the Netherlands. Immunicum’s shares will continue to trade on the Nasdaq Stockholm. The transaction will allow Immunicum to further build and strengthen its position as a leader in cell-based cancer immunotherapies. Pursuant to the transaction, Erik Manting, Ph.D., currently CEO of DCprime, will join Immunicum’s leadership team as Chief Business Officer and deputy CEO. Jeroen Rovers, MD, Ph.D., currently Chief Medical Officer at DCprime, will have the role of the Managing Director of DCprime in the combination. Erik Penser Bankaktiebolag is acting as financial advisor, Asperion is acting as strategic advisor and Advokatfirman Delphi AB is acting as legal advisor to Immunicum. Kempen & Co is acting as financial advisor, while Advokatfirman Cederquist KB and Allen & Overy LLP are acting as legal advisor to DCprime. Deal History: Announced: On November 11, 2020, Immunicum entered into an agreement to acquire all of the shares in DCprime from Van Herk Investments. | AI6: The transaction will allow Immunicum to further build and strengthen its position as a leader in cell-based cancer immunotherapies. | AL6: Unknown | AM6: Unknown | AS6: Mendus AB | AT6: DC Prime BV | AU6: Not reviewed | AV6: Not assessed | AW6: Unknown | AX6: Unknown | AY6: Unknown | AZ6: Unknown | BA6: Unknown | BB6: Unknown | BF6: Not collected | BG6: Not collected | BH6: Not defined | BI6: =IF($Q6="","",$Q6-3) -> 2017 | BJ6: =IF($Q6="","",$Q6-2) -> 2018 | BK6: =IF($Q6="","",$Q6-1) -> 2019 | BL6: =IF($Q6="","",$Q6+0) -> 2020 | BM6: =IF($Q6="","",$Q6+1) -> 2021 | BN6: =IF($Q6="","",$Q6+2) -> 2022 | BO6: =IF($Q6="","",$Q6+3) -> 2023 | EQ6: =IF(OR($EO6="",$EP6="",$EO6=0),"",$EP6/$EO6) | ES6: Unknown | ET6: Unknown | EU6: =IF(COUNT($DF6,$DG6,$DH6)=0,"",AVERAGE($DF6,$DG6,$DH6)) | EV6: =IF(COUNT($DJ6,$DK6,$DL6)=0,"",AVERAGE($DJ6,$DK6,$DL6)) | EW6: =IF(OR($EU6="",$EV6=""),"",$EV6-$EU6) | EX6: =IF(COUNT($DM6,$DN6,$DO6)=0,"",AVERAGE($DM6,$DN6,$DO6)) | EY6: =IF(COUNT($DQ6,$DR6,$DS6)=0,"",AVERAGE($DQ6,$DR6,$DS6)) | EZ6: =IF(OR($EX6="",$EY6=""),"",$EY6-$EX6) | FA6: =IF(COUNT($EA6,$EB6,$EC6)=0,"",AVERAGE($EA6,$EB6,$EC6)) | FB6: =IF(COUNT($EE6,$EF6,$EG6)=0,"",AVERAGE($EE6,$EF6,$EG6)) | FC6: =IF(OR($FA6="",$FB6=""),"",$FB6-$FA6) | FD6: =IF(COUNT($EH6,$EI6,$EJ6)=0,"",AVERAGE($EH6,$EI6,$EJ6)) | FE6: =IF(COUNT($EL6,$EM6,$EN6)=0,"",AVERAGE($EL6,$EM6,$EN6)) | FF6: =IF(OR($FD6="",$FE6=""),"",$FE6-$FD6) | FG6: =IF(COUNT($DF6,$DG6,$DH6,$DJ6,$DK6,$DL6,$DM6,$DN6,$DO6,$DQ6,$DR6,$DS6)=12,"Yes","No") -> No | FH6: =IF(COUNT($EA6,$EB6,$EC6,$EE6,$EF6,$EG6,$EH6,$EI6,$EJ6,$EL6,$EM6,$EN6)=12,"Yes","No") -> No | FI6: =IF(AND($M6="Include",OR($FG6="Yes",$FH6="Yes")),"Ready","Not ready") -> Not ready
A7: CTL-0005 | B7: 16 | C7: Candidate alternative-rationale group | D7: 0 | E7: DATA non-innovation deals.xlsx | F7: ucb acquires handl therapeutics | G7: No | H7: No | I7: No | J7: 1 | K7: Not started | L7: Eligible - 100% | M7: Review | O7: 44147 | P7: 44147 | Q7: 2020 | R7: Q4 2020 | S7: Completed | T7: UCB Acquires Handl Therapeutics | U7: Mergers & Acquisitions | V7: Acquisition | W7: 100% Acquisition | X7: Belgium | Y7: 100% Acquisition | AB7: UCB SA | AC7: ucb | AD7: Handl Therapeutics | AE7: handl therapeutics | AG7: n/a | AH7: UCB SA, a biopharmaceutical company, has acquired Handl Therapeutics BV, a gene therapy company. The Handl Therapeutics team will continue to be based in Leuven, Belgium, and will work very closely with UCB’s international research teams. The transaction will allow UCB to accelerate its ambition in gene therapy and strengthens its capabilities to discover and develop differentiated solutions with unique outcomes for patients. Concurrently, UCB has announced a new gene therapy research collaboration with Lacerta Therapeutics. | AI7: The transaction will allow UCB to accelerate its ambition in gene therapy and strengthens its capabilities to discover and develop differentiated solutions with unique outcomes for patients. | AL7: Unknown | AM7: Unknown | AN7: UCB BB | AS7: UCB SA | AT7: Handl Therapeutics | AU7: Not reviewed | AV7: Not assessed | AW7: Unknown | AX7: Unknown | AY7: Unknown | AZ7: Unknown | BA7: Unknown | BB7: Unknown | BE7: EUR | BF7: Complete | BG7: Complete event window — 7/7 years covered | BH7: Applicant/owner alias match for UCB Biopharma and UCB Pharma entities. | BI7: =IF($Q7="","",$Q7-3) -> 2017 | BJ7: =IF($Q7="","",$Q7-2) -> 2018 | BK7: =IF($Q7="","",$Q7-1) -> 2019 | BL7: =IF($Q7="","",$Q7+0) -> 2020 | BM7: =IF($Q7="","",$Q7+1) -> 2021 | BN7: =IF($Q7="","",$Q7+2) -> 2022 | BO7: =IF($Q7="","",$Q7+3) -> 2023 | BP7: 4530 | BQ7: 4632 | BR7: 4913 | BS7: 5347 | BT7: 5777 | BU7: 5517 | BV7: 5252 | BW7: 1130 | BX7: 1105 | BY7: 1118 | BZ7: 1093 | CA7: 1318 | CB7: 679 | CC7: 659 | CD7: 753 | CE7: 800 | CF7: 792 | CG7: 732 | CH7: 1058 | CI7: 418 | CJ7: 343 | CK7: 9917 | CL7: 10514 | CM7: 11081 | CN7: 13319 | CO7: 14210 | CP7: 15868 | CQ7: 15539 | CR7: 1630 | CS7: 1531 | CT7: 1282 | CU7: 2750 | CV7: 2141 | CW7: 3000 | CX7: 3102 | CY7: 1057 | CZ7: 1161 | DA7: 1272 | DB7: 1569 | DC7: 1629 | DD7: 1670 | DE7: 1630 | DF7: 7.4817 | DG7: 7.8312 | DH7: 7.335 | DI7: 6 | DJ7: 7.6864 | DK7: 2.7794 | DL7: 2.1842 | DM7: 24.9448 | DN7: 23.8558 | DO7: 22.756 | DP7: 20.4414 | DQ7: 22.8146 | DR7: 12.3074 | DS7: 12.5476 | DT7: 16.4364 | DU7: 14.5615 | DV7: 11.5694 | DW7: 20.6472 | DX7: 15.0669 | DY7: 18.906 | DZ7: 19.9627 | EA7: 27 | EB7: 15 | EC7: 18 | ED7: 25 | EE7: 17 | EF7: 5 | EG7: 0 | EH7: 107 | EI7: 5 | EJ7: 26 | EK7: 7 | EL7: 2 | EM7: 0 | EN7: 0 | EQ7: =IF(OR($EO7="",$EP7="",$EO7=0),"",$EP7/$EO7) | ES7: Unknown | ET7: Unknown | EU7: =IF(COUNT($DF7,$DG7,$DH7)=0,"",AVERAGE($DF7,$DG7,$DH7)) -> 7.5493 | EV7: =IF(COUNT($DJ7,$DK7,$DL7)=0,"",AVERAGE($DJ7,$DK7,$DL7)) -> 4.2166667 | EW7: =IF(OR($EU7="",$EV7=""),"",$EV7-$EU7) -> -3.3326333 | EX7: =IF(COUNT($DM7,$DN7,$DO7)=0,"",AVERAGE($DM7,$DN7,$DO7)) -> 23.8522 | EY7: =IF(COUNT($DQ7,$DR7,$DS7)=0,"",AVERAGE($DQ7,$DR7,$DS7)) -> 15.889867 | EZ7: =IF(OR($EX7="",$EY7=""),"",$EY7-$EX7) -> -7.9623333 | FA7: =IF(COUNT($EA7,$EB7,$EC7)=0,"",AVERAGE($EA7,$EB7,$EC7)) -> 20 | FB7: =IF(COUNT($EE7,$EF7,$EG7)=0,"",AVERAGE($EE7,$EF7,$EG7)) -> 7.3333333 | FC7: =IF(OR($FA7="",$FB7=""),"",$FB7-$FA7) -> -12.666667 | FD7: =IF(COUNT($EH7,$EI7,$EJ7)=0,"",AVERAGE($EH7,$EI7,$EJ7)) -> 46 | FE7: =IF(COUNT($EL7,$EM7,$EN7)=0,"",AVERAGE($EL7,$EM7,$EN7)) -> 0.66666667 | FF7: =IF(OR($FD7="",$FE7=""),"",$FE7-$FD7) -> -45.333333 | FG7: =IF(COUNT($DF7,$DG7,$DH7,$DJ7,$DK7,$DL7,$DM7,$DN7,$DO7,$DQ7,$DR7,$DS7)=12,"Yes","No") -> Yes | FH7: =IF(COUNT($EA7,$EB7,$EC7,$EE7,$EF7,$EG7,$EH7,$EI7,$EJ7,$EL7,$EM7,$EN7)=12,"Yes","No") -> Yes | FI7: =IF(AND($M7="Include",OR($FG7="Yes",$FH7="Yes")),"Ready","Not ready") -> Not ready
A8: CTL-0006 | B8: 17 | C8: Candidate alternative-rationale group | D8: 0 | E8: DATA non-innovation deals.xlsx | F8: perkinelmer acquires horizon discovery | G8: No | H8: No | I8: Yes | J8: 2 | K8: Not started | L8: Eligible - 100% | M8: Review | O8: 44137 | P8: 44188 | Q8: 2020 | R8: Q4 2020 | S8: Completed | T8: PerkinElmer Acquires Horizon Discovery | U8: Mergers & Acquisitions | V8: Acquisition | W8: 100% Acquisition | X8: United Kingdom | Y8: 100% Acquisition | Z8: Evercore Inc , Perella Weinberg Partners LP , Numis Securities Ltd | AA8: Hogan Lovells International LLP , Covington & Burling LLP | AB8: Revvity Inc | AC8: revvity | AD8: Horizon Discovery Group Ltd | AE8: horizon discovery | AF8: 383 | AG8: 383 | AH8: PerkinElmer, Inc., a provider of detection, imaging, and informatics solutions and services, has acquired Horizon Discovery Group Plc, a company engaged in the application of gene editing and gene modulation for cell line engineering, for approximately USD383 million. The transaction will allow PerkinElmer to expand its portfolio of automated life sciences discovery and applied genomics solutions to include gene editing and gene modulation tools, with future opportunities to improve cell based discovery for precision medicine. PerkinElmer UK will finance the cash consideration payable to Horizon Shareholders pursuant to the Acquisition from PerkinElmer's existing cash resources. Evercore Inc is a financial advisor, while Covington & Burling LLP is acting as legal advisor for Horizon Discovery Group. Consilium Strategic Communications Limited is acting as financial media and UK investor relations adviser to Horizon. Perella Weinberg Partners LP is acting as financial advisor, while Hogan Lovells International LLP is acting as legal advisor for PerkinElmer. Deal History: Announcement: On November 2, 2020, PerkinElmer has reached an agreement on the terms of a recommended all cash offer to acquire Horizon Discovery Group. The transaction has a total enterprise value of approximately USD368 million, is expected to close in the first quarter of 2021 subject to customary closing conditions. | AI8: The transaction will allow PerkinElmer to expand its portfolio of automated life sciences discovery and applied genomics solutions to include gene editing and gene modulation tools, with future opportunities to improve cell based discovery for precision medicine. | AL8: Unknown | AM8: Unknown | AS8: Revvity Inc | AT8: Horizon Discovery Group Ltd | AU8: Not reviewed | AV8: Not assessed | AW8: Unknown | AX8: Unknown | AY8: Unknown | AZ8: Unknown | BA8: Unknown | BB8: Unknown | BF8: Not collected | BG8: Not collected | BH8: Not defined | BI8: =IF($Q8="","",$Q8-3) -> 2017 | BJ8: =IF($Q8="","",$Q8-2) -> 2018 | BK8: =IF($Q8="","",$Q8-1) -> 2019 | BL8: =IF($Q8="","",$Q8+0) -> 2020 | BM8: =IF($Q8="","",$Q8+1) -> 2021 | BN8: =IF($Q8="","",$Q8+2) -> 2022 | BO8: =IF($Q8="","",$Q8+3) -> 2023 | EQ8: =IF(OR($EO8="",$EP8="",$EO8=0),"",$EP8/$EO8) | ES8: Unknown | ET8: Unknown | EU8: =IF(COUNT($DF8,$DG8,$DH8)=0,"",AVERAGE($DF8,$DG8,$DH8)) | EV8: =IF(COUNT($DJ8,$DK8,$DL8)=0,"",AVERAGE($DJ8,$DK8,$DL8)) | EW8: =IF(OR($EU8="",$EV8=""),"",$EV8-$EU8) | EX8: =IF(COUNT($DM8,$DN8,$DO8)=0,"",AVERAGE($DM8,$DN8,$DO8)) | EY8: =IF(COUNT($DQ8,$DR8,$DS8)=0,"",AVERAGE($DQ8,$DR8,$DS8)) | EZ8: =IF(OR($EX8="",$EY8=""),"",$EY8-$EX8) | FA8: =IF(COUNT($EA8,$EB8,$EC8)=0,"",AVERAGE($EA8,$EB8,$EC8)) | FB8: =IF(COUNT($EE8,$EF8,$EG8)=0,"",AVERAGE($EE8,$EF8,$EG8)) | FC8: =IF(OR($FA8="",$FB8=""),"",$FB8-$FA8) | FD8: =IF(COUNT($EH8,$EI8,$EJ8)=0,"",AVERAGE($EH8,$EI8,$EJ8)) | FE8: =IF(COUNT($EL8,$EM8,$EN8)=0,"",AVERAGE($EL8,$EM8,$EN8)) | FF8: =IF(OR($FD8="",$FE8=""),"",$FE8-$FD8) | FG8: =IF(COUNT($DF8,$DG8,$DH8,$DJ8,$DK8,$DL8,$DM8,$DN8,$DO8,$DQ8,$DR8,$DS8)=12,"Yes","No") -> No | FH8: =IF(COUNT($EA8,$EB8,$EC8,$EE8,$EF8,$EG8,$EH8,$EI8,$EJ8,$EL8,$EM8,$EN8)=12,"Yes","No") -> No | FI8: =IF(AND($M8="Include",OR($FG8="Yes",$FH8="Yes")),"Ready","Not ready") -> Not ready
A9: CTL-0007 | B9: 18 | C9: Candidate alternative-rationale group | D9: 0 | E9: DATA non-innovation deals.xlsx | F9: retrophin acquires orphan technologies | G9: No | H9: No | I9: No | J9: 1 | K9: Not started | L9: Eligible - 100% | M9: Review | O9: 44126 | P9: 44147 | Q9: 2020 | R9: Q4 2020 | S9: Completed | T9: Retrophin Acquires Orphan Technologies | U9: Mergers & Acquisitions | V9: Acquisition | W9: 100% Acquisition | X9: Switzerland | Y9: 100% Acquisition | Z9: Barclays Plc , Cantor Fitzgerald & Co Inc | AA9: Cooley LLP , Hogan Lovells US LLP | AB9: Travere Therapeutics Inc | AC9: travere therapeutics | AD9: Orphan Technologies Ltd | AE9: orphan technologies | AF9: 517 | AG9: 517 | AH9: Retrophin, Inc., a biopharmaceutical company, has acquired Orphan Technologies Ltd, a privately held, clinical-stage biopharmaceutical company focused on the development of product candidate OT-58 for the treatment of classical homocystinuria (HCU). Under the terms of the agreement, Retrophin will make an upfront payment of USD90 million in cash upon closing of the transaction. Orphan Technologies shareholders will also be eligible to receive up to USD427 million in additional cash payments contingent upon the achievement of key milestones in the development and commercialization of OT-58. Retrophin will also pay a tiered mid-single digit royalty on future net sales of OT-58 in the US and Europe, and potentially make a milestone payment in the event a pediatric rare disease voucher is granted. The transaction will allow Retrophin to expand pipeline of potential first-in-class therapies targeting rare diseases. Barclays Plc acted as financial advisor, while Cooley LLP acted as legal advisor to Retrophin. Cantor Fitzgerald & Co. acted as financial advisor, while Hogan Lovells US LLP acted as legal advisor to Orphan Technologies. Deal History: Announced: On October 22, 2020, Retrophin has entered into a definitive agreement to acquire Orphan Technologies. | AI9: The transaction will allow Retrophin to expand pipeline of potential first-in-class therapies targeting rare diseases. | AL9: Unknown | AM9: Unknown | AS9: Travere Therapeutics Inc | AT9: Orphan Technologies Ltd | AU9: Not reviewed | AV9: Not assessed | AW9: Unknown | AX9: Unknown | AY9: Unknown | AZ9: Unknown | BA9: Unknown | BB9: Unknown | BF9: Not collected | BG9: Not collected | BH9: Not defined | BI9: =IF($Q9="","",$Q9-3) -> 2017 | BJ9: =IF($Q9="","",$Q9-2) -> 2018 | BK9: =IF($Q9="","",$Q9-1) -> 2019 | BL9: =IF($Q9="","",$Q9+0) -> 2020 | BM9: =IF($Q9="","",$Q9+1) -> 2021 | BN9: =IF($Q9="","",$Q9+2) -> 2022 | BO9: =IF($Q9="","",$Q9+3) -> 2023 | EQ9: =IF(OR($EO9="",$EP9="",$EO9=0),"",$EP9/$EO9) | ES9: Unknown | ET9: Unknown | EU9: =IF(COUNT($DF9,$DG9,$DH9)=0,"",AVERAGE($DF9,$DG9,$DH9)) | EV9: =IF(COUNT($DJ9,$DK9,$DL9)=0,"",AVERAGE($DJ9,$DK9,$DL9)) | EW9: =IF(OR($EU9="",$EV9=""),"",$EV9-$EU9) | EX9: =IF(COUNT($DM9,$DN9,$DO9)=0,"",AVERAGE($DM9,$DN9,$DO9)) | EY9: =IF(COUNT($DQ9,$DR9,$DS9)=0,"",AVERAGE($DQ9,$DR9,$DS9)) | EZ9: =IF(OR($EX9="",$EY9=""),"",$EY9-$EX9) | FA9: =IF(COUNT($EA9,$EB9,$EC9)=0,"",AVERAGE($EA9,$EB9,$EC9)) | FB9: =IF(COUNT($EE9,$EF9,$EG9)=0,"",AVERAGE($EE9,$EF9,$EG9)) | FC9: =IF(OR($FA9="",$FB9=""),"",$FB9-$FA9) | FD9: =IF(COUNT($EH9,$EI9,$EJ9)=0,"",AVERAGE($EH9,$EI9,$EJ9)) | FE9: =IF(COUNT($EL9,$EM9,$EN9)=0,"",AVERAGE($EL9,$EM9,$EN9)) | FF9: =IF(OR($FD9="",$FE9=""),"",$FE9-$FD9) | FG9: =IF(COUNT($DF9,$DG9,$DH9,$DJ9,$DK9,$DL9,$DM9,$DN9,$DO9,$DQ9,$DR9,$DS9)=12,"Yes","No") -> No | FH9: =IF(COUNT($EA9,$EB9,$EC9,$EE9,$EF9,$EG9,$EH9,$EI9,$EJ9,$EL9,$EM9,$EN9)=12,"Yes","No") -> No | FI9: =IF(AND($M9="Include",OR($FG9="Yes",$FH9="Yes")),"Ready","Not ready") -> Not ready
A10: CTL-0008 | B10: 19 | C10: Candidate alternative-rationale group | D10: 0 | E10: DATA non-innovation deals.xlsx | F10: stada arzneimittel acquires lobsor pharma | G10: No | H10: No | I10: Yes | J10: 2 | K10: Not started | L10: Eligible - 100% | M10: Review | O10: 44106 | P10: 44106 | Q10: 2020 | R10: Q4 2020 | S10: Completed | T10: STADA Arzneimittel Acquires Lobsor Pharma | U10: Mergers & Acquisitions | V10: Acquisition | W10: 100% Acquisition | X10: Sweden | Y10: 100% Acquisition | AA10: Baker & McKenzie LLP | AB10: Stada Arzneimittel AG | AC10: stada arzneimittel | AD10: LobSor Pharmaceuticals AB | AE10: lobsor pharmaceuticals ab | AG10: n/a | AH10: STADA Arzneimittel AG, a pharmaceutical company, has acquired Lobsor Pharmaceuticals AB, a specialty pharmaceutical company focusing on innovative, proprietary technologies and drug formulations, currently for the treatment of Parkinson’s disease. By acquiring Lobsor Pharma, STADA gains rights to a triple fixed combination (levodopa, carbidopa, entacapone), delivered via modern pump technology, that has already been successfully launched in Nordic countries. The acquisition complements STADA’s portfolio and expertise in the treatment of late-stage Parkinson’s disease, where it has strong expertise via company Britannia Pharmaceuticals. This acquisition expands STADA’s specialty footprint and serves as further evidence that STADA is a go-to-partner for specialty pharmaceuticals, generics and consumer health products. Baker McKenzie acted as legal advisor to STADA for the transaction. Baker McKenzie's core deal team consists of Peder Oxhammar, Costin Mihailescu, Edvard Henriksson, Seher Budak and Maja Uppgren. | AI10: This acquisition expands STADA’s specialty footprint and serves as further evidence that STADA is a go-to-partner for specialty pharmaceuticals, generics and consumer health products. | AL10: Unknown | AM10: Unknown | AS10: Stada Arzneimittel AG | AT10: LobSor Pharmaceuticals AB | AU10: Not reviewed | AV10: Not assessed | AW10: Unknown | AX10: Unknown | AY10: Unknown | AZ10: Unknown | BA10: Unknown | BB10: Unknown | BF10: Not collected | BG10: Not collected | BH10: Not defined | BI10: =IF($Q10="","",$Q10-3) -> 2017 | BJ10: =IF($Q10="","",$Q10-2) -> 2018 | BK10: =IF($Q10="","",$Q10-1) -> 2019 | BL10: =IF($Q10="","",$Q10+0) -> 2020 | BM10: =IF($Q10="","",$Q10+1) -> 2021 | BN10: =IF($Q10="","",$Q10+2) -> 2022 | BO10: =IF($Q10="","",$Q10+3) -> 2023 | EQ10: =IF(OR($EO10="",$EP10="",$EO10=0),"",$EP10/$EO10) | ES10: Unknown | ET10: Unknown | EU10: =IF(COUNT($DF10,$DG10,$DH10)=0,"",AVERAGE($DF10,$DG10,$DH10)) | EV10: =IF(COUNT($DJ10,$DK10,$DL10)=0,"",AVERAGE($DJ10,$DK10,$DL10)) | EW10: =IF(OR($EU10="",$EV10=""),"",$EV10-$EU10) | EX10: =IF(COUNT($DM10,$DN10,$DO10)=0,"",AVERAGE($DM10,$DN10,$DO10)) | EY10: =IF(COUNT($DQ10,$DR10,$DS10)=0,"",AVERAGE($DQ10,$DR10,$DS10)) | EZ10: =IF(OR($EX10="",$EY10=""),"",$EY10-$EX10) | FA10: =IF(COUNT($EA10,$EB10,$EC10)=0,"",AVERAGE($EA10,$EB10,$EC10)) | FB10: =IF(COUNT($EE10,$EF10,$EG10)=0,"",AVERAGE($EE10,$EF10,$EG10)) | FC10: =IF(OR($FA10="",$FB10=""),"",$FB10-$FA10) | FD10: =IF(COUNT($EH10,$EI10,$EJ10)=0,"",AVERAGE($EH10,$EI10,$EJ10)) | FE10: =IF(COUNT($EL10,$EM10,$EN10)=0,"",AVERAGE($EL10,$EM10,$EN10)) | FF10: =IF(OR($FD10="",$FE10=""),"",$FE10-$FD10) | FG10: =IF(COUNT($DF10,$DG10,$DH10,$DJ10,$DK10,$DL10,$DM10,$DN10,$DO10,$DQ10,$DR10,$DS10)=12,"Yes","No") -> No | FH10: =IF(COUNT($EA10,$EB10,$EC10,$EE10,$EF10,$EG10,$EH10,$EI10,$EJ10,$EL10,$EM10,$EN10)=12,"Yes","No") -> No | FI10: =IF(AND($M10="Include",OR($FG10="Yes",$FH10="Yes")),"Ready","Not ready") -> Not ready
A11: CTL-0009 | B11: 20 | C11: Candidate alternative-rationale group | D11: 0 | E11: DATA non-innovation deals.xlsx | F11: c o c farma acquires tubilux pharma | G11: No | H11: No | I11: No | J11: 1 | K11: Not started | L11: Eligible - 100% | M11: Review | O11: 44105 | P11: 44105 | Q11: 2020 | R11: Q4 2020 | S11: Completed | T11: C.O.C. Farma Acquires Tubilux Pharma | U11: Mergers & Acquisitions | V11: Acquisition | W11: 100% Acquisition | X11: Italy | Y11: 100% Acquisition | AA11: CMS Legal Services EEIG | AB11: COC Farmaceutici Srl | AC11: coc farmaceutici | AD11: Tubilux Pharma SpA | AE11: tubilux pharma | AG11: n/a | AH11: C.O.C. Farmaceutici Srl, a contract manufacturing company, has acquired Tubilux Pharma SpA, a contract developer and manufacturer company specialising in ophthalmology. The transaction will allow both C.O.C. Farma and Tubilux Pharma to create an all-Italian CDMO in the ophthalmic field, with services, skills and technologies fully integrated; and to reinforce their ophthalmic market share, giving them a considerable competitive advantage, with promising opportunities for growth in Europe, in the M.E.N.A. market and in the US. | AI11: The transaction will allow both C.O.C. Farma and Tubilux Pharma to create an all-Italian CDMO in the ophthalmic field, with services, skills and technologies fully integrated; and to reinforce their ophthalmic market share, giving them a considerable competitive advantage, with promising opportunities for growth in Europe, in the M.E.N.A. market and in the US. | AL11: Unknown | AM11: Unknown | AS11: COC Farmaceutici Srl | AT11: Tubilux Pharma SpA | AU11: Not reviewed | AV11: Not assessed | AW11: Unknown | AX11: Unknown | AY11: Unknown | AZ11: Unknown | BA11: Unknown | BB11: Unknown | BF11: Not collected | BG11: Not collected | BH11: Not defined | BI11: =IF($Q11="","",$Q11-3) -> 2017 | BJ11: =IF($Q11="","",$Q11-2) -> 2018 | BK11: =IF($Q11="","",$Q11-1) -> 2019 | BL11: =IF($Q11="","",$Q11+0) -> 2020 | BM11: =IF($Q11="","",$Q11+1) -> 2021 | BN11: =IF($Q11="","",$Q11+2) -> 2022 | BO11: =IF($Q11="","",$Q11+3) -> 2023 | EQ11: =IF(OR($EO11="",$EP11="",$EO11=0),"",$EP11/$EO11) | ES11: Unknown | ET11: Unknown | EU11: =IF(COUNT($DF11,$DG11,$DH11)=0,"",AVERAGE($DF11,$DG11,$DH11)) | EV11: =IF(COUNT($DJ11,$DK11,$DL11)=0,"",AVERAGE($DJ11,$DK11,$DL11)) | EW11: =IF(OR($EU11="",$EV11=""),"",$EV11-$EU11) | EX11: =IF(COUNT($DM11,$DN11,$DO11)=0,"",AVERAGE($DM11,$DN11,$DO11)) | EY11: =IF(COUNT($DQ11,$DR11,$DS11)=0,"",AVERAGE($DQ11,$DR11,$DS11)) | EZ11: =IF(OR($EX11="",$EY11=""),"",$EY11-$EX11) | FA11: =IF(COUNT($EA11,$EB11,$EC11)=0,"",AVERAGE($EA11,$EB11,$EC11)) | FB11: =IF(COUNT($EE11,$EF11,$EG11)=0,"",AVERAGE($EE11,$EF11,$EG11)) | FC11: =IF(OR($FA11="",$FB11=""),"",$FB11-$FA11) | FD11: =IF(COUNT($EH11,$EI11,$EJ11)=0,"",AVERAGE($EH11,$EI11,$EJ11)) | FE11: =IF(COUNT($EL11,$EM11,$EN11)=0,"",AVERAGE($EL11,$EM11,$EN11)) | FF11: =IF(OR($FD11="",$FE11=""),"",$FE11-$FD11) | FG11: =IF(COUNT($DF11,$DG11,$DH11,$DJ11,$DK11,$DL11,$DM11,$DN11,$DO11,$DQ11,$DR11,$DS11)=12,"Yes","No") -> No | FH11: =IF(COUNT($EA11,$EB11,$EC11,$EE11,$EF11,$EG11,$EH11,$EI11,$EJ11,$EL11,$EM11,$EN11)=12,"Yes","No") -> No | FI11: =IF(AND($M11="Include",OR($FG11="Yes",$FH11="Yes")),"Ready","Not ready") -> Not ready
A12: CTL-0010 | B12: 21 | C12: Candidate alternative-rationale group | D12: 0 | E12: DATA non-innovation deals.xlsx | F12: pharmalex merges with biostat solutions | G12: No | H12: No | I12: Yes | J12: 13 | K12: Not started | L12: Review - merger | M12: Review | O12: 44103 | P12: 44103 | Q12: 2020 | R12: Q3 2020 | S12: Completed | T12: Pharmalex Merges with BioStat Solutions | U12: Mergers & Acquisitions | V12: Merger | X12: Germany , United States | AD12: BIOSTAT SOLUTIONS, INC.; PharmaLex GmbH | AE12: biostat solutions pharmalex | AG12: n/a | AH12: PharmaLex GmbH, a provider of specialized services for the pharma, biotech and medtech industries, has merged with BioStat Solutions Inc (BSSI), a company that provides business consulting services on a contract and fee basis. Following the merger with PharmaLex, Lin Li will take over management of BSSI. Ron Bromley will step down as CEO, whilst Ena Bromley will continue to provide support as non-executive director and principal consultant. | AI12: The merger with BioStat Solutions diversifies PharmaLex’s existing statistical and data science service portfolio._x000D_ _x000D_ | AL12: Unknown | AM12: Unknown | AT12: BIOSTAT SOLUTIONS, INC.; PharmaLex GmbH | AU12: Not reviewed | AV12: Not assessed | AW12: Unknown | AX12: Unknown | AY12: Unknown | AZ12: Unknown | BA12: Unknown | BB12: Unknown | BF12: Not collected | BG12: Not collected | BH12: Not defined | BI12: =IF($Q12="","",$Q12-3) -> 2017 | BJ12: =IF($Q12="","",$Q12-2) -> 2018 | BK12: =IF($Q12="","",$Q12-1) -> 2019 | BL12: =IF($Q12="","",$Q12+0) -> 2020 | BM12: =IF($Q12="","",$Q12+1) -> 2021 | BN12: =IF($Q12="","",$Q12+2) -> 2022 | BO12: =IF($Q12="","",$Q12+3) -> 2023 | EQ12: =IF(OR($EO12="",$EP12="",$EO12=0),"",$EP12/$EO12) | ES12: Unknown | ET12: Unknown | EU12: =IF(COUNT($DF12,$DG12,$DH12)=0,"",AVERAGE($DF12,$DG12,$DH12)) | EV12: =IF(COUNT($DJ12,$DK12,$DL12)=0,"",AVERAGE($DJ12,$DK12,$DL12)) | EW12: =IF(OR($EU12="",$EV12=""),"",$EV12-$EU12) | EX12: =IF(COUNT($DM12,$DN12,$DO12)=0,"",AVERAGE($DM12,$DN12,$DO12)) | EY12: =IF(COUNT($DQ12,$DR12,$DS12)=0,"",AVERAGE($DQ12,$DR12,$DS12)) | EZ12: =IF(OR($EX12="",$EY12=""),"",$EY12-$EX12) | FA12: =IF(COUNT($EA12,$EB12,$EC12)=0,"",AVERAGE($EA12,$EB12,$EC12)) | FB12: =IF(COUNT($EE12,$EF12,$EG12)=0,"",AVERAGE($EE12,$EF12,$EG12)) | FC12: =IF(OR($FA12="",$FB12=""),"",$FB12-$FA12) | FD12: =IF(COUNT($EH12,$EI12,$EJ12)=0,"",AVERAGE($EH12,$EI12,$EJ12)) | FE12: =IF(COUNT($EL12,$EM12,$EN12)=0,"",AVERAGE($EL12,$EM12,$EN12)) | FF12: =IF(OR($FD12="",$FE12=""),"",$FE12-$FD12) | FG12: =IF(COUNT($DF12,$DG12,$DH12,$DJ12,$DK12,$DL12,$DM12,$DN12,$DO12,$DQ12,$DR12,$DS12)=12,"Yes","No") -> No | FH12: =IF(COUNT($EA12,$EB12,$EC12,$EE12,$EF12,$EG12,$EH12,$EI12,$EJ12,$EL12,$EM12,$EN12)=12,"Yes","No") -> No | FI12: =IF(AND($M12="Include",OR($FG12="Yes",$FH12="Yes")),"Ready","Not ready") -> Not ready
A13: CTL-0011 | B13: 22 | C13: Candidate alternative-rationale group | D13: 0 | E13: DATA non-innovation deals.xlsx | F13: bayer acquires kandy therapeutics | G13: No | H13: No | I13: Yes | J13: 2 | K13: Not started | L13: Eligible - 100% | M13: Review | O13: 44054 | P13: 44083 | Q13: 2020 | R13: Q3 2020 | S13: Completed | T13: Bayer Acquires KaNDy Therapeutics | U13: Mergers & Acquisitions | V13: Acquisition | W13: 100% Acquisition | X13: United Kingdom | Y13: 100% Acquisition | Z13: Morgan Stanley & Co LLC , Goldman Sachs International | AA13: Linklaters LLP , Goodwin Power, LLC | AB13: Bayer AG | AC13: bayer | AD13: KaNDy Therapeutics Ltd | AE13: kandy therapeutics | AF13: 875 | AG13: 875 | AH13: Bayer AG, a life science company, has completed the acquisition KaNDy Therapeutics Ltd, a clinical-stage Women’s Health company. Under the terms of the agreement Bayer will pay an upfront consideration of USD425 million, potential milestone payments of up to USD450 million until launch followed by potential additional triple digit million sales milestone payments. The acquisition will allow Bayer to expand its drug development pipeline in women’s healthcare. Morgan Stanley acted as financial advisor to Bayer, while Linklaters acted as legal counsel. Goldman Sachs International acted as financial advisor to KaNDy Therapeutics Ltd., while Goodwin acted as legal counsel. Deal History: Announced: On August 11, 2020, Bayer agreed to acquire KaNDy Therapeutics. | AI13: The acquisition will allow Bayer to expand its drug development pipeline in women’s healthcare. | AL13: Unknown | AM13: Unknown | AS13: Bayer AG | AT13: KaNDy Therapeutics Ltd | AU13: Not reviewed | AV13: Not assessed | AW13: Unknown | AX13: Unknown | AY13: Unknown | AZ13: Unknown | BA13: Unknown | BB13: Unknown | BF13: Not collected | BG13: Not collected | BH13: Not defined | BI13: =IF($Q13="","",$Q13-3) -> 2017 | BJ13: =IF($Q13="","",$Q13-2) -> 2018 | BK13: =IF($Q13="","",$Q13-1) -> 2019 | BL13: =IF($Q13="","",$Q13+0) -> 2020 | BM13: =IF($Q13="","",$Q13+1) -> 2021 | BN13: =IF($Q13="","",$Q13+2) -> 2022 | BO13: =IF($Q13="","",$Q13+3) -> 2023 | EQ13: =IF(OR($EO13="",$EP13="",$EO13=0),"",$EP13/$EO13) | ES13: Unknown | ET13: Unknown | EU13: =IF(COUNT($DF13,$DG13,$DH13)=0,"",AVERAGE($DF13,$DG13,$DH13)) | EV13: =IF(COUNT($DJ13,$DK13,$DL13)=0,"",AVERAGE($DJ13,$DK13,$DL13)) | EW13: =IF(OR($EU13="",$EV13=""),"",$EV13-$EU13) | EX13: =IF(COUNT($DM13,$DN13,$DO13)=0,"",AVERAGE($DM13,$DN13,$DO13)) | EY13: =IF(COUNT($DQ13,$DR13,$DS13)=0,"",AVERAGE($DQ13,$DR13,$DS13)) | EZ13: =IF(OR($EX13="",$EY13=""),"",$EY13-$EX13) | FA13: =IF(COUNT($EA13,$EB13,$EC13)=0,"",AVERAGE($EA13,$EB13,$EC13)) | FB13: =IF(COUNT($EE13,$EF13,$EG13)=0,"",AVERAGE($EE13,$EF13,$EG13)) | FC13: =IF(OR($FA13="",$FB13=""),"",$FB13-$FA13) | FD13: =IF(COUNT($EH13,$EI13,$EJ13)=0,"",AVERAGE($EH13,$EI13,$EJ13)) | FE13: =IF(COUNT($EL13,$EM13,$EN13)=0,"",AVERAGE($EL13,$EM13,$EN13)) | FF13: =IF(OR($FD13="",$FE13=""),"",$FE13-$FD13) | FG13: =IF(COUNT($DF13,$DG13,$DH13,$DJ13,$DK13,$DL13,$DM13,$DN13,$DO13,$DQ13,$DR13,$DS13)=12,"Yes","No") -> No | FH13: =IF(COUNT($EA13,$EB13,$EC13,$EE13,$EF13,$EG13,$EH13,$EI13,$EJ13,$EL13,$EM13,$EN13)=12,"Yes","No") -> No | FI13: =IF(AND($M13="Include",OR($FG13="Yes",$FH13="Yes")),"Ready","Not ready") -> Not ready
A14: CTL-0012 | B14: 23 | C14: Candidate alternative-rationale group | D14: 0 | E14: DATA non-innovation deals.xlsx | F14: jr holding acquires 16 6 stake in helix immuno oncology | G14: No | H14: No | I14: No | J14: 1 | K14: Not started | L14: Exclude - minority | M14: Review | O14: 44006 | P14: 44006 | Q14: 2020 | R14: Q2 2020 | S14: Completed | T14: JR Holding Acquires 16.6% Stake in Helix Immuno-Oncology | U14: Mergers & Acquisitions | V14: Acquisition | W14: Minority Acquisition | X14: Poland | Y14: Minority Acquisition | AB14: JRH ASI SA | AC14: jrh asi | AD14: Helix Immuno-Oncology SA | AE14: helix immuno oncology | AF14: 1 | AG14: 1 | AH14: JR Holding S.A. (Operates as JR Holding Alternatywna Spolka Inwestycyjna SA) has acquired 2,200,000 series B shares, representing a 16.64% stake, in Helix Immuno-Oncology SA, a developer of innovative products based on proprietary technologies to be used in cancer immunotherapy, for gross proceeds of PLN2.97 million. As part of the transaction, JR Holding has acquired 2,200,000 series B shares at a price of PLN1.35 per share. The transaction will allow Helix Immuno-Oncology for further development and commercialization of its products. | AI14: The transaction will allow Helix Immuno-Oncology for further development and commercialization of its products. | AL14: Unknown | AM14: Unknown | AS14: JRH ASI SA | AT14: Helix Immuno-Oncology SA | AU14: Not reviewed | AV14: Not assessed | AW14: Unknown | AX14: Unknown | AY14: Unknown | AZ14: Unknown | BA14: Unknown | BB14: Unknown | BF14: Not collected | BG14: Not collected | BH14: Not defined | BI14: =IF($Q14="","",$Q14-3) -> 2017 | BJ14: =IF($Q14="","",$Q14-2) -> 2018 | BK14: =IF($Q14="","",$Q14-1) -> 2019 | BL14: =IF($Q14="","",$Q14+0) -> 2020 | BM14: =IF($Q14="","",$Q14+1) -> 2021 | BN14: =IF($Q14="","",$Q14+2) -> 2022 | BO14: =IF($Q14="","",$Q14+3) -> 2023 | EQ14: =IF(OR($EO14="",$EP14="",$EO14=0),"",$EP14/$EO14) | ES14: Unknown | ET14: Unknown | EU14: =IF(COUNT($DF14,$DG14,$DH14)=0,"",AVERAGE($DF14,$DG14,$DH14)) | EV14: =IF(COUNT($DJ14,$DK14,$DL14)=0,"",AVERAGE($DJ14,$DK14,$DL14)) | EW14: =IF(OR($EU14="",$EV14=""),"",$EV14-$EU14) | EX14: =IF(COUNT($DM14,$DN14,$DO14)=0,"",AVERAGE($DM14,$DN14,$DO14)) | EY14: =IF(COUNT($DQ14,$DR14,$DS14)=0,"",AVERAGE($DQ14,$DR14,$DS14)) | EZ14: =IF(OR($EX14="",$EY14=""),"",$EY14-$EX14) | FA14: =IF(COUNT($EA14,$EB14,$EC14)=0,"",AVERAGE($EA14,$EB14,$EC14)) | FB14: =IF(COUNT($EE14,$EF14,$EG14)=0,"",AVERAGE($EE14,$EF14,$EG14)) | FC14: =IF(OR($FA14="",$FB14=""),"",$FB14-$FA14) | FD14: =IF(COUNT($EH14,$EI14,$EJ14)=0,"",AVERAGE($EH14,$EI14,$EJ14)) | FE14: =IF(COUNT($EL14,$EM14,$EN14)=0,"",AVERAGE($EL14,$EM14,$EN14)) | FF14: =IF(OR($FD14="",$FE14=""),"",$FE14-$FD14) | FG14: =IF(COUNT($DF14,$DG14,$DH14,$DJ14,$DK14,$DL14,$DM14,$DN14,$DO14,$DQ14,$DR14,$DS14)=12,"Yes","No") -> No | FH14: =IF(COUNT($EA14,$EB14,$EC14,$EE14,$EF14,$EG14,$EH14,$EI14,$EJ14,$EL14,$EM14,$EN14)=12,"Yes","No") -> No | FI14: =IF(AND($M14="Include",OR($FG14="Yes",$FH14="Yes")),"Ready","Not ready") -> Not ready
A15: CTL-0013 | B15: 24 | C15: Candidate alternative-rationale group | D15: 0 | E15: DATA non-innovation deals.xlsx | F15: kreditanstalt fur wiederaufbau acquires 23 stake in curevac for | G15: No | H15: No | I15: No | J15: 1 | K15: Not started | L15: Exclude - minority | M15: Review | O15: 43997 | P15: 44049 | Q15: 2020 | R15: Q2 2020 | S15: Completed | T15: Kreditanstalt fur Wiederaufbau Acquires 23% Stake in CureVac for USD337.5 Million | U15: Mergers & Acquisitions | V15: Acquisition | W15: Minority Acquisition | X15: Germany | Y15: Minority Acquisition | AA15: Linklaters LLP , Rittershaus, Wissmann & von Rosenstiel GmbH | AB15: Kreditanstalt fur Wiederaufbau | AC15: kreditanstalt fur wiederaufbau | AD15: Curevac NV | AE15: curevac | AF15: 337 | AG15: 337 | AH15: The Federal Republic of Germany has invested EUR300 million (USD337.5 million) in CureVac AG, a biopharmaceutical company. The investment will be made by the Kreditanstalt fur Wiederaufbau (KfW), have been laid out in a definitive draft agreement. Under the agreement, the KfW will hold a stake of around 23% in CureVac. CureVac intends to use the proceeds for the further development of its proprietary pipeline and mRNA platform technology and the expansion of business activities. | AI15: CureVac intends to use the proceeds for the further development of its proprietary pipeline and mRNA platform technology and the expansion of business activities. | AL15: Unknown | AM15: Unknown | AS15: Kreditanstalt fur Wiederaufbau | AT15: Curevac NV | AU15: Not reviewed | AV15: Not assessed | AW15: Unknown | AX15: Unknown | AY15: Unknown | AZ15: Unknown | BA15: Unknown | BB15: Unknown | BF15: Not collected | BG15: Not collected | BH15: Not defined | BI15: =IF($Q15="","",$Q15-3) -> 2017 | BJ15: =IF($Q15="","",$Q15-2) -> 2018 | BK15: =IF($Q15="","",$Q15-1) -> 2019 | BL15: =IF($Q15="","",$Q15+0) -> 2020 | BM15: =IF($Q15="","",$Q15+1) -> 2021 | BN15: =IF($Q15="","",$Q15+2) -> 2022 | BO15: =IF($Q15="","",$Q15+3) -> 2023 | EQ15: =IF(OR($EO15="",$EP15="",$EO15=0),"",$EP15/$EO15) | ES15: Unknown | ET15: Unknown | EU15: =IF(COUNT($DF15,$DG15,$DH15)=0,"",AVERAGE($DF15,$DG15,$DH15)) | EV15: =IF(COUNT($DJ15,$DK15,$DL15)=0,"",AVERAGE($DJ15,$DK15,$DL15)) | EW15: =IF(OR($EU15="",$EV15=""),"",$EV15-$EU15) | EX15: =IF(COUNT($DM15,$DN15,$DO15)=0,"",AVERAGE($DM15,$DN15,$DO15)) | EY15: =IF(COUNT($DQ15,$DR15,$DS15)=0,"",AVERAGE($DQ15,$DR15,$DS15)) | EZ15: =IF(OR($EX15="",$EY15=""),"",$EY15-$EX15) | FA15: =IF(COUNT($EA15,$EB15,$EC15)=0,"",AVERAGE($EA15,$EB15,$EC15)) | FB15: =IF(COUNT($EE15,$EF15,$EG15)=0,"",AVERAGE($EE15,$EF15,$EG15)) | FC15: =IF(OR($FA15="",$FB15=""),"",$FB15-$FA15) | FD15: =IF(COUNT($EH15,$EI15,$EJ15)=0,"",AVERAGE($EH15,$EI15,$EJ15)) | FE15: =IF(COUNT($EL15,$EM15,$EN15)=0,"",AVERAGE($EL15,$EM15,$EN15)) | FF15: =IF(OR($FD15="",$FE15=""),"",$FE15-$FD15) | FG15: =IF(COUNT($DF15,$DG15,$DH15,$DJ15,$DK15,$DL15,$DM15,$DN15,$DO15,$DQ15,$DR15,$DS15)=12,"Yes","No") -> No | FH15: =IF(COUNT($EA15,$EB15,$EC15,$EE15,$EF15,$EG15,$EH15,$EI15,$EJ15,$EL15,$EM15,$EN15)=12,"Yes","No") -> No | FI15: =IF(AND($M15="Include",OR($FG15="Yes",$FH15="Yes")),"Ready","Not ready") -> Not ready
A16: CTL-0014 | B16: 25 | C16: Candidate alternative-rationale group | D16: 0 | E16: DATA non-innovation deals.xlsx | F16: bbi group acquires diarect | G16: No | H16: No | I16: No | J16: 1 | K16: Not started | L16: Eligible - 100% | M16: Review | O16: 43985 | P16: 43985 | Q16: 2020 | R16: Q2 2020 | S16: Completed | T16: BBI Group Acquires DIARECT | U16: Mergers & Acquisitions | V16: Acquisition | W16: 100% Acquisition | X16: Germany | Y16: 100% Acquisition | AA16: Allen Overy Shearman Sterling LLP | AB16: BBI Group Holding Ltd (Inactive) | AC16: bbi | AD16: Diarect AG | AE16: diarect | AG16: n/a | AH16: BBI Group Holding Ltd (BBI Group), a provider a portfolio of products and services through its businesses to the diagnostic, healthcare, research, defence, food and cosmetics industries, has acquired DIARECT AG, a company specializes in the development and production of recombinant and native antigens. The transaction will allow BBI Group to enhance its position as the world’s largest diagnostics components company with a market antigen portfolio. | AI16: The transaction will allow BBI Group to enhance its position as the world’s largest diagnostics components company with a market antigen portfolio. | AL16: Unknown | AM16: Unknown | AS16: BBI Group Holding Ltd (Inactive) | AT16: Diarect AG | AU16: Not reviewed | AV16: Not assessed | AW16: Unknown | AX16: Unknown | AY16: Unknown | AZ16: Unknown | BA16: Unknown | BB16: Unknown | BF16: Not collected | BG16: Not collected | BH16: Not defined | BI16: =IF($Q16="","",$Q16-3) -> 2017 | BJ16: =IF($Q16="","",$Q16-2) -> 2018 | BK16: =IF($Q16="","",$Q16-1) -> 2019 | BL16: =IF($Q16="","",$Q16+0) -> 2020 | BM16: =IF($Q16="","",$Q16+1) -> 2021 | BN16: =IF($Q16="","",$Q16+2) -> 2022 | BO16: =IF($Q16="","",$Q16+3) -> 2023 | EQ16: =IF(OR($EO16="",$EP16="",$EO16=0),"",$EP16/$EO16) | ES16: Unknown | ET16: Unknown | EU16: =IF(COUNT($DF16,$DG16,$DH16)=0,"",AVERAGE($DF16,$DG16,$DH16)) | EV16: =IF(COUNT($DJ16,$DK16,$DL16)=0,"",AVERAGE($DJ16,$DK16,$DL16)) | EW16: =IF(OR($EU16="",$EV16=""),"",$EV16-$EU16) | EX16: =IF(COUNT($DM16,$DN16,$DO16)=0,"",AVERAGE($DM16,$DN16,$DO16)) | EY16: =IF(COUNT($DQ16,$DR16,$DS16)=0,"",AVERAGE($DQ16,$DR16,$DS16)) | EZ16: =IF(OR($EX16="",$EY16=""),"",$EY16-$EX16) | FA16: =IF(COUNT($EA16,$EB16,$EC16)=0,"",AVERAGE($EA16,$EB16,$EC16)) | FB16: =IF(COUNT($EE16,$EF16,$EG16)=0,"",AVERAGE($EE16,$EF16,$EG16)) | FC16: =IF(OR($FA16="",$FB16=""),"",$FB16-$FA16) | FD16: =IF(COUNT($EH16,$EI16,$EJ16)=0,"",AVERAGE($EH16,$EI16,$EJ16)) | FE16: =IF(COUNT($EL16,$EM16,$EN16)=0,"",AVERAGE($EL16,$EM16,$EN16)) | FF16: =IF(OR($FD16="",$FE16=""),"",$FE16-$FD16) | FG16: =IF(COUNT($DF16,$DG16,$DH16,$DJ16,$DK16,$DL16,$DM16,$DN16,$DO16,$DQ16,$DR16,$DS16)=12,"Yes","No") -> No | FH16: =IF(COUNT($EA16,$EB16,$EC16,$EE16,$EF16,$EG16,$EH16,$EI16,$EJ16,$EL16,$EM16,$EN16)=12,"Yes","No") -> No | FI16: =IF(AND($M16="Include",OR($FG16="Yes",$FH16="Yes")),"Ready","Not ready") -> Not ready
A17: CTL-0015 | B17: 26 | C17: Candidate alternative-rationale group | D17: 0 | E17: DATA non-innovation deals.xlsx | F17: sygnature discovery acquires alderley oncology | G17: No | H17: No | I17: No | J17: 1 | K17: Not started | L17: Eligible - 100% | M17: Review | O17: 43985 | P17: 43985 | Q17: 2020 | R17: Q2 2020 | S17: Completed | T17: Sygnature Discovery Acquires Alderley Oncology | U17: Mergers & Acquisitions | V17: Acquisition | W17: 100% Acquisition | X17: United Kingdom | Y17: 100% Acquisition | AB17: Sygnature Discovery Ltd | AC17: sygnature discovery | AD17: Alderley Oncology | AE17: alderley oncology | AG17: n/a | AH17: Sygnature Discovery, a provider of integrated drug discovery resource and expertise, has acquired Alderley Oncology, a company focused in vivo pharmacology service provider. Until the acquisition, Alderley Oncology was run by Bruntwood SciTech, owners of Alderley Park. The acquisition will allow Sygnature Discovery to expand and enhance its drug discovery services portfolio, and further boosts its on-going investments in oncology. | AI17: The acquisition will allow Sygnature Discovery to expand and enhance its drug discovery services portfolio, and further boosts its on-going investments in oncology. | AL17: Unknown | AM17: Unknown | AS17: Sygnature Discovery Ltd | AT17: Alderley Oncology | AU17: Not reviewed | AV17: Not assessed | AW17: Unknown | AX17: Unknown | AY17: Unknown | AZ17: Unknown | BA17: Unknown | BB17: Unknown | BF17: Not collected | BG17: Not collected | BH17: Not defined | BI17: =IF($Q17="","",$Q17-3) -> 2017 | BJ17: =IF($Q17="","",$Q17-2) -> 2018 | BK17: =IF($Q17="","",$Q17-1) -> 2019 | BL17: =IF($Q17="","",$Q17+0) -> 2020 | BM17: =IF($Q17="","",$Q17+1) -> 2021 | BN17: =IF($Q17="","",$Q17+2) -> 2022 | BO17: =IF($Q17="","",$Q17+3) -> 2023 | EQ17: =IF(OR($EO17="",$EP17="",$EO17=0),"",$EP17/$EO17) | ES17: Unknown | ET17: Unknown | EU17: =IF(COUNT($DF17,$DG17,$DH17)=0,"",AVERAGE($DF17,$DG17,$DH17)) | EV17: =IF(COUNT($DJ17,$DK17,$DL17)=0,"",AVERAGE($DJ17,$DK17,$DL17)) | EW17: =IF(OR($EU17="",$EV17=""),"",$EV17-$EU17) | EX17: =IF(COUNT($DM17,$DN17,$DO17)=0,"",AVERAGE($DM17,$DN17,$DO17)) | EY17: =IF(COUNT($DQ17,$DR17,$DS17)=0,"",AVERAGE($DQ17,$DR17,$DS17)) | EZ17: =IF(OR($EX17="",$EY17=""),"",$EY17-$EX17) | FA17: =IF(COUNT($EA17,$EB17,$EC17)=0,"",AVERAGE($EA17,$EB17,$EC17)) | FB17: =IF(COUNT($EE17,$EF17,$EG17)=0,"",AVERAGE($EE17,$EF17,$EG17)) | FC17: =IF(OR($FA17="",$FB17=""),"",$FB17-$FA17) | FD17: =IF(COUNT($EH17,$EI17,$EJ17)=0,"",AVERAGE($EH17,$EI17,$EJ17)) | FE17: =IF(COUNT($EL17,$EM17,$EN17)=0,"",AVERAGE($EL17,$EM17,$EN17)) | FF17: =IF(OR($FD17="",$FE17=""),"",$FE17-$FD17) | FG17: =IF(COUNT($DF17,$DG17,$DH17,$DJ17,$DK17,$DL17,$DM17,$DN17,$DO17,$DQ17,$DR17,$DS17)=12,"Yes","No") -> No | FH17: =IF(COUNT($EA17,$EB17,$EC17,$EE17,$EF17,$EG17,$EH17,$EI17,$EJ17,$EL17,$EM17,$EN17)=12,"Yes","No") -> No | FI17: =IF(AND($M17="Include",OR($FG17="Yes",$FH17="Yes")),"Ready","Not ready") -> Not ready
A18: CTL-0016 | B18: 27 | C18: Candidate alternative-rationale group | D18: 0 | E18: DATA non-innovation deals.xlsx | F18: novavax acquires praha vaccines | G18: No | H18: No | I18: No | J18: 1 | K18: Not started | L18: Eligible - 100% | M18: Review | O18: 43978 | P18: 43978 | Q18: 2020 | R18: Q2 2020 | S18: Completed | T18: Novavax Acquires Praha Vaccines | U18: Mergers & Acquisitions | V18: Acquisition | W18: 100% Acquisition | X18: Czech Republic | Y18: 100% Acquisition | AA18: Bird & Bird LLP , Ropes & Gray LLP | AB18: Novavax Inc | AC18: novavax | AD18: Novavax CZ | AE18: novavax cz | AF18: 167 | AG18: 167 | AH18: Novavax, Inc. a late-stage biotechnology company developing next-generation vaccines for serious infectious diseases, has acquired Praha Vaccines a.s., a manufacturing unit of Cyrus Poonawalla Group, in an all cash transaction of approximately USD167 million. The acquisition includes a biologics manufacturing facility and associated assets in Bohumil, Czech Republic. The facility is expected to provide an annual capacity of over 1 billion doses of antigen starting in 2021 for NVX-CoV2373, Novavax’ COVID-19 vaccine candidate. NVX-CoV2373 consists of a stable, prefusion protein antigen made using its proprietary nanoparticle technology and includes Novavax’ proprietary Matrix-M adjuvant. The acquisition includes a 150,000-square foot state of the art vaccine and biologics manufacturing facility and other support buildings, along with the existing employees and all related and required infrastructure. The facility is completing a renovation that includes Biosafety Level-3 (BSL-3) capabilities. As part of the transaction, approximately 150 employees with significant experience in vaccine manufacturing and support have joined Novavax. The acquisition of Praha Vaccines is supported by Novavax’ funding arrangement with the Coalition for Epidemic Preparedness Innovations (CEPI), enabling Novavax to dramatically expand its manufacturing capacity. Novavax will work collaboratively with the Serum Institute of India (SII), part of the Cyrus Poonawalla Group, to increase production levels at the Bohumil facility by the end of 2020. The transaction will allow Novavax to produce 1 billion doses of its COVID-19 vaccine candidate next year. | AI18: The transaction will allow Novavax to produce 1 billion doses of its COVID-19 vaccine candidate next year. | AL18: Unknown | AM18: Unknown | AS18: Novavax Inc | AT18: Novavax CZ | AU18: Not reviewed | AV18: Not assessed | AW18: Unknown | AX18: Unknown | AY18: Unknown | AZ18: Unknown | BA18: Unknown | BB18: Unknown | BF18: Not collected | BG18: Not collected | BH18: Not defined | BI18: =IF($Q18="","",$Q18-3) -> 2017 | BJ18: =IF($Q18="","",$Q18-2) -> 2018 | BK18: =IF($Q18="","",$Q18-1) -> 2019 | BL18: =IF($Q18="","",$Q18+0) -> 2020 | BM18: =IF($Q18="","",$Q18+1) -> 2021 | BN18: =IF($Q18="","",$Q18+2) -> 2022 | BO18: =IF($Q18="","",$Q18+3) -> 2023 | EQ18: =IF(OR($EO18="",$EP18="",$EO18=0),"",$EP18/$EO18) | ES18: Unknown | ET18: Unknown | EU18: =IF(COUNT($DF18,$DG18,$DH18)=0,"",AVERAGE($DF18,$DG18,$DH18)) | EV18: =IF(COUNT($DJ18,$DK18,$DL18)=0,"",AVERAGE($DJ18,$DK18,$DL18)) | EW18: =IF(OR($EU18="",$EV18=""),"",$EV18-$EU18) | EX18: =IF(COUNT($DM18,$DN18,$DO18)=0,"",AVERAGE($DM18,$DN18,$DO18)) | EY18: =IF(COUNT($DQ18,$DR18,$DS18)=0,"",AVERAGE($DQ18,$DR18,$DS18)) | EZ18: =IF(OR($EX18="",$EY18=""),"",$EY18-$EX18) | FA18: =IF(COUNT($EA18,$EB18,$EC18)=0,"",AVERAGE($EA18,$EB18,$EC18)) | FB18: =IF(COUNT($EE18,$EF18,$EG18)=0,"",AVERAGE($EE18,$EF18,$EG18)) | FC18: =IF(OR($FA18="",$FB18=""),"",$FB18-$FA18) | FD18: =IF(COUNT($EH18,$EI18,$EJ18)=0,"",AVERAGE($EH18,$EI18,$EJ18)) | FE18: =IF(COUNT($EL18,$EM18,$EN18)=0,"",AVERAGE($EL18,$EM18,$EN18)) | FF18: =IF(OR($FD18="",$FE18=""),"",$FE18-$FD18) | FG18: =IF(COUNT($DF18,$DG18,$DH18,$DJ18,$DK18,$DL18,$DM18,$DN18,$DO18,$DQ18,$DR18,$DS18)=12,"Yes","No") -> No | FH18: =IF(COUNT($EA18,$EB18,$EC18,$EE18,$EF18,$EG18,$EH18,$EI18,$EJ18,$EL18,$EM18,$EN18)=12,"Yes","No") -> No | FI18: =IF(AND($M18="Include",OR($FG18="Yes",$FH18="Yes")),"Ready","Not ready") -> Not ready
A19: CTL-0017 | B19: 28 | C19: Candidate alternative-rationale group | D19: 0 | E19: DATA non-innovation deals.xlsx | F19: serb acquires veriton pharma | G19: No | H19: No | I19: No | J19: 1 | K19: Not started | L19: Eligible - 100% | M19: Review | O19: 43972 | P19: 43972 | Q19: 2020 | R19: Q2 2020 | S19: Completed | T19: Serb Acquires Veriton Pharma | U19: Mergers & Acquisitions | V19: Acquisition | W19: 100% Acquisition | X19: United Kingdom | Y19: 100% Acquisition | Z19: Eight Advisory (8 ADVISORY) | AA19: Mayer Brown LLP , Charles Russell Speechlys | AB19: Serb SAS | AC19: serb | AD19: Veriton Pharma Ltd | AE19: veriton pharma | AG19: n/a | AH19: Serb SA, a specialist pharmaceutical company that focuses on prescription medicines which address rare and life-threatening diseases, has acquired Veriton Pharma Ltd, a specialist pharmaceutical company which focuses on developing medicines for people with neurological or rare metabolic conditions. Eight Advisory advised Serb on the acquisition. The transaction allows Serb to expand its presence in UK. | AI19: The transaction will allow Serb to expand its presence in UK. | AL19: Unknown | AM19: Unknown | AS19: Serb SAS | AT19: Veriton Pharma Ltd | AU19: Not reviewed | AV19: Not assessed | AW19: Unknown | AX19: Unknown | AY19: Unknown | AZ19: Unknown | BA19: Unknown | BB19: Unknown | BF19: Not collected | BG19: Not collected | BH19: Not defined | BI19: =IF($Q19="","",$Q19-3) -> 2017 | BJ19: =IF($Q19="","",$Q19-2) -> 2018 | BK19: =IF($Q19="","",$Q19-1) -> 2019 | BL19: =IF($Q19="","",$Q19+0) -> 2020 | BM19: =IF($Q19="","",$Q19+1) -> 2021 | BN19: =IF($Q19="","",$Q19+2) -> 2022 | BO19: =IF($Q19="","",$Q19+3) -> 2023 | EQ19: =IF(OR($EO19="",$EP19="",$EO19=0),"",$EP19/$EO19) | ES19: Unknown | ET19: Unknown | EU19: =IF(COUNT($DF19,$DG19,$DH19)=0,"",AVERAGE($DF19,$DG19,$DH19)) | EV19: =IF(COUNT($DJ19,$DK19,$DL19)=0,"",AVERAGE($DJ19,$DK19,$DL19)) | EW19: =IF(OR($EU19="",$EV19=""),"",$EV19-$EU19) | EX19: =IF(COUNT($DM19,$DN19,$DO19)=0,"",AVERAGE($DM19,$DN19,$DO19)) | EY19: =IF(COUNT($DQ19,$DR19,$DS19)=0,"",AVERAGE($DQ19,$DR19,$DS19)) | EZ19: =IF(OR($EX19="",$EY19=""),"",$EY19-$EX19) | FA19: =IF(COUNT($EA19,$EB19,$EC19)=0,"",AVERAGE($EA19,$EB19,$EC19)) | FB19: =IF(COUNT($EE19,$EF19,$EG19)=0,"",AVERAGE($EE19,$EF19,$EG19)) | FC19: =IF(OR($FA19="",$FB19=""),"",$FB19-$FA19) | FD19: =IF(COUNT($EH19,$EI19,$EJ19)=0,"",AVERAGE($EH19,$EI19,$EJ19)) | FE19: =IF(COUNT($EL19,$EM19,$EN19)=0,"",AVERAGE($EL19,$EM19,$EN19)) | FF19: =IF(OR($FD19="",$FE19=""),"",$FE19-$FD19) | FG19: =IF(COUNT($DF19,$DG19,$DH19,$DJ19,$DK19,$DL19,$DM19,$DN19,$DO19,$DQ19,$DR19,$DS19)=12,"Yes","No") -> No | FH19: =IF(COUNT($EA19,$EB19,$EC19,$EE19,$EF19,$EG19,$EH19,$EI19,$EJ19,$EL19,$EM19,$EN19)=12,"Yes","No") -> No | FI19: =IF(AND($M19="Include",OR($FG19="Yes",$FH19="Yes")),"Ready","Not ready") -> Not ready
A20: CTL-0018 | B20: 29 | C20: Candidate alternative-rationale group | D20: 0 | E20: DATA non-innovation deals.xlsx | F20: mediolanum farmaceutici acquires elsalys biotech | G20: No | H20: No | I20: No | J20: 1 | K20: Not started | L20: Eligible - 100% | M20: Review | O20: 43958 | P20: 43958 | Q20: 2020 | R20: Q2 2020 | S20: Completed | T20: Mediolanum Farmaceutici Acquires ElsaLys Biotech | U20: Mergers & Acquisitions | V20: Acquisition | W20: 100% Acquisition | X20: France | Y20: 100% Acquisition | AB20: Mediolanum farmaceutici SpA | AC20: mediolanum farmaceutici | AD20: Elsalys Biotech SA | AE20: elsalys biotech | AG20: n/a | AH20: Mediolanum Farmaceutici Spa, a pharmaceutical company, has acquired ElsaLys Biotech, a clinical stage immuno-oncology company that designs and develops a new generation of therapeutic antibodies that target tumors and their immune and vascular microenvironment. This acquisition enables Mediolanum Farmaceutici to strengthens its commitment to Research & Development in oncology and consolidate its international expansion process. | AI20: This acquisition enables Mediolanum Farmaceutici to strengthen its commitment to Research & Development in oncology and consolidate its international expansion process. | AL20: Unknown | AM20: Unknown | AS20: Mediolanum farmaceutici SpA | AT20: Elsalys Biotech SA | AU20: Not reviewed | AV20: Not assessed | AW20: Unknown | AX20: Unknown | AY20: Unknown | AZ20: Unknown | BA20: Unknown | BB20: Unknown | BF20: Not collected | BG20: Not collected | BH20: Not defined | BI20: =IF($Q20="","",$Q20-3) -> 2017 | BJ20: =IF($Q20="","",$Q20-2) -> 2018 | BK20: =IF($Q20="","",$Q20-1) -> 2019 | BL20: =IF($Q20="","",$Q20+0) -> 2020 | BM20: =IF($Q20="","",$Q20+1) -> 2021 | BN20: =IF($Q20="","",$Q20+2) -> 2022 | BO20: =IF($Q20="","",$Q20+3) -> 2023 | EQ20: =IF(OR($EO20="",$EP20="",$EO20=0),"",$EP20/$EO20) | ES20: Unknown | ET20: Unknown | EU20: =IF(COUNT($DF20,$DG20,$DH20)=0,"",AVERAGE($DF20,$DG20,$DH20)) | EV20: =IF(COUNT($DJ20,$DK20,$DL20)=0,"",AVERAGE($DJ20,$DK20,$DL20)) | EW20: =IF(OR($EU20="",$EV20=""),"",$EV20-$EU20) | EX20: =IF(COUNT($DM20,$DN20,$DO20)=0,"",AVERAGE($DM20,$DN20,$DO20)) | EY20: =IF(COUNT($DQ20,$DR20,$DS20)=0,"",AVERAGE($DQ20,$DR20,$DS20)) | EZ20: =IF(OR($EX20="",$EY20=""),"",$EY20-$EX20) | FA20: =IF(COUNT($EA20,$EB20,$EC20)=0,"",AVERAGE($EA20,$EB20,$EC20)) | FB20: =IF(COUNT($EE20,$EF20,$EG20)=0,"",AVERAGE($EE20,$EF20,$EG20)) | FC20: =IF(OR($FA20="",$FB20=""),"",$FB20-$FA20) | FD20: =IF(COUNT($EH20,$EI20,$EJ20)=0,"",AVERAGE($EH20,$EI20,$EJ20)) | FE20: =IF(COUNT($EL20,$EM20,$EN20)=0,"",AVERAGE($EL20,$EM20,$EN20)) | FF20: =IF(OR($FD20="",$FE20=""),"",$FE20-$FD20) | FG20: =IF(COUNT($DF20,$DG20,$DH20,$DJ20,$DK20,$DL20,$DM20,$DN20,$DO20,$DQ20,$DR20,$DS20)=12,"Yes","No") -> No | FH20: =IF(COUNT($EA20,$EB20,$EC20,$EE20,$EF20,$EG20,$EH20,$EI20,$EJ20,$EL20,$EM20,$EN20)=12,"Yes","No") -> No | FI20: =IF(AND($M20="Include",OR($FG20="Yes",$FH20="Yes")),"Ready","Not ready") -> Not ready
A21: CTL-0019 | B21: 30 | C21: Candidate alternative-rationale group | D21: 0 | E21: DATA non-innovation deals.xlsx | F21: ascenion and innovationsstarter fonds hamburg acquires shares in provirex | G21: No | H21: No | I21: No | J21: 1 | K21: Not started | L21: Eligible - 100% | M21: Review | O21: 43950 | P21: 43950 | Q21: 2020 | R21: Q2 2020 | S21: Completed | T21: Ascenion and Innovationsstarter Fonds Hamburg Acquires Shares in Provirex | U21: Mergers & Acquisitions | V21: Acquisition | W21: 100% Acquisition | X21: Germany | Y21: 100% Acquisition | AB21: Ascenion GmbH; IFB Innovationsstarter GmbH (Innovationsstarter Hamburg GmbH) | AC21: ascenion ifb innovationsstarter innovationsstarter hamburg | AD21: PROVIREX Genome Editing Therapies GmbH | AE21: provirex genome editing therapies | AG21: n/a | AH21: Ascenion GmbH, a technology transfer company with a life-science focus company and Innovationsstarter Fonds Hamburg GmbH, a financial service company acquire shares in PROVIREX Genome Editing Therapies GmbH, a biotech start-up. The concept is based on research work by Prof. Joachim Hauber and team at the Heinrich Pette Institute (HPI) - Leibniz Institute for Experimental Virology and Prof. Frank Buchholz at the Technical University of Dresden, who was formerly at the Max Planck Institute for Molecular Cell Biology and genetics. Together they developed and optimized a so-called genetic scissors, the designer recombinase Brec1. The approach is currently being prepared for clinical trials in a cooperation between the HPI and the University Hospital Hamburg-Eppendorf (UKE). It will initially be evaluated as part of stem cell therapy in eight HIV patients in the UKE's Stem Cell Therapy Clinic under the direction of Prof. Nicolaus Kröger. For this purpose, the Federal Ministry of Education and Research (BMBF), the Hamburg Senate and ForTra gGmbH have provided funding and investment funds for research transfer to the Else Kröner-Fresenius Foundation. | AI21: The acquisition allows Ascenion GmbH and Innovationsstarter Fonds Hamburg GmbH to gain access to the innovative 'gene scissors' technology developed by PROVIREX for the treatment of HIV patients. | AL21: Unknown | AM21: Unknown | AS21: Ascenion GmbH; IFB Innovationsstarter GmbH (Innovationsstarter Hamburg GmbH) | AT21: PROVIREX Genome Editing Therapies GmbH | AU21: Not reviewed | AV21: Not assessed | AW21: Unknown | AX21: Unknown | AY21: Unknown | AZ21: Unknown | BA21: Unknown | BB21: Unknown | BF21: Not collected | BG21: Not collected | BH21: Not defined | BI21: =IF($Q21="","",$Q21-3) -> 2017 | BJ21: =IF($Q21="","",$Q21-2) -> 2018 | BK21: =IF($Q21="","",$Q21-1) -> 2019 | BL21: =IF($Q21="","",$Q21+0) -> 2020 | BM21: =IF($Q21="","",$Q21+1) -> 2021 | BN21: =IF($Q21="","",$Q21+2) -> 2022 | BO21: =IF($Q21="","",$Q21+3) -> 2023 | EQ21: =IF(OR($EO21="",$EP21="",$EO21=0),"",$EP21/$EO21) | ES21: Unknown | ET21: Unknown | EU21: =IF(COUNT($DF21,$DG21,$DH21)=0,"",AVERAGE($DF21,$DG21,$DH21)) | EV21: =IF(COUNT($DJ21,$DK21,$DL21)=0,"",AVERAGE($DJ21,$DK21,$DL21)) | EW21: =IF(OR($EU21="",$EV21=""),"",$EV21-$EU21) | EX21: =IF(COUNT($DM21,$DN21,$DO21)=0,"",AVERAGE($DM21,$DN21,$DO21)) | EY21: =IF(COUNT($DQ21,$DR21,$DS21)=0,"",AVERAGE($DQ21,$DR21,$DS21)) | EZ21: =IF(OR($EX21="",$EY21=""),"",$EY21-$EX21) | FA21: =IF(COUNT($EA21,$EB21,$EC21)=0,"",AVERAGE($EA21,$EB21,$EC21)) | FB21: =IF(COUNT($EE21,$EF21,$EG21)=0,"",AVERAGE($EE21,$EF21,$EG21)) | FC21: =IF(OR($FA21="",$FB21=""),"",$FB21-$FA21) | FD21: =IF(COUNT($EH21,$EI21,$EJ21)=0,"",AVERAGE($EH21,$EI21,$EJ21)) | FE21: =IF(COUNT($EL21,$EM21,$EN21)=0,"",AVERAGE($EL21,$EM21,$EN21)) | FF21: =IF(OR($FD21="",$FE21=""),"",$FE21-$FD21) | FG21: =IF(COUNT($DF21,$DG21,$DH21,$DJ21,$DK21,$DL21,$DM21,$DN21,$DO21,$DQ21,$DR21,$DS21)=12,"Yes","No") -> No | FH21: =IF(COUNT($EA21,$EB21,$EC21,$EE21,$EF21,$EG21,$EH21,$EI21,$EJ21,$EL21,$EM21,$EN21)=12,"Yes","No") -> No | FI21: =IF(AND($M21="Include",OR($FG21="Yes",$FH21="Yes")),"Ready","Not ready") -> Not ready
A22: CTL-0020 | B22: 31 | C22: Candidate alternative-rationale group | D22: 0 | E22: DATA non-innovation deals.xlsx | F22: asklepios biopharma askbio acquires brainvectis | G22: No | H22: No | I22: No | J22: 1 | K22: Not started | L22: Eligible - 100% | M22: Review | O22: 43943 | P22: 43943 | Q22: 2020 | R22: Q2 2020 | S22: Completed | T22: Asklepios BioPharma (AskBio) Acquires BrainVectis | U22: Mergers & Acquisitions | V22: Acquisition | W22: 100% Acquisition | X22: France | Y22: 100% Acquisition | AB22: Asklepios BioPharmaceutical Inc | AC22: asklepios biopharmaceutical | AD22: Brainvectis SAS | AE22: brainvectis | AG22: n/a | AH22: Asklepios BioPharmaceutical, Inc. (AskBio), a clinical-stage adeno-associated virus (AAV) gene therapy company, has acquired BrainVectis, a gene therapy company and French National Institute for Health and Medical Research (INSERM) spin-out with expertise and an intellectual property estate for the treatment of neurodegenerative disorders. BrainVectis is particularly focused on therapies that restore brain cholesterol metabolism as a treatment for Huntington's disease and other disorders. BrainVectis will operate as a wholly owned subsidiary of AskBio and maintain its office in Paris, France. AskBio will leverage its proprietary capsid and synthetic promotor design technologies and manufacturing technology and capacity to advance the development of this and other BrainVectis programs. This agreement enables AskBio to expand its clinical pipeline for neurodegenerative diseases. | AI22: This agreement enables AskBio to expand its clinical pipeline for neurodegenerative diseases. | AL22: Unknown | AM22: Unknown | AS22: Asklepios BioPharmaceutical Inc | AT22: Brainvectis SAS | AU22: Not reviewed | AV22: Not assessed | AW22: Unknown | AX22: Unknown | AY22: Unknown | AZ22: Unknown | BA22: Unknown | BB22: Unknown | BF22: Not collected | BG22: Not collected | BH22: Not defined | BI22: =IF($Q22="","",$Q22-3) -> 2017 | BJ22: =IF($Q22="","",$Q22-2) -> 2018 | BK22: =IF($Q22="","",$Q22-1) -> 2019 | BL22: =IF($Q22="","",$Q22+0) -> 2020 | BM22: =IF($Q22="","",$Q22+1) -> 2021 | BN22: =IF($Q22="","",$Q22+2) -> 2022 | BO22: =IF($Q22="","",$Q22+3) -> 2023 | EQ22: =IF(OR($EO22="",$EP22="",$EO22=0),"",$EP22/$EO22) | ES22: Unknown | ET22: Unknown | EU22: =IF(COUNT($DF22,$DG22,$DH22)=0,"",AVERAGE($DF22,$DG22,$DH22)) | EV22: =IF(COUNT($DJ22,$DK22,$DL22)=0,"",AVERAGE($DJ22,$DK22,$DL22)) | EW22: =IF(OR($EU22="",$EV22=""),"",$EV22-$EU22) | EX22: =IF(COUNT($DM22,$DN22,$DO22)=0,"",AVERAGE($DM22,$DN22,$DO22)) | EY22: =IF(COUNT($DQ22,$DR22,$DS22)=0,"",AVERAGE($DQ22,$DR22,$DS22)) | EZ22: =IF(OR($EX22="",$EY22=""),"",$EY22-$EX22) | FA22: =IF(COUNT($EA22,$EB22,$EC22)=0,"",AVERAGE($EA22,$EB22,$EC22)) | FB22: =IF(COUNT($EE22,$EF22,$EG22)=0,"",AVERAGE($EE22,$EF22,$EG22)) | FC22: =IF(OR($FA22="",$FB22=""),"",$FB22-$FA22) | FD22: =IF(COUNT($EH22,$EI22,$EJ22)=0,"",AVERAGE($EH22,$EI22,$EJ22)) | FE22: =IF(COUNT($EL22,$EM22,$EN22)=0,"",AVERAGE($EL22,$EM22,$EN22)) | FF22: =IF(OR($FD22="",$FE22=""),"",$FE22-$FD22) | FG22: =IF(COUNT($DF22,$DG22,$DH22,$DJ22,$DK22,$DL22,$DM22,$DN22,$DO22,$DQ22,$DR22,$DS22)=12,"Yes","No") -> No | FH22: =IF(COUNT($EA22,$EB22,$EC22,$EE22,$EF22,$EG22,$EH22,$EI22,$EJ22,$EL22,$EM22,$EN22)=12,"Yes","No") -> No | FI22: =IF(AND($M22="Include",OR($FG22="Yes",$FH22="Yes")),"Ready","Not ready") -> Not ready
A23: CTL-0021 | B23: 32 | C23: Candidate alternative-rationale group | D23: 0 | E23: DATA non-innovation deals.xlsx | F23: astellas pharma acquires nanna therapeutics | G23: No | H23: No | I23: No | J23: 1 | K23: Not started | L23: Eligible - 100% | M23: Review | O23: 43942 | P23: 43942 | Q23: 2020 | R23: Q2 2020 | S23: Completed | T23: Astellas Pharma Acquires Nanna Therapeutics | U23: Mergers & Acquisitions | V23: Acquisition | W23: 100% Acquisition | X23: United Kingdom | Y23: 100% Acquisition | AB23: Astellas Pharma Europe Ltd | AC23: astellas pharma europe | AD23: Nanna Therapeutics Ltd | AE23: nanna therapeutics | AF23: 87 | AG23: 87 | AH23: Astellas Pharma Inc., through its subsidiary Astellas Pharma Europe Ltd., has acquired all of the issued share capital of Nanna Therapeutics Limited, a biotech company focused on addressing age-related diseases with high unmet medical need including mitochondria-related diseases, through execution of a share purchase agreement. Pursuant to the transaction, Astellas Pharma paid a consideration of GBP12 million upon closing of the acquisition, and Nanna became a wholly owned subsidiary of Astellas. In addition to this payment, Nanna’s shareholders are eligible to receive potential future development milestone payments of up to GBP57.5 million. The impact of this transaction on Astellas’ financial results for the fiscal year ending March 31, 2021, is expected to be immaterial. Adding Nanna’s proprietary and advanced screening platform with new DNA-encoded chemical libraries (DELs) technology significantly bolsters Astellas’ early stage drug development capabilities. Nanna’s unique capabilities enable the creation and rapid testing of more diverse chemical libraries. The approach enables phenotype-based screening which is not feasible with conventional DELs. It can also be applied to various assay systems including cell-based assays utilizing patient-derived cells, potentially enabling screens that are tailored to a specific disease biology. The acquisition enables Astellas Pharma to create new solutions that address unmet medical needs by combining Nanna’s unique technology platform with its research and development capabilities related to mitochondrial diseases. | AI23: The acquisition enables Astellas Pharma to create new solutions that address unmet medical needs by combining Nanna’s unique technology platform with its research and development capabilities related to mitochondrial diseases. | AL23: Unknown | AM23: Unknown | AS23: Astellas Pharma Europe Ltd | AT23: Nanna Therapeutics Ltd | AU23: Not reviewed | AV23: Not assessed | AW23: Unknown | AX23: Unknown | AY23: Unknown | AZ23: Unknown | BA23: Unknown | BB23: Unknown | BF23: Not collected | BG23: Not collected | BH23: Not defined | BI23: =IF($Q23="","",$Q23-3) -> 2017 | BJ23: =IF($Q23="","",$Q23-2) -> 2018 | BK23: =IF($Q23="","",$Q23-1) -> 2019 | BL23: =IF($Q23="","",$Q23+0) -> 2020 | BM23: =IF($Q23="","",$Q23+1) -> 2021 | BN23: =IF($Q23="","",$Q23+2) -> 2022 | BO23: =IF($Q23="","",$Q23+3) -> 2023 | EQ23: =IF(OR($EO23="",$EP23="",$EO23=0),"",$EP23/$EO23) | ES23: Unknown | ET23: Unknown | EU23: =IF(COUNT($DF23,$DG23,$DH23)=0,"",AVERAGE($DF23,$DG23,$DH23)) | EV23: =IF(COUNT($DJ23,$DK23,$DL23)=0,"",AVERAGE($DJ23,$DK23,$DL23)) | EW23: =IF(OR($EU23="",$EV23=""),"",$EV23-$EU23) | EX23: =IF(COUNT($DM23,$DN23,$DO23)=0,"",AVERAGE($DM23,$DN23,$DO23)) | EY23: =IF(COUNT($DQ23,$DR23,$DS23)=0,"",AVERAGE($DQ23,$DR23,$DS23)) | EZ23: =IF(OR($EX23="",$EY23=""),"",$EY23-$EX23) | FA23: =IF(COUNT($EA23,$EB23,$EC23)=0,"",AVERAGE($EA23,$EB23,$EC23)) | FB23: =IF(COUNT($EE23,$EF23,$EG23)=0,"",AVERAGE($EE23,$EF23,$EG23)) | FC23: =IF(OR($FA23="",$FB23=""),"",$FB23-$FA23) | FD23: =IF(COUNT($EH23,$EI23,$EJ23)=0,"",AVERAGE($EH23,$EI23,$EJ23)) | FE23: =IF(COUNT($EL23,$EM23,$EN23)=0,"",AVERAGE($EL23,$EM23,$EN23)) | FF23: =IF(OR($FD23="",$FE23=""),"",$FE23-$FD23) | FG23: =IF(COUNT($DF23,$DG23,$DH23,$DJ23,$DK23,$DL23,$DM23,$DN23,$DO23,$DQ23,$DR23,$DS23)=12,"Yes","No") -> No | FH23: =IF(COUNT($EA23,$EB23,$EC23,$EE23,$EF23,$EG23,$EH23,$EI23,$EJ23,$EL23,$EM23,$EN23)=12,"Yes","No") -> No | FI23: =IF(AND($M23="Include",OR($FG23="Yes",$FH23="Yes")),"Ready","Not ready") -> Not ready
A24: CTL-0022 | B24: 33 | C24: Candidate alternative-rationale group | D24: 0 | E24: DATA non-innovation deals.xlsx | F24: les laboratoires servier acquires symphogen | G24: Yes | H24: No | I24: No | J24: 1 | K24: Not started | L24: Eligible - 100% | M24: Review | O24: 43924 | P24: 43986 | Q24: 2020 | R24: Q2 2020 | S24: Completed | T24: Les Laboratoires Servier Acquires Symphogen | U24: Mergers & Acquisitions | V24: Acquisition | W24: 100% Acquisition | X24: Denmark | Y24: 100% Acquisition | Z24: Lazard Inc , Rothschild & Co Bank AG | AA24: Plesner , McDermott Will & Emery LLP , Perkins Coie LLP , Gorrissen Federspiel Advokatpartnerselskab | AB24: Les Laboratoires Servier SAS | AC24: les laboratoires servier | AD24: Symphogen A/S | AE24: symphogen a s | AG24: n/a | AH24: Les Laboratoires Servier SA, a pharmaceutical company, has completed the acquisition of Symphogen A/S, a therapeutic antibody discovery company. Following the transaction, Symphogen will now function as the antibody center of excellence of Servier in several different therapeutic areas including oncology. Symphogen, now a subsidiary of Servier, will keep its operational autonomy and continue to rely on its experienced employees while maintaining its headquarters in Ballerup, Denmark. As part of the acquisition, Christophe Thurieau, Executive Director of Servier Research Institute, has been appointed Chief Executive Officer of Symphogen and Karin Garre, former Chief Operating Officer of Symphogen, has been appointed General Manager of Symphogen. Martin Olin, former Chief Executive Officer of Symphogen, will act as an external consultant to support this transition. This transaction enables Servier to strengthen its R&D pipeline by acquiring antibody pipeline and next-generation antibody technologies. Lazard acted as financial advisor, while McDermott Will & Emery and Gorrissen Federspiel Advokatpartnerselskab acted as legal advisors to Servier. Rothschild & Co. acted as financial advisor and Plesner Advokatpartnerselskab and Perkins Coie LLP acted as legal advisors to Symphogen. Deal History: Announced: On April 3, 2020, Les Laboratoires Servier entered into a definitive agreement with the owners of Symphogen. | AI24: This transaction enables Servier to strengthen its R&D pipeline by acquiring antibody pipeline and next-generation antibody technologies. | AL24: Unknown | AM24: Unknown | AS24: Les Laboratoires Servier SAS | AT24: Symphogen A/S | AU24: Not reviewed | AV24: Not assessed | AW24: Unknown | AX24: Unknown | AY24: Unknown | AZ24: Unknown | BA24: Unknown | BB24: Unknown | BF24: Not collected | BG24: Not collected | BH24: Not defined | BI24: =IF($Q24="","",$Q24-3) -> 2017 | BJ24: =IF($Q24="","",$Q24-2) -> 2018 | BK24: =IF($Q24="","",$Q24-1) -> 2019 | BL24: =IF($Q24="","",$Q24+0) -> 2020 | BM24: =IF($Q24="","",$Q24+1) -> 2021 | BN24: =IF($Q24="","",$Q24+2) -> 2022 | BO24: =IF($Q24="","",$Q24+3) -> 2023 | EQ24: =IF(OR($EO24="",$EP24="",$EO24=0),"",$EP24/$EO24) | ES24: Unknown | ET24: Unknown | EU24: =IF(COUNT($DF24,$DG24,$DH24)=0,"",AVERAGE($DF24,$DG24,$DH24)) | EV24: =IF(COUNT($DJ24,$DK24,$DL24)=0,"",AVERAGE($DJ24,$DK24,$DL24)) | EW24: =IF(OR($EU24="",$EV24=""),"",$EV24-$EU24) | EX24: =IF(COUNT($DM24,$DN24,$DO24)=0,"",AVERAGE($DM24,$DN24,$DO24)) | EY24: =IF(COUNT($DQ24,$DR24,$DS24)=0,"",AVERAGE($DQ24,$DR24,$DS24)) | EZ24: =IF(OR($EX24="",$EY24=""),"",$EY24-$EX24) | FA24: =IF(COUNT($EA24,$EB24,$EC24)=0,"",AVERAGE($EA24,$EB24,$EC24)) | FB24: =IF(COUNT($EE24,$EF24,$EG24)=0,"",AVERAGE($EE24,$EF24,$EG24)) | FC24: =IF(OR($FA24="",$FB24=""),"",$FB24-$FA24) | FD24: =IF(COUNT($EH24,$EI24,$EJ24)=0,"",AVERAGE($EH24,$EI24,$EJ24)) | FE24: =IF(COUNT($EL24,$EM24,$EN24)=0,"",AVERAGE($EL24,$EM24,$EN24)) | FF24: =IF(OR($FD24="",$FE24=""),"",$FE24-$FD24) | FG24: =IF(COUNT($DF24,$DG24,$DH24,$DJ24,$DK24,$DL24,$DM24,$DN24,$DO24,$DQ24,$DR24,$DS24)=12,"Yes","No") -> No | FH24: =IF(COUNT($EA24,$EB24,$EC24,$EE24,$EF24,$EG24,$EH24,$EI24,$EJ24,$EL24,$EM24,$EN24)=12,"Yes","No") -> No | FI24: =IF(AND($M24="Include",OR($FG24="Yes",$FH24="Yes")),"Ready","Not ready") -> Not ready
A25: CTL-0023 | B25: 34 | C25: Candidate alternative-rationale group | D25: 0 | E25: DATA non-innovation deals.xlsx | F25: ovoca bio acquires remaining minority stake in ivix | G25: No | H25: No | I25: No | J25: 1 | K25: Not started | L25: Exclude - minority | M25: Review | O25: 43914 | P25: 43914 | Q25: 2020 | R25: Q1 2020 | S25: Completed | T25: Ovoca Bio Acquires Remaining Minority Stake in IVIX | U25: Mergers & Acquisitions | V25: Acquisition | W25: Minority Acquisition | X25: Russia | Y25: Minority Acquisition | AB25: Ovoca Bio Plc | AC25: ovoca bio | AD25: Ivix Ltd | AE25: ivix | AF25: 5 | AG25: 5 | AH25: Ovoca Bio, a biopharmaceutical company with a focus on women's health, has entered into an agreement to acquire the remaining shareholding in IVIX LLC (IVIX Ltd), for a total cash consideration of approximately approximately USD5 million. IVIX was the original developer of BP-101, a novel medicinal treatment for premenopausal women with hypoactive sexual desire disorder (HSDD) a condition characterized by a distressing lack or loss of sexual desire in women. In September 2018, Ovoca completed the acquisition of a 50.02% participation interest of IVIX, a Russian incorporated biopharmaceutical company, for a cash consideration of approximately USD4.1 million. As a result of the acquisition, Ovoca refocused its core business on biotechnology and particularly the continued development and commercialisation of BP-101. In March 2019, Ovoca exercised its right to acquire a further participation interest for approximately USD2 million, whereby the Company increased its holding to a 59.9% interest in the charter capital of IVIX. The transaction will allow Ovoca Bio to accelerate development of lead asset BP-101 for the treatment of HSDD. | AI25: The transaction will allow Ovoca Bio to accelerate development of lead asset BP-101 for the treatment of HSDD. | AL25: Unknown | AM25: Unknown | AS25: Ovoca Bio Plc | AT25: Ivix Ltd | AU25: Not reviewed | AV25: Not assessed | AW25: Unknown | AX25: Unknown | AY25: Unknown | AZ25: Unknown | BA25: Unknown | BB25: Unknown | BF25: Not collected | BG25: Not collected | BH25: Not defined | BI25: =IF($Q25="","",$Q25-3) -> 2017 | BJ25: =IF($Q25="","",$Q25-2) -> 2018 | BK25: =IF($Q25="","",$Q25-1) -> 2019 | BL25: =IF($Q25="","",$Q25+0) -> 2020 | BM25: =IF($Q25="","",$Q25+1) -> 2021 | BN25: =IF($Q25="","",$Q25+2) -> 2022 | BO25: =IF($Q25="","",$Q25+3) -> 2023 | EQ25: =IF(OR($EO25="",$EP25="",$EO25=0),"",$EP25/$EO25) | ES25: Unknown | ET25: Unknown | EU25: =IF(COUNT($DF25,$DG25,$DH25)=0,"",AVERAGE($DF25,$DG25,$DH25)) | EV25: =IF(COUNT($DJ25,$DK25,$DL25)=0,"",AVERAGE($DJ25,$DK25,$DL25)) | EW25: =IF(OR($EU25="",$EV25=""),"",$EV25-$EU25) | EX25: =IF(COUNT($DM25,$DN25,$DO25)=0,"",AVERAGE($DM25,$DN25,$DO25)) | EY25: =IF(COUNT($DQ25,$DR25,$DS25)=0,"",AVERAGE($DQ25,$DR25,$DS25)) | EZ25: =IF(OR($EX25="",$EY25=""),"",$EY25-$EX25) | FA25: =IF(COUNT($EA25,$EB25,$EC25)=0,"",AVERAGE($EA25,$EB25,$EC25)) | FB25: =IF(COUNT($EE25,$EF25,$EG25)=0,"",AVERAGE($EE25,$EF25,$EG25)) | FC25: =IF(OR($FA25="",$FB25=""),"",$FB25-$FA25) | FD25: =IF(COUNT($EH25,$EI25,$EJ25)=0,"",AVERAGE($EH25,$EI25,$EJ25)) | FE25: =IF(COUNT($EL25,$EM25,$EN25)=0,"",AVERAGE($EL25,$EM25,$EN25)) | FF25: =IF(OR($FD25="",$FE25=""),"",$FE25-$FD25) | FG25: =IF(COUNT($DF25,$DG25,$DH25,$DJ25,$DK25,$DL25,$DM25,$DN25,$DO25,$DQ25,$DR25,$DS25)=12,"Yes","No") -> No | FH25: =IF(COUNT($EA25,$EB25,$EC25,$EE25,$EF25,$EG25,$EH25,$EI25,$EJ25,$EL25,$EM25,$EN25)=12,"Yes","No") -> No | FI25: =IF(AND($M25="Include",OR($FG25="Yes",$FH25="Yes")),"Ready","Not ready") -> Not ready
A26: CTL-0024 | B26: 35 | C26: Candidate alternative-rationale group | D26: 0 | E26: DATA non-innovation deals.xlsx | F26: norgine acquires azanta | G26: No | H26: No | I26: No | J26: 1 | K26: Not started | L26: Eligible - 100% | M26: Review | O26: 43914 | P26: 43914 | Q26: 2020 | R26: Q1 2020 | S26: Completed | T26: Norgine Acquires Azanta | U26: Mergers & Acquisitions | V26: Acquisition | W26: 100% Acquisition | X26: Denmark | Y26: 100% Acquisition | Z26: PricewaterhouseCoopers International Ltd | AB26: Norgine BV | AC26: norgine | AD26: Azanta A/S | AE26: azanta a s | AG26: n/a | AH26: Norgine B.V., announces the acquisition of Azanta A/S, a biopharmaceutical company operating within women’s healthcare, addiction medicine and oncology. Azanta becomes a wholly-owned subsidiary of Norgine. As a result of the transaction, Norgine acquires Azanta’s portfolio of products, including Angusta for labour induction and Nimorazole, a hypoxic radiosensitizer for the treatment of head and neck cancer patients undergoing primary radiotherapy. Angusta was approved in first quarter of 2017 in the Nordics, and in fourth quarter of 2017 in France and 10 CEE countries. Regulatory approval for the rest of Europe is expected to be filed in first half of 2020. Nimorazole has EMA orphan drug status and is ready for Phase III stage development. Azanta is headquartered in Denmark with pharmaceutical sales subsidiaries in the other Nordic countries and in France. Norgine has a direct presence in 12 European countries, as well as Australia and New Zealand and has a track-record of bringing products to market across Europe. This acquisition strengthens Norgine’s business in Europe. | AI26: This acquisition strengthens Norgine’s business in Europe. | AL26: Unknown | AM26: Unknown | AS26: Norgine BV | AT26: Azanta A/S | AU26: Not reviewed | AV26: Not assessed | AW26: Unknown | AX26: Unknown | AY26: Unknown | AZ26: Unknown | BA26: Unknown | BB26: Unknown | BF26: Not collected | BG26: Not collected | BH26: Not defined | BI26: =IF($Q26="","",$Q26-3) -> 2017 | BJ26: =IF($Q26="","",$Q26-2) -> 2018 | BK26: =IF($Q26="","",$Q26-1) -> 2019 | BL26: =IF($Q26="","",$Q26+0) -> 2020 | BM26: =IF($Q26="","",$Q26+1) -> 2021 | BN26: =IF($Q26="","",$Q26+2) -> 2022 | BO26: =IF($Q26="","",$Q26+3) -> 2023 | EQ26: =IF(OR($EO26="",$EP26="",$EO26=0),"",$EP26/$EO26) | ES26: Unknown | ET26: Unknown | EU26: =IF(COUNT($DF26,$DG26,$DH26)=0,"",AVERAGE($DF26,$DG26,$DH26)) | EV26: =IF(COUNT($DJ26,$DK26,$DL26)=0,"",AVERAGE($DJ26,$DK26,$DL26)) | EW26: =IF(OR($EU26="",$EV26=""),"",$EV26-$EU26) | EX26: =IF(COUNT($DM26,$DN26,$DO26)=0,"",AVERAGE($DM26,$DN26,$DO26)) | EY26: =IF(COUNT($DQ26,$DR26,$DS26)=0,"",AVERAGE($DQ26,$DR26,$DS26)) | EZ26: =IF(OR($EX26="",$EY26=""),"",$EY26-$EX26) | FA26: =IF(COUNT($EA26,$EB26,$EC26)=0,"",AVERAGE($EA26,$EB26,$EC26)) | FB26: =IF(COUNT($EE26,$EF26,$EG26)=0,"",AVERAGE($EE26,$EF26,$EG26)) | FC26: =IF(OR($FA26="",$FB26=""),"",$FB26-$FA26) | FD26: =IF(COUNT($EH26,$EI26,$EJ26)=0,"",AVERAGE($EH26,$EI26,$EJ26)) | FE26: =IF(COUNT($EL26,$EM26,$EN26)=0,"",AVERAGE($EL26,$EM26,$EN26)) | FF26: =IF(OR($FD26="",$FE26=""),"",$FE26-$FD26) | FG26: =IF(COUNT($DF26,$DG26,$DH26,$DJ26,$DK26,$DL26,$DM26,$DN26,$DO26,$DQ26,$DR26,$DS26)=12,"Yes","No") -> No | FH26: =IF(COUNT($EA26,$EB26,$EC26,$EE26,$EF26,$EG26,$EH26,$EI26,$EJ26,$EL26,$EM26,$EN26)=12,"Yes","No") -> No | FI26: =IF(AND($M26="Include",OR($FG26="Yes",$FH26="Yes")),"Ready","Not ready") -> Not ready
A27: CTL-0025 | B27: 36 | C27: Candidate alternative-rationale group | D27: 0 | E27: DATA non-innovation deals.xlsx | F27: dermapharm acquires allergopharma from merck | G27: No | H27: No | I27: Yes | J27: 3 | K27: Not started | L27: Eligible - 100% | M27: Review | O27: 43880 | P27: 43921 | Q27: 2020 | R27: Q1 2020 | S27: Completed | T27: Dermapharm Acquires Allergopharma from Merck | U27: Mergers & Acquisitions | V27: Acquisition | W27: 100% Acquisition | X27: Germany | Y27: 100% Acquisition | Z27: FERBER & CO. GmbH , goetzpartners , Deloitte & Touche Corporate Finance GmbH | AA27: Cleary Gottlieb Steen & Hamilton LLP , Cleary Gottlieb Steen & Hamilton LLP , P+P Pollath + Partners , Clifford Chance LLP (Germany) | AB27: Dermapharm Holding SE | AC27: dermapharm | AD27: Allergopharma GmbH & Co KG | AE27: allergopharma kg | AG27: n/a | AH27: Dermapharm Holding SE, a manufacturer of off-patent branded medicines, has acquired Allergopharma GmbH & Co KG, a manufacturer of diagnostics and prescription drugs for allergen immunotherapy (AIT), from Merck KGaA, a science and technology company, following regulatory approval and the satisfaction of other customary closing conditions. With the transaction closing, the Merck's Healthcare business sector will further sharpen its focus on the development of innovative medicines for difficult-to-treat diseases. The divestment to Dermapharm sustainably strengthens the business of Allergopharma. The allergy business of Merck in Europe was transferred to Dermapharm on March 31. The transfer of the Allergopharma business in China is planned for the second half of 2020. Deal History: Announced: On February 19, 2020, Dermapharm agreed to acquire Allergopharma from Merck. Rumor: On January 9, 2020, Merck intended to sell Allergopharma, according to the sources, citing people familiar with the matter. Earlier in 2015, Merck intended to sell Allergopharma for EUR600 million, according to the sources. | AI27: The divestment to Dermapharm sustainably strengthens the business of Allergopharma. | AL27: Unknown | AM27: Unknown | AS27: Dermapharm Holding SE | AT27: Allergopharma GmbH & Co KG | AU27: Not reviewed | AV27: Not assessed | AW27: Unknown | AX27: Unknown | AY27: Unknown | AZ27: Unknown | BA27: Unknown | BB27: Unknown | BF27: Not collected | BG27: Not collected | BH27: Not defined | BI27: =IF($Q27="","",$Q27-3) -> 2017 | BJ27: =IF($Q27="","",$Q27-2) -> 2018 | BK27: =IF($Q27="","",$Q27-1) -> 2019 | BL27: =IF($Q27="","",$Q27+0) -> 2020 | BM27: =IF($Q27="","",$Q27+1) -> 2021 | BN27: =IF($Q27="","",$Q27+2) -> 2022 | BO27: =IF($Q27="","",$Q27+3) -> 2023 | EQ27: =IF(OR($EO27="",$EP27="",$EO27=0),"",$EP27/$EO27) | ES27: Unknown | ET27: Unknown | EU27: =IF(COUNT($DF27,$DG27,$DH27)=0,"",AVERAGE($DF27,$DG27,$DH27)) | EV27: =IF(COUNT($DJ27,$DK27,$DL27)=0,"",AVERAGE($DJ27,$DK27,$DL27)) | EW27: =IF(OR($EU27="",$EV27=""),"",$EV27-$EU27) | EX27: =IF(COUNT($DM27,$DN27,$DO27)=0,"",AVERAGE($DM27,$DN27,$DO27)) | EY27: =IF(COUNT($DQ27,$DR27,$DS27)=0,"",AVERAGE($DQ27,$DR27,$DS27)) | EZ27: =IF(OR($EX27="",$EY27=""),"",$EY27-$EX27) | FA27: =IF(COUNT($EA27,$EB27,$EC27)=0,"",AVERAGE($EA27,$EB27,$EC27)) | FB27: =IF(COUNT($EE27,$EF27,$EG27)=0,"",AVERAGE($EE27,$EF27,$EG27)) | FC27: =IF(OR($FA27="",$FB27=""),"",$FB27-$FA27) | FD27: =IF(COUNT($EH27,$EI27,$EJ27)=0,"",AVERAGE($EH27,$EI27,$EJ27)) | FE27: =IF(COUNT($EL27,$EM27,$EN27)=0,"",AVERAGE($EL27,$EM27,$EN27)) | FF27: =IF(OR($FD27="",$FE27=""),"",$FE27-$FD27) | FG27: =IF(COUNT($DF27,$DG27,$DH27,$DJ27,$DK27,$DL27,$DM27,$DN27,$DO27,$DQ27,$DR27,$DS27)=12,"Yes","No") -> No | FH27: =IF(COUNT($EA27,$EB27,$EC27,$EE27,$EF27,$EG27,$EH27,$EI27,$EJ27,$EL27,$EM27,$EN27)=12,"Yes","No") -> No | FI27: =IF(AND($M27="Include",OR($FG27="Yes",$FH27="Yes")),"Ready","Not ready") -> Not ready
A28: CTL-0026 | B28: 37 | C28: Candidate alternative-rationale group | D28: 0 | E28: DATA non-innovation deals.xlsx | F28: laboratoires equilibre acquires labcatal | G28: No | H28: No | I28: No | J28: 1 | K28: Not started | L28: Eligible - 100% | M28: Review | O28: 43875 | P28: 43875 | Q28: 2020 | R28: Q1 2020 | S28: Completed | T28: Laboratoires Equilibre Acquires Labcatal | U28: Mergers & Acquisitions | V28: Acquisition | W28: 100% Acquisition | X28: France | Y28: 100% Acquisition | AB28: Laboratoires Equilibre Attitude | AC28: laboratoires equilibre attitude | AD28: Labcatal | AE28: labcatal | AG28: n/a | AH28: Laboratoires Equilibre Attitude (Equilibre), a developer, manufacturer and distributor of products for sport nutrition, fitness, health, and weight loss, has acquired Labcatal, a developer and manufacturer of pharmacy products include Oligo-elements-based drugs and dermatological drugs. The acquisition will allow Equilibre to democratize a modern Oligotherapy bearing strong values: efficiency, naturalness and safety. | AI28: The acquisition will allow Equilibre to democratize a modern Oligotherapy bearing strong values: efficiency, naturalness and safety. | AL28: Unknown | AM28: Unknown | AS28: Laboratoires Equilibre Attitude | AT28: Labcatal | AU28: Not reviewed | AV28: Not assessed | AW28: Unknown | AX28: Unknown | AY28: Unknown | AZ28: Unknown | BA28: Unknown | BB28: Unknown | BF28: Not collected | BG28: Not collected | BH28: Not defined | BI28: =IF($Q28="","",$Q28-3) -> 2017 | BJ28: =IF($Q28="","",$Q28-2) -> 2018 | BK28: =IF($Q28="","",$Q28-1) -> 2019 | BL28: =IF($Q28="","",$Q28+0) -> 2020 | BM28: =IF($Q28="","",$Q28+1) -> 2021 | BN28: =IF($Q28="","",$Q28+2) -> 2022 | BO28: =IF($Q28="","",$Q28+3) -> 2023 | EQ28: =IF(OR($EO28="",$EP28="",$EO28=0),"",$EP28/$EO28) | ES28: Unknown | ET28: Unknown | EU28: =IF(COUNT($DF28,$DG28,$DH28)=0,"",AVERAGE($DF28,$DG28,$DH28)) | EV28: =IF(COUNT($DJ28,$DK28,$DL28)=0,"",AVERAGE($DJ28,$DK28,$DL28)) | EW28: =IF(OR($EU28="",$EV28=""),"",$EV28-$EU28) | EX28: =IF(COUNT($DM28,$DN28,$DO28)=0,"",AVERAGE($DM28,$DN28,$DO28)) | EY28: =IF(COUNT($DQ28,$DR28,$DS28)=0,"",AVERAGE($DQ28,$DR28,$DS28)) | EZ28: =IF(OR($EX28="",$EY28=""),"",$EY28-$EX28) | FA28: =IF(COUNT($EA28,$EB28,$EC28)=0,"",AVERAGE($EA28,$EB28,$EC28)) | FB28: =IF(COUNT($EE28,$EF28,$EG28)=0,"",AVERAGE($EE28,$EF28,$EG28)) | FC28: =IF(OR($FA28="",$FB28=""),"",$FB28-$FA28) | FD28: =IF(COUNT($EH28,$EI28,$EJ28)=0,"",AVERAGE($EH28,$EI28,$EJ28)) | FE28: =IF(COUNT($EL28,$EM28,$EN28)=0,"",AVERAGE($EL28,$EM28,$EN28)) | FF28: =IF(OR($FD28="",$FE28=""),"",$FE28-$FD28) | FG28: =IF(COUNT($DF28,$DG28,$DH28,$DJ28,$DK28,$DL28,$DM28,$DN28,$DO28,$DQ28,$DR28,$DS28)=12,"Yes","No") -> No | FH28: =IF(COUNT($EA28,$EB28,$EC28,$EE28,$EF28,$EG28,$EH28,$EI28,$EJ28,$EL28,$EM28,$EN28)=12,"Yes","No") -> No | FI28: =IF(AND($M28="Include",OR($FG28="Yes",$FH28="Yes")),"Ready","Not ready") -> Not ready
A29: CTL-0027 | B29: 38 | C29: Candidate alternative-rationale group | D29: 0 | E29: DATA non-innovation deals.xlsx | F29: galen acquires poa pharma scandinavia | G29: No | H29: No | I29: No | J29: 1 | K29: Not started | L29: Eligible - 100% | M29: Review | O29: 43838 | P29: 43838 | Q29: 2020 | R29: Q1 2020 | S29: Completed | T29: Galen Acquires POA Pharma Scandinavia | U29: Mergers & Acquisitions | V29: Acquisition | W29: 100% Acquisition | X29: Sweden | Y29: 100% Acquisition | AB29: Chilcott UK Ltd | AC29: chilcott uk | AD29: POA Pharma Scandinavia AB | AE29: poa pharma scandinavia ab | AG29: n/a | AH29: Galen, a pharmaceutical sales and marketing company, announced the completion of a multi-million pound acquisition and takeover of POA Pharma Scandinavia AB, a pharmaceutical company. The acquisition enable Galen to expand its global reach and product portfolio in exciting new therapy areas, such as rare metabolic disease. | AI29: The acquisition enable Galen to expand its global reach and product portfolio in exciting new therapy areas, such as rare metabolic disease. | AL29: Unknown | AM29: Unknown | AS29: Chilcott UK Ltd | AT29: POA Pharma Scandinavia AB | AU29: Not reviewed | AV29: Not assessed | AW29: Unknown | AX29: Unknown | AY29: Unknown | AZ29: Unknown | BA29: Unknown | BB29: Unknown | BF29: Not collected | BG29: Not collected | BH29: Not defined | BI29: =IF($Q29="","",$Q29-3) -> 2017 | BJ29: =IF($Q29="","",$Q29-2) -> 2018 | BK29: =IF($Q29="","",$Q29-1) -> 2019 | BL29: =IF($Q29="","",$Q29+0) -> 2020 | BM29: =IF($Q29="","",$Q29+1) -> 2021 | BN29: =IF($Q29="","",$Q29+2) -> 2022 | BO29: =IF($Q29="","",$Q29+3) -> 2023 | EQ29: =IF(OR($EO29="",$EP29="",$EO29=0),"",$EP29/$EO29) | ES29: Unknown | ET29: Unknown | EU29: =IF(COUNT($DF29,$DG29,$DH29)=0,"",AVERAGE($DF29,$DG29,$DH29)) | EV29: =IF(COUNT($DJ29,$DK29,$DL29)=0,"",AVERAGE($DJ29,$DK29,$DL29)) | EW29: =IF(OR($EU29="",$EV29=""),"",$EV29-$EU29) | EX29: =IF(COUNT($DM29,$DN29,$DO29)=0,"",AVERAGE($DM29,$DN29,$DO29)) | EY29: =IF(COUNT($DQ29,$DR29,$DS29)=0,"",AVERAGE($DQ29,$DR29,$DS29)) | EZ29: =IF(OR($EX29="",$EY29=""),"",$EY29-$EX29) | FA29: =IF(COUNT($EA29,$EB29,$EC29)=0,"",AVERAGE($EA29,$EB29,$EC29)) | FB29: =IF(COUNT($EE29,$EF29,$EG29)=0,"",AVERAGE($EE29,$EF29,$EG29)) | FC29: =IF(OR($FA29="",$FB29=""),"",$FB29-$FA29) | FD29: =IF(COUNT($EH29,$EI29,$EJ29)=0,"",AVERAGE($EH29,$EI29,$EJ29)) | FE29: =IF(COUNT($EL29,$EM29,$EN29)=0,"",AVERAGE($EL29,$EM29,$EN29)) | FF29: =IF(OR($FD29="",$FE29=""),"",$FE29-$FD29) | FG29: =IF(COUNT($DF29,$DG29,$DH29,$DJ29,$DK29,$DL29,$DM29,$DN29,$DO29,$DQ29,$DR29,$DS29)=12,"Yes","No") -> No | FH29: =IF(COUNT($EA29,$EB29,$EC29,$EE29,$EF29,$EG29,$EH29,$EI29,$EJ29,$EL29,$EM29,$EN29)=12,"Yes","No") -> No | FI29: =IF(AND($M29="Include",OR($FG29="Yes",$FH29="Yes")),"Ready","Not ready") -> Not ready
A30: CTL-0028 | B30: 39 | C30: Candidate alternative-rationale group | D30: 0 | E30: DATA non-innovation deals.xlsx | F30: esteve pharma acquires riemser pharma from ardian | G30: No | H30: No | I30: No | J30: 1 | K30: Not started | L30: Eligible - 100% | M30: Review | O30: 43838 | P30: 43868 | Q30: 2020 | R30: Q1 2020 | S30: Completed | T30: Esteve Pharma Acquires Riemser Pharma from Ardian | U30: Mergers & Acquisitions | V30: Acquisition | W30: 100% Acquisition | X30: Germany | Y30: 100% Acquisition | Z30: Rothschild & Co SCA , PricewaterhouseCoopers International Ltd , Ernst & Young Global Ltd | AA30: NOVACOS Rechtsanwalte , Hogan Lovells International LLP , Willkie Farr & Gallagher LLP | AB30: Esteve Pharmaceuticals SA | AC30: esteve pharmaceuticals | AD30: ESTEVE Pharmaceuticals GmbH | AE30: esteve pharmaceuticals | AG30: n/a | AH30: Esteve Pharmaceuticals SA, a pharmaceutical company, has acquired 100% of the shares in Riemser Pharma GmbH, a pharmaceutical company from Ardian, an investment company. The product portfolio of Riemser comprises the three main therapy areas oncology, neurology and niche therapies. Riemser operates a pharmaceutical production facility in Germany and is represented in four of the five most important European countries with a company headquarters or a subsidiary: Germany, Great Britain, France and Spain. RIEMSER generates around 80% of its sales with products for clinical use, especially specialty pharmaceuticals and a wide range of medicinal products for therapeutic niche areas. Through the acquisition, Esteve is also expanding its access to the hospital market. This acquisition will enable Esteve Pharma to accelerate its transformation into a specialty pharma company. Deal History: On January 8, 2020, Esteve Pharmaceuticals SA, has entered into an agreement to acquire 100% of the shares in Riemser Pharma GmbH, a pharmaceutical company from Ardian, an investment company. | AI30: This acquisition will enable Esteve Pharma to accelerate its transformation into a specialty pharma company. | AL30: Unknown | AM30: Unknown | AN30: 0646926D SM | AS30: Esteve Pharmaceuticals SA | AT30: ESTEVE Pharmaceuticals GmbH | AU30: Not reviewed | AV30: Not assessed | AW30: Unknown | AX30: Unknown | AY30: Unknown | AZ30: Unknown | BA30: Unknown | BB30: Unknown | BE30: EUR | BF30: Partial | BG30: Not imported — source export failed company-alias validation | BH30: Uploaded export does not contain Esteve applicants/owners; it contains Samyang entities. Preserved for audit but not imported. | BI30: =IF($Q30="","",$Q30-3) -> 2017 | BJ30: =IF($Q30="","",$Q30-2) -> 2018 | BK30: =IF($Q30="","",$Q30-1) -> 2019 | BL30: =IF($Q30="","",$Q30+0) -> 2020 | BM30: =IF($Q30="","",$Q30+1) -> 2021 | BN30: =IF($Q30="","",$Q30+2) -> 2022 | BO30: =IF($Q30="","",$Q30+3) -> 2023 | BP30: 21.7254 | BQ30: 16.6488 | BR30: 174.3453 | BS30: 6.5 | BT30: 54.348 | BW30: 19.8088 | BX30: 12.6743 | BY30: 166.8558 | BZ30: -23.2304 | CA30: 46.584 | CD30: 19.6108 | CE30: 16.2293 | CF30: 168.7513 | CG30: 66.1837 | CH30: 42.709 | CK30: 458.8717 | CL30: 538.6484 | CM30: 890.9543 | CN30: 851.7258 | CO30: 779.869 | CR30: 0 | CS30: 17.1185 | CT30: 23.5852 | CU30: 30.0069 | CV30: 0.021 | DF30: 4.4884 | DG30: 3.2539 | DH30: 23.6081 | DI30: 7.5956 | DJ30: 5.2352 | DM30: 91.1781 | DN30: 76.1274 | DO30: 95.7042 | DP30: -357.3914 | DQ30: 85.7143 | DT30: 0 | DU30: 3.178 | DV30: 2.6472 | DW30: 3.5231 | DX30: 0.0027 | EQ30: =IF(OR($EO30="",$EP30="",$EO30=0),"",$EP30/$EO30) | ES30: Unknown | ET30: Unknown | EU30: =IF(COUNT($DF30,$DG30,$DH30)=0,"",AVERAGE($DF30,$DG30,$DH30)) -> 10.450133 | EV30: =IF(COUNT($DJ30,$DK30,$DL30)=0,"",AVERAGE($DJ30,$DK30,$DL30)) -> 5.2352 | EW30: =IF(OR($EU30="",$EV30=""),"",$EV30-$EU30) -> -5.2149333 | EX30: =IF(COUNT($DM30,$DN30,$DO30)=0,"",AVERAGE($DM30,$DN30,$DO30)) -> 87.6699 | EY30: =IF(COUNT($DQ30,$DR30,$DS30)=0,"",AVERAGE($DQ30,$DR30,$DS30)) -> 85.7143 | EZ30: =IF(OR($EX30="",$EY30=""),"",$EY30-$EX30) -> -1.9556 | FA30: =IF(COUNT($EA30,$EB30,$EC30)=0,"",AVERAGE($EA30,$EB30,$EC30)) | FB30: =IF(COUNT($EE30,$EF30,$EG30)=0,"",AVERAGE($EE30,$EF30,$EG30)) | FC30: =IF(OR($FA30="",$FB30=""),"",$FB30-$FA30) | FD30: =IF(COUNT($EH30,$EI30,$EJ30)=0,"",AVERAGE($EH30,$EI30,$EJ30)) | FE30: =IF(COUNT($EL30,$EM30,$EN30)=0,"",AVERAGE($EL30,$EM30,$EN30)) | FF30: =IF(OR($FD30="",$FE30=""),"",$FE30-$FD30) | FG30: =IF(COUNT($DF30,$DG30,$DH30,$DJ30,$DK30,$DL30,$DM30,$DN30,$DO30,$DQ30,$DR30,$DS30)=12,"Yes","No") -> No | FH30: =IF(COUNT($EA30,$EB30,$EC30,$EE30,$EF30,$EG30,$EH30,$EI30,$EJ30,$EL30,$EM30,$EN30)=12,"Yes","No") -> No | FI30: =IF(AND($M30="Include",OR($FG30="Yes",$FH30="Yes")),"Ready","Not ready") -> Not ready
A31: CTL-0029 | B31: 40 | C31: Candidate alternative-rationale group | D31: 0 | E31: DATA non-innovation deals.xlsx | F31: towa pharma acquires pensa investments | G31: Yes | H31: No | I31: No | J31: 1 | K31: Not started | L31: Eligible - 100% | M31: Review | O31: 43822 | P31: 43861 | Q31: 2020 | R31: Q4 2019 | S31: Completed | T31: Towa Pharma Acquires Pensa Investments | U31: Mergers & Acquisitions | V31: Acquisition | W31: 100% Acquisition | X31: Spain | Y31: 100% Acquisition | Z31: Lazard Inc , Barclays Plc | AA31: Nishimura & Asahi , Clifford Chance LLP , Gomez-Acebo & Pombo Abogados SLP | AB31: Towa Pharmaceutical Co Ltd | AC31: towa pharmaceutical | AD31: Pensa Investments, S.L. | AE31: pensa investments s l | AF31: 354 | AG31: 354 | AH31: Towa Pharmaceutical Co. Ltd., a company engaged in the manufacture and distribution of pharmaceutical products, has completed its acquisition of Pensa Investments, S.L., a company that provides affiliate pharmaceutical manufacturing facilities including pharmaceutical development, from Esteve Pharmaceuticals, S.A., a pharmaceutical company. Breckenridge Pharma announced Towa Pharma completed its acquisition of Esteve’s generics division, including Breckenridge. The purchase price of Pensa will be an all cash deal with an upfront payment of EUR320 million. The transaction will allow Towa Pharma to accelerate its overseas business presence and to provide quality and value-added generic medicines to patients in all over world. Deal History: Announced: On December 21, 2019, Towa Pharma reached an agreement to acquire 100% stake in Pensa Investments from Esteve Pharma. | AI31: The transaction will allow Towa Pharma to accelerate its overseas business presence and to provide quality and value-added generic medicines to patients in all over world. | AL31: Unknown | AM31: Unknown | AS31: Towa Pharmaceutical Co Ltd | AT31: Pensa Investments, S.L. | AU31: Not reviewed | AV31: Not assessed | AW31: Unknown | AX31: Unknown | AY31: Unknown | AZ31: Unknown | BA31: Unknown | BB31: Unknown | BF31: Not collected | BG31: Not collected | BH31: Not defined | BI31: =IF($Q31="","",$Q31-3) -> 2017 | BJ31: =IF($Q31="","",$Q31-2) -> 2018 | BK31: =IF($Q31="","",$Q31-1) -> 2019 | BL31: =IF($Q31="","",$Q31+0) -> 2020 | BM31: =IF($Q31="","",$Q31+1) -> 2021 | BN31: =IF($Q31="","",$Q31+2) -> 2022 | BO31: =IF($Q31="","",$Q31+3) -> 2023 | EQ31: =IF(OR($EO31="",$EP31="",$EO31=0),"",$EP31/$EO31) | ES31: Unknown | ET31: Unknown | EU31: =IF(COUNT($DF31,$DG31,$DH31)=0,"",AVERAGE($DF31,$DG31,$DH31)) | EV31: =IF(COUNT($DJ31,$DK31,$DL31)=0,"",AVERAGE($DJ31,$DK31,$DL31)) | EW31: =IF(OR($EU31="",$EV31=""),"",$EV31-$EU31) | EX31: =IF(COUNT($DM31,$DN31,$DO31)=0,"",AVERAGE($DM31,$DN31,$DO31)) | EY31: =IF(COUNT($DQ31,$DR31,$DS31)=0,"",AVERAGE($DQ31,$DR31,$DS31)) | EZ31: =IF(OR($EX31="",$EY31=""),"",$EY31-$EX31) | FA31: =IF(COUNT($EA31,$EB31,$EC31)=0,"",AVERAGE($EA31,$EB31,$EC31)) | FB31: =IF(COUNT($EE31,$EF31,$EG31)=0,"",AVERAGE($EE31,$EF31,$EG31)) | FC31: =IF(OR($FA31="",$FB31=""),"",$FB31-$FA31) | FD31: =IF(COUNT($EH31,$EI31,$EJ31)=0,"",AVERAGE($EH31,$EI31,$EJ31)) | FE31: =IF(COUNT($EL31,$EM31,$EN31)=0,"",AVERAGE($EL31,$EM31,$EN31)) | FF31: =IF(OR($FD31="",$FE31=""),"",$FE31-$FD31) | FG31: =IF(COUNT($DF31,$DG31,$DH31,$DJ31,$DK31,$DL31,$DM31,$DN31,$DO31,$DQ31,$DR31,$DS31)=12,"Yes","No") -> No | FH31: =IF(COUNT($EA31,$EB31,$EC31,$EE31,$EF31,$EG31,$EH31,$EI31,$EJ31,$EL31,$EM31,$EN31)=12,"Yes","No") -> No | FI31: =IF(AND($M31="Include",OR($FG31="Yes",$FH31="Yes")),"Ready","Not ready") -> Not ready
A32: CTL-0030 | B32: 41 | C32: Candidate alternative-rationale group | D32: 0 | E32: DATA non-innovation deals.xlsx | F32: curium pharma acquires map medical technologies | G32: No | H32: No | I32: No | J32: 1 | K32: Not started | L32: Eligible - 100% | M32: Review | O32: 43801 | P32: 43801 | Q32: 2019 | R32: Q4 2019 | S32: Completed | T32: Curium Pharma Acquires MAP Medical Technologies | U32: Mergers & Acquisitions | V32: Acquisition | W32: 100% Acquisition | X32: Finland | Y32: 100% Acquisition | AA32: Krogerus Attorneys Ltd , Morgan, Lewis & Bockius LLP | AB32: Curium Holding France SAS | AC32: curium france | AD32: MAP Medical Technologies Oy | AE32: map medical technologies oy | AG32: n/a | AH32: Curium Pharma LLC, a radiopharmaceutical product manufacturer, has completed the acquisition of MAP Medical Technologies Oy, a radiopharmaceuticals company. MAP Medical operates three GMP manufacturing sites across Finland, two in Helsinki and one in Tikkakoski, and has been supplying critical radiopharmaceutical agents to customers across Nordics and Baltics since 1991. The Company employs c.50 people and offers a range of PET diagnostic agents. It is also a distributor of Curium’s SPECT product portfolio in Finland. This acquisition further expand Curium’s footprint in Europe, providing direct access to Nordic and Baltic countries for its broad portfolio of life saving diagnostic solutions. Morgan, Lewis & Bockius LLP and Krogerus Attorneys Ltd acted as legal advisors for Curium Pharma. | AI32: This acquisition further expand Curium’s footprint in Europe, providing direct access to Nordic and Baltic countries for its broad portfolio of life saving diagnostic solutions. | AL32: Unknown | AM32: Unknown | AS32: Curium Holding France SAS | AT32: MAP Medical Technologies Oy | AU32: Not reviewed | AV32: Not assessed | AW32: Unknown | AX32: Unknown | AY32: Unknown | AZ32: Unknown | BA32: Unknown | BB32: Unknown | BF32: Not collected | BG32: Not collected | BH32: Not defined | BI32: =IF($Q32="","",$Q32-3) -> 2016 | BJ32: =IF($Q32="","",$Q32-2) -> 2017 | BK32: =IF($Q32="","",$Q32-1) -> 2018 | BL32: =IF($Q32="","",$Q32+0) -> 2019 | BM32: =IF($Q32="","",$Q32+1) -> 2020 | BN32: =IF($Q32="","",$Q32+2) -> 2021 | BO32: =IF($Q32="","",$Q32+3) -> 2022 | EQ32: =IF(OR($EO32="",$EP32="",$EO32=0),"",$EP32/$EO32) | ES32: Unknown | ET32: Unknown | EU32: =IF(COUNT($DF32,$DG32,$DH32)=0,"",AVERAGE($DF32,$DG32,$DH32)) | EV32: =IF(COUNT($DJ32,$DK32,$DL32)=0,"",AVERAGE($DJ32,$DK32,$DL32)) | EW32: =IF(OR($EU32="",$EV32=""),"",$EV32-$EU32) | EX32: =IF(COUNT($DM32,$DN32,$DO32)=0,"",AVERAGE($DM32,$DN32,$DO32)) | EY32: =IF(COUNT($DQ32,$DR32,$DS32)=0,"",AVERAGE($DQ32,$DR32,$DS32)) | EZ32: =IF(OR($EX32="",$EY32=""),"",$EY32-$EX32) | FA32: =IF(COUNT($EA32,$EB32,$EC32)=0,"",AVERAGE($EA32,$EB32,$EC32)) | FB32: =IF(COUNT($EE32,$EF32,$EG32)=0,"",AVERAGE($EE32,$EF32,$EG32)) | FC32: =IF(OR($FA32="",$FB32=""),"",$FB32-$FA32) | FD32: =IF(COUNT($EH32,$EI32,$EJ32)=0,"",AVERAGE($EH32,$EI32,$EJ32)) | FE32: =IF(COUNT($EL32,$EM32,$EN32)=0,"",AVERAGE($EL32,$EM32,$EN32)) | FF32: =IF(OR($FD32="",$FE32=""),"",$FE32-$FD32) | FG32: =IF(COUNT($DF32,$DG32,$DH32,$DJ32,$DK32,$DL32,$DM32,$DN32,$DO32,$DQ32,$DR32,$DS32)=12,"Yes","No") -> No | FH32: =IF(COUNT($EA32,$EB32,$EC32,$EE32,$EF32,$EG32,$EH32,$EI32,$EJ32,$EL32,$EM32,$EN32)=12,"Yes","No") -> No | FI32: =IF(AND($M32="Include",OR($FG32="Yes",$FH32="Yes")),"Ready","Not ready") -> Not ready
A33: CTL-0031 | B33: 42 | C33: Candidate alternative-rationale group | D33: 0 | E33: DATA non-innovation deals.xlsx | F33: biocodex acquires iprad | G33: No | H33: No | I33: No | J33: 1 | K33: Not started | L33: Eligible - 100% | M33: Review | O33: 43787 | P33: 43836 | Q33: 2020 | R33: Q4 2019 | S33: Completed | T33: Biocodex Acquires IPRAD | U33: Mergers & Acquisitions | V33: Acquisition | W33: 100% Acquisition | X33: France | Y33: 100% Acquisition | Z33: Stifel Europe Ltd | AB33: Biocodex | AC33: biocodex | AD33: Iprad Sante SA | AE33: iprad sante | AG33: n/a | AH33: Biocodex, a pharmaceutical company, has announced the acquisition of Laboratoires Iprad (Iprad Sante SA), a pharmaceutical company. The new dynamic that will emerge from the complementarity of these two companies will consolidate the growth of the two entities. It will strengthen their respective positions in France and accelerate the international development of IPRAD Laboratories' products. Bryan, Garnier & Co acted as financial advisor to Biocodex. The transaction is subject to the information and authorization procedures provided for by the regulations in force, including the approval of the French Competition Authority, and should be effective from January 2020. Deal History: Planning: On November 18, 2019, Biocodex entered into exclusive negotiations for the acquisition of Laboratoires Iprad, | AI33: The new dynamic that will emerge from the complementarity of Biocodex and IPRAD will consolidate the growth of the two entities. It will strengthen their respective positions in France and accelerate the international development of IPRAD Laboratories' products. | AL33: Unknown | AM33: Unknown | AS33: Biocodex | AT33: Iprad Sante SA | AU33: Not reviewed | AV33: Not assessed | AW33: Unknown | AX33: Unknown | AY33: Unknown | AZ33: Unknown | BA33: Unknown | BB33: Unknown | BF33: Not collected | BG33: Not collected | BH33: Not defined | BI33: =IF($Q33="","",$Q33-3) -> 2017 | BJ33: =IF($Q33="","",$Q33-2) -> 2018 | BK33: =IF($Q33="","",$Q33-1) -> 2019 | BL33: =IF($Q33="","",$Q33+0) -> 2020 | BM33: =IF($Q33="","",$Q33+1) -> 2021 | BN33: =IF($Q33="","",$Q33+2) -> 2022 | BO33: =IF($Q33="","",$Q33+3) -> 2023 | EQ33: =IF(OR($EO33="",$EP33="",$EO33=0),"",$EP33/$EO33) | ES33: Unknown | ET33: Unknown | EU33: =IF(COUNT($DF33,$DG33,$DH33)=0,"",AVERAGE($DF33,$DG33,$DH33)) | EV33: =IF(COUNT($DJ33,$DK33,$DL33)=0,"",AVERAGE($DJ33,$DK33,$DL33)) | EW33: =IF(OR($EU33="",$EV33=""),"",$EV33-$EU33) | EX33: =IF(COUNT($DM33,$DN33,$DO33)=0,"",AVERAGE($DM33,$DN33,$DO33)) | EY33: =IF(COUNT($DQ33,$DR33,$DS33)=0,"",AVERAGE($DQ33,$DR33,$DS33)) | EZ33: =IF(OR($EX33="",$EY33=""),"",$EY33-$EX33) | FA33: =IF(COUNT($EA33,$EB33,$EC33)=0,"",AVERAGE($EA33,$EB33,$EC33)) | FB33: =IF(COUNT($EE33,$EF33,$EG33)=0,"",AVERAGE($EE33,$EF33,$EG33)) | FC33: =IF(OR($FA33="",$FB33=""),"",$FB33-$FA33) | FD33: =IF(COUNT($EH33,$EI33,$EJ33)=0,"",AVERAGE($EH33,$EI33,$EJ33)) | FE33: =IF(COUNT($EL33,$EM33,$EN33)=0,"",AVERAGE($EL33,$EM33,$EN33)) | FF33: =IF(OR($FD33="",$FE33=""),"",$FE33-$FD33) | FG33: =IF(COUNT($DF33,$DG33,$DH33,$DJ33,$DK33,$DL33,$DM33,$DN33,$DO33,$DQ33,$DR33,$DS33)=12,"Yes","No") -> No | FH33: =IF(COUNT($EA33,$EB33,$EC33,$EE33,$EF33,$EG33,$EH33,$EI33,$EJ33,$EL33,$EM33,$EN33)=12,"Yes","No") -> No | FI33: =IF(AND($M33="Include",OR($FG33="Yes",$FH33="Yes")),"Ready","Not ready") -> Not ready
A34: CTL-0032 | B34: 43 | C34: Candidate alternative-rationale group | D34: 0 | E34: DATA non-innovation deals.xlsx | F34: linnane pharma acquires stake in selectimmune pharma | G34: No | H34: No | I34: No | J34: 1 | K34: Not started | L34: Exclude - minority | M34: Review | O34: 43777 | P34: 43777 | Q34: 2019 | R34: Q4 2019 | S34: Completed | T34: Linnane Pharma Acquires Stake in SelectImmune Pharma | U34: Mergers & Acquisitions | V34: Acquisition | W34: Minority Acquisition | X34: Sweden | Y34: Minority Acquisition | AB34: Linnane Pharma AB | AC34: linnane pharma ab | AD34: SelectImmune Pharma AB (Inactive) | AE34: selectimmune pharma ab | AF34: 0 | AG34: 0 | AH34: Linnane Pharma AB has acquired the block of 200,000 B shares in SelectImmune Pharma AB, a pharmaceutical company that develops immunotherapies to treat acute and chronic infections, from the estate of Bengt Furberg, for SEK3.1 million at a price of SEK15.5 per share. The transaction will allow Linnane Pharma to strengthen its holding in SelectImmune Pharma. | AI34: The transaction will allow Linnane Pharma to strengthen its holding in SelectImmune Pharma. | AL34: Unknown | AM34: Unknown | AS34: Linnane Pharma AB | AT34: SelectImmune Pharma AB (Inactive) | AU34: Not reviewed | AV34: Not assessed | AW34: Unknown | AX34: Unknown | AY34: Unknown | AZ34: Unknown | BA34: Unknown | BB34: Unknown | BF34: Not collected | BG34: Not collected | BH34: Not defined | BI34: =IF($Q34="","",$Q34-3) -> 2016 | BJ34: =IF($Q34="","",$Q34-2) -> 2017 | BK34: =IF($Q34="","",$Q34-1) -> 2018 | BL34: =IF($Q34="","",$Q34+0) -> 2019 | BM34: =IF($Q34="","",$Q34+1) -> 2020 | BN34: =IF($Q34="","",$Q34+2) -> 2021 | BO34: =IF($Q34="","",$Q34+3) -> 2022 | EQ34: =IF(OR($EO34="",$EP34="",$EO34=0),"",$EP34/$EO34) | ES34: Unknown | ET34: Unknown | EU34: =IF(COUNT($DF34,$DG34,$DH34)=0,"",AVERAGE($DF34,$DG34,$DH34)) | EV34: =IF(COUNT($DJ34,$DK34,$DL34)=0,"",AVERAGE($DJ34,$DK34,$DL34)) | EW34: =IF(OR($EU34="",$EV34=""),"",$EV34-$EU34) | EX34: =IF(COUNT($DM34,$DN34,$DO34)=0,"",AVERAGE($DM34,$DN34,$DO34)) | EY34: =IF(COUNT($DQ34,$DR34,$DS34)=0,"",AVERAGE($DQ34,$DR34,$DS34)) | EZ34: =IF(OR($EX34="",$EY34=""),"",$EY34-$EX34) | FA34: =IF(COUNT($EA34,$EB34,$EC34)=0,"",AVERAGE($EA34,$EB34,$EC34)) | FB34: =IF(COUNT($EE34,$EF34,$EG34)=0,"",AVERAGE($EE34,$EF34,$EG34)) | FC34: =IF(OR($FA34="",$FB34=""),"",$FB34-$FA34) | FD34: =IF(COUNT($EH34,$EI34,$EJ34)=0,"",AVERAGE($EH34,$EI34,$EJ34)) | FE34: =IF(COUNT($EL34,$EM34,$EN34)=0,"",AVERAGE($EL34,$EM34,$EN34)) | FF34: =IF(OR($FD34="",$FE34=""),"",$FE34-$FD34) | FG34: =IF(COUNT($DF34,$DG34,$DH34,$DJ34,$DK34,$DL34,$DM34,$DN34,$DO34,$DQ34,$DR34,$DS34)=12,"Yes","No") -> No | FH34: =IF(COUNT($EA34,$EB34,$EC34,$EE34,$EF34,$EG34,$EH34,$EI34,$EJ34,$EL34,$EM34,$EN34)=12,"Yes","No") -> No | FI34: =IF(AND($M34="Include",OR($FG34="Yes",$FH34="Yes")),"Ready","Not ready") -> Not ready
A35: CTL-0033 | B35: 44 | C35: Candidate alternative-rationale group | D35: 0 | E35: DATA non-innovation deals.xlsx | F35: klaria pharma acquires 100 stake in uppsalagruppen medical | G35: No | H35: No | I35: Yes | J35: 2 | K35: Not started | L35: Eligible - 100% | M35: Review | O35: 43774 | P35: 43774 | Q35: 2019 | R35: Q4 2019 | S35: Completed | T35: Klaria Pharma Acquires 100% Stake in Uppsalagruppen Medical | U35: Mergers & Acquisitions | V35: Acquisition | W35: 100% Acquisition | X35: Sweden | Y35: 100% Acquisition | AB35: Klaria Pharma Holding AB | AC35: klaria pharma ab | AD35: Uppsalagruppen Medical AB | AE35: uppsalagruppen medical ab | AG35: n/a | AH35: Klaria Pharma Holding AB, a pharmaceutical company, has acquired Uppsalagruppen Medical AB and the patent that protects Klaria’s drug delivery technology. Uppsalagruppen Medical is a provider of pharmaceutical products. The transaction is structured as a share transfer agreement between the owners of Klaria and Uppsalagruppen, whereby all shares in Uppsalagruppen are acquired by Klaria. As part of the consideration, Klaria has agreed to pay license fees and royalty payments on future earnings, substantially in line with the current license agreement between Klaria and Uppsalagruppen for Klaria’s use of the patent. The transaction will enable Klaria Pharma to strengthen its IP-position. | AI35: The transaction will enable Klaria Pharma to strengthen its IP-position. | AL35: Unknown | AM35: Unknown | AS35: Klaria Pharma Holding AB | AT35: Uppsalagruppen Medical AB | AU35: Not reviewed | AV35: Not assessed | AW35: Unknown | AX35: Unknown | AY35: Unknown | AZ35: Unknown | BA35: Unknown | BB35: Unknown | BF35: Not collected | BG35: Not collected | BH35: Not defined | BI35: =IF($Q35="","",$Q35-3) -> 2016 | BJ35: =IF($Q35="","",$Q35-2) -> 2017 | BK35: =IF($Q35="","",$Q35-1) -> 2018 | BL35: =IF($Q35="","",$Q35+0) -> 2019 | BM35: =IF($Q35="","",$Q35+1) -> 2020 | BN35: =IF($Q35="","",$Q35+2) -> 2021 | BO35: =IF($Q35="","",$Q35+3) -> 2022 | EQ35: =IF(OR($EO35="",$EP35="",$EO35=0),"",$EP35/$EO35) | ES35: Unknown | ET35: Unknown | EU35: =IF(COUNT($DF35,$DG35,$DH35)=0,"",AVERAGE($DF35,$DG35,$DH35)) | EV35: =IF(COUNT($DJ35,$DK35,$DL35)=0,"",AVERAGE($DJ35,$DK35,$DL35)) | EW35: =IF(OR($EU35="",$EV35=""),"",$EV35-$EU35) | EX35: =IF(COUNT($DM35,$DN35,$DO35)=0,"",AVERAGE($DM35,$DN35,$DO35)) | EY35: =IF(COUNT($DQ35,$DR35,$DS35)=0,"",AVERAGE($DQ35,$DR35,$DS35)) | EZ35: =IF(OR($EX35="",$EY35=""),"",$EY35-$EX35) | FA35: =IF(COUNT($EA35,$EB35,$EC35)=0,"",AVERAGE($EA35,$EB35,$EC35)) | FB35: =IF(COUNT($EE35,$EF35,$EG35)=0,"",AVERAGE($EE35,$EF35,$EG35)) | FC35: =IF(OR($FA35="",$FB35=""),"",$FB35-$FA35) | FD35: =IF(COUNT($EH35,$EI35,$EJ35)=0,"",AVERAGE($EH35,$EI35,$EJ35)) | FE35: =IF(COUNT($EL35,$EM35,$EN35)=0,"",AVERAGE($EL35,$EM35,$EN35)) | FF35: =IF(OR($FD35="",$FE35=""),"",$FE35-$FD35) | FG35: =IF(COUNT($DF35,$DG35,$DH35,$DJ35,$DK35,$DL35,$DM35,$DN35,$DO35,$DQ35,$DR35,$DS35)=12,"Yes","No") -> No | FH35: =IF(COUNT($EA35,$EB35,$EC35,$EE35,$EF35,$EG35,$EH35,$EI35,$EJ35,$EL35,$EM35,$EN35)=12,"Yes","No") -> No | FI35: =IF(AND($M35="Include",OR($FG35="Yes",$FH35="Yes")),"Ready","Not ready") -> Not ready
A36: CTL-0034 | B36: 45 | C36: Candidate alternative-rationale group | D36: 0 | E36: DATA non-innovation deals.xlsx | F36: klaria pharma merges with karessa pharma | G36: No | H36: No | I36: Yes | J36: 2 | K36: Not started | L36: Review - merger | M36: Review | O36: 43774 | P36: 43896 | Q36: 2020 | R36: Q4 2019 | S36: Completed | T36: Klaria Pharma Merges with Karessa Pharma | U36: Mergers & Acquisitions | V36: Merger | X36: Sweden | Z36: Skarpa AB , Avane AB | AA36: Hamilton Advokatbyra , Setterwalls Advokatbyra AB | AB36: Klaria Pharma Holding AB | AC36: klaria pharma ab | AD36: Karessa Pharma Holding AB (Inactive); Klaria Pharma Holding AB | AE36: karessa pharma ab klaria pharma ab | AF36: 5 | AG36: 5 | AH36: Klaria Pharma Holding AB, a developer of fast acting medicinal products that designs, develops and commercialize therapeutics for migraine and cancer related pain, has merged with Karessa Pharma Holding AB, engaged in research and development of novel drugs in male health and central nervous system therapy areas. The merged entity will maintain the company name Klaria Pharma Holding AB (publ) and will continue to have its registered office in Stockholm, Sweden. The SCRO’s registration of the merger completes the merger process from a legal perspective and all of Karessa’s assets and liabilities have been transferred to Klaria. In connection with the registration of the merger, the SCRO has today registered the issue of 6,635,200 new shares in Klaria as merger consideration. Thus, Klaria has in total 38,728,448 outstanding shares. As part of the transcation, new shares in Klaria will be issued to Karessa's shareholders in relation to their existing shareholdings in Karessa with the exchange rate 0.6032:1, i.e one share in Karessa entitles the holder to receive 0.6032 new shares in Klaria. Based on the volume weighted average price during the last 60 trading days for Klaria's share, the offer values Karessa at approximately SEK4.47 per share, which means no discount or premium compared to Karessa's volume weighted average price during the last sixty trading days but a discount of about 25% compared to the closing price on November 4, 2019 of SEK5.95. Shareholders in Klaria representing more than 37% of the votes and shares in Klaria and shareholders in Karessa representing more than 47% of the votes and shares in Karessa have committed or submitted their intention to vote to approve the merger at the forthcoming extraordinary general meeting. Klaria shall pay merger consideration to Karessa's shareholders as set out below. When calculating the merger consideration, the Boards have only taken into account the volume-weighted average prices of the companies on Nasdaq First North Growth Market during the last 60 days of trading (as of November 4, 2019, the last day of trading prior to the disclosure of the merger). One share in Karessa entitles the holder to receive 0.6032 new shares in Klaria, ie. new shares in Klaria will be issued to Karessa's shareholders in relation to their existing shareholdings in Karessa at an exchange rate of 0.6032:1. The shareholders of Karessa will thus receive an economic ownership of approximately 17.13% in New Klaria Pharma. Furthermore, the Boards propose that the merger shall be implemented with Klaria as the absorbing company and Karessa as the absorbed company. All 11,000,000 shares in Karessa shall be included in the merger. Only whole shares in Klaria will be paid to shareholders in Karessa as a merger Consideration. Klaria and Karessa will therefore retain a third party (Securities Broker) to aggregate all fractions of Karessa shares which do not entitle the holder to a whole new Klaria share and the total number of shares in Klaria corresponding to such fractions will then be sold by the Securities Broker at Nasdaq First North Growth Market. The sale will be made as soon as possible after the registration of the merger with the Swedish Companies Registration Office. Avane AB as an independent financial advisor, while Setterwalls Advokatbyra acted as legal advisor to Klaria. Skarpa AB acted as an independent financial advisor, while Hamilton Advokatbyra Firm acted as legal advisor to Karessa. The merger will create a drug development candidates based on innovative drug delivery systems with clear competitive advantages in each therapy area. Deal History: Announced: On November 5, 2019, Klaria Pharma Holding has agreed to merge with Karessa Pharma. | AI36: The merger will create a drug development candidates based on innovative drug delivery systems with clear competitive advantages in each therapy area. | AL36: Unknown | AM36: Unknown | AS36: Klaria Pharma Holding AB | AT36: Karessa Pharma Holding AB (Inactive); Klaria Pharma Holding AB | AU36: Not reviewed | AV36: Not assessed | AW36: Unknown | AX36: Unknown | AY36: Unknown | AZ36: Unknown | BA36: Unknown | BB36: Unknown | BF36: Not collected | BG36: Not collected | BH36: Not defined | BI36: =IF($Q36="","",$Q36-3) -> 2017 | BJ36: =IF($Q36="","",$Q36-2) -> 2018 | BK36: =IF($Q36="","",$Q36-1) -> 2019 | BL36: =IF($Q36="","",$Q36+0) -> 2020 | BM36: =IF($Q36="","",$Q36+1) -> 2021 | BN36: =IF($Q36="","",$Q36+2) -> 2022 | BO36: =IF($Q36="","",$Q36+3) -> 2023 | EQ36: =IF(OR($EO36="",$EP36="",$EO36=0),"",$EP36/$EO36) | ES36: Unknown | ET36: Unknown | EU36: =IF(COUNT($DF36,$DG36,$DH36)=0,"",AVERAGE($DF36,$DG36,$DH36)) | EV36: =IF(COUNT($DJ36,$DK36,$DL36)=0,"",AVERAGE($DJ36,$DK36,$DL36)) | EW36: =IF(OR($EU36="",$EV36=""),"",$EV36-$EU36) | EX36: =IF(COUNT($DM36,$DN36,$DO36)=0,"",AVERAGE($DM36,$DN36,$DO36)) | EY36: =IF(COUNT($DQ36,$DR36,$DS36)=0,"",AVERAGE($DQ36,$DR36,$DS36)) | EZ36: =IF(OR($EX36="",$EY36=""),"",$EY36-$EX36) | FA36: =IF(COUNT($EA36,$EB36,$EC36)=0,"",AVERAGE($EA36,$EB36,$EC36)) | FB36: =IF(COUNT($EE36,$EF36,$EG36)=0,"",AVERAGE($EE36,$EF36,$EG36)) | FC36: =IF(OR($FA36="",$FB36=""),"",$FB36-$FA36) | FD36: =IF(COUNT($EH36,$EI36,$EJ36)=0,"",AVERAGE($EH36,$EI36,$EJ36)) | FE36: =IF(COUNT($EL36,$EM36,$EN36)=0,"",AVERAGE($EL36,$EM36,$EN36)) | FF36: =IF(OR($FD36="",$FE36=""),"",$FE36-$FD36) | FG36: =IF(COUNT($DF36,$DG36,$DH36,$DJ36,$DK36,$DL36,$DM36,$DN36,$DO36,$DQ36,$DR36,$DS36)=12,"Yes","No") -> No | FH36: =IF(COUNT($EA36,$EB36,$EC36,$EE36,$EF36,$EG36,$EH36,$EI36,$EJ36,$EL36,$EM36,$EN36)=12,"Yes","No") -> No | FI36: =IF(AND($M36="Include",OR($FG36="Yes",$FH36="Yes")),"Ready","Not ready") -> Not ready
A37: CTL-0035 | B37: 46 | C37: Candidate alternative-rationale group | D37: 0 | E37: DATA non-innovation deals.xlsx | F37: stryker acquires wright medical | G37: No | H37: No | I37: No | J37: 1 | K37: Not started | L37: Eligible - 100% | M37: Review | O37: 43773 | P37: 44146 | Q37: 2020 | R37: Q4 2019 | S37: Completed | T37: Stryker Acquires Wright Medical | U37: Mergers & Acquisitions | V37: Acquisition | W37: 100% Acquisition | X37: The Netherlands | Y37: 100% Acquisition | Z37: J.P. Morgan Securities LLC , Guggenheim Securities LLC | AA37: Baker & McKenzie LLP , Skadden, Arps, Slate, Meagher & Flom LLP & Affiliates , Houthoff Cooperatief UA , Ropes & Gray LLP , Stibbe NV , Latham & Watkins LLP , Abdulaziz Alajlan & Partners | AB37: Stryker Corp | AC37: stryker | AD37: Wright Medical Group NV | AE37: wright medical | AF37: 5400 | AG37: 5400 | AH37: Stryker Corp., a medical technology company, has completed the acquisition of Wright Medical Group N.V., a medical device company focused on extremities and biologics, for USD30.75 per share, or a total equity value of approximately USD4 billion and a total enterprise value of approximately USD5.4 billion (including convertible notes). The cash tender offer for all outstanding ordinary shares of Wright Medical for USD30.75 per share, without interest and less applicable withholding taxes, by Stryker B.V., an indirect, wholly owned subsidiary of Stryker, expired at 5:00 p.m., Eastern Time, on November 10, 2020. American Stock Transfer & Trust Company, LLC, the depositary for the tender offer, has advised Stryker B.V. that 124,901,861 Wright Medical ordinary shares, representing approximately 96% of the outstanding Wright Medical ordinary shares, were validly tendered pursuant to the tender offer and not properly withdrawn prior to the expiration time. All of the conditions to the tender offer have been satisfied, and Stryker B.V. accepted for payment, and will promptly pay for, all shares validly tendered pursuant to the tender offer and not properly withdrawn. Following completion of the tender offer, Stryker completed the acquisition of Wright Medical through a series a mergers implemented pursuant to the agreement and plan of merger, dated as of November 10, 2020, by and among Stryker and Wright Medical. In connection with the mergers, each ordinary share of Wright Medical not validly tendered pursuant to the tender offer (other than shares owned by Wright Medical as treasury shares or owned by Stryker, or any other direct or indirect wholly owned subsidiary of Stryker immediately prior to the mergers) has been converted automatically into the right to receive the merger consideration provided in the merger agreement in cash, without interest and less applicable withholding taxes. Pursuant to the merger agreement, USD1.85 per share has been deducted and withheld from the USD30.75 per share of merger consideration in connection with Dutch dividend withholding tax described in the tender offer statement on Schedule TO filed by Stryker. Upon completion of the mergers, Wright Medical became a wholly owned subsidiary of Stryker. Shares of Wright Medical ceased trading prior to the open of the market on November 11, 2020 and will be delisted from the Nasdaq Global Select Market. On November 10, 2020, Stryker intended to complete the acquisition of Wright Medical by effectuating the mergers described in the tender offer statement on Schedule TO filed by Stryker. On November 3, 2020, Stryker won US antitrust approval to buy Wright Medical on condition it sell certain assets, the Federal Trade Commission. On February 26, 2020, Stryker extended the offering period of its cash tender offer for all outstanding ordinary shares of Wright Medical. American Stock Transfer & Trust Company, LLC advised Stryker that as on February 25, 2020, 17,446,435 Wright Medical ordinary shares, representing approximately 13.6% of the outstanding Wright Medical ordinary shares, have been validly tendered pursuant to the tender offer and not properly withdrawn. On April 27, 2020, Stryker extended the offering period of its cash tender offer for all outstanding ordinary shares of Wright Medical. American Stock Transfer & Trust Company, LLC, advised Stryker B.V. that as on April 24, 2020, 5,343,007 Wright Medical ordinary shares (excluding Wright Medical ordinary shares tendered pursuant to guaranteed delivery procedures), representing approximately 4.2% of the outstanding Wright Medical ordinary shares, have been validly tendered pursuant to the tender offer and not properly withdrawn and an additional 534,244 Wright Medical ordinary shares, representing approximately 0.4% of the outstanding Wright Medical ordinary shares, had been tendered pursuant to guaranteed delivery procedures. On June 29, 2020, Stryker extended the offering period of its previously announced cash tender offer for all outstanding ordinary shares of Wright Medical. American Stock Transfer & Trust Company, LLC, advised Stryker B.V. that as on June 26, 2020, 10,400,780 Wright Medical ordinary shares (excluding Wright Medical ordinary shares tendered pursuant to guaranteed delivery procedures), representing approximately 8.1% of the outstanding Wright Medical ordinary shares, have been validly tendered pursuant to the tender offer and not properly withdrawn and an additional 1,122,988 Wright Medical ordinary shares, representing approximately 0.9% of the outstanding Wright Medical ordinary shares, had been tendered pursuant to guaranteed delivery procedures. On August 28, 2020, Stryker has extended the offering period of its cash tender offer for all outstanding ordinary shares of Wright Medical. American Stock Transfer & Trust Company, LLC advised Stryker B.V. that as on August 27, 2020, 13,610,322 Wright Medical ordinary shares (excluding Wright Medical ordinary shares tendered pursuant to guaranteed delivery procedures), representing approximately 10.5% of the outstanding Wright Medical ordinary shares, have been validly tendered pursuant to the tender offer and not properly withdrawn and an additional 729,308 Wright Medical ordinary shares, representing approximately 0.6% of the outstanding Wright Medical ordinary shares, had been tendered pursuant to guaranteed delivery procedures. On September 29, 2020, Stryker extended the offering period of its announced cash tender offer for all outstanding ordinary shares of Wright Medical. American Stock Transfer & Trust Company, LLC advised Stryker B.V. that as on September 28, 2020, 13,817,681 Wright Medical ordinary shares (excluding Wright Medical ordinary shares tendered pursuant to guaranteed delivery procedures), representing approximately 10.6% of the outstanding Wright Medical ordinary shares, have been validly tendered pursuant to the tender offer and not properly withdrawn and an additional 1,399,083 Wright Medical ordinary shares, representing approximately 1.1% of the outstanding Wright Medical ordinary shares, had been tendered pursuant to guaranteed delivery procedures. On October 13, 2020, Stryker extended the offering period of its cash tender offer for all outstanding ordinary shares of Wright Medical. American Stock Transfer & Trust Company, LLC advised Stryker B.V. that as on October 12, 2020, 13,870,057 Wright Medical ordinary shares, representing approximately 10.7% of the outstanding Wright Medical ordinary shares, have been validly tendered pursuant to the tender offer and not properly withdrawn. On October 26, 2020, Stryker extended the offering period of its cash tender offer for all outstanding ordinary shares of Wright Medical. American Stock Transfer & Trust Company, LLC advised Stryker B.V. that as on October 23, 2020, 16,152,437 Wright Medical ordinary shares, representing approximately 12.4% of the outstanding Wright Medical ordinary shares, have been validly tendered pursuant to the tender offer and not properly withdrawn. The transaction enhance Stryker's global market position in trauma & extremities, providing significant opportunities to advance innovation, improve outcomes and reach more patients. Guggenheim Securities and J.P. Morgan Securities LLC acted as financial advisors, while Ropes & Gray LLP acted as legal advisor to Wright Medical. Deal History: Announced: On November 4, 2019, Stryker entered into definitive agreement to acquire all of the issued and outstanding ordinary shares of Wright Medical, for USD30.75 per share, or a total equity value of approximately USD4 billion and a total enterprise value of approximately USD5.4 billion (including convertible notes). The boards of directors of both Stryker and Wright Medical have approved the transaction. | AI37: The transaction enhances Stryker's global market position in trauma & extremities, providing significant opportunities to advance innovation, improve outcomes and reach more patients. | AL37: Unknown | AM37: Unknown | AS37: Stryker Corp | AT37: Wright Medical Group NV | AU37: Not reviewed | AV37: Not assessed | AW37: Unknown | AX37: Unknown | AY37: Unknown | AZ37: Unknown | BA37: Unknown | BB37: Unknown | BF37: Not collected | BG37: Not collected | BH37: Not defined | BI37: =IF($Q37="","",$Q37-3) -> 2017 | BJ37: =IF($Q37="","",$Q37-2) -> 2018 | BK37: =IF($Q37="","",$Q37-1) -> 2019 | BL37: =IF($Q37="","",$Q37+0) -> 2020 | BM37: =IF($Q37="","",$Q37+1) -> 2021 | BN37: =IF($Q37="","",$Q37+2) -> 2022 | BO37: =IF($Q37="","",$Q37+3) -> 2023 | EQ37: =IF(OR($EO37="",$EP37="",$EO37=0),"",$EP37/$EO37) | ES37: Unknown | ET37: Unknown | EU37: =IF(COUNT($DF37,$DG37,$DH37)=0,"",AVERAGE($DF37,$DG37,$DH37)) | EV37: =IF(COUNT($DJ37,$DK37,$DL37)=0,"",AVERAGE($DJ37,$DK37,$DL37)) | EW37: =IF(OR($EU37="",$EV37=""),"",$EV37-$EU37) | EX37: =IF(COUNT($DM37,$DN37,$DO37)=0,"",AVERAGE($DM37,$DN37,$DO37)) | EY37: =IF(COUNT($DQ37,$DR37,$DS37)=0,"",AVERAGE($DQ37,$DR37,$DS37)) | EZ37: =IF(OR($EX37="",$EY37=""),"",$EY37-$EX37) | FA37: =IF(COUNT($EA37,$EB37,$EC37)=0,"",AVERAGE($EA37,$EB37,$EC37)) | FB37: =IF(COUNT($EE37,$EF37,$EG37)=0,"",AVERAGE($EE37,$EF37,$EG37)) | FC37: =IF(OR($FA37="",$FB37=""),"",$FB37-$FA37) | FD37: =IF(COUNT($EH37,$EI37,$EJ37)=0,"",AVERAGE($EH37,$EI37,$EJ37)) | FE37: =IF(COUNT($EL37,$EM37,$EN37)=0,"",AVERAGE($EL37,$EM37,$EN37)) | FF37: =IF(OR($FD37="",$FE37=""),"",$FE37-$FD37) | FG37: =IF(COUNT($DF37,$DG37,$DH37,$DJ37,$DK37,$DL37,$DM37,$DN37,$DO37,$DQ37,$DR37,$DS37)=12,"Yes","No") -> No | FH37: =IF(COUNT($EA37,$EB37,$EC37,$EE37,$EF37,$EG37,$EH37,$EI37,$EJ37,$EL37,$EM37,$EN37)=12,"Yes","No") -> No | FI37: =IF(AND($M37="Include",OR($FG37="Yes",$FH37="Yes")),"Ready","Not ready") -> Not ready
A38: CTL-0036 | B38: 47 | C38: Candidate alternative-rationale group | D38: 0 | E38: DATA non-innovation deals.xlsx | F38: neopharmed gentili acquires mdm | G38: No | H38: No | I38: No | J38: 1 | K38: Not started | L38: Eligible - 100% | M38: Review | O38: 43769 | P38: 43769 | Q38: 2019 | R38: Q4 2019 | S38: Completed | T38: Neopharmed Gentili Acquires MDM | U38: Mergers & Acquisitions | V38: Acquisition | W38: 100% Acquisition | X38: Italy | Y38: 100% Acquisition | AB38: Neopharmed Gentili SpA | AC38: neopharmed gentili | AD38: MDM SpA | AE38: mdm | AG38: n/a | AH38: Neopharmed Gentili S.r.l., a company engaged in the marketing and sale of pharmaceutical products, has acquired MDM SpA, a pharmaceutical company active in the distribution of drugs, nutraceutical products and medical devices for neurology and orthopedics. This acquisition enables Neopharmed to consolidate its presence in the Italian market as well as expand the range of products in therapeutic areas considered to be highly strategic. | AI38: This acquisition enables Neopharmed to consolidate its presence in the Italian market as well as expand the range of products in therapeutic areas considered to be highly strategic. | AL38: Unknown | AM38: Unknown | AS38: Neopharmed Gentili SpA | AT38: MDM SpA | AU38: Not reviewed | AV38: Not assessed | AW38: Unknown | AX38: Unknown | AY38: Unknown | AZ38: Unknown | BA38: Unknown | BB38: Unknown | BF38: Not collected | BG38: Not collected | BH38: Not defined | BI38: =IF($Q38="","",$Q38-3) -> 2016 | BJ38: =IF($Q38="","",$Q38-2) -> 2017 | BK38: =IF($Q38="","",$Q38-1) -> 2018 | BL38: =IF($Q38="","",$Q38+0) -> 2019 | BM38: =IF($Q38="","",$Q38+1) -> 2020 | BN38: =IF($Q38="","",$Q38+2) -> 2021 | BO38: =IF($Q38="","",$Q38+3) -> 2022 | EQ38: =IF(OR($EO38="",$EP38="",$EO38=0),"",$EP38/$EO38) | ES38: Unknown | ET38: Unknown | EU38: =IF(COUNT($DF38,$DG38,$DH38)=0,"",AVERAGE($DF38,$DG38,$DH38)) | EV38: =IF(COUNT($DJ38,$DK38,$DL38)=0,"",AVERAGE($DJ38,$DK38,$DL38)) | EW38: =IF(OR($EU38="",$EV38=""),"",$EV38-$EU38) | EX38: =IF(COUNT($DM38,$DN38,$DO38)=0,"",AVERAGE($DM38,$DN38,$DO38)) | EY38: =IF(COUNT($DQ38,$DR38,$DS38)=0,"",AVERAGE($DQ38,$DR38,$DS38)) | EZ38: =IF(OR($EX38="",$EY38=""),"",$EY38-$EX38) | FA38: =IF(COUNT($EA38,$EB38,$EC38)=0,"",AVERAGE($EA38,$EB38,$EC38)) | FB38: =IF(COUNT($EE38,$EF38,$EG38)=0,"",AVERAGE($EE38,$EF38,$EG38)) | FC38: =IF(OR($FA38="",$FB38=""),"",$FB38-$FA38) | FD38: =IF(COUNT($EH38,$EI38,$EJ38)=0,"",AVERAGE($EH38,$EI38,$EJ38)) | FE38: =IF(COUNT($EL38,$EM38,$EN38)=0,"",AVERAGE($EL38,$EM38,$EN38)) | FF38: =IF(OR($FD38="",$FE38=""),"",$FE38-$FD38) | FG38: =IF(COUNT($DF38,$DG38,$DH38,$DJ38,$DK38,$DL38,$DM38,$DN38,$DO38,$DQ38,$DR38,$DS38)=12,"Yes","No") -> No | FH38: =IF(COUNT($EA38,$EB38,$EC38,$EE38,$EF38,$EG38,$EH38,$EI38,$EJ38,$EL38,$EM38,$EN38)=12,"Yes","No") -> No | FI38: =IF(AND($M38="Include",OR($FG38="Yes",$FH38="Yes")),"Ready","Not ready") -> Not ready
A39: CTL-0037 | B39: 48 | C39: Candidate alternative-rationale group | D39: 0 | E39: DATA non-innovation deals.xlsx | F39: cato research and specialized medical services oncology sms oncology complete merger | G39: No | H39: No | I39: Yes | J39: 13 | K39: Not started | L39: Review - merger | M39: Review | O39: 43766 | P39: 43766 | Q39: 2019 | R39: Q4 2019 | S39: Completed | T39: Cato Research and Specialized Medical Services-oncology (SMS-oncology) Complete Merger | U39: Mergers & Acquisitions | V39: Merger | X39: The Netherlands , United States | Z39: Achelous Partners, LLC | AD39: Cato Research LLC (Inactive); Specialized Medical Services-oncology BV (Inactive) | AE39: cato research specialized medical services oncology | AG39: n/a | AH39: Cato Research, LLC (CATO), has merged with Specialized Medical Services-oncology BV (SMS-oncology), a contract research organization. The combined company will transition to the new name, CATO SMS, in the coming year. By joining forces, CATO and SMS-oncology expand their presence across Europe and North America, deepen their oncology and regulatory expertise, and broaden their suite of services. The boutique CRO's deep expertise in designing and executing complex oncology and immuno-oncology trials complements CATO's regulatory knowledge and drug development services. Van den Tol and the management team will continue to lead the company's operations. Dr. Goldberg will serve as executive chairman of the combined entity. CATO and SMS-oncology will operate under their respective brands until the transition to their new name, CATO SMS, is complete. This transaction enables Cato Research and SMS-oncology to bolster its portfolio of global solutions dedicated to supporting life science organizations with advancing drug development. Achelous Partners LLC served as financial advisers to SMS-oncology on the merger. | AI39: This transaction enables Cato Research and SMS-oncology to bolster its portfolio of global solutions dedicated to supporting life science organizations with advancing drug development. | AL39: Unknown | AM39: Unknown | AT39: Cato Research LLC (Inactive); Specialized Medical Services-oncology BV (Inactive) | AU39: Not reviewed | AV39: Not assessed | AW39: Unknown | AX39: Unknown | AY39: Unknown | AZ39: Unknown | BA39: Unknown | BB39: Unknown | BF39: Not collected | BG39: Not collected | BH39: Not defined | BI39: =IF($Q39="","",$Q39-3) -> 2016 | BJ39: =IF($Q39="","",$Q39-2) -> 2017 | BK39: =IF($Q39="","",$Q39-1) -> 2018 | BL39: =IF($Q39="","",$Q39+0) -> 2019 | BM39: =IF($Q39="","",$Q39+1) -> 2020 | BN39: =IF($Q39="","",$Q39+2) -> 2021 | BO39: =IF($Q39="","",$Q39+3) -> 2022 | EQ39: =IF(OR($EO39="",$EP39="",$EO39=0),"",$EP39/$EO39) | ES39: Unknown | ET39: Unknown | EU39: =IF(COUNT($DF39,$DG39,$DH39)=0,"",AVERAGE($DF39,$DG39,$DH39)) | EV39: =IF(COUNT($DJ39,$DK39,$DL39)=0,"",AVERAGE($DJ39,$DK39,$DL39)) | EW39: =IF(OR($EU39="",$EV39=""),"",$EV39-$EU39) | EX39: =IF(COUNT($DM39,$DN39,$DO39)=0,"",AVERAGE($DM39,$DN39,$DO39)) | EY39: =IF(COUNT($DQ39,$DR39,$DS39)=0,"",AVERAGE($DQ39,$DR39,$DS39)) | EZ39: =IF(OR($EX39="",$EY39=""),"",$EY39-$EX39) | FA39: =IF(COUNT($EA39,$EB39,$EC39)=0,"",AVERAGE($EA39,$EB39,$EC39)) | FB39: =IF(COUNT($EE39,$EF39,$EG39)=0,"",AVERAGE($EE39,$EF39,$EG39)) | FC39: =IF(OR($FA39="",$FB39=""),"",$FB39-$FA39) | FD39: =IF(COUNT($EH39,$EI39,$EJ39)=0,"",AVERAGE($EH39,$EI39,$EJ39)) | FE39: =IF(COUNT($EL39,$EM39,$EN39)=0,"",AVERAGE($EL39,$EM39,$EN39)) | FF39: =IF(OR($FD39="",$FE39=""),"",$FE39-$FD39) | FG39: =IF(COUNT($DF39,$DG39,$DH39,$DJ39,$DK39,$DL39,$DM39,$DN39,$DO39,$DQ39,$DR39,$DS39)=12,"Yes","No") -> No | FH39: =IF(COUNT($EA39,$EB39,$EC39,$EE39,$EF39,$EG39,$EH39,$EI39,$EJ39,$EL39,$EM39,$EN39)=12,"Yes","No") -> No | FI39: =IF(AND($M39="Include",OR($FG39="Yes",$FH39="Yes")),"Ready","Not ready") -> Not ready
A40: CTL-0038 | B40: 49 | C40: Candidate alternative-rationale group | D40: 0 | E40: DATA non-innovation deals.xlsx | F40: zentiva acquires labormed pharma from alvogen | G40: No | H40: No | I40: Yes | J40: 2 | K40: Not started | L40: Eligible - 100% | M40: Review | O40: 43763 | P40: 43928 | Q40: 2020 | R40: Q4 2019 | S40: Completed | T40: Zentiva Acquires Labormed Pharma from Alvogen | U40: Mergers & Acquisitions | V40: Acquisition | W40: 100% Acquisition | X40: Romania | Y40: 100% Acquisition | Z40: Morgan Stanley , UniCredit SpA , Jefferies International Ltd , Goldman Sachs & Co LLC | AA40: CMS Legal Services EEIG , Freshfields LLP , Allen Overy Shearman Sterling LLP , White & Case LLP , Milbank LLP | AB40: Zentiva Group AS | AC40: zentiva | AD40: LaborMed Pharma SA | AE40: labormed pharma | AG40: n/a | AH40: Zentiva Group AS, has completed the acquisition of LaborMed Pharma SA, a manufacturer of generic drugs, from Alvogen Inc. This acquisition strengthens Zentiva's position in Central and Eastern Europe as it expands into new markets and will increase its OTC competences and portfolio of medicines. Deal History: Announced: On October 25, 2019, Zentiva agreed to acquire LaborMed Pharma, from Alvogen Inc. | AI40: This acquisition strengthens Zentiva's position in Central and Eastern Europe as it expands into new markets and will increase its OTC competences and portfolio of medicines. | AL40: Unknown | AM40: Unknown | AN40: 1193932D CP | AS40: Zentiva Group AS | AT40: LaborMed Pharma SA | AU40: Not reviewed | AV40: Not assessed | AW40: Unknown | AX40: Unknown | AY40: Unknown | AZ40: Unknown | BA40: Unknown | BB40: Unknown | BE40: EUR | BF40: Partial | BG40: Partial event window — 4/7 years covered | BH40: Applicant/owner alias match for Zentiva entities; the most recent event windows are only partially covered. | BI40: =IF($Q40="","",$Q40-3) -> 2017 | BJ40: =IF($Q40="","",$Q40-2) -> 2018 | BK40: =IF($Q40="","",$Q40-1) -> 2019 | BL40: =IF($Q40="","",$Q40+0) -> 2020 | BM40: =IF($Q40="","",$Q40+1) -> 2021 | BN40: =IF($Q40="","",$Q40+2) -> 2022 | BO40: =IF($Q40="","",$Q40+3) -> 2023 | BP40: 44.2803 | BW40: -8.793 | CD40: 11.4095 | CK40: 587.4154 | DF40: 2.0474 | DM40: -19.8576 | EA40: 0 | EB40: 0 | EC40: 0 | ED40: 1 | EH40: 0 | EI40: 0 | EJ40: 0 | EK40: 0 | EQ40: =IF(OR($EO40="",$EP40="",$EO40=0),"",$EP40/$EO40) | ES40: Unknown | ET40: Unknown | EU40: =IF(COUNT($DF40,$DG40,$DH40)=0,"",AVERAGE($DF40,$DG40,$DH40)) -> 2.0474 | EV40: =IF(COUNT($DJ40,$DK40,$DL40)=0,"",AVERAGE($DJ40,$DK40,$DL40)) | EW40: =IF(OR($EU40="",$EV40=""),"",$EV40-$EU40) | EX40: =IF(COUNT($DM40,$DN40,$DO40)=0,"",AVERAGE($DM40,$DN40,$DO40)) -> -19.8576 | EY40: =IF(COUNT($DQ40,$DR40,$DS40)=0,"",AVERAGE($DQ40,$DR40,$DS40)) | EZ40: =IF(OR($EX40="",$EY40=""),"",$EY40-$EX40) | FA40: =IF(COUNT($EA40,$EB40,$EC40)=0,"",AVERAGE($EA40,$EB40,$EC40)) -> 0 | FB40: =IF(COUNT($EE40,$EF40,$EG40)=0,"",AVERAGE($EE40,$EF40,$EG40)) | FC40: =IF(OR($FA40="",$FB40=""),"",$FB40-$FA40) | FD40: =IF(COUNT($EH40,$EI40,$EJ40)=0,"",AVERAGE($EH40,$EI40,$EJ40)) -> 0 | FE40: =IF(COUNT($EL40,$EM40,$EN40)=0,"",AVERAGE($EL40,$EM40,$EN40)) | FF40: =IF(OR($FD40="",$FE40=""),"",$FE40-$FD40) | FG40: =IF(COUNT($DF40,$DG40,$DH40,$DJ40,$DK40,$DL40,$DM40,$DN40,$DO40,$DQ40,$DR40,$DS40)=12,"Yes","No") -> No | FH40: =IF(COUNT($EA40,$EB40,$EC40,$EE40,$EF40,$EG40,$EH40,$EI40,$EJ40,$EL40,$EM40,$EN40)=12,"Yes","No") -> No | FI40: =IF(AND($M40="Include",OR($FG40="Yes",$FH40="Yes")),"Ready","Not ready") -> Not ready
A41: CTL-0039 | B41: 50 | C41: Candidate alternative-rationale group | D41: 0 | E41: DATA non-innovation deals.xlsx | F41: meiragtx acquires arthrogen | G41: No | H41: No | I41: No | J41: 1 | K41: Not started | L41: Eligible - 100% | M41: Review | O41: 43755 | P41: 43755 | Q41: 2019 | R41: Q4 2019 | S41: Completed | T41: MeiraGTx Acquires Arthrogen | U41: Mergers & Acquisitions | V41: Acquisition | W41: 100% Acquisition | X41: The Netherlands | Y41: 100% Acquisition | AB41: MeiraGTx Holdings Plc | AC41: meiragtx | AD41: Arthrogen BV | AE41: arthrogen | AG41: n/a | AH41: MeiraGTx Holdings plc, a clinical stage gene therapy company, has acquired 100% of the outstanding equity of Arthrogen B.V., a biopharmaceutical company developing gene therapy for different indications, using viral mediated gene transfer. Arthrogen specializes in the development of viral gene therapy vectors, in particular adeno-associated virus (AAV-) based therapeutics. The acquisition of Arthrogen is part of the Company’s continuing efforts to expand its focus to develop additional gene therapy treatments for patients suffering from a range of serious diseases” | AI41: The acquisition of Arthrogen is part of MeiraGTx's continuing efforts to expand its focus to develop additional gene therapy treatments for patients suffering from a range of serious diseases. | AL41: Unknown | AM41: Unknown | AS41: MeiraGTx Holdings Plc | AT41: Arthrogen BV | AU41: Not reviewed | AV41: Not assessed | AW41: Unknown | AX41: Unknown | AY41: Unknown | AZ41: Unknown | BA41: Unknown | BB41: Unknown | BF41: Not collected | BG41: Not collected | BH41: Not defined | BI41: =IF($Q41="","",$Q41-3) -> 2016 | BJ41: =IF($Q41="","",$Q41-2) -> 2017 | BK41: =IF($Q41="","",$Q41-1) -> 2018 | BL41: =IF($Q41="","",$Q41+0) -> 2019 | BM41: =IF($Q41="","",$Q41+1) -> 2020 | BN41: =IF($Q41="","",$Q41+2) -> 2021 | BO41: =IF($Q41="","",$Q41+3) -> 2022 | EQ41: =IF(OR($EO41="",$EP41="",$EO41=0),"",$EP41/$EO41) | ES41: Unknown | ET41: Unknown | EU41: =IF(COUNT($DF41,$DG41,$DH41)=0,"",AVERAGE($DF41,$DG41,$DH41)) | EV41: =IF(COUNT($DJ41,$DK41,$DL41)=0,"",AVERAGE($DJ41,$DK41,$DL41)) | EW41: =IF(OR($EU41="",$EV41=""),"",$EV41-$EU41) | EX41: =IF(COUNT($DM41,$DN41,$DO41)=0,"",AVERAGE($DM41,$DN41,$DO41)) | EY41: =IF(COUNT($DQ41,$DR41,$DS41)=0,"",AVERAGE($DQ41,$DR41,$DS41)) | EZ41: =IF(OR($EX41="",$EY41=""),"",$EY41-$EX41) | FA41: =IF(COUNT($EA41,$EB41,$EC41)=0,"",AVERAGE($EA41,$EB41,$EC41)) | FB41: =IF(COUNT($EE41,$EF41,$EG41)=0,"",AVERAGE($EE41,$EF41,$EG41)) | FC41: =IF(OR($FA41="",$FB41=""),"",$FB41-$FA41) | FD41: =IF(COUNT($EH41,$EI41,$EJ41)=0,"",AVERAGE($EH41,$EI41,$EJ41)) | FE41: =IF(COUNT($EL41,$EM41,$EN41)=0,"",AVERAGE($EL41,$EM41,$EN41)) | FF41: =IF(OR($FD41="",$FE41=""),"",$FE41-$FD41) | FG41: =IF(COUNT($DF41,$DG41,$DH41,$DJ41,$DK41,$DL41,$DM41,$DN41,$DO41,$DQ41,$DR41,$DS41)=12,"Yes","No") -> No | FH41: =IF(COUNT($EA41,$EB41,$EC41,$EE41,$EF41,$EG41,$EH41,$EI41,$EJ41,$EL41,$EM41,$EN41)=12,"Yes","No") -> No | FI41: =IF(AND($M41="Include",OR($FG41="Yes",$FH41="Yes")),"Ready","Not ready") -> Not ready
A42: CTL-0040 | B42: 51 | C42: Candidate alternative-rationale group | D42: 0 | E42: DATA non-innovation deals.xlsx | F42: orpea acquires remaining 55 stake in groupe sinoue | G42: No | H42: No | I42: No | J42: 1 | K42: Not started | L42: Review - majority | M42: Review | O42: 43732 | P42: 43732 | Q42: 2019 | R42: Q3 2019 | S42: Completed | T42: Orpea Acquires Remaining 55 % Stake in Groupe Sinoue | U42: Mergers & Acquisitions | V42: Acquisition | W42: Majority Acquisition | X42: France | Y42: Majority Acquisition | AB42: Emeis SA | AC42: emeis | AD42: Groupe Sinoue | AE42: groupe sinoue | AG42: n/a | AH42: Orpea SA, a nursing care facilities company, has acquired remaining 55% stake in Groupe Sinoue, a mental healthcare provider. Both the companies are based in France. Groupe Sinoue manages a wide range of innovative mental health care, treating all types of psychiatric disorders such as depression, addiction, bipolar disorder and sleeping disorders. | AI42: The acquisition allows Orpea to stepped up its premium psychiatric care offering. | AL42: Unknown | AM42: Unknown | AS42: Emeis SA | AT42: Groupe Sinoue | AU42: Not reviewed | AV42: Not assessed | AW42: Unknown | AX42: Unknown | AY42: Unknown | AZ42: Unknown | BA42: Unknown | BB42: Unknown | BF42: Not collected | BG42: Not collected | BH42: Not defined | BI42: =IF($Q42="","",$Q42-3) -> 2016 | BJ42: =IF($Q42="","",$Q42-2) -> 2017 | BK42: =IF($Q42="","",$Q42-1) -> 2018 | BL42: =IF($Q42="","",$Q42+0) -> 2019 | BM42: =IF($Q42="","",$Q42+1) -> 2020 | BN42: =IF($Q42="","",$Q42+2) -> 2021 | BO42: =IF($Q42="","",$Q42+3) -> 2022 | EQ42: =IF(OR($EO42="",$EP42="",$EO42=0),"",$EP42/$EO42) | ES42: Unknown | ET42: Unknown | EU42: =IF(COUNT($DF42,$DG42,$DH42)=0,"",AVERAGE($DF42,$DG42,$DH42)) | EV42: =IF(COUNT($DJ42,$DK42,$DL42)=0,"",AVERAGE($DJ42,$DK42,$DL42)) | EW42: =IF(OR($EU42="",$EV42=""),"",$EV42-$EU42) | EX42: =IF(COUNT($DM42,$DN42,$DO42)=0,"",AVERAGE($DM42,$DN42,$DO42)) | EY42: =IF(COUNT($DQ42,$DR42,$DS42)=0,"",AVERAGE($DQ42,$DR42,$DS42)) | EZ42: =IF(OR($EX42="",$EY42=""),"",$EY42-$EX42) | FA42: =IF(COUNT($EA42,$EB42,$EC42)=0,"",AVERAGE($EA42,$EB42,$EC42)) | FB42: =IF(COUNT($EE42,$EF42,$EG42)=0,"",AVERAGE($EE42,$EF42,$EG42)) | FC42: =IF(OR($FA42="",$FB42=""),"",$FB42-$FA42) | FD42: =IF(COUNT($EH42,$EI42,$EJ42)=0,"",AVERAGE($EH42,$EI42,$EJ42)) | FE42: =IF(COUNT($EL42,$EM42,$EN42)=0,"",AVERAGE($EL42,$EM42,$EN42)) | FF42: =IF(OR($FD42="",$FE42=""),"",$FE42-$FD42) | FG42: =IF(COUNT($DF42,$DG42,$DH42,$DJ42,$DK42,$DL42,$DM42,$DN42,$DO42,$DQ42,$DR42,$DS42)=12,"Yes","No") -> No | FH42: =IF(COUNT($EA42,$EB42,$EC42,$EE42,$EF42,$EG42,$EH42,$EI42,$EJ42,$EL42,$EM42,$EN42)=12,"Yes","No") -> No | FI42: =IF(AND($M42="Include",OR($FG42="Yes",$FH42="Yes")),"Ready","Not ready") -> Not ready
A43: CTL-0041 | B43: 52 | C43: Candidate alternative-rationale group | D43: 0 | E43: DATA non-innovation deals.xlsx | F43: hero wellbeing hero acquires the balanced you | G43: No | H43: No | I43: No | J43: 1 | K43: Not started | L43: Review - majority | M43: Review | O43: 43697 | P43: 43697 | Q43: 2019 | R43: Q3 2019 | S43: Completed | T43: Hero Wellbeing (Hero) Acquires The Balanced You | U43: Mergers & Acquisitions | V43: Acquisition | W43: Majority Acquisition | X43: United Kingdom | Y43: Majority Acquisition | AB43: Hero Wellbeing Ltd | AC43: hero wellbeing | AD43: The Balanced You | AE43: balanced you | AG43: n/a | AH43: Hero Wellbeing Ltd (hero), a digital wellbeing platform, has acquired The Balanced You, a provider of mental health and wellbeing services, including one-to-one counselling, mindfulness sessions, wellbeing retreats, reiki and hypnotherapy. Both companies involved in the transaction are based in the UK. Ashleigh Turner is the founder of The Balanced You, and will join Hero. | AI43: The transaction will enable Hero to develop The Balanced You’s existing offering, using technology to further broaden its mental health services and in-person support and also bolster hero's offer and its team of experienced, qualified and passionate specialists. | AL43: Unknown | AM43: Unknown | AS43: Hero Wellbeing Ltd | AT43: The Balanced You | AU43: Not reviewed | AV43: Not assessed | AW43: Unknown | AX43: Unknown | AY43: Unknown | AZ43: Unknown | BA43: Unknown | BB43: Unknown | BF43: Not collected | BG43: Not collected | BH43: Not defined | BI43: =IF($Q43="","",$Q43-3) -> 2016 | BJ43: =IF($Q43="","",$Q43-2) -> 2017 | BK43: =IF($Q43="","",$Q43-1) -> 2018 | BL43: =IF($Q43="","",$Q43+0) -> 2019 | BM43: =IF($Q43="","",$Q43+1) -> 2020 | BN43: =IF($Q43="","",$Q43+2) -> 2021 | BO43: =IF($Q43="","",$Q43+3) -> 2022 | EQ43: =IF(OR($EO43="",$EP43="",$EO43=0),"",$EP43/$EO43) | ES43: Unknown | ET43: Unknown | EU43: =IF(COUNT($DF43,$DG43,$DH43)=0,"",AVERAGE($DF43,$DG43,$DH43)) | EV43: =IF(COUNT($DJ43,$DK43,$DL43)=0,"",AVERAGE($DJ43,$DK43,$DL43)) | EW43: =IF(OR($EU43="",$EV43=""),"",$EV43-$EU43) | EX43: =IF(COUNT($DM43,$DN43,$DO43)=0,"",AVERAGE($DM43,$DN43,$DO43)) | EY43: =IF(COUNT($DQ43,$DR43,$DS43)=0,"",AVERAGE($DQ43,$DR43,$DS43)) | EZ43: =IF(OR($EX43="",$EY43=""),"",$EY43-$EX43) | FA43: =IF(COUNT($EA43,$EB43,$EC43)=0,"",AVERAGE($EA43,$EB43,$EC43)) | FB43: =IF(COUNT($EE43,$EF43,$EG43)=0,"",AVERAGE($EE43,$EF43,$EG43)) | FC43: =IF(OR($FA43="",$FB43=""),"",$FB43-$FA43) | FD43: =IF(COUNT($EH43,$EI43,$EJ43)=0,"",AVERAGE($EH43,$EI43,$EJ43)) | FE43: =IF(COUNT($EL43,$EM43,$EN43)=0,"",AVERAGE($EL43,$EM43,$EN43)) | FF43: =IF(OR($FD43="",$FE43=""),"",$FE43-$FD43) | FG43: =IF(COUNT($DF43,$DG43,$DH43,$DJ43,$DK43,$DL43,$DM43,$DN43,$DO43,$DQ43,$DR43,$DS43)=12,"Yes","No") -> No | FH43: =IF(COUNT($EA43,$EB43,$EC43,$EE43,$EF43,$EG43,$EH43,$EI43,$EJ43,$EL43,$EM43,$EN43)=12,"Yes","No") -> No | FI43: =IF(AND($M43="Include",OR($FG43="Yes",$FH43="Yes")),"Ready","Not ready") -> Not ready
A44: CTL-0042 | B44: 53 | C44: Candidate alternative-rationale group | D44: 0 | E44: DATA non-innovation deals.xlsx | F44: canopy growth acquires beckley canopy therapeutics | G44: No | H44: No | I44: No | J44: 1 | K44: Not started | L44: Eligible - 100% | M44: Review | O44: 43686 | P44: 43753 | Q44: 2019 | R44: Q3 2019 | S44: Completed | T44: Canopy Growth Acquires Beckley Canopy Therapeutics | U44: Mergers & Acquisitions | V44: Acquisition | W44: 100% Acquisition | X44: United Kingdom | Y44: 100% Acquisition | AB44: Canopy Growth Corp | AC44: canopy growth | AD44: Beckley Canopy Therapeutics Ltd | AE44: beckley canopy therapeutics | AG44: n/a | AH44: Canopy Growth Corporation, a Canada-based cannabis company, has acquired all outstanding shares in the global cannabinoid based research company Beckley Canopy Therapeutics (Beckley Canopy), including the joint commercial venture Spectrum Biomedical UK. These teams will now be integrated into the broader Spectrum Therapeutics organization to increase the breadth of the clinical research being pursued under the Spectrum banner and to combine continental European and United Kingdom commercial teams. As a part of the acquisition, Canopy Growth’s European management structure will evolve. Paul Steckler and Steven Wooding will assume the roles of Co-Managing Directors in charge of all European operations. Paul is a seasoned pharmaceutical executive with over 20 years’ experience in commercial roles, having worked in both large and small pharmaceutical companies including Pfizer. Steve has held multiple positions within a 27-year career at Janssen, the Pharmaceutical arm of Johnson & Johnson. Most recently, he was head of Global Commercial Strategy and Market Access for Janssen. “The acquisition comes at a time when commercial opportunities across Europe are ramping up,” said Mark Zekulin, CEO, Canopy Growth. “Spectrum Biomedical has completed all necessary approvals to import cannabis into the UK market and is proud to facilitate patient access to safe cannabinoid-based medicines there. Consolidating our UK-based operations will allow Canopy to simultaneously improve its research and commercial capabilities across the continent.” Deal History: Announced: On August 9, 2019, Canopy Growth entered into an agreement to acquire Beckley Canopy Therapeutics. | AI44: The acquisition of Beckley Canopy will allow Spectrum Therapeutics to continue expanding its medical cannabis leadership around the world, strengthening its foothold in the UK and more broadly across Europe. | AL44: Unknown | AM44: Unknown | AS44: Canopy Growth Corp | AT44: Beckley Canopy Therapeutics Ltd | AU44: Not reviewed | AV44: Not assessed | AW44: Unknown | AX44: Unknown | AY44: Unknown | AZ44: Unknown | BA44: Unknown | BB44: Unknown | BF44: Not collected | BG44: Not collected | BH44: Not defined | BI44: =IF($Q44="","",$Q44-3) -> 2016 | BJ44: =IF($Q44="","",$Q44-2) -> 2017 | BK44: =IF($Q44="","",$Q44-1) -> 2018 | BL44: =IF($Q44="","",$Q44+0) -> 2019 | BM44: =IF($Q44="","",$Q44+1) -> 2020 | BN44: =IF($Q44="","",$Q44+2) -> 2021 | BO44: =IF($Q44="","",$Q44+3) -> 2022 | EQ44: =IF(OR($EO44="",$EP44="",$EO44=0),"",$EP44/$EO44) | ES44: Unknown | ET44: Unknown | EU44: =IF(COUNT($DF44,$DG44,$DH44)=0,"",AVERAGE($DF44,$DG44,$DH44)) | EV44: =IF(COUNT($DJ44,$DK44,$DL44)=0,"",AVERAGE($DJ44,$DK44,$DL44)) | EW44: =IF(OR($EU44="",$EV44=""),"",$EV44-$EU44) | EX44: =IF(COUNT($DM44,$DN44,$DO44)=0,"",AVERAGE($DM44,$DN44,$DO44)) | EY44: =IF(COUNT($DQ44,$DR44,$DS44)=0,"",AVERAGE($DQ44,$DR44,$DS44)) | EZ44: =IF(OR($EX44="",$EY44=""),"",$EY44-$EX44) | FA44: =IF(COUNT($EA44,$EB44,$EC44)=0,"",AVERAGE($EA44,$EB44,$EC44)) | FB44: =IF(COUNT($EE44,$EF44,$EG44)=0,"",AVERAGE($EE44,$EF44,$EG44)) | FC44: =IF(OR($FA44="",$FB44=""),"",$FB44-$FA44) | FD44: =IF(COUNT($EH44,$EI44,$EJ44)=0,"",AVERAGE($EH44,$EI44,$EJ44)) | FE44: =IF(COUNT($EL44,$EM44,$EN44)=0,"",AVERAGE($EL44,$EM44,$EN44)) | FF44: =IF(OR($FD44="",$FE44=""),"",$FE44-$FD44) | FG44: =IF(COUNT($DF44,$DG44,$DH44,$DJ44,$DK44,$DL44,$DM44,$DN44,$DO44,$DQ44,$DR44,$DS44)=12,"Yes","No") -> No | FH44: =IF(COUNT($EA44,$EB44,$EC44,$EE44,$EF44,$EG44,$EH44,$EI44,$EJ44,$EL44,$EM44,$EN44)=12,"Yes","No") -> No | FI44: =IF(AND($M44="Include",OR($FG44="Yes",$FH44="Yes")),"Ready","Not ready") -> Not ready
A45: CTL-0043 | B45: 54 | C45: Candidate alternative-rationale group | D45: 0 | E45: DATA non-innovation deals.xlsx | F45: nec acquires oncoimmunity | G45: No | H45: No | I45: No | J45: 1 | K45: Not started | L45: Eligible - 100% | M45: Review | O45: 43675 | P45: 43675 | Q45: 2019 | R45: Q3 2019 | S45: Completed | T45: NEC Acquires OncoImmunity | U45: Mergers & Acquisitions | V45: Acquisition | W45: 100% Acquisition | X45: Norway | Y45: 100% Acquisition | Z45: GCA Corp | AB45: NEC Corp | AC45: nec | AD45: NEC OncoImmunity AS | AE45: nec oncoimmunity | AG45: n/a | AH45: NEC Corp., announced the acquisition of OncoImmunity AS, a Norway-based bioinformatics company that develops proprietary machine learning software to support the fight against cancer. OncoImmunity AS will now become a subsidiary of NEC and operate under the name of NEC OncoImmunity AS. This acquisition is integral for enhancing the resources and capabilities that support the development of its individualized immunotherapy pipelines. NEC will maintain its focus on drug discovery, while NEC OncoImmunity AS continues its neoantigen prediction services. This acquisition will help strengthen NEC’s individualized immunotherapy programs. GCA Corp acted as financial advisor to NEC. | AI45: This acquisition will help strengthen NEC’s individualized immunotherapy programs. | AL45: Unknown | AM45: Unknown | AS45: NEC Corp | AT45: NEC OncoImmunity AS | AU45: Not reviewed | AV45: Not assessed | AW45: Unknown | AX45: Unknown | AY45: Unknown | AZ45: Unknown | BA45: Unknown | BB45: Unknown | BF45: Not collected | BG45: Not collected | BH45: Not defined | BI45: =IF($Q45="","",$Q45-3) -> 2016 | BJ45: =IF($Q45="","",$Q45-2) -> 2017 | BK45: =IF($Q45="","",$Q45-1) -> 2018 | BL45: =IF($Q45="","",$Q45+0) -> 2019 | BM45: =IF($Q45="","",$Q45+1) -> 2020 | BN45: =IF($Q45="","",$Q45+2) -> 2021 | BO45: =IF($Q45="","",$Q45+3) -> 2022 | EQ45: =IF(OR($EO45="",$EP45="",$EO45=0),"",$EP45/$EO45) | ES45: Unknown | ET45: Unknown | EU45: =IF(COUNT($DF45,$DG45,$DH45)=0,"",AVERAGE($DF45,$DG45,$DH45)) | EV45: =IF(COUNT($DJ45,$DK45,$DL45)=0,"",AVERAGE($DJ45,$DK45,$DL45)) | EW45: =IF(OR($EU45="",$EV45=""),"",$EV45-$EU45) | EX45: =IF(COUNT($DM45,$DN45,$DO45)=0,"",AVERAGE($DM45,$DN45,$DO45)) | EY45: =IF(COUNT($DQ45,$DR45,$DS45)=0,"",AVERAGE($DQ45,$DR45,$DS45)) | EZ45: =IF(OR($EX45="",$EY45=""),"",$EY45-$EX45) | FA45: =IF(COUNT($EA45,$EB45,$EC45)=0,"",AVERAGE($EA45,$EB45,$EC45)) | FB45: =IF(COUNT($EE45,$EF45,$EG45)=0,"",AVERAGE($EE45,$EF45,$EG45)) | FC45: =IF(OR($FA45="",$FB45=""),"",$FB45-$FA45) | FD45: =IF(COUNT($EH45,$EI45,$EJ45)=0,"",AVERAGE($EH45,$EI45,$EJ45)) | FE45: =IF(COUNT($EL45,$EM45,$EN45)=0,"",AVERAGE($EL45,$EM45,$EN45)) | FF45: =IF(OR($FD45="",$FE45=""),"",$FE45-$FD45) | FG45: =IF(COUNT($DF45,$DG45,$DH45,$DJ45,$DK45,$DL45,$DM45,$DN45,$DO45,$DQ45,$DR45,$DS45)=12,"Yes","No") -> No | FH45: =IF(COUNT($EA45,$EB45,$EC45,$EE45,$EF45,$EG45,$EH45,$EI45,$EJ45,$EL45,$EM45,$EN45)=12,"Yes","No") -> No | FI45: =IF(AND($M45="Include",OR($FG45="Yes",$FH45="Yes")),"Ready","Not ready") -> Not ready
A46: CTL-0044 | B46: 55 | C46: Candidate alternative-rationale group | D46: 0 | E46: DATA non-innovation deals.xlsx | F46: boehringer ingelheim acquires amal therapeutics | G46: No | H46: No | I46: Yes | J46: 3 | K46: Not started | L46: Eligible - 100% | M46: Review | O46: 43661 | P46: 43661 | Q46: 2019 | R46: Q3 2019 | S46: Completed | T46: Boehringer Ingelheim Acquires Amal Therapeutics | U46: Mergers & Acquisitions | V46: Acquisition | W46: 100% Acquisition | X46: Switzerland | Y46: 100% Acquisition | AA46: Walder Wyss & Partners Ltd | AB46: Boehringer Ingelheim International GmbH | AC46: boehringer ingelheim international | AD46: Amal Therapeutics SA | AE46: amal therapeutics | AF46: 366 | AG46: 366 | AH46: Boehringer Ingelheim International GmbH, a pharmaceutical company, announced its acquisition of all shares of AMAL Therapeutics SA, a biotechnology company focused on cancer immunotherapy and advancing therapeutic cancer vaccines derived from its technology platform KISIMA. AMAL’s vaccine ATP128 is currently developed for stage IV colorectal cancer and is slated to begin trials later this month. Boehringer Ingelheim plans to develop new therapies by combining assets from its cancer immunology portfolio with AMAL’s proprietary KISIMA immunization platform. The total transaction could amount up to EUR325 million, which includes USD225 million of upfront payment as well as contingent clinical, development and regulatory milestones plus up to EUR100 million if certain commercial milestones are hit. This acquisition strengthens Boehringer Ingelheim’s strategic focus on immune cell-directed therapies. | AI46: This acquisition strengthens Boehringer Ingelheim’s strategic focus on immune cell-directed therapies. | AL46: Unknown | AM46: Unknown | AS46: Boehringer Ingelheim International GmbH | AT46: Amal Therapeutics SA | AU46: Not reviewed | AV46: Not assessed | AW46: Unknown | AX46: Unknown | AY46: Unknown | AZ46: Unknown | BA46: Unknown | BB46: Unknown | BF46: Not collected | BG46: Not collected | BH46: Not defined | BI46: =IF($Q46="","",$Q46-3) -> 2016 | BJ46: =IF($Q46="","",$Q46-2) -> 2017 | BK46: =IF($Q46="","",$Q46-1) -> 2018 | BL46: =IF($Q46="","",$Q46+0) -> 2019 | BM46: =IF($Q46="","",$Q46+1) -> 2020 | BN46: =IF($Q46="","",$Q46+2) -> 2021 | BO46: =IF($Q46="","",$Q46+3) -> 2022 | EQ46: =IF(OR($EO46="",$EP46="",$EO46=0),"",$EP46/$EO46) | ES46: Unknown | ET46: Unknown | EU46: =IF(COUNT($DF46,$DG46,$DH46)=0,"",AVERAGE($DF46,$DG46,$DH46)) | EV46: =IF(COUNT($DJ46,$DK46,$DL46)=0,"",AVERAGE($DJ46,$DK46,$DL46)) | EW46: =IF(OR($EU46="",$EV46=""),"",$EV46-$EU46) | EX46: =IF(COUNT($DM46,$DN46,$DO46)=0,"",AVERAGE($DM46,$DN46,$DO46)) | EY46: =IF(COUNT($DQ46,$DR46,$DS46)=0,"",AVERAGE($DQ46,$DR46,$DS46)) | EZ46: =IF(OR($EX46="",$EY46=""),"",$EY46-$EX46) | FA46: =IF(COUNT($EA46,$EB46,$EC46)=0,"",AVERAGE($EA46,$EB46,$EC46)) | FB46: =IF(COUNT($EE46,$EF46,$EG46)=0,"",AVERAGE($EE46,$EF46,$EG46)) | FC46: =IF(OR($FA46="",$FB46=""),"",$FB46-$FA46) | FD46: =IF(COUNT($EH46,$EI46,$EJ46)=0,"",AVERAGE($EH46,$EI46,$EJ46)) | FE46: =IF(COUNT($EL46,$EM46,$EN46)=0,"",AVERAGE($EL46,$EM46,$EN46)) | FF46: =IF(OR($FD46="",$FE46=""),"",$FE46-$FD46) | FG46: =IF(COUNT($DF46,$DG46,$DH46,$DJ46,$DK46,$DL46,$DM46,$DN46,$DO46,$DQ46,$DR46,$DS46)=12,"Yes","No") -> No | FH46: =IF(COUNT($EA46,$EB46,$EC46,$EE46,$EF46,$EG46,$EH46,$EI46,$EJ46,$EL46,$EM46,$EN46)=12,"Yes","No") -> No | FI46: =IF(AND($M46="Include",OR($FG46="Yes",$FH46="Yes")),"Ready","Not ready") -> Not ready
A47: CTL-0045 | B47: 56 | C47: Candidate alternative-rationale group | D47: 0 | E47: DATA non-innovation deals.xlsx | F47: lifespan biosciences acquires nordic mubio | G47: No | H47: No | I47: No | J47: 1 | K47: Not started | L47: Eligible - 100% | M47: Review | O47: 43654 | P47: 43654 | Q47: 2019 | R47: Q3 2019 | S47: Completed | T47: LifeSpan BioSciences Acquires Nordic MUbio | U47: Mergers & Acquisitions | V47: Acquisition | W47: 100% Acquisition | X47: The Netherlands | Y47: 100% Acquisition | Z47: Achelous Partners, LLC | AB47: LifeSpan Biosciences Inc | AC47: lifespan biosciences | AD47: Nordic-MUbio BV | AE47: nordic mubio | AG47: n/a | AH47: LifeSpan BioSciences (LSBio), a provider of antibodies and life science research reagents, has acquired Nordic MUbio BV, a company engaged in developing antibodies targeting Cell Adhesion, Nuclear and Cytoskeletal Proteins. As part of the acquisition, LSBio acquired Nordic MUbio product ranges, which also includes Exalpha Biologicals Inc., Gallus Immunotech & Biologo. The acquisition enables LSBio to further expand its product offering and strengthens its position in the research reagent market. Achelous Partners, LLC acted as financial advisor to LifeSpan BioSciences for the transaction. | AI47: The acquisition enables LSBio to further expand its product offering and strengthens its position in the research reagent market. | AL47: Unknown | AM47: Unknown | AS47: LifeSpan Biosciences Inc | AT47: Nordic-MUbio BV | AU47: Not reviewed | AV47: Not assessed | AW47: Unknown | AX47: Unknown | AY47: Unknown | AZ47: Unknown | BA47: Unknown | BB47: Unknown | BF47: Not collected | BG47: Not collected | BH47: Not defined | BI47: =IF($Q47="","",$Q47-3) -> 2016 | BJ47: =IF($Q47="","",$Q47-2) -> 2017 | BK47: =IF($Q47="","",$Q47-1) -> 2018 | BL47: =IF($Q47="","",$Q47+0) -> 2019 | BM47: =IF($Q47="","",$Q47+1) -> 2020 | BN47: =IF($Q47="","",$Q47+2) -> 2021 | BO47: =IF($Q47="","",$Q47+3) -> 2022 | EQ47: =IF(OR($EO47="",$EP47="",$EO47=0),"",$EP47/$EO47) | ES47: Unknown | ET47: Unknown | EU47: =IF(COUNT($DF47,$DG47,$DH47)=0,"",AVERAGE($DF47,$DG47,$DH47)) | EV47: =IF(COUNT($DJ47,$DK47,$DL47)=0,"",AVERAGE($DJ47,$DK47,$DL47)) | EW47: =IF(OR($EU47="",$EV47=""),"",$EV47-$EU47) | EX47: =IF(COUNT($DM47,$DN47,$DO47)=0,"",AVERAGE($DM47,$DN47,$DO47)) | EY47: =IF(COUNT($DQ47,$DR47,$DS47)=0,"",AVERAGE($DQ47,$DR47,$DS47)) | EZ47: =IF(OR($EX47="",$EY47=""),"",$EY47-$EX47) | FA47: =IF(COUNT($EA47,$EB47,$EC47)=0,"",AVERAGE($EA47,$EB47,$EC47)) | FB47: =IF(COUNT($EE47,$EF47,$EG47)=0,"",AVERAGE($EE47,$EF47,$EG47)) | FC47: =IF(OR($FA47="",$FB47=""),"",$FB47-$FA47) | FD47: =IF(COUNT($EH47,$EI47,$EJ47)=0,"",AVERAGE($EH47,$EI47,$EJ47)) | FE47: =IF(COUNT($EL47,$EM47,$EN47)=0,"",AVERAGE($EL47,$EM47,$EN47)) | FF47: =IF(OR($FD47="",$FE47=""),"",$FE47-$FD47) | FG47: =IF(COUNT($DF47,$DG47,$DH47,$DJ47,$DK47,$DL47,$DM47,$DN47,$DO47,$DQ47,$DR47,$DS47)=12,"Yes","No") -> No | FH47: =IF(COUNT($EA47,$EB47,$EC47,$EE47,$EF47,$EG47,$EH47,$EI47,$EJ47,$EL47,$EM47,$EN47)=12,"Yes","No") -> No | FI47: =IF(AND($M47="Include",OR($FG47="Yes",$FH47="Yes")),"Ready","Not ready") -> Not ready
A48: CTL-0046 | B48: 57 | C48: Candidate alternative-rationale group | D48: 0 | E48: DATA non-innovation deals.xlsx | F48: b braun avitum acquires nephtec | G48: No | H48: No | I48: No | J48: 1 | K48: Not started | L48: Eligible - 100% | M48: Review | O48: 43650 | P48: 43650 | Q48: 2019 | R48: Q3 2019 | S48: Completed | T48: B. Braun Avitum Acquires Nephtec | U48: Mergers & Acquisitions | V48: Acquisition | W48: 100% Acquisition | X48: Germany | Y48: 100% Acquisition | AB48: B. Braun Avitum AG | AC48: b braun avitum | AD48: Nephtec GmbH | AE48: nephtec | AG48: n/a | AH48: B. Braun Avitum AG, a systems provider for extracorporeal blood treatment (dialysis), has acquired business operations of Nephtec GmbH. This acquisition strengthens B. Braun Avitum's product portfolio in the area of the central preparation of dialysis concentrates. | AI48: This acquisition strengthens B. Braun Avitum's product portfolio in the area of the central preparation of dialysis concentrates. | AL48: Unknown | AM48: Unknown | AS48: B. Braun Avitum AG | AT48: Nephtec GmbH | AU48: Not reviewed | AV48: Not assessed | AW48: Unknown | AX48: Unknown | AY48: Unknown | AZ48: Unknown | BA48: Unknown | BB48: Unknown | BF48: Not collected | BG48: Not collected | BH48: Not defined | BI48: =IF($Q48="","",$Q48-3) -> 2016 | BJ48: =IF($Q48="","",$Q48-2) -> 2017 | BK48: =IF($Q48="","",$Q48-1) -> 2018 | BL48: =IF($Q48="","",$Q48+0) -> 2019 | BM48: =IF($Q48="","",$Q48+1) -> 2020 | BN48: =IF($Q48="","",$Q48+2) -> 2021 | BO48: =IF($Q48="","",$Q48+3) -> 2022 | EQ48: =IF(OR($EO48="",$EP48="",$EO48=0),"",$EP48/$EO48) | ES48: Unknown | ET48: Unknown | EU48: =IF(COUNT($DF48,$DG48,$DH48)=0,"",AVERAGE($DF48,$DG48,$DH48)) | EV48: =IF(COUNT($DJ48,$DK48,$DL48)=0,"",AVERAGE($DJ48,$DK48,$DL48)) | EW48: =IF(OR($EU48="",$EV48=""),"",$EV48-$EU48) | EX48: =IF(COUNT($DM48,$DN48,$DO48)=0,"",AVERAGE($DM48,$DN48,$DO48)) | EY48: =IF(COUNT($DQ48,$DR48,$DS48)=0,"",AVERAGE($DQ48,$DR48,$DS48)) | EZ48: =IF(OR($EX48="",$EY48=""),"",$EY48-$EX48) | FA48: =IF(COUNT($EA48,$EB48,$EC48)=0,"",AVERAGE($EA48,$EB48,$EC48)) | FB48: =IF(COUNT($EE48,$EF48,$EG48)=0,"",AVERAGE($EE48,$EF48,$EG48)) | FC48: =IF(OR($FA48="",$FB48=""),"",$FB48-$FA48) | FD48: =IF(COUNT($EH48,$EI48,$EJ48)=0,"",AVERAGE($EH48,$EI48,$EJ48)) | FE48: =IF(COUNT($EL48,$EM48,$EN48)=0,"",AVERAGE($EL48,$EM48,$EN48)) | FF48: =IF(OR($FD48="",$FE48=""),"",$FE48-$FD48) | FG48: =IF(COUNT($DF48,$DG48,$DH48,$DJ48,$DK48,$DL48,$DM48,$DN48,$DO48,$DQ48,$DR48,$DS48)=12,"Yes","No") -> No | FH48: =IF(COUNT($EA48,$EB48,$EC48,$EE48,$EF48,$EG48,$EH48,$EI48,$EJ48,$EL48,$EM48,$EN48)=12,"Yes","No") -> No | FI48: =IF(AND($M48="Include",OR($FG48="Yes",$FH48="Yes")),"Ready","Not ready") -> Not ready
A49: CTL-0047 | B49: 58 | C49: Candidate alternative-rationale group | D49: 0 | E49: DATA non-innovation deals.xlsx | F49: tekni plex acquires lameplast from aksia group | G49: No | H49: No | I49: No | J49: 1 | K49: Not started | L49: Review - majority | M49: Review | O49: 43648 | P49: 43648 | Q49: 2019 | R49: Q3 2019 | S49: Completed | T49: Tekni-Plex Acquires Lameplast from Aksia Group | U49: Mergers & Acquisitions | V49: Acquisition | W49: Majority Acquisition | X49: Italy | Y49: Majority Acquisition | AA49: Jones Day LLP | AB49: Tekni-Plex Inc | AC49: tekni plex | AD49: Lameplast SpA | AE49: lameplast | AG49: n/a | AH49: Tekni-Plex has purchased Italian healthcare packaging company Lameplast SpA, an Italian manufacturer of plastic single/multi-dose containers for pharmaceutical, diagnostic, medical device, veterinary and cosmetic applications, from Aksìa Group SGR S.p.A, a private equity firm. Lameplast will become part of Tekni-Plex's global Tekni-Films business. | AI49: The transaction will support Tekni-Plex's strategy to grow its business though transformative acquisitions and strategic add-ons. | AL49: Unknown | AM49: Unknown | AS49: Tekni-Plex Inc | AT49: Lameplast SpA | AU49: Not reviewed | AV49: Not assessed | AW49: Unknown | AX49: Unknown | AY49: Unknown | AZ49: Unknown | BA49: Unknown | BB49: Unknown | BF49: Not collected | BG49: Not collected | BH49: Not defined | BI49: =IF($Q49="","",$Q49-3) -> 2016 | BJ49: =IF($Q49="","",$Q49-2) -> 2017 | BK49: =IF($Q49="","",$Q49-1) -> 2018 | BL49: =IF($Q49="","",$Q49+0) -> 2019 | BM49: =IF($Q49="","",$Q49+1) -> 2020 | BN49: =IF($Q49="","",$Q49+2) -> 2021 | BO49: =IF($Q49="","",$Q49+3) -> 2022 | EQ49: =IF(OR($EO49="",$EP49="",$EO49=0),"",$EP49/$EO49) | ES49: Unknown | ET49: Unknown | EU49: =IF(COUNT($DF49,$DG49,$DH49)=0,"",AVERAGE($DF49,$DG49,$DH49)) | EV49: =IF(COUNT($DJ49,$DK49,$DL49)=0,"",AVERAGE($DJ49,$DK49,$DL49)) | EW49: =IF(OR($EU49="",$EV49=""),"",$EV49-$EU49) | EX49: =IF(COUNT($DM49,$DN49,$DO49)=0,"",AVERAGE($DM49,$DN49,$DO49)) | EY49: =IF(COUNT($DQ49,$DR49,$DS49)=0,"",AVERAGE($DQ49,$DR49,$DS49)) | EZ49: =IF(OR($EX49="",$EY49=""),"",$EY49-$EX49) | FA49: =IF(COUNT($EA49,$EB49,$EC49)=0,"",AVERAGE($EA49,$EB49,$EC49)) | FB49: =IF(COUNT($EE49,$EF49,$EG49)=0,"",AVERAGE($EE49,$EF49,$EG49)) | FC49: =IF(OR($FA49="",$FB49=""),"",$FB49-$FA49) | FD49: =IF(COUNT($EH49,$EI49,$EJ49)=0,"",AVERAGE($EH49,$EI49,$EJ49)) | FE49: =IF(COUNT($EL49,$EM49,$EN49)=0,"",AVERAGE($EL49,$EM49,$EN49)) | FF49: =IF(OR($FD49="",$FE49=""),"",$FE49-$FD49) | FG49: =IF(COUNT($DF49,$DG49,$DH49,$DJ49,$DK49,$DL49,$DM49,$DN49,$DO49,$DQ49,$DR49,$DS49)=12,"Yes","No") -> No | FH49: =IF(COUNT($EA49,$EB49,$EC49,$EE49,$EF49,$EG49,$EH49,$EI49,$EJ49,$EL49,$EM49,$EN49)=12,"Yes","No") -> No | FI49: =IF(AND($M49="Include",OR($FG49="Yes",$FH49="Yes")),"Ready","Not ready") -> Not ready
A50: CTL-0048 | B50: 59 | C50: Candidate alternative-rationale group | D50: 0 | E50: DATA non-innovation deals.xlsx | F50: abbvie acquires allergan | G50: No | H50: No | I50: No | J50: 1 | K50: Not started | L50: Eligible - 100% | M50: Review | O50: 43641 | P50: 43959 | Q50: 2020 | R50: Q2 2019 | S50: Completed | T50: AbbVie Acquires Allergan | U50: Mergers & Acquisitions | V50: Acquisition | W50: 100% Acquisition | X50: Ireland | Y50: 100% Acquisition | Z50: Evercore Inc , The Goldman Sachs Group Inc , PJT Partners Inc , J.P. Morgan Securities LLC , Morgan Stanley & Co LLC | AA50: McCann FitzGerald , Wachtell, Lipton, Rosen & Katz , Arthur Cox , Baker & McKenzie LLP , Slaughter and May , Davis Polk & Wardwell LLP , Weil, Gotshal & Manges LLP , Kirkland & Ellis LLP , Debevoise & Plimpton LLP | AB50: AbbVie Inc | AC50: abbvie | AD50: Allergan Ltd | AE50: allergan | AF50: 85737 | AG50: 85737 | AH50: AbbVie Inc., a research-driven biopharmaceutical company, Acquirer Sub, a wholly-owned subsidiary of AbbVie, has completed its acquisition of Allergan plc, a pharmaceutical company, following receipt of regulatory approval from all government authorities required by the transaction agreement and approval by the Irish High Court. The transaction was unanimously approved by the AbbVie Board and the Independent Allergan Directors. Under the terms of the agreement, Allergan shareholders will receive 0.8660 AbbVie shares and USD120.3 in cash for each Allergan share, for a total consideration of USD193.23 per Allergan share (based on the closing price of AbbVie's common stock of USD84.22 on May 7, 2020). Allergan common stock ceased trading on the New York Stock Exchange as of the close of trading today. Pursuant to the acquisition, AbbVie shareholders own approximately 83% of AbbVie on a fully diluted basis and the Allergan shareholders own approximately 17% of AbbVie on a fully diluted basis. The purchase consideration was based on the closing price of AbbVie's common stock of USD78.45 on June 24, 2019. The transaction represents a 45% premium to the closing price of Allergan's Shares on June 24, 2019. Enterprise value for the transaction is USD85.74 billion. AbbVie has secured fully underwritten financing commitments from Morgan Stanley Senior Funding, Inc. and MUFG Bank, Ltd., for an aggregate amount of USD38 billion, to finance together with AbbVie's own cash resources, the cash portion of the acquisition. AbbVie's lead financial advisor, Morgan Stanley & Co. LLC delivered a fairness opinion and has provided the committed financing for the transaction, and its legal advisors were Kirkland & Ellis LLP and McCann FitzGerald. PJT Partners LP served as a financial advisor to AbbVie. Allergan's exclusive financial advisor was J.P. Morgan Securities LLC and its legal advisors were Wachtell, Lipton, Rosen & Katz and Arthur Cox. Weil Gotshal & Manges LLP acted as antitrust counsel. Davis Polk & Wardwell LLP represented Morgan Stanley and Debevoise & Plimpton LLP represented J.P. Morgan Securities. Deal History: Update: On May 5, 2020, AbbVie and Allergan announced that the US Federal Trade Commission (FTC) has accepted the proposed consent order in connection with the transaction. The acceptance by the FTC satisfies all required antitrust clearances needed to be obtained for the acquisition of Allergan by AbbVie. Further, AbbVie announced the extension of the expiration date of the offers to exchange any and all outstanding notes of certain series issued by Allergan Finance, LLC, Allergan, Inc., Allergan Sales, LLC and Allergan Funding SCS for new notes to be issued by AbbVie and the related consent solicitations being made by AbbVie on behalf of Allergan to adopt certain amendments to each of the indentures governing the Allergan notes. AbbVie hereby extends such expiration date from May 8, 2020 to May 12, 2020. AbbVie currently expects that there will be no further extensions of the Expiration Date. Update: On April 28, 2020, Allergan has notified the NYSE of its intention to voluntarily withdraw from listing on the NYSE and from registration under Section 12(b) of the Securities Exchange Act of 1934, as amended any and all outstanding notes and related guarantees issued by Allergan Funding following the consummation of the proposed acquisition by AbbVie by means of a scheme of arrangement. Update: On April 27, 2020, AbbVie announced the extension of the expiration date of the offers to exchange any and all outstanding notes of certain series issued by Allergan Finance, Allergan, Inc., Allergan Sales and Allergan Funding for new notes to be issued by AbbVie and the related consent solicitations being made by AbbVie on behalf of Allergan to adopt certain amendments to each of the indentures governing the Allergan notes. AbbVie hereby extends such expiration date from May 1, 2020 to May 8, 2020. Update: On April 6, 2020, AbbVie has extended the expiration date of its (i) offers to exchange any and all outstanding notes of certain series issued by Allergan Finance, LLC, Allergan, Inc., Allergan Sales, LLC and Allergan Funding SCS for new notes to be issued by AbbVie and (ii) related consent solicitations being made by AbbVie on behalf of Allergan to adopt certain amendments to eliminate substantially all of the covenants, restrictive provisions, events of default and any guarantees of the related Allergan Notes in each of the indentures governing the Allergan Notes. AbbVie extended such expiration date from April 10, 2020 to April 24, 2020. Update: On March 17, 2020, AbbVie and Allergan have entered into a consent decree agreement with staff of the US FTC regarding AbbVie's pending acquisition of Allergan. Under the terms of the agreement, AbbVie and Allergan agreed to divest brazikumab to AstraZeneca and Zenpep to Nestle. Nestle will also acquire Viokace, as part of the same transaction. The consent decree, including the proposed purchasers, remains subject to further review and approval by the Commissioners of the FTC. The transaction is being pushed back to at least May after the US Justice Department said it will delay merger and acquisition reviews because of interruptions caused by the coronavirus pandemic. Update: On March 3, 2020, AbbVie and Allergan, announced that the European Commission has approved the divestiture of brazikumab to AstraZeneca. The European Commission's approval of AbbVie's pending acquisition of Allergan in January was conditional upon the divestiture of brazikumab to a suitable purchaser. The transaction remains subject to additional customary closing conditions, but the European Commission's final approval clears the pathway in Europe to close the pending transaction. Update: On February 24, 2020, AbbVie announced the extension of the expiration date of the offers to exchange any and all outstanding notes of certain series issued by AbbVie and the related consent solicitations being made by AbbVie. AbbVie hereby extends such expiration date from 5:00 p.m., New York City time, on February 28, 2020 to 5:00 p.m., on March 13, 2020. Update: On February 18, 2020, Coalition of consumer groups and unions hopes to convince the FTC to alter the terms of AbbVie’s (ABBV) USD63 billion acquisition of Allergan by arguing the deal as currently conceived would thwart competition and unfairly maintain higher drug prices for consumers. Update: On January 10, 2020, AbbVie and Allergan received conditional approval of the transaction by the European Commission, subject to the approved divestiture of brazikumab and other conditions. Update: On January 8, 2020, AbbVie announced the creation of a new global business, Allergan Aesthetics, an AbbVie company, and the proposed leadership team for the combined company, effective upon the expected first-quarter 2020 close of the Allergan acquisition. Update: On October 14, 2019, Allergan's shareholders have voted to approve the proposed acquisition of Allergan by AbbVie. More than 99% of the votes cast at both a special court-ordered meeting of shareholders and at an extraordinary general meeting of shareholders were in favor of the transaction, representing approximately 68.6% of the shares outstanding and eligible to be voted. Update: On September 27, 2019, AbbVie and Allergan have each received a Request for Additional Information (Second Request) from the FTC in connection with AbbVie's pending acquisition of Allergan. Announced: On June 25, 2019, AbbVie, Acquirer Sub, a wholly-owned subsidiary of AbbVie, and Allergan plc, entered into a definitive transaction agreement under which AbbVie agreed to acquire Allergan in a cash and stock transaction for a transaction equity value of approximately USD63 billion. | AI50: This acquisition enables Abbvie, new growth platforms and positions to diversify and expand its revenue base; scale and enhanced profitability for its's growth platform. | AL50: Unknown | AM50: Unknown | AS50: AbbVie Inc | AT50: Allergan Ltd | AU50: Not reviewed | AV50: Not assessed | AW50: Unknown | AX50: Unknown | AY50: Unknown | AZ50: Unknown | BA50: Unknown | BB50: Unknown | BF50: Not collected | BG50: Not collected | BH50: Not defined | BI50: =IF($Q50="","",$Q50-3) -> 2017 | BJ50: =IF($Q50="","",$Q50-2) -> 2018 | BK50: =IF($Q50="","",$Q50-1) -> 2019 | BL50: =IF($Q50="","",$Q50+0) -> 2020 | BM50: =IF($Q50="","",$Q50+1) -> 2021 | BN50: =IF($Q50="","",$Q50+2) -> 2022 | BO50: =IF($Q50="","",$Q50+3) -> 2023 | EQ50: =IF(OR($EO50="",$EP50="",$EO50=0),"",$EP50/$EO50) | ES50: Unknown | ET50: Unknown | EU50: =IF(COUNT($DF50,$DG50,$DH50)=0,"",AVERAGE($DF50,$DG50,$DH50)) | EV50: =IF(COUNT($DJ50,$DK50,$DL50)=0,"",AVERAGE($DJ50,$DK50,$DL50)) | EW50: =IF(OR($EU50="",$EV50=""),"",$EV50-$EU50) | EX50: =IF(COUNT($DM50,$DN50,$DO50)=0,"",AVERAGE($DM50,$DN50,$DO50)) | EY50: =IF(COUNT($DQ50,$DR50,$DS50)=0,"",AVERAGE($DQ50,$DR50,$DS50)) | EZ50: =IF(OR($EX50="",$EY50=""),"",$EY50-$EX50) | FA50: =IF(COUNT($EA50,$EB50,$EC50)=0,"",AVERAGE($EA50,$EB50,$EC50)) | FB50: =IF(COUNT($EE50,$EF50,$EG50)=0,"",AVERAGE($EE50,$EF50,$EG50)) | FC50: =IF(OR($FA50="",$FB50=""),"",$FB50-$FA50) | FD50: =IF(COUNT($EH50,$EI50,$EJ50)=0,"",AVERAGE($EH50,$EI50,$EJ50)) | FE50: =IF(COUNT($EL50,$EM50,$EN50)=0,"",AVERAGE($EL50,$EM50,$EN50)) | FF50: =IF(OR($FD50="",$FE50=""),"",$FE50-$FD50) | FG50: =IF(COUNT($DF50,$DG50,$DH50,$DJ50,$DK50,$DL50,$DM50,$DN50,$DO50,$DQ50,$DR50,$DS50)=12,"Yes","No") -> No | FH50: =IF(COUNT($EA50,$EB50,$EC50,$EE50,$EF50,$EG50,$EH50,$EI50,$EJ50,$EL50,$EM50,$EN50)=12,"Yes","No") -> No | FI50: =IF(AND($M50="Include",OR($FG50="Yes",$FH50="Yes")),"Ready","Not ready") -> Not ready
A51: CTL-0049 | B51: 60 | C51: Candidate alternative-rationale group | D51: 0 | E51: DATA non-innovation deals.xlsx | F51: pfizer acquires therachon for | G51: Yes | H51: No | I51: Yes | J51: 2 | K51: Not started | L51: Eligible - 100% | M51: Review | O51: 43593 | P51: 43647 | Q51: 2019 | R51: Q2 2019 | S51: Completed | T51: Pfizer Acquires Therachon for USD810 Million | U51: Mergers & Acquisitions | V51: Acquisition | W51: 100% Acquisition | X51: Switzerland | Y51: 100% Acquisition | Z51: The Goldman Sachs Group Inc | AA51: Cooley LLP , Homburger AG , Lenz & Staehelin , Arnold & Porter LLP | AB51: Pfizer Inc | AC51: pfizer | AD51: Therachon AG (Inactive) | AE51: therachon | AF51: 810 | AG51: 810 | AH51: Pfizer Inc., a pharmaceutical company, has completion acquisition of all the shares of Therachon Holding AG, a clinical-stage biotechnology company focused on rare diseases with assets in development for the treatment of achondroplasia and short bowel syndrome (SBS). Under the terms of the transaction, Pfizer acquired Therachon for USD340 million with an additional USD470 million in additional payments contingent on the achievement of key milestones in the development and commercialization of TA-46. TA-46 is an investigational, soluble recombinant human fibroblast growth factor receptor 3 (FGFR3) decoy, for bone development abnormalities associated with achondroplasia. Prior to the closing of the transaction with Pfizer, Therachon will spin-off its apraglutide development program into a separate, independent company. Apraglutide is a GLP-2 analog in Phase II development for short bowel syndrome. Pfizer Ventures, the venture capital arm of Pfizer Inc., currently holds a minority stake and will continue to hold an equity stake in the new company. The transaction is not expected to impact Pfizer’s current 2019 adjusted financial guidance. The acquisition enables Pfizer to expand its rare disease portfolio with potential first-in-class therapy for achondroplasia through the development of TA-46. Goldman Sachs acted as financial advisor while Cooley LLP and Homburger AG acted as legal advisors to Therachon. Arnold & Porter and Lenz & Staehelin acted as legal advisors to Pfizer. Deal History: Announced: On May 8, 2019, Pfizer entered into a definitive agreement to acquire all the shares of Therachon. | AI51: The acquisition enables Pfizer to expand its rare disease portfolio with potential first-in-class therapy for achondroplasia through the development of TA-46. | AL51: Unknown | AM51: Unknown | AS51: Pfizer Inc | AT51: Therachon AG (Inactive) | AU51: Not reviewed | AV51: Not assessed | AW51: Unknown | AX51: Unknown | AY51: Unknown | AZ51: Unknown | BA51: Unknown | BB51: Unknown | BF51: Not collected | BG51: Not collected | BH51: Not defined | BI51: =IF($Q51="","",$Q51-3) -> 2016 | BJ51: =IF($Q51="","",$Q51-2) -> 2017 | BK51: =IF($Q51="","",$Q51-1) -> 2018 | BL51: =IF($Q51="","",$Q51+0) -> 2019 | BM51: =IF($Q51="","",$Q51+1) -> 2020 | BN51: =IF($Q51="","",$Q51+2) -> 2021 | BO51: =IF($Q51="","",$Q51+3) -> 2022 | EQ51: =IF(OR($EO51="",$EP51="",$EO51=0),"",$EP51/$EO51) | ES51: Unknown | ET51: Unknown | EU51: =IF(COUNT($DF51,$DG51,$DH51)=0,"",AVERAGE($DF51,$DG51,$DH51)) | EV51: =IF(COUNT($DJ51,$DK51,$DL51)=0,"",AVERAGE($DJ51,$DK51,$DL51)) | EW51: =IF(OR($EU51="",$EV51=""),"",$EV51-$EU51) | EX51: =IF(COUNT($DM51,$DN51,$DO51)=0,"",AVERAGE($DM51,$DN51,$DO51)) | EY51: =IF(COUNT($DQ51,$DR51,$DS51)=0,"",AVERAGE($DQ51,$DR51,$DS51)) | EZ51: =IF(OR($EX51="",$EY51=""),"",$EY51-$EX51) | FA51: =IF(COUNT($EA51,$EB51,$EC51)=0,"",AVERAGE($EA51,$EB51,$EC51)) | FB51: =IF(COUNT($EE51,$EF51,$EG51)=0,"",AVERAGE($EE51,$EF51,$EG51)) | FC51: =IF(OR($FA51="",$FB51=""),"",$FB51-$FA51) | FD51: =IF(COUNT($EH51,$EI51,$EJ51)=0,"",AVERAGE($EH51,$EI51,$EJ51)) | FE51: =IF(COUNT($EL51,$EM51,$EN51)=0,"",AVERAGE($EL51,$EM51,$EN51)) | FF51: =IF(OR($FD51="",$FE51=""),"",$FE51-$FD51) | FG51: =IF(COUNT($DF51,$DG51,$DH51,$DJ51,$DK51,$DL51,$DM51,$DN51,$DO51,$DQ51,$DR51,$DS51)=12,"Yes","No") -> No | FH51: =IF(COUNT($EA51,$EB51,$EC51,$EE51,$EF51,$EG51,$EH51,$EI51,$EJ51,$EL51,$EM51,$EN51)=12,"Yes","No") -> No | FI51: =IF(AND($M51="Include",OR($FG51="Yes",$FH51="Yes")),"Ready","Not ready") -> Not ready
A52: CTL-0050 | B52: 61 | C52: Candidate alternative-rationale group | D52: 0 | E52: DATA non-innovation deals.xlsx | F52: ever pharma acquires amneal deutschland | G52: No | H52: No | I52: Yes | J52: 2 | K52: Not started | L52: Eligible - 100% | M52: Review | O52: 43591 | P52: 43591 | Q52: 2019 | R52: Q2 2019 | S52: Completed | T52: EVER Pharma Acquires Amneal Deutschland | U52: Mergers & Acquisitions | V52: Acquisition | W52: 100% Acquisition | X52: Germany | Y52: 100% Acquisition | AB52: EVER Neuro Pharma GmbH | AC52: ever neuro pharma | AD52: EVER Pharma GmbH | AE52: ever pharma | AG52: n/a | AH52: EVER Pharma Holding Ges.m.b.H (Austria) has completed the acquisition of Amneal Deutschland GmbH, a subsidiary of Amneal Pharmaceuticals that operates the company's commercial operations in Germany. Amneal Deutschland already distributes several EVER Pharma products in Germany. The acquired entity will be rebranded to EVER Pharma GmbH. This acquisition enables EVER Pharma to extend its commercial presence in Europe. | AI52: This acquisition enables EVER Pharma to extend its commercial presence in Europe. | AL52: Unknown | AM52: Unknown | AS52: EVER Neuro Pharma GmbH | AT52: EVER Pharma GmbH | AU52: Not reviewed | AV52: Not assessed | AW52: Unknown | AX52: Unknown | AY52: Unknown | AZ52: Unknown | BA52: Unknown | BB52: Unknown | BF52: Not collected | BG52: Not collected | BH52: Not defined | BI52: =IF($Q52="","",$Q52-3) -> 2016 | BJ52: =IF($Q52="","",$Q52-2) -> 2017 | BK52: =IF($Q52="","",$Q52-1) -> 2018 | BL52: =IF($Q52="","",$Q52+0) -> 2019 | BM52: =IF($Q52="","",$Q52+1) -> 2020 | BN52: =IF($Q52="","",$Q52+2) -> 2021 | BO52: =IF($Q52="","",$Q52+3) -> 2022 | EQ52: =IF(OR($EO52="",$EP52="",$EO52=0),"",$EP52/$EO52) | ES52: Unknown | ET52: Unknown | EU52: =IF(COUNT($DF52,$DG52,$DH52)=0,"",AVERAGE($DF52,$DG52,$DH52)) | EV52: =IF(COUNT($DJ52,$DK52,$DL52)=0,"",AVERAGE($DJ52,$DK52,$DL52)) | EW52: =IF(OR($EU52="",$EV52=""),"",$EV52-$EU52) | EX52: =IF(COUNT($DM52,$DN52,$DO52)=0,"",AVERAGE($DM52,$DN52,$DO52)) | EY52: =IF(COUNT($DQ52,$DR52,$DS52)=0,"",AVERAGE($DQ52,$DR52,$DS52)) | EZ52: =IF(OR($EX52="",$EY52=""),"",$EY52-$EX52) | FA52: =IF(COUNT($EA52,$EB52,$EC52)=0,"",AVERAGE($EA52,$EB52,$EC52)) | FB52: =IF(COUNT($EE52,$EF52,$EG52)=0,"",AVERAGE($EE52,$EF52,$EG52)) | FC52: =IF(OR($FA52="",$FB52=""),"",$FB52-$FA52) | FD52: =IF(COUNT($EH52,$EI52,$EJ52)=0,"",AVERAGE($EH52,$EI52,$EJ52)) | FE52: =IF(COUNT($EL52,$EM52,$EN52)=0,"",AVERAGE($EL52,$EM52,$EN52)) | FF52: =IF(OR($FD52="",$FE52=""),"",$FE52-$FD52) | FG52: =IF(COUNT($DF52,$DG52,$DH52,$DJ52,$DK52,$DL52,$DM52,$DN52,$DO52,$DQ52,$DR52,$DS52)=12,"Yes","No") -> No | FH52: =IF(COUNT($EA52,$EB52,$EC52,$EE52,$EF52,$EG52,$EH52,$EI52,$EJ52,$EL52,$EM52,$EN52)=12,"Yes","No") -> No | FI52: =IF(AND($M52="Include",OR($FG52="Yes",$FH52="Yes")),"Ready","Not ready") -> Not ready
A53: CTL-0051 | B53: 62 | C53: Candidate alternative-rationale group | D53: 0 | E53: DATA non-innovation deals.xlsx | F53: perkinelmer acquires cisbio bioassays | G53: No | H53: No | I53: Yes | J53: 2 | K53: Not started | L53: Eligible - 100% | M53: Review | O53: 43580 | P53: 43580 | Q53: 2019 | R53: Q2 2019 | S53: Completed | T53: PerkinElmer Acquires Cisbio Bioassays | U53: Mergers & Acquisitions | V53: Acquisition | W53: 100% Acquisition | X53: France | Y53: 100% Acquisition | Z53: Edmond de Rothschild | AA53: Taylor Wessing LLP , DLA Piper LLP (US) , Hogan Lovells International LLP | AB53: Revvity Inc | AC53: revvity | AD53: Cisbio Bioassays | AE53: cisbio bioassays | AG53: n/a | AH53: PerkinElmer, Inc., a provider of products, services, and solutions to the diagnostics, life sciences, and applied services markets, has acquired Cisbio Bioassays, a custom assay service provider, from Abenex Capital. Founded in 1974, and headquartered in Codolet, France, Cisbio develops, manufactures and markets high quality kits and reagents for the life sciences and diagnostics markets. The acquisition will expand PerkinElmer’s current offerings for life sciences researchers, which include a wide range of validated drug discovery screening reagents and kits for high throughput and profiling assays, as well as research-use only in vitro diagnostic kits. Specifically, Cisbio’s market-leading HTRF screening technology can be integrated into PerkinElmer’s customers’ upstream workflows such as target identification and characterization, along with downstream applications such as lead optimization and validation. Cisbio also significantly expands PerkinElmer’s cell-based assay R&D capabilities, and from a commercial standpoint, PerkinElmer expects to be able to leverage Cisbio’s customer base in growth regions including the Americas, Europe and China to expand its market reach for reagents. This acquisition bolsters PerkinElmer’s position in life sciences and diagnostics markets. Hogan Lovells acted as legal advisor to PerkinElmer. Edmond de Rothschild acted as financial advisor and DLA Piper and Taylor Wessing acted as legal advisor to Abenex. | AI53: This acquisition bolsters PerkinElmer’s position in life sciences and diagnostics markets. | AL53: Unknown | AM53: Unknown | AS53: Revvity Inc | AT53: Cisbio Bioassays | AU53: Not reviewed | AV53: Not assessed | AW53: Unknown | AX53: Unknown | AY53: Unknown | AZ53: Unknown | BA53: Unknown | BB53: Unknown | BF53: Not collected | BG53: Not collected | BH53: Not defined | BI53: =IF($Q53="","",$Q53-3) -> 2016 | BJ53: =IF($Q53="","",$Q53-2) -> 2017 | BK53: =IF($Q53="","",$Q53-1) -> 2018 | BL53: =IF($Q53="","",$Q53+0) -> 2019 | BM53: =IF($Q53="","",$Q53+1) -> 2020 | BN53: =IF($Q53="","",$Q53+2) -> 2021 | BO53: =IF($Q53="","",$Q53+3) -> 2022 | EQ53: =IF(OR($EO53="",$EP53="",$EO53=0),"",$EP53/$EO53) | ES53: Unknown | ET53: Unknown | EU53: =IF(COUNT($DF53,$DG53,$DH53)=0,"",AVERAGE($DF53,$DG53,$DH53)) | EV53: =IF(COUNT($DJ53,$DK53,$DL53)=0,"",AVERAGE($DJ53,$DK53,$DL53)) | EW53: =IF(OR($EU53="",$EV53=""),"",$EV53-$EU53) | EX53: =IF(COUNT($DM53,$DN53,$DO53)=0,"",AVERAGE($DM53,$DN53,$DO53)) | EY53: =IF(COUNT($DQ53,$DR53,$DS53)=0,"",AVERAGE($DQ53,$DR53,$DS53)) | EZ53: =IF(OR($EX53="",$EY53=""),"",$EY53-$EX53) | FA53: =IF(COUNT($EA53,$EB53,$EC53)=0,"",AVERAGE($EA53,$EB53,$EC53)) | FB53: =IF(COUNT($EE53,$EF53,$EG53)=0,"",AVERAGE($EE53,$EF53,$EG53)) | FC53: =IF(OR($FA53="",$FB53=""),"",$FB53-$FA53) | FD53: =IF(COUNT($EH53,$EI53,$EJ53)=0,"",AVERAGE($EH53,$EI53,$EJ53)) | FE53: =IF(COUNT($EL53,$EM53,$EN53)=0,"",AVERAGE($EL53,$EM53,$EN53)) | FF53: =IF(OR($FD53="",$FE53=""),"",$FE53-$FD53) | FG53: =IF(COUNT($DF53,$DG53,$DH53,$DJ53,$DK53,$DL53,$DM53,$DN53,$DO53,$DQ53,$DR53,$DS53)=12,"Yes","No") -> No | FH53: =IF(COUNT($EA53,$EB53,$EC53,$EE53,$EF53,$EG53,$EH53,$EI53,$EJ53,$EL53,$EM53,$EN53)=12,"Yes","No") -> No | FI53: =IF(AND($M53="Include",OR($FG53="Yes",$FH53="Yes")),"Ready","Not ready") -> Not ready
