Workbook

Sheet Deal_Master_Wide
A1: AUDIT & ELIGIBILITY | O1: DEAL CHARACTERISTICS | AJ1: FIRM, CLASSIFICATION & SOURCE STATUS | BI1: EVENT-YEAR MAP | BP1: FINANCIAL DATA — ENTER VALUES IN REPORTED CURRENCY, MILLIONS | EA1: PATENT DATA — UNIQUE FAMILIES / CITATION-WEIGHTED OUTPUT | EO1: PATENT MODERATORS | EU1: DERIVED DiD CHECKS
A2: Deal_ID | B2: Source_Row | C2: Initial_Group | D2: Initial_Treatment_Indicator | E2: Source_File | F2: Cross_File_Key | G2: Overlap_Flag | H2: Duplicate_Flag | I2: Multiple_Deal_Acquirer | J2: Acquirer_Deal_Count_in_File | K2: Manual_Review_Status | L2: Initial_Control_Transfer_Status | M2: Main_DiD_Decision | N2: Exclusion_Reason | O2: Announced_Date | P2: Completion_Date | Q2: Completion_Year | R2: Completion_Quarter | S2: Deal_Status | T2: Deal_Headline | U2: Deal_Type_Level_1 | V2: Deal_Subtype_Level_2 | W2: Deal_Subtype_Level_3 | X2: Deal_Country_s | Y2: Deal_Subcategory | Z2: Financial_Advisors | AA2: Legal_Advisors | AB2: Acquirer_Raw | AC2: Acquirer_Normalized | AD2: Target_Raw | AE2: Target_Normalized | AF2: Deal_Value_USD_m | AG2: Deal_Value_Raw | AH2: Description | AI2: Deal_Rationale | AJ2: Acquirer_Country | AK2: Target_Country | AL2: Cross_Border_Flag | AM2: Acquirer_Listed | AN2: Bloomberg_Ticker | AO2: ISIN | AP2: LEI | AQ2: Acquirer_Parent_Mapping | AR2: Target_Parent_Mapping | AS2: Patent_Search_Acquirer_Names | AT2: Patent_Search_Target_Names | AU2: Final_Classification | AV2: Classification_Confidence | AW2: Patent_Evidence | AX2: Pipeline_Evidence | AY2: Platform_Evidence | AZ2: R_and_D_Evidence | BA2: Commercial_or_Geographic_Evidence | BB2: Mixed_Motive_Flag | BC2: Classification_Notes | BD2: Deal_Validation_Source_URL | BE2: Financial_Currency | BF2: Financial_Data_Status | BG2: Patent_Data_Status | BH2: Patent_Entity_Scope | BI2: Calendar_Year_t-3 | BJ2: Calendar_Year_t-2 | BK2: Calendar_Year_t-1 | BL2: Calendar_Year_t0 | BM2: Calendar_Year_t+1 | BN2: Calendar_Year_t+2 | BO2: Calendar_Year_t+3 | BP2: Revenue_m_t-3 | BQ2: Revenue_m_t-2 | BR2: Revenue_m_t-1 | BS2: Revenue_m_t0 | BT2: Revenue_m_t+1 | BU2: Revenue_m_t+2 | BV2: Revenue_m_t+3 | BW2: Operating_Income_m_t-3 | BX2: Operating_Income_m_t-2 | BY2: Operating_Income_m_t-1 | BZ2: Operating_Income_m_t0 | CA2: Operating_Income_m_t+1 | CB2: Operating_Income_m_t+2 | CC2: Operating_Income_m_t+3 | CD2: Net_Income_m_t-3 | CE2: Net_Income_m_t-2 | CF2: Net_Income_m_t-1 | CG2: Net_Income_m_t0 | CH2: Net_Income_m_t+1 | CI2: Net_Income_m_t+2 | CJ2: Net_Income_m_t+3 | CK2: Total_Assets_m_t-3 | CL2: Total_Assets_m_t-2 | CM2: Total_Assets_m_t-1 | CN2: Total_Assets_m_t0 | CO2: Total_Assets_m_t+1 | CP2: Total_Assets_m_t+2 | CQ2: Total_Assets_m_t+3 | CR2: Total_Debt_m_t-3 | CS2: Total_Debt_m_t-2 | CT2: Total_Debt_m_t-1 | CU2: Total_Debt_m_t0 | CV2: Total_Debt_m_t+1 | CW2: Total_Debt_m_t+2 | CX2: Total_Debt_m_t+3 | CY2: R_and_D_Expense_m_t-3 | CZ2: R_and_D_Expense_m_t-2 | DA2: R_and_D_Expense_m_t-1 | DB2: R_and_D_Expense_m_t0 | DC2: R_and_D_Expense_m_t+1 | DD2: R_and_D_Expense_m_t+2 | DE2: R_and_D_Expense_m_t+3 | DF2: ROA_pct_t-3 | DG2: ROA_pct_t-2 | DH2: ROA_pct_t-1 | DI2: ROA_pct_t0 | DJ2: ROA_pct_t+1 | DK2: ROA_pct_t+2 | DL2: ROA_pct_t+3 | DM2: Operating_Margin_pct_t-3 | DN2: Operating_Margin_pct_t-2 | DO2: Operating_Margin_pct_t-1 | DP2: Operating_Margin_pct_t0 | DQ2: Operating_Margin_pct_t+1 | DR2: Operating_Margin_pct_t+2 | DS2: Operating_Margin_pct_t+3 | DT2: Leverage_pct_t-3 | DU2: Leverage_pct_t-2 | DV2: Leverage_pct_t-1 | DW2: Leverage_pct_t0 | DX2: Leverage_pct_t+1 | DY2: Leverage_pct_t+2 | DZ2: Leverage_pct_t+3 | EA2: Patent_Family_Count_t-3 | EB2: Patent_Family_Count_t-2 | EC2: Patent_Family_Count_t-1 | ED2: Patent_Family_Count_t0 | EE2: Patent_Family_Count_t+1 | EF2: Patent_Family_Count_t+2 | EG2: Patent_Family_Count_t+3 | EH2: Citation_Weighted_Output_t-3 | EI2: Citation_Weighted_Output_t-2 | EJ2: Citation_Weighted_Output_t-1 | EK2: Citation_Weighted_Output_t0 | EL2: Citation_Weighted_Output_t+1 | EM2: Citation_Weighted_Output_t+2 | EN2: Citation_Weighted_Output_t+3 | EO2: Acquirer_PreDeal_Patent_Stock | EP2: Target_PreDeal_Patent_Stock | EQ2: Relative_Knowledge_Base_Size | ER2: Technological_Relatedness_Cosine | ES2: Inventor_Location_Available | ET2: Cross_Border_Relocation_Testable | EU2: Pre_Avg_ROA | EV2: Post_Avg_ROA | EW2: Delta_ROA | EX2: Pre_Avg_Operating_Margin | EY2: Post_Avg_Operating_Margin | EZ2: Delta_Operating_Margin | FA2: Pre_Avg_Patent_Families | FB2: Post_Avg_Patent_Families | FC2: Delta_Patent_Families | FD2: Pre_Avg_Citation_Weighted | FE2: Post_Avg_Citation_Weighted | FF2: Delta_Citation_Weighted | FG2: Complete_Financial_Window | FH2: Complete_Patent_Window | FI2: Data_Ready_Flag
A3: TRT-0001 | B3: 12 | C3: Candidate treatment group | D3: 1 | E3: DATA - Innovation driven deals.xlsx | F3: les laboratoires servier acquires symphogen | G3: Yes | H3: No | I3: No | J3: 1 | K3: Not started | L3: Eligible - 100% | M3: Review | O3: 43924 | P3: 43986 | Q3: 2020 | R3: Q2 2020 | S3: Completed | T3: Les Laboratoires Servier Acquires Symphogen | U3: Mergers & Acquisitions | V3: Acquisition | W3: 100% Acquisition | X3: Denmark | Y3: 100% Acquisition | Z3: Lazard Inc , Rothschild & Co Bank AG | AA3: Plesner , McDermott Will & Emery LLP , Perkins Coie LLP , Gorrissen Federspiel Advokatpartnerselskab | AB3: Les Laboratoires Servier SAS | AC3: les laboratoires servier | AD3: Symphogen A/S | AE3: symphogen a s | AG3: n/a | AH3: Les Laboratoires Servier SA, a pharmaceutical company, has completed the acquisition of Symphogen A/S, a therapeutic antibody discovery company. Following the transaction, Symphogen will now function as the antibody center of excellence of Servier in several different therapeutic areas including oncology. Symphogen, now a subsidiary of Servier, will keep its operational autonomy and continue to rely on its experienced employees while maintaining its headquarters in Ballerup, Denmark. As part of the acquisition, Christophe Thurieau, Executive Director of Servier Research Institute, has been appointed Chief Executive Officer of Symphogen and Karin Garre, former Chief Operating Officer of Symphogen, has been appointed General Manager of Symphogen. Martin Olin, former Chief Executive Officer of Symphogen, will act as an external consultant to support this transition. This transaction enables Servier to strengthen its R&D pipeline by acquiring antibody pipeline and next-generation antibody technologies. Lazard acted as financial advisor, while McDermott Will & Emery and Gorrissen Federspiel Advokatpartnerselskab acted as legal advisors to Servier. Rothschild & Co. acted as financial advisor and Plesner Advokatpartnerselskab and Perkins Coie LLP acted as legal advisors to Symphogen. Deal History: Announced: On April 3, 2020, Les Laboratoires Servier entered into a definitive agreement with the owners of Symphogen. | AI3: This transaction enables Servier to strengthen its R&D pipeline by acquiring antibody pipeline and next-generation antibody technologies. | AL3: Unknown | AM3: Unknown | AS3: Les Laboratoires Servier SAS | AT3: Symphogen A/S | AU3: Not reviewed | AV3: Not assessed | AW3: Unknown | AX3: Unknown | AY3: Unknown | AZ3: Unknown | BA3: Unknown | BB3: Unknown | BF3: Not collected | BG3: Not collected | BH3: Not defined | BI3: =IF($Q3="","",$Q3-3) -> 2017 | BJ3: =IF($Q3="","",$Q3-2) -> 2018 | BK3: =IF($Q3="","",$Q3-1) -> 2019 | BL3: =IF($Q3="","",$Q3+0) -> 2020 | BM3: =IF($Q3="","",$Q3+1) -> 2021 | BN3: =IF($Q3="","",$Q3+2) -> 2022 | BO3: =IF($Q3="","",$Q3+3) -> 2023 | EQ3: =IF(OR($EO3="",$EP3="",$EO3=0),"",$EP3/$EO3) | ES3: Unknown | ET3: Unknown | EU3: =IF(COUNT($DF3,$DG3,$DH3)=0,"",AVERAGE($DF3,$DG3,$DH3)) | EV3: =IF(COUNT($DJ3,$DK3,$DL3)=0,"",AVERAGE($DJ3,$DK3,$DL3)) | EW3: =IF(OR($EU3="",$EV3=""),"",$EV3-$EU3) | EX3: =IF(COUNT($DM3,$DN3,$DO3)=0,"",AVERAGE($DM3,$DN3,$DO3)) | EY3: =IF(COUNT($DQ3,$DR3,$DS3)=0,"",AVERAGE($DQ3,$DR3,$DS3)) | EZ3: =IF(OR($EX3="",$EY3=""),"",$EY3-$EX3) | FA3: =IF(COUNT($EA3,$EB3,$EC3)=0,"",AVERAGE($EA3,$EB3,$EC3)) | FB3: =IF(COUNT($EE3,$EF3,$EG3)=0,"",AVERAGE($EE3,$EF3,$EG3)) | FC3: =IF(OR($FA3="",$FB3=""),"",$FB3-$FA3) | FD3: =IF(COUNT($EH3,$EI3,$EJ3)=0,"",AVERAGE($EH3,$EI3,$EJ3)) | FE3: =IF(COUNT($EL3,$EM3,$EN3)=0,"",AVERAGE($EL3,$EM3,$EN3)) | FF3: =IF(OR($FD3="",$FE3=""),"",$FE3-$FD3) | FG3: =IF(COUNT($DF3,$DG3,$DH3,$DJ3,$DK3,$DL3,$DM3,$DN3,$DO3,$DQ3,$DR3,$DS3)=12,"Yes","No") -> No | FH3: =IF(COUNT($EA3,$EB3,$EC3,$EE3,$EF3,$EG3,$EH3,$EI3,$EJ3,$EL3,$EM3,$EN3)=12,"Yes","No") -> No | FI3: =IF(AND($M3="Include",OR($FG3="Yes",$FH3="Yes")),"Ready","Not ready") -> Not ready
A4: TRT-0002 | B4: 13 | C4: Candidate treatment group | D4: 1 | E4: DATA - Innovation driven deals.xlsx | F4: towa pharma acquires pensa investments | G4: Yes | H4: No | I4: No | J4: 1 | K4: Not started | L4: Eligible - 100% | M4: Review | O4: 43822 | P4: 43861 | Q4: 2020 | R4: Q4 2019 | S4: Completed | T4: Towa Pharma Acquires Pensa Investments | U4: Mergers & Acquisitions | V4: Acquisition | W4: 100% Acquisition | X4: Spain | Y4: 100% Acquisition | Z4: Lazard Inc , Barclays Plc | AA4: Nishimura & Asahi , Clifford Chance LLP , Gomez-Acebo & Pombo Abogados SLP | AB4: Towa Pharmaceutical Co Ltd | AC4: towa pharmaceutical | AD4: Pensa Investments, S.L. | AE4: pensa investments s l | AF4: 354 | AG4: 354 | AH4: Towa Pharmaceutical Co. Ltd., a company engaged in the manufacture and distribution of pharmaceutical products, has completed its acquisition of Pensa Investments, S.L., a company that provides affiliate pharmaceutical manufacturing facilities including pharmaceutical development, from Esteve Pharmaceuticals, S.A., a pharmaceutical company. Breckenridge Pharma announced Towa Pharma completed its acquisition of Esteve’s generics division, including Breckenridge. The purchase price of Pensa will be an all cash deal with an upfront payment of EUR320 million. The transaction will allow Towa Pharma to accelerate its overseas business presence and to provide quality and value-added generic medicines to patients in all over world. Deal History: Announced: On December 21, 2019, Towa Pharma reached an agreement to acquire 100% stake in Pensa Investments from Esteve Pharma. | AI4: The transaction will allow Towa Pharma to accelerate its overseas business presence and to provide quality and value-added generic medicines to patients in all over world. | AL4: Unknown | AM4: Unknown | AS4: Towa Pharmaceutical Co Ltd | AT4: Pensa Investments, S.L. | AU4: Not reviewed | AV4: Not assessed | AW4: Unknown | AX4: Unknown | AY4: Unknown | AZ4: Unknown | BA4: Unknown | BB4: Unknown | BF4: Not collected | BG4: Not collected | BH4: Not defined | BI4: =IF($Q4="","",$Q4-3) -> 2017 | BJ4: =IF($Q4="","",$Q4-2) -> 2018 | BK4: =IF($Q4="","",$Q4-1) -> 2019 | BL4: =IF($Q4="","",$Q4+0) -> 2020 | BM4: =IF($Q4="","",$Q4+1) -> 2021 | BN4: =IF($Q4="","",$Q4+2) -> 2022 | BO4: =IF($Q4="","",$Q4+3) -> 2023 | EQ4: =IF(OR($EO4="",$EP4="",$EO4=0),"",$EP4/$EO4) | ES4: Unknown | ET4: Unknown | EU4: =IF(COUNT($DF4,$DG4,$DH4)=0,"",AVERAGE($DF4,$DG4,$DH4)) | EV4: =IF(COUNT($DJ4,$DK4,$DL4)=0,"",AVERAGE($DJ4,$DK4,$DL4)) | EW4: =IF(OR($EU4="",$EV4=""),"",$EV4-$EU4) | EX4: =IF(COUNT($DM4,$DN4,$DO4)=0,"",AVERAGE($DM4,$DN4,$DO4)) | EY4: =IF(COUNT($DQ4,$DR4,$DS4)=0,"",AVERAGE($DQ4,$DR4,$DS4)) | EZ4: =IF(OR($EX4="",$EY4=""),"",$EY4-$EX4) | FA4: =IF(COUNT($EA4,$EB4,$EC4)=0,"",AVERAGE($EA4,$EB4,$EC4)) | FB4: =IF(COUNT($EE4,$EF4,$EG4)=0,"",AVERAGE($EE4,$EF4,$EG4)) | FC4: =IF(OR($FA4="",$FB4=""),"",$FB4-$FA4) | FD4: =IF(COUNT($EH4,$EI4,$EJ4)=0,"",AVERAGE($EH4,$EI4,$EJ4)) | FE4: =IF(COUNT($EL4,$EM4,$EN4)=0,"",AVERAGE($EL4,$EM4,$EN4)) | FF4: =IF(OR($FD4="",$FE4=""),"",$FE4-$FD4) | FG4: =IF(COUNT($DF4,$DG4,$DH4,$DJ4,$DK4,$DL4,$DM4,$DN4,$DO4,$DQ4,$DR4,$DS4)=12,"Yes","No") -> No | FH4: =IF(COUNT($EA4,$EB4,$EC4,$EE4,$EF4,$EG4,$EH4,$EI4,$EJ4,$EL4,$EM4,$EN4)=12,"Yes","No") -> No | FI4: =IF(AND($M4="Include",OR($FG4="Yes",$FH4="Yes")),"Ready","Not ready") -> Not ready
A5: TRT-0003 | B5: 14 | C5: Candidate treatment group | D5: 1 | E5: DATA - Innovation driven deals.xlsx | F5: pfizer acquires therachon for | G5: Yes | H5: No | I5: No | J5: 1 | K5: Not started | L5: Eligible - 100% | M5: Review | O5: 43593 | P5: 43647 | Q5: 2019 | R5: Q2 2019 | S5: Completed | T5: Pfizer Acquires Therachon for USD810 Million | U5: Mergers & Acquisitions | V5: Acquisition | W5: 100% Acquisition | X5: Switzerland | Y5: 100% Acquisition | Z5: The Goldman Sachs Group Inc | AA5: Cooley LLP , Homburger AG , Lenz & Staehelin , Arnold & Porter LLP | AB5: Pfizer Inc | AC5: pfizer | AD5: Therachon AG (Inactive) | AE5: therachon | AF5: 810 | AG5: 810 | AH5: Pfizer Inc., a pharmaceutical company, has completion acquisition of all the shares of Therachon Holding AG, a clinical-stage biotechnology company focused on rare diseases with assets in development for the treatment of achondroplasia and short bowel syndrome (SBS). Under the terms of the transaction, Pfizer acquired Therachon for USD340 million with an additional USD470 million in additional payments contingent on the achievement of key milestones in the development and commercialization of TA-46. TA-46 is an investigational, soluble recombinant human fibroblast growth factor receptor 3 (FGFR3) decoy, for bone development abnormalities associated with achondroplasia. Prior to the closing of the transaction with Pfizer, Therachon will spin-off its apraglutide development program into a separate, independent company. Apraglutide is a GLP-2 analog in Phase II development for short bowel syndrome. Pfizer Ventures, the venture capital arm of Pfizer Inc., currently holds a minority stake and will continue to hold an equity stake in the new company. The transaction is not expected to impact Pfizer’s current 2019 adjusted financial guidance. The acquisition enables Pfizer to expand its rare disease portfolio with potential first-in-class therapy for achondroplasia through the development of TA-46. Goldman Sachs acted as financial advisor while Cooley LLP and Homburger AG acted as legal advisors to Therachon. Arnold & Porter and Lenz & Staehelin acted as legal advisors to Pfizer. Deal History: Announced: On May 8, 2019, Pfizer entered into a definitive agreement to acquire all the shares of Therachon. | AI5: The acquisition enables Pfizer to expand its rare disease portfolio with potential first-in-class therapy for achondroplasia through the development of TA-46. | AL5: Unknown | AM5: Unknown | AS5: Pfizer Inc | AT5: Therachon AG (Inactive) | AU5: Not reviewed | AV5: Not assessed | AW5: Unknown | AX5: Unknown | AY5: Unknown | AZ5: Unknown | BA5: Unknown | BB5: Unknown | BF5: Not collected | BG5: Not collected | BH5: Not defined | BI5: =IF($Q5="","",$Q5-3) -> 2016 | BJ5: =IF($Q5="","",$Q5-2) -> 2017 | BK5: =IF($Q5="","",$Q5-1) -> 2018 | BL5: =IF($Q5="","",$Q5+0) -> 2019 | BM5: =IF($Q5="","",$Q5+1) -> 2020 | BN5: =IF($Q5="","",$Q5+2) -> 2021 | BO5: =IF($Q5="","",$Q5+3) -> 2022 | EQ5: =IF(OR($EO5="",$EP5="",$EO5=0),"",$EP5/$EO5) | ES5: Unknown | ET5: Unknown | EU5: =IF(COUNT($DF5,$DG5,$DH5)=0,"",AVERAGE($DF5,$DG5,$DH5)) | EV5: =IF(COUNT($DJ5,$DK5,$DL5)=0,"",AVERAGE($DJ5,$DK5,$DL5)) | EW5: =IF(OR($EU5="",$EV5=""),"",$EV5-$EU5) | EX5: =IF(COUNT($DM5,$DN5,$DO5)=0,"",AVERAGE($DM5,$DN5,$DO5)) | EY5: =IF(COUNT($DQ5,$DR5,$DS5)=0,"",AVERAGE($DQ5,$DR5,$DS5)) | EZ5: =IF(OR($EX5="",$EY5=""),"",$EY5-$EX5) | FA5: =IF(COUNT($EA5,$EB5,$EC5)=0,"",AVERAGE($EA5,$EB5,$EC5)) | FB5: =IF(COUNT($EE5,$EF5,$EG5)=0,"",AVERAGE($EE5,$EF5,$EG5)) | FC5: =IF(OR($FA5="",$FB5=""),"",$FB5-$FA5) | FD5: =IF(COUNT($EH5,$EI5,$EJ5)=0,"",AVERAGE($EH5,$EI5,$EJ5)) | FE5: =IF(COUNT($EL5,$EM5,$EN5)=0,"",AVERAGE($EL5,$EM5,$EN5)) | FF5: =IF(OR($FD5="",$FE5=""),"",$FE5-$FD5) | FG5: =IF(COUNT($DF5,$DG5,$DH5,$DJ5,$DK5,$DL5,$DM5,$DN5,$DO5,$DQ5,$DR5,$DS5)=12,"Yes","No") -> No | FH5: =IF(COUNT($EA5,$EB5,$EC5,$EE5,$EF5,$EG5,$EH5,$EI5,$EJ5,$EL5,$EM5,$EN5)=12,"Yes","No") -> No | FI5: =IF(AND($M5="Include",OR($FG5="Yes",$FH5="Yes")),"Ready","Not ready") -> Not ready
A6: TRT-0004 | B6: 15 | C6: Candidate treatment group | D6: 1 | E6: DATA - Innovation driven deals.xlsx | F6: gyroscope therapeutics merges with orbit biomedical | G6: Yes | H6: No | I6: No | J6: 1 | K6: Not started | L6: Review - merger | M6: Review | O6: 43566 | P6: 43566 | Q6: 2019 | R6: Q2 2019 | S6: Completed | T6: Gyroscope Therapeutics Merges with Orbit Biomedical | U6: Mergers & Acquisitions | V6: Merger | X6: United Kingdom , United States | AB6: Gyroscope Therapeutics Holdings Plc | AC6: gyroscope therapeutics | AD6: Orbit Biomedical Inc; Gyroscope Therapeutics Holdings Plc | AE6: orbit biomedical gyroscope therapeutics | AG6: n/a | AH6: Gyroscope Therapeutics Ltd, an ophthalmology company developing genetically defined therapies for retinal diseases, and Orbit Biomedical, a medical device company focused on precision sub-retinal therapeutic delivery, have merged to form a combined retinal gene therapy platform. Under the terms, Syncona Ltd, the shareholder of both the companies, will own 82% of the enlarged company, which will retain the Gyroscope name. The merger enables the companies to form a sub-retinal surgical platform with Gyroscope's clinical stage pipeline and gene therapy manufacturing platform. | AI6: The merger enables the companies to form a sub-retinal surgical platform with Gyroscope's clinical stage pipeline and gene therapy manufacturing platform. | AL6: Unknown | AM6: Unknown | AS6: Gyroscope Therapeutics Holdings Plc | AT6: Orbit Biomedical Inc; Gyroscope Therapeutics Holdings Plc | AU6: Not reviewed | AV6: Not assessed | AW6: Unknown | AX6: Unknown | AY6: Unknown | AZ6: Unknown | BA6: Unknown | BB6: Unknown | BF6: Not collected | BG6: Not collected | BH6: Not defined | BI6: =IF($Q6="","",$Q6-3) -> 2016 | BJ6: =IF($Q6="","",$Q6-2) -> 2017 | BK6: =IF($Q6="","",$Q6-1) -> 2018 | BL6: =IF($Q6="","",$Q6+0) -> 2019 | BM6: =IF($Q6="","",$Q6+1) -> 2020 | BN6: =IF($Q6="","",$Q6+2) -> 2021 | BO6: =IF($Q6="","",$Q6+3) -> 2022 | EQ6: =IF(OR($EO6="",$EP6="",$EO6=0),"",$EP6/$EO6) | ES6: Unknown | ET6: Unknown | EU6: =IF(COUNT($DF6,$DG6,$DH6)=0,"",AVERAGE($DF6,$DG6,$DH6)) | EV6: =IF(COUNT($DJ6,$DK6,$DL6)=0,"",AVERAGE($DJ6,$DK6,$DL6)) | EW6: =IF(OR($EU6="",$EV6=""),"",$EV6-$EU6) | EX6: =IF(COUNT($DM6,$DN6,$DO6)=0,"",AVERAGE($DM6,$DN6,$DO6)) | EY6: =IF(COUNT($DQ6,$DR6,$DS6)=0,"",AVERAGE($DQ6,$DR6,$DS6)) | EZ6: =IF(OR($EX6="",$EY6=""),"",$EY6-$EX6) | FA6: =IF(COUNT($EA6,$EB6,$EC6)=0,"",AVERAGE($EA6,$EB6,$EC6)) | FB6: =IF(COUNT($EE6,$EF6,$EG6)=0,"",AVERAGE($EE6,$EF6,$EG6)) | FC6: =IF(OR($FA6="",$FB6=""),"",$FB6-$FA6) | FD6: =IF(COUNT($EH6,$EI6,$EJ6)=0,"",AVERAGE($EH6,$EI6,$EJ6)) | FE6: =IF(COUNT($EL6,$EM6,$EN6)=0,"",AVERAGE($EL6,$EM6,$EN6)) | FF6: =IF(OR($FD6="",$FE6=""),"",$FE6-$FD6) | FG6: =IF(COUNT($DF6,$DG6,$DH6,$DJ6,$DK6,$DL6,$DM6,$DN6,$DO6,$DQ6,$DR6,$DS6)=12,"Yes","No") -> No | FH6: =IF(COUNT($EA6,$EB6,$EC6,$EE6,$EF6,$EG6,$EH6,$EI6,$EJ6,$EL6,$EM6,$EN6)=12,"Yes","No") -> No | FI6: =IF(AND($M6="Include",OR($FG6="Yes",$FH6="Yes")),"Ready","Not ready") -> Not ready
A7: TRT-0005 | B7: 16 | C7: Candidate treatment group | D7: 1 | E7: DATA - Innovation driven deals.xlsx | F7: trinetx acquires custodix | G7: Yes | H7: No | I7: No | J7: 1 | K7: Not started | L7: Eligible - 100% | M7: Review | O7: 43557 | P7: 43557 | Q7: 2019 | R7: Q2 2019 | S7: Completed | T7: TriNetX Acquires Custodix | U7: Mergers & Acquisitions | V7: Acquisition | W7: 100% Acquisition | X7: Belgium | Y7: 100% Acquisition | AB7: TriNetX LLC | AC7: trinetx | AD7: Custodix NV | AE7: custodix | AG7: n/a | AH7: TriNetX, Inc., a health research network, has acquired Custodix NV and its InSite network, a provider of services for clinical trial design, patient feasibility, and enabling workflow for patient recruitment. The InSite platform allows the re-use of Electronic Health Records (EHR) data for research. The acquisition enables TriNetx to provide a largest platform for clinical research to healthcare organizations throughout Europe. | AI7: The acquisition enables TriNetx to provide a largest platform for clinical research to healthcare organizations throughout Europe. | AL7: Unknown | AM7: Unknown | AS7: TriNetX LLC | AT7: Custodix NV | AU7: Not reviewed | AV7: Not assessed | AW7: Unknown | AX7: Unknown | AY7: Unknown | AZ7: Unknown | BA7: Unknown | BB7: Unknown | BF7: Not collected | BG7: Not collected | BH7: Not defined | BI7: =IF($Q7="","",$Q7-3) -> 2016 | BJ7: =IF($Q7="","",$Q7-2) -> 2017 | BK7: =IF($Q7="","",$Q7-1) -> 2018 | BL7: =IF($Q7="","",$Q7+0) -> 2019 | BM7: =IF($Q7="","",$Q7+1) -> 2020 | BN7: =IF($Q7="","",$Q7+2) -> 2021 | BO7: =IF($Q7="","",$Q7+3) -> 2022 | EQ7: =IF(OR($EO7="",$EP7="",$EO7=0),"",$EP7/$EO7) | ES7: Unknown | ET7: Unknown | EU7: =IF(COUNT($DF7,$DG7,$DH7)=0,"",AVERAGE($DF7,$DG7,$DH7)) | EV7: =IF(COUNT($DJ7,$DK7,$DL7)=0,"",AVERAGE($DJ7,$DK7,$DL7)) | EW7: =IF(OR($EU7="",$EV7=""),"",$EV7-$EU7) | EX7: =IF(COUNT($DM7,$DN7,$DO7)=0,"",AVERAGE($DM7,$DN7,$DO7)) | EY7: =IF(COUNT($DQ7,$DR7,$DS7)=0,"",AVERAGE($DQ7,$DR7,$DS7)) | EZ7: =IF(OR($EX7="",$EY7=""),"",$EY7-$EX7) | FA7: =IF(COUNT($EA7,$EB7,$EC7)=0,"",AVERAGE($EA7,$EB7,$EC7)) | FB7: =IF(COUNT($EE7,$EF7,$EG7)=0,"",AVERAGE($EE7,$EF7,$EG7)) | FC7: =IF(OR($FA7="",$FB7=""),"",$FB7-$FA7) | FD7: =IF(COUNT($EH7,$EI7,$EJ7)=0,"",AVERAGE($EH7,$EI7,$EJ7)) | FE7: =IF(COUNT($EL7,$EM7,$EN7)=0,"",AVERAGE($EL7,$EM7,$EN7)) | FF7: =IF(OR($FD7="",$FE7=""),"",$FE7-$FD7) | FG7: =IF(COUNT($DF7,$DG7,$DH7,$DJ7,$DK7,$DL7,$DM7,$DN7,$DO7,$DQ7,$DR7,$DS7)=12,"Yes","No") -> No | FH7: =IF(COUNT($EA7,$EB7,$EC7,$EE7,$EF7,$EG7,$EH7,$EI7,$EJ7,$EL7,$EM7,$EN7)=12,"Yes","No") -> No | FI7: =IF(AND($M7="Include",OR($FG7="Yes",$FH7="Yes")),"Ready","Not ready") -> Not ready
A8: TRT-0006 | B8: 17 | C8: Candidate treatment group | D8: 1 | E8: DATA - Innovation driven deals.xlsx | F8: bravo bidco boston scientific acquires btg for | G8: Yes | H8: No | I8: No | J8: 1 | K8: Not started | L8: Eligible - 100% | M8: Review | O8: 43424 | P8: 43696 | Q8: 2019 | R8: Q4 2018 | S8: Completed | T8: Bravo Bidco (Boston Scientific) Acquires BTG for USD4.24 Billion | U8: Mergers & Acquisitions | V8: Acquisition | W8: 100% Acquisition | X8: United Kingdom | Y8: 100% Acquisition | Z8: Rothschild & Co SCA , The Goldman Sachs Group Inc , Deutsche Bank AG , J.P. Morgan Cazenove Ltd (Inactive) , Barclays Wealth Management , Goldman Sachs International | AA8: Shearman & Sterling LLP , Simpson Thacher & Bartlett LLP , Allen Overy Shearman Sterling LLP , Travers Smith LLP , White & Case LLP , Arnold & Porter Kaye Scholer LLP | AB8: Bravo Bidco Ltd | AC8: bravo bidco | AD8: BTG Ltd | AE8: btg | AF8: 4239 | AG8: 4239 | AH8: Boston Scientific Corp, a medical technology, through its wholly-owned subsidiary, Bravo Bidco Ltd, has completed the acquisition of BTG plc, a company which develops and commercializes products used in minimally-invasive procedures targeting cancer and vascular diseases, as well as acute care pharmaceuticals, for GBP3.3 billion. In addition to the Interventional Medicine product lines, the BTG portfolio also includes a specialty pharmaceutical business comprised of acute care antidotes to treat overexposure to certain medications and toxins, and a licensing business that receives royalties related to BTG intellectual property and product license agreements. Upon the effectiveness of the scheme of arrangement, BTG became a wholly-owned subsidiary of Boston Scientific, and BTG shares no longer trade on the London Stock Exchange. Under the terms of the previously announced transaction, holders of BTG common shares will receive 840 pence in cash per share. The transaction would be funded with a combination of cash on hand and proceeds from debt financing entered into by Boston Scientific. The acquisition will enable Bravo Bidco to expand peripheral interventions portfolio with minimally-invasive treatments for cancers and vascular conditions. Goldman Sachs International, Deutsche Bank AG, J.P. Morgan Cazenove and Rothschild & Co acted as financial advisors where as Allen & Overy LLP acted as legal adviser to BTG, while Barclays acted as financial advisor where as Shearman & Sterling LLP, Simpson Thacher & Bartlett LLP, Arnold & Porter Kaye Scholer LLP and Travers Smith LLP acted as legal advisors, respectively, to Bravo Bidco. Deal History: Announced: On November 20, 2018, Boston Scientific reached an agreement on the terms of a recommended cash offer by its wholly-owned subsidiary, Bravo Bidco Ltd, for the acquisition of the entire issued and to be issued ordinary share capital (100%) of BTG plc, a company which develops and commercializes products used in minimally-invasive procedures targeting cancer and vascular diseases, as well as acute care pharmaceuticals, for GBP3.3 billion. Update: On December 12, 2018, BTG, Boston Scientific and Bidco entered into an amendment to the Co-operation Agreement to extend the date by which certain regulatory filings must be made in Spain, Germany and other relevant jurisdictions. The filing of the notification in respect of the Acquisition under the HSR Act was made yesterday. Update: On February 15, 2019, The Transaction has received merger control clearance in Germany under the German Act Against Restraints of Competition and the Taiwan Fair Trade Commission has terminated its investigation. Update: On February 28, 2019, The shareholders of BTG have approved in respect of the previously announced recommended cash offer to acquire the entire issued and to be issued ordinary share capital of BTG by Bravo Bidco, an indirect wholly-owned subsidiary of Boston Scientific. Update: On August 2, 2019, BTG and Boston Scientific are pleased to confirm that the Transaction has received merger control clearance from the US Federal Trade Commission under the HSR Act, on July 25, 2019 the CNMC issued a clearance decision under the Spanish Competition Act and on August 2, 2019, the Federal Competition Authority of Austria issued a clearance decision pursuant to Sec 11 Para 4 Austrian Cartel Act. | AI8: The acquisition will enable Bravo Bidco to expand peripheral interventions portfolio with minimally-invasive treatments for cancers and vascular conditions. | AL8: Unknown | AM8: Unknown | AS8: Bravo Bidco Ltd | AT8: BTG Ltd | AU8: Not reviewed | AV8: Not assessed | AW8: Unknown | AX8: Unknown | AY8: Unknown | AZ8: Unknown | BA8: Unknown | BB8: Unknown | BF8: Not collected | BG8: Not collected | BH8: Not defined | BI8: =IF($Q8="","",$Q8-3) -> 2016 | BJ8: =IF($Q8="","",$Q8-2) -> 2017 | BK8: =IF($Q8="","",$Q8-1) -> 2018 | BL8: =IF($Q8="","",$Q8+0) -> 2019 | BM8: =IF($Q8="","",$Q8+1) -> 2020 | BN8: =IF($Q8="","",$Q8+2) -> 2021 | BO8: =IF($Q8="","",$Q8+3) -> 2022 | EQ8: =IF(OR($EO8="",$EP8="",$EO8=0),"",$EP8/$EO8) | ES8: Unknown | ET8: Unknown | EU8: =IF(COUNT($DF8,$DG8,$DH8)=0,"",AVERAGE($DF8,$DG8,$DH8)) | EV8: =IF(COUNT($DJ8,$DK8,$DL8)=0,"",AVERAGE($DJ8,$DK8,$DL8)) | EW8: =IF(OR($EU8="",$EV8=""),"",$EV8-$EU8) | EX8: =IF(COUNT($DM8,$DN8,$DO8)=0,"",AVERAGE($DM8,$DN8,$DO8)) | EY8: =IF(COUNT($DQ8,$DR8,$DS8)=0,"",AVERAGE($DQ8,$DR8,$DS8)) | EZ8: =IF(OR($EX8="",$EY8=""),"",$EY8-$EX8) | FA8: =IF(COUNT($EA8,$EB8,$EC8)=0,"",AVERAGE($EA8,$EB8,$EC8)) | FB8: =IF(COUNT($EE8,$EF8,$EG8)=0,"",AVERAGE($EE8,$EF8,$EG8)) | FC8: =IF(OR($FA8="",$FB8=""),"",$FB8-$FA8) | FD8: =IF(COUNT($EH8,$EI8,$EJ8)=0,"",AVERAGE($EH8,$EI8,$EJ8)) | FE8: =IF(COUNT($EL8,$EM8,$EN8)=0,"",AVERAGE($EL8,$EM8,$EN8)) | FF8: =IF(OR($FD8="",$FE8=""),"",$FE8-$FD8) | FG8: =IF(COUNT($DF8,$DG8,$DH8,$DJ8,$DK8,$DL8,$DM8,$DN8,$DO8,$DQ8,$DR8,$DS8)=12,"Yes","No") -> No | FH8: =IF(COUNT($EA8,$EB8,$EC8,$EE8,$EF8,$EG8,$EH8,$EI8,$EJ8,$EL8,$EM8,$EN8)=12,"Yes","No") -> No | FI8: =IF(AND($M8="Include",OR($FG8="Yes",$FH8="Yes")),"Ready","Not ready") -> Not ready
A9: TRT-0007 | B9: 18 | C9: Candidate treatment group | D9: 1 | E9: DATA - Innovation driven deals.xlsx | F9: aphria acquires cc pharma | G9: Yes | H9: No | I9: No | J9: 1 | K9: Not started | L9: Review - majority | M9: Review | O9: 43409 | P9: 43474 | Q9: 2019 | R9: Q4 2018 | S9: Completed | T9: Aphria Acquires CC Pharma | U9: Mergers & Acquisitions | V9: Acquisition | W9: Majority Acquisition | X9: Germany | Y9: Majority Acquisition | AB9: Aphria Inc | AC9: aphria | AD9: CC Pharma GmbH | AE9: cc pharma | AF9: 28 | AG9: 28 | AH9: Aphria Inc., a global cannabis company, has completed the acquisition of CC Pharma GmbH, a distributor of pharmaceutical products. Under the terms of consideration, Aphria will pay EUR24.5 million in cash to CC Pharma at closing, with an earn-out multiple on future EBITDA of up to another EUR23.5 million following closing, if certain performance milestones are met. Aphria, through its subsidiary Aphria International, previously announced a supply agreement with CC Pharma to export approximately 1,200 kilograms of medical cannabis products from Canada to Germany. CC Pharma operates a production, repackaging and labeling facility at its headquarters in Densborn. The transaction enables Aphria to strengthen its end-to-end medical cannabis operations and infrastructure in Germany. Deal History: Announced: On November 5, 2011, Aphria announced its proposed acquisition of CC Pharma. | AI9: The transaction enables Aphria to strengthen its end-to-end medical cannabis operations and infrastructure in Germany. | AL9: Unknown | AM9: Unknown | AS9: Aphria Inc | AT9: CC Pharma GmbH | AU9: Not reviewed | AV9: Not assessed | AW9: Unknown | AX9: Unknown | AY9: Unknown | AZ9: Unknown | BA9: Unknown | BB9: Unknown | BF9: Not collected | BG9: Not collected | BH9: Not defined | BI9: =IF($Q9="","",$Q9-3) -> 2016 | BJ9: =IF($Q9="","",$Q9-2) -> 2017 | BK9: =IF($Q9="","",$Q9-1) -> 2018 | BL9: =IF($Q9="","",$Q9+0) -> 2019 | BM9: =IF($Q9="","",$Q9+1) -> 2020 | BN9: =IF($Q9="","",$Q9+2) -> 2021 | BO9: =IF($Q9="","",$Q9+3) -> 2022 | EQ9: =IF(OR($EO9="",$EP9="",$EO9=0),"",$EP9/$EO9) | ES9: Unknown | ET9: Unknown | EU9: =IF(COUNT($DF9,$DG9,$DH9)=0,"",AVERAGE($DF9,$DG9,$DH9)) | EV9: =IF(COUNT($DJ9,$DK9,$DL9)=0,"",AVERAGE($DJ9,$DK9,$DL9)) | EW9: =IF(OR($EU9="",$EV9=""),"",$EV9-$EU9) | EX9: =IF(COUNT($DM9,$DN9,$DO9)=0,"",AVERAGE($DM9,$DN9,$DO9)) | EY9: =IF(COUNT($DQ9,$DR9,$DS9)=0,"",AVERAGE($DQ9,$DR9,$DS9)) | EZ9: =IF(OR($EX9="",$EY9=""),"",$EY9-$EX9) | FA9: =IF(COUNT($EA9,$EB9,$EC9)=0,"",AVERAGE($EA9,$EB9,$EC9)) | FB9: =IF(COUNT($EE9,$EF9,$EG9)=0,"",AVERAGE($EE9,$EF9,$EG9)) | FC9: =IF(OR($FA9="",$FB9=""),"",$FB9-$FA9) | FD9: =IF(COUNT($EH9,$EI9,$EJ9)=0,"",AVERAGE($EH9,$EI9,$EJ9)) | FE9: =IF(COUNT($EL9,$EM9,$EN9)=0,"",AVERAGE($EL9,$EM9,$EN9)) | FF9: =IF(OR($FD9="",$FE9=""),"",$FE9-$FD9) | FG9: =IF(COUNT($DF9,$DG9,$DH9,$DJ9,$DK9,$DL9,$DM9,$DN9,$DO9,$DQ9,$DR9,$DS9)=12,"Yes","No") -> No | FH9: =IF(COUNT($EA9,$EB9,$EC9,$EE9,$EF9,$EG9,$EH9,$EI9,$EJ9,$EL9,$EM9,$EN9)=12,"Yes","No") -> No | FI9: =IF(AND($M9="Include",OR($FG9="Yes",$FH9="Yes")),"Ready","Not ready") -> Not ready
A10: TRT-0008 | B10: 19 | C10: Candidate treatment group | D10: 1 | E10: DATA - Innovation driven deals.xlsx | F10: ingenza acquires stake in amprologix | G10: Yes | H10: No | I10: No | J10: 1 | K10: Not started | L10: Exclude - minority | M10: Review | O10: 43363 | P10: 43363 | Q10: 2018 | R10: Q3 2018 | S10: Completed | T10: Ingenza Acquires Stake in Amprologix | U10: Mergers & Acquisitions | V10: Acquisition | W10: Minority Acquisition | X10: United Kingdom | Y10: Minority Acquisition | AB10: Ingenza Ltd | AC10: ingenza | AD10: Amprologix Ltd | AE10: amprologix | AG10: n/a | AH10: Ingenza Ltd, an industrial biotechnology and synthetic biology company, has acquired a stake in Amprologix Ltd, a spin-out company from the University of Plymouth. Amprologix develops and commercialises epidermicins, a new class of antibiotics capable of rapidly killing harmful bacteria, including methicillin-resistant Staphylococcus aureus (MRSA), Streptoccus and Enterococcus at very low doses. The acquisition enables Ingenza to discover and improve new antimicrobial classes. | AI10: The acquisition enables Ingenza to discover and improve new antimicrobial classes. | AL10: Unknown | AM10: Unknown | AS10: Ingenza Ltd | AT10: Amprologix Ltd | AU10: Not reviewed | AV10: Not assessed | AW10: Unknown | AX10: Unknown | AY10: Unknown | AZ10: Unknown | BA10: Unknown | BB10: Unknown | BF10: Not collected | BG10: Not collected | BH10: Not defined | BI10: =IF($Q10="","",$Q10-3) -> 2015 | BJ10: =IF($Q10="","",$Q10-2) -> 2016 | BK10: =IF($Q10="","",$Q10-1) -> 2017 | BL10: =IF($Q10="","",$Q10+0) -> 2018 | BM10: =IF($Q10="","",$Q10+1) -> 2019 | BN10: =IF($Q10="","",$Q10+2) -> 2020 | BO10: =IF($Q10="","",$Q10+3) -> 2021 | EQ10: =IF(OR($EO10="",$EP10="",$EO10=0),"",$EP10/$EO10) | ES10: Unknown | ET10: Unknown | EU10: =IF(COUNT($DF10,$DG10,$DH10)=0,"",AVERAGE($DF10,$DG10,$DH10)) | EV10: =IF(COUNT($DJ10,$DK10,$DL10)=0,"",AVERAGE($DJ10,$DK10,$DL10)) | EW10: =IF(OR($EU10="",$EV10=""),"",$EV10-$EU10) | EX10: =IF(COUNT($DM10,$DN10,$DO10)=0,"",AVERAGE($DM10,$DN10,$DO10)) | EY10: =IF(COUNT($DQ10,$DR10,$DS10)=0,"",AVERAGE($DQ10,$DR10,$DS10)) | EZ10: =IF(OR($EX10="",$EY10=""),"",$EY10-$EX10) | FA10: =IF(COUNT($EA10,$EB10,$EC10)=0,"",AVERAGE($EA10,$EB10,$EC10)) | FB10: =IF(COUNT($EE10,$EF10,$EG10)=0,"",AVERAGE($EE10,$EF10,$EG10)) | FC10: =IF(OR($FA10="",$FB10=""),"",$FB10-$FA10) | FD10: =IF(COUNT($EH10,$EI10,$EJ10)=0,"",AVERAGE($EH10,$EI10,$EJ10)) | FE10: =IF(COUNT($EL10,$EM10,$EN10)=0,"",AVERAGE($EL10,$EM10,$EN10)) | FF10: =IF(OR($FD10="",$FE10=""),"",$FE10-$FD10) | FG10: =IF(COUNT($DF10,$DG10,$DH10,$DJ10,$DK10,$DL10,$DM10,$DN10,$DO10,$DQ10,$DR10,$DS10)=12,"Yes","No") -> No | FH10: =IF(COUNT($EA10,$EB10,$EC10,$EE10,$EF10,$EG10,$EH10,$EI10,$EJ10,$EL10,$EM10,$EN10)=12,"Yes","No") -> No | FI10: =IF(AND($M10="Include",OR($FG10="Yes",$FH10="Yes")),"Ready","Not ready") -> Not ready
A11: TRT-0009 | B11: 20 | C11: Candidate treatment group | D11: 1 | E11: DATA - Innovation driven deals.xlsx | F11: telix pharma acquires atlab pharma for | G11: Yes | H11: No | I11: No | J11: 1 | K11: Not started | L11: Eligible - 100% | M11: Review | O11: 43354 | P11: 43354 | Q11: 2018 | R11: Q3 2018 | S11: Completed | T11: Telix Pharma Acquires Atlab Pharma for USD10 Million | U11: Mergers & Acquisitions | V11: Acquisition | W11: 100% Acquisition | X11: France | Y11: 100% Acquisition | AB11: Telix Pharmaceuticals Ltd | AC11: telix pharmaceuticals | AD11: ATLAB Pharma SAS | AE11: atlab pharma | AF11: 10 | AG11: 10 | AH11: Telix Pharmaceuticals Limited, a clinical-stage biotechnology company, has completed the acquisition of Atlab Pharma SAS, a biotechnology company, for a purchase consideration of USD10 million. Telix Pharma has exercised an option to acquire Atlab Pharma. A total of 14,840,000 shares were issued in consideration. The consideration of USD10 million is issued as USD9 million in Telix shares to Atlab shareholders, at USD0.89 per share, USD0.5 million in Telix shares to BZL, also at USD0.89 per share. These shares are paid to BZL as partial consideration for a significant reduction in royalty rates for the background IP, as a closing condition of the transaction, and USD0.5 million in warrants over Telix shares to BZL, with an exercise price of USD1.34 per share. As part of the transaction, Telix Pharma has also entered into a limited back - license with BZL Biologics LLC(BZL) for certain IP rights to support ongoing commercial research activities that are outside of the scope of product development focus for Telix Pharma. Prof. Jean-Francois Chatal (Atlab/ Universite de Nantes) and Prof. Neil Bander (BZL/ WCMC ) will continue to serve as members of Telix’s scientific advisory board. The transaction enables Telix Pharma to support potential indication expansion for TLX591, notably the combination use of anti-PSMA therapeutics in conjunction with anti-androgen drugs, further increasing the value and relevance of its TLX591 program; Atlab Pharma possesses rights to an extensive clinical data set in approximately 200 patients that is highly informative to the development of TLX591, including unpublished data around dose optimization schemes for antibody-based PSMA radiopharmaceuticals. This data may accelerate and further de-risk the future development of TLX591; Atlab Pharma and BZL, together, bring considerable knowledge and expertise to the Telix team; and Atlab possesses the rights and materials necessary to develop huJ591, the most widely clinically-studied anti-PSMA antibody. Telix will keep huJ591 as a back-up clinical drug candidate and continue to support several high-value academic collaborations around the use of this antibody that may also be informative to the future development of TLX591, including in non-prostate cancer indications. | AI11: The transaction enables Telix Pharma to support potential indication expansion for TLX591, notably the combination use of anti-PSMA therapeutics in conjunction with anti-androgen drugs, further increasing the value and relevance of its TLX591 program; Atlab Pharma possesses rights to an extensive clinical data set in approximately 200 patients that is highly informative to the development of TLX591, including unpublished data around dose optimization schemes for antibody-based PSMA radiopharmaceuticals. This data may accelerate and further de-risk the future development of TLX591; Atlab Pharma and BZL, together, bring considerable knowledge and expertise to the Telix team; and Atlab possesses the rights and materials necessary to develop huJ591, the most widely clinically-studied anti-PSMA antibody. Telix will keep huJ591 as a back-up clinical drug candidate and continue to support several high-value academic collaborations around the use of this antibody that may also be informative to the future development of TLX591, including in non-prostate cancer indications. | AL11: Unknown | AM11: Unknown | AS11: Telix Pharmaceuticals Ltd | AT11: ATLAB Pharma SAS | AU11: Not reviewed | AV11: Not assessed | AW11: Unknown | AX11: Unknown | AY11: Unknown | AZ11: Unknown | BA11: Unknown | BB11: Unknown | BF11: Not collected | BG11: Not collected | BH11: Not defined | BI11: =IF($Q11="","",$Q11-3) -> 2015 | BJ11: =IF($Q11="","",$Q11-2) -> 2016 | BK11: =IF($Q11="","",$Q11-1) -> 2017 | BL11: =IF($Q11="","",$Q11+0) -> 2018 | BM11: =IF($Q11="","",$Q11+1) -> 2019 | BN11: =IF($Q11="","",$Q11+2) -> 2020 | BO11: =IF($Q11="","",$Q11+3) -> 2021 | EQ11: =IF(OR($EO11="",$EP11="",$EO11=0),"",$EP11/$EO11) | ES11: Unknown | ET11: Unknown | EU11: =IF(COUNT($DF11,$DG11,$DH11)=0,"",AVERAGE($DF11,$DG11,$DH11)) | EV11: =IF(COUNT($DJ11,$DK11,$DL11)=0,"",AVERAGE($DJ11,$DK11,$DL11)) | EW11: =IF(OR($EU11="",$EV11=""),"",$EV11-$EU11) | EX11: =IF(COUNT($DM11,$DN11,$DO11)=0,"",AVERAGE($DM11,$DN11,$DO11)) | EY11: =IF(COUNT($DQ11,$DR11,$DS11)=0,"",AVERAGE($DQ11,$DR11,$DS11)) | EZ11: =IF(OR($EX11="",$EY11=""),"",$EY11-$EX11) | FA11: =IF(COUNT($EA11,$EB11,$EC11)=0,"",AVERAGE($EA11,$EB11,$EC11)) | FB11: =IF(COUNT($EE11,$EF11,$EG11)=0,"",AVERAGE($EE11,$EF11,$EG11)) | FC11: =IF(OR($FA11="",$FB11=""),"",$FB11-$FA11) | FD11: =IF(COUNT($EH11,$EI11,$EJ11)=0,"",AVERAGE($EH11,$EI11,$EJ11)) | FE11: =IF(COUNT($EL11,$EM11,$EN11)=0,"",AVERAGE($EL11,$EM11,$EN11)) | FF11: =IF(OR($FD11="",$FE11=""),"",$FE11-$FD11) | FG11: =IF(COUNT($DF11,$DG11,$DH11,$DJ11,$DK11,$DL11,$DM11,$DN11,$DO11,$DQ11,$DR11,$DS11)=12,"Yes","No") -> No | FH11: =IF(COUNT($EA11,$EB11,$EC11,$EE11,$EF11,$EG11,$EH11,$EI11,$EJ11,$EL11,$EM11,$EN11)=12,"Yes","No") -> No | FI11: =IF(AND($M11="Include",OR($FG11="Yes",$FH11="Yes")),"Ready","Not ready") -> Not ready
A12: TRT-0010 | B12: 21 | C12: Candidate treatment group | D12: 1 | E12: DATA - Innovation driven deals.xlsx | F12: sanofi acquires ablynx for | G12: Yes | H12: No | I12: No | J12: 1 | K12: Not started | L12: Eligible - 100% | M12: Review | O12: 43129 | P12: 43270 | Q12: 2018 | R12: Q1 2018 | S12: Completed | T12: Sanofi Acquires Ablynx for USD4.85 Billion | U12: Mergers & Acquisitions | V12: Acquisition | W12: 100% Acquisition | X12: Belgium | Y12: 100% Acquisition | Z12: Morgan Stanley , Lazard Inc , J.P. Morgan Securities LLC | AA12: Eubelius , Goodwin Procter LLP , Linklaters LLP , Weil, Gotshal & Manges LLP , NautaDutilh NV | AB12: Sanofi | AC12: sanofi | AD12: Ablynx NV | AE12: ablynx | AF12: 4847 | AG12: 4847 | AH12: Sanofi, a pharmaceutical company, has acquired all outstanding shares of Ablynx NV, a biopharmaceutical company focused on the discovery and development of nanobodies, for an aggregate equity value of approximately EUR3.9 billion (USD4.85 billion). The Squeeze-out period commenced on May 22, 2018, in accordance with applicable Belgian and the US law, following the acquisition by Sanofi of over 95% of the outstanding shares of Ablynx upon settlement of the initial acceptance period of its tender offer for Ablynx. On June 12, 2018, upon expiration of the Squeeze-out period, 2,893,201 shares (including 7,163 shares represented by ADSs) and 8 convertible bonds of Ablynx were tendered in the Squeeze-out. The securities tendered during the Squeeze-out period are expected to be settled on or about June 19, 2018. All shares (including all shares represented by ADSs) and all convertible bonds of Ablynx not tendered during the Squeeze-out are deemed transferred to Sanofi by operation of law. The funds required for the payment of the price thereof are kept with the Bank for official deposits (Deposito- en Consignatiekas / Caisse des depots et consignations). The former Ablynx holders of these Securities retain the right to receive EUR45 (USD55.92) per share (or ADS) and EUR393,700.78 per convertible bond. In order to receive these amounts, they must contact the bank for official deposits, where the funds will remain available. On June 13, 2018, The shares of Ablynx were delisted from the regulated market of Euronext Brussels, (ii) the ADSs were delisted from NASDAQ Global Select Market and (iii) the convertible bonds were delisted from the open market Frankfurt MTF (Freiverkehr). In accordance with the Belgian requirement of certainty of funds, Sanofi has entered into a bank credit facility, BNP Paribas Fortis SA/NA acting as the sole credit facility arranger. This transaction enables Sanofi to strengthen its R&D strategy with Nanobody technology platform and expands its rare blood disorders franchise with Ablynx’s late-stage investigational caplacizumab aTTP treatment. Morgan Stanley and Lazard Ltd. acted as financial advisors, Weil, Gotshal & Manges LLP and NautaDutilh NV acted as legal advisors to Sanofi; J.P. Morgan Securities LLC acted as financial advisor, while Eubelius CVBA, Goodwin Procter LLP and Linklaters LLP acted as legal advisors to Ablynx for the transaction. Deal History: Update: On May 14, 2018, Sanofi and Ablynx announced the results of the initial tender offer period of Sanofi’s previously announced tender offers to acquire all of the outstanding shares (including shares represented by American Depositary Shares (ADSs)), warrants and convertible bonds (together, the Securities) of Ablynx. Update: On March 29, 2018, Sanofi entered into definitive agreement with Ablynx to acquire all of the outstanding ordinary shares of Ablynx at a price per share of EUR45 (USD55.92) in cash, which represents an aggregate equity value of approximately EUR3.9 billion (USD4.85). The transaction was unanimously approved by both the Sanofi and Ablynx boards of directors. Sanofi and Ablynx have received an approval and publication of the tender offer documents and response by Ablynx’s Board of Directors. Sanofi confirmed that, as of the expiration of the initial acceptance period, which expired on May 4, 2018, a total of 71,972,994 shares (including 7,446,312 shares represented by ADSs), 2,594,841 warrants and 975 convertible bonds had been validly tendered into the offers and not withdrawn. Sanofi will own 95.60% of the outstanding shares of Ablynx on the settlement date of the offers, of which more than 90% were acquired through the offers. Sanofi further confirmed that the Minimum tender condition and the other conditions to the offers have been satisfied. Under the terms of the agreement, Sanofi will commence the tender offers to acquire all of the outstanding shares (includes shares represented by ADS), warrants and convertible bonds of Ablynx in cash for EUR45 (USD55.6) per share or ADS; EUR18.66 (USD23) - EUR41.79 (USD51.6) per warrant; and EUR0.39 (USD0.48) per convertible bond. Sanofi has complied with the formalities set forth in the Belgian takeover legislation and filed the mandatory documents with the FSMA. Update: On March 27, 2018, Sanofi and Ablynx have received prospectus approved by the Belgian Financial Services and Markets Authority (FSMA). Update: On March 1, 2018, Sanofi announced that the waiting period under the Hart-Scott-Rodino Antitrust Improvements Act of 1976 has expired and that Sanofi has received clearance from the Federal Cartel Office of Germany in accordance with the Act Against Restraints of Competition, applicable to the transaction. Earlier on January 5, 2018, Ablynx rejected the proposal from Novo Nordisk A/S for up to EUR30.5 (USD36.2) per share, including EUR28 (USD33.23) per share in cash and one CVR with total potential cash payments over time of up to EUR2.5 (USD2.97) per share or total equity valuation of EUR2.6 billion (USD3.09 billion), taking into account the interests of all its stakeholders, unanimously concluded that the proposal fundamentally undervalues Ablynx and its strong prospects for continued growth and value creation. | AI12: This transaction enables Sanofi to strengthen its R&D strategy with Nanobody technology platform and expands its rare blood disorders franchise with Ablynx’s late-stage investigational caplacizumab aTTP treatment. | AL12: Unknown | AM12: Yes | AN12: SAN FP | AS12: Sanofi | AT12: Ablynx NV | AU12: Not reviewed | AV12: Not assessed | AW12: Lens.org acquirer-side patent export imported; target patent export not supplied. | AX12: Unknown | AY12: Unknown | AZ12: Unknown | BA12: Unknown | BB12: Unknown | BE12: EUR | BF12: Complete | BG12: Complete event window — provisional; EP-only scope | BH12: EP-focused applicant-family export, 2015–2021; not directly comparable with multi-jurisdiction exports without harmonisation. | BI12: 2015 | BJ12: 2016 | BK12: 2017 | BL12: 2018 | BM12: 2019 | BN12: 2020 | BO12: 2021 | BP12: 34861 | BQ12: 34708 | BR12: 36221 | BS12: 35677 | BT12: 37631 | BU12: 37369 | BV12: 39175 | BW12: 7085 | BX12: 7489 | BY12: 7112 | BZ12: 5845 | CA12: 6882 | CB12: 7583 | CC12: 8729 | CD12: 4287 | CE12: 4709 | CF12: 8416 | CG12: 4306 | CH12: 2754 | CI12: 12294 | CJ12: 6223 | CK12: 102321 | CL12: 104672 | CM12: 99813 | CN12: 111408 | CO12: 112630 | CP12: 114413 | CQ12: 120242 | CR12: 16589 | CS12: 18589 | CT12: 15601 | CU12: 24640 | CV12: 25933 | CW12: 23675 | CX12: 22414 | CY12: 5082 | CZ12: 5172 | DA12: 5472 | DB12: 5894 | DC12: 6020 | DD12: 5530 | DE12: 5692 | DF12: 4.2932 | DG12: 4.5499 | DH12: 8.2314 | DI12: 4.0772 | DJ12: 2.4585 | DK12: 10.8297 | DL12: 5.304 | DM12: 16.4138 | DN12: 18.8256 | DO12: 16.0239 | DP12: 13.1065 | DQ12: 8.1077 | DR12: 37.7666 | DS12: 20.7428 | DT12: 16.2127 | DU12: 17.7593 | DV12: 15.6302 | DW12: 22.1169 | DX12: 23.0249 | DY12: 20.6926 | DZ12: 18.6407 | EA12: 15 | EB12: 28 | EC12: 36 | ED12: 38 | EE12: 42 | EF12: 20 | EG12: 13 | EH12: 9 | EI12: 4 | EJ12: 0 | EK12: 1 | EL12: 4 | EM12: 1 | EN12: 0 | EO12: 79 | EQ12: =IF(OR($EO12="",$EP12="",$EO12=0),"",$EP12/$EO12) | ES12: No | ET12: No | EU12: =IF(COUNT($DF12,$DG12,$DH12)=0,"",AVERAGE($DF12,$DG12,$DH12)) -> 5.6915 | EV12: =IF(COUNT($DJ12,$DK12,$DL12)=0,"",AVERAGE($DJ12,$DK12,$DL12)) -> 6.1974 | EW12: =IF(OR($EU12="",$EV12=""),"",$EV12-$EU12) -> 0.5059 | EX12: =IF(COUNT($DM12,$DN12,$DO12)=0,"",AVERAGE($DM12,$DN12,$DO12)) -> 17.087767 | EY12: =IF(COUNT($DQ12,$DR12,$DS12)=0,"",AVERAGE($DQ12,$DR12,$DS12)) -> 22.2057 | EZ12: =IF(OR($EX12="",$EY12=""),"",$EY12-$EX12) -> 5.1179333 | FA12: =IF(COUNT($EA12,$EB12,$EC12)=0,"",AVERAGE($EA12,$EB12,$EC12)) -> 26.333333 | FB12: =IF(COUNT($EE12,$EF12,$EG12)=0,"",AVERAGE($EE12,$EF12,$EG12)) -> 25 | FC12: =IF(OR($FA12="",$FB12=""),"",$FB12-$FA12) -> -1.3333333 | FD12: =IF(COUNT($EH12,$EI12,$EJ12)=0,"",AVERAGE($EH12,$EI12,$EJ12)) -> 4.3333333 | FE12: =IF(COUNT($EL12,$EM12,$EN12)=0,"",AVERAGE($EL12,$EM12,$EN12)) -> 1.6666667 | FF12: =IF(OR($FD12="",$FE12=""),"",$FE12-$FD12) -> -2.6666667 | FG12: =IF(COUNT($DF12,$DG12,$DH12,$DJ12,$DK12,$DL12,$DM12,$DN12,$DO12,$DQ12,$DR12,$DS12)=12,"Yes","No") -> Yes | FH12: =IF(COUNT($EA12,$EB12,$EC12,$EE12,$EF12,$EG12,$EH12,$EI12,$EJ12,$EL12,$EM12,$EN12)=12,"Yes","No") -> Yes | FI12: =IF(AND($M12="Include",OR($FG12="Yes",$FH12="Yes")),"Ready","Not ready") -> Not ready
A13: TRT-0011 | B13: 22 | C13: Candidate treatment group | D13: 1 | E13: DATA - Innovation driven deals.xlsx | F13: takeda pharma acquires tigenix for | G13: Yes | H13: No | I13: No | J13: 1 | K13: Not started | L13: Eligible - 100% | M13: Review | O13: 43105 | P13: 43312 | Q13: 2018 | R13: Q1 2018 | S13: Completed | T13: Takeda Pharma Acquires TiGenix for USD626.4 Million | U13: Mergers & Acquisitions | V13: Acquisition | W13: 100% Acquisition | X13: Belgium | Y13: 100% Acquisition | Z13: Cowen and Company, LLC (Inactive) , Centerview Partners UK LLP | AA13: Covington & Burling LLP , DLA Piper US LLP , Davis Polk & Wardwell LLP , DLA Piper UK LLP , Osborne Clarke N.V. | AB13: Takeda Pharmaceutical Co Ltd | AC13: takeda pharmaceutical | AD13: TiGenix NV | AE13: tigenix | AF13: 626 | AG13: 626 | AH13: Takeda Pharmaceutical Co. Ltd., a pharmaceutical company, has completed the acquisition of TiGenix NV, a biopharmaceutical company developing stem cell therapies for serious medical conditions, for a purchase consideration of approximately EUR520 million (USD626.4 million). Takeda Pharma intends to fund the transaction cost from existing cash balances. Pursuant to the transaction, TiGenix becomes a wholly owned subsidiary of Takeda. On June 6, 2018, Takeda Pharma announced the results of the first acceptance period of Takeda’s previously announced tender offer in cash for all outstanding ordinary shares, warrants and American Depositary Shares (ADSs) and together with the ordinary shares and the warrants, the securities) of TiGenix that are not yet owned by Takeda and its affiliates, which expired as scheduled on May 31, 2018. The second acceptance period for the Belgian offer will commence on June 20, 2018, and the second acceptance period for the US offer will commence today, June 6, 2018, and is scheduled to expire for both the Belgian offer and the US offer, subject to any extension, on July 3, 2018, respectively. The results of the second acceptance period are expected to be published on July 6, 2018. Payment for the ordinary shares, warrants and ADSs validly tendered and not withdrawn in the second acceptance period is currently expected to commence on July 10, 2018. During the second acceptance period, holders of ordinary shares, warrants and ADSs can tender their securities in the bid by following the instructions set out in the prospectus or the tender offer statement on schedule TO, as applicable to them. On April 25, 2018, Takeda Pharma announced that the first acceptance period of tender offer in cash for all outstanding ordinary shares. warrants and ADSs of TiGenix that are not yet owned by Takeda and its affiliates, at an acquisition price of EUR1.78 per ordinary share in cash; EUR35.60 (USD42.8) per ADS in cash and an amount per warrant in cash depending on the strike price and maturity of such Warrant, will commence on April 30, 2018. The first acceptance period for the bid will start on April 30, 2018 and is scheduled to expire, subject to any extension, on May 31, 2018. The results of the first acceptance period are expected to be published on June 6, 2018. Payment for the ordinary shares, warrants and ADSs validly tendered and not withdrawn in the first acceptance period is currently scheduled for June 8, 2018 although the Belgian offer and the US offer may have different payment dates. During the first acceptance period, holders of ordinary shares, warrants and ADSs can tender their securities in the bid by following the instructions set out in the prospectus or the tender offer statement on schedule TO, as applicable to them. Pursuant to the transaction, Takeda Pharma intends to acquire 100% of the securities with voting rights or giving access to voting rights of TiGenix not already owned by Takeda Pharma or its affiliates at an acquisition price of EUR1.78 (USD2.14) per share in cash and an equivalent price per American Depositary Share (ADS), warrant and convertible bond, representing a transaction value of approximately EUR520 million (USD626.44 million) on a fully diluted basis. The transaction is structured as an all cash voluntary public takeover bid by Takeda Pharma with respect to 100% of the securities with voting rights or giving access to voting rights of TiGenix that are not already owned by Takeda Pharma or its affiliates. Takeda Pharma and TiGenix entered into an offer and support agreement confirming TiGenix’s support and the terms and conditions of the bid. Gri-Cel SA, holding 32,238,178 TiGenix shares, and its affiliate Grifols Worldwide Operations Ltd., holding 7,189,800 TiGenix shares in the form of ADS, have irrevocably confirmed that they will tender their shares and ADSs into the potential public takeover bid. The acquisition extends an existing exclusive ex-US license, development and commercialization agreement between Takeda and TiGenix to develop and commercialize Cx601 (darvadstrocel) entered in July 2016. This acquisition enables Takeda Pharma to expand its late stage gastroenterology pipeline and strengthen presence in the US specialty care market. Centerview Partners UK LLP acted as financial advisor, DLA Piper UK LLP and DLA Piper US LLP acted as legal advisor to Takeda Pharma; Cowen and Company, LLC acted as financial advisor, while Osborne Clarke CVBA and Davis Polk & Wardwell LLP acted as legal advisor to Tingenix for the transaction. Deal History: Announced: On January 5, 2018, Takeda Pharma intends to acquire TiGenix, for a purchase consideration of approximately EUR520 million (USD626.4 million). Takeda Pharma intends to fund the transaction cost from existing cash balances. Takeda Pharma has also entered into an offer and support agreement with TiGenix which provides for a recommended potential voluntary public takeover bid for TiGenix. The agreement has been unanimously supported by the TiGenix board of directors (including its CEO). The bid will be comprised of two separate offers (i) an offer to all holders of ordinary shares and warrants in accordance with the applicable law in Belgium (Belgian offer), and (ii) an offer to holders of ordinary shares who are resident in the US in accordance with applicable the US law and to holders of ADSs wherever located (the US offer). Following closing of the potential voluntary public takeover bid, Takeda Pharma intends to launch a squeeze-out if the applicable conditions for such squeeze-out are met to delist the shares of TiGenix from Euronext Brussels and NASDAQ. After the squeeze-out, TiGenix would become a wholly-owned subsidiary of Takeda. | AI13: This acquisition enables Takeda Pharma to expand its late stage gastroenterology pipeline and strengthen presence in the US specialty care market. | AL13: Unknown | AM13: Unknown | AS13: Takeda Pharmaceutical Co Ltd | AT13: TiGenix NV | AU13: Not reviewed | AV13: Not assessed | AW13: Unknown | AX13: Unknown | AY13: Unknown | AZ13: Unknown | BA13: Unknown | BB13: Unknown | BF13: Not collected | BG13: Not collected | BH13: Not defined | BI13: =IF($Q13="","",$Q13-3) -> 2015 | BJ13: =IF($Q13="","",$Q13-2) -> 2016 | BK13: =IF($Q13="","",$Q13-1) -> 2017 | BL13: =IF($Q13="","",$Q13+0) -> 2018 | BM13: =IF($Q13="","",$Q13+1) -> 2019 | BN13: =IF($Q13="","",$Q13+2) -> 2020 | BO13: =IF($Q13="","",$Q13+3) -> 2021 | EQ13: =IF(OR($EO13="",$EP13="",$EO13=0),"",$EP13/$EO13) | ES13: Unknown | ET13: Unknown | EU13: =IF(COUNT($DF13,$DG13,$DH13)=0,"",AVERAGE($DF13,$DG13,$DH13)) | EV13: =IF(COUNT($DJ13,$DK13,$DL13)=0,"",AVERAGE($DJ13,$DK13,$DL13)) | EW13: =IF(OR($EU13="",$EV13=""),"",$EV13-$EU13) | EX13: =IF(COUNT($DM13,$DN13,$DO13)=0,"",AVERAGE($DM13,$DN13,$DO13)) | EY13: =IF(COUNT($DQ13,$DR13,$DS13)=0,"",AVERAGE($DQ13,$DR13,$DS13)) | EZ13: =IF(OR($EX13="",$EY13=""),"",$EY13-$EX13) | FA13: =IF(COUNT($EA13,$EB13,$EC13)=0,"",AVERAGE($EA13,$EB13,$EC13)) | FB13: =IF(COUNT($EE13,$EF13,$EG13)=0,"",AVERAGE($EE13,$EF13,$EG13)) | FC13: =IF(OR($FA13="",$FB13=""),"",$FB13-$FA13) | FD13: =IF(COUNT($EH13,$EI13,$EJ13)=0,"",AVERAGE($EH13,$EI13,$EJ13)) | FE13: =IF(COUNT($EL13,$EM13,$EN13)=0,"",AVERAGE($EL13,$EM13,$EN13)) | FF13: =IF(OR($FD13="",$FE13=""),"",$FE13-$FD13) | FG13: =IF(COUNT($DF13,$DG13,$DH13,$DJ13,$DK13,$DL13,$DM13,$DN13,$DO13,$DQ13,$DR13,$DS13)=12,"Yes","No") -> No | FH13: =IF(COUNT($EA13,$EB13,$EC13,$EE13,$EF13,$EG13,$EH13,$EI13,$EJ13,$EL13,$EM13,$EN13)=12,"Yes","No") -> No | FI13: =IF(AND($M13="Include",OR($FG13="Yes",$FH13="Yes")),"Ready","Not ready") -> Not ready
A14: TRT-0012 | B14: 23 | C14: Candidate treatment group | D14: 1 | E14: DATA - Innovation driven deals.xlsx | F14: impilo acquires 37 stake in ferrosan medical devices | G14: Yes | H14: No | I14: No | J14: 1 | K14: Not started | L14: Exclude - minority | M14: Review | O14: 42923 | P14: 42923 | Q14: 2017 | R14: Q3 2017 | S14: Completed | T14: Impilo Acquires 37% stake in Ferrosan Medical Devices | U14: Mergers & Acquisitions | V14: Acquisition | W14: Minority Acquisition | X14: Denmark | Y14: Minority Acquisition | AB14: Impilo AB | AC14: impilo ab | AD14: Ferrosan Medical Devices AS | AE14: ferrosan medical devices | AG14: n/a | AH14: Impilo AB, a investment company focussed in the healthcare sector, has acquired 37% stake in Ferrosan Medical Devices A/S, a medical device company Ferrosan Medical Devices, which develops and produces hemostatic products used to stop bleeding during surgery, as well as miniature electrical engineering used in equipment for regional anesthesia and minimal invasive surgery. The transaction enables Ferrosan to broaden and strengthen the development of its products, also to expand its products geographically. | AI14: The transaction enables Ferrosan to broaden and strengthen the development of its products, also to expand its products geographically. | AL14: Unknown | AM14: Unknown | AS14: Impilo AB | AT14: Ferrosan Medical Devices AS | AU14: Not reviewed | AV14: Not assessed | AW14: Unknown | AX14: Unknown | AY14: Unknown | AZ14: Unknown | BA14: Unknown | BB14: Unknown | BF14: Not collected | BG14: Not collected | BH14: Not defined | BI14: =IF($Q14="","",$Q14-3) -> 2014 | BJ14: =IF($Q14="","",$Q14-2) -> 2015 | BK14: =IF($Q14="","",$Q14-1) -> 2016 | BL14: =IF($Q14="","",$Q14+0) -> 2017 | BM14: =IF($Q14="","",$Q14+1) -> 2018 | BN14: =IF($Q14="","",$Q14+2) -> 2019 | BO14: =IF($Q14="","",$Q14+3) -> 2020 | EQ14: =IF(OR($EO14="",$EP14="",$EO14=0),"",$EP14/$EO14) | ES14: Unknown | ET14: Unknown | EU14: =IF(COUNT($DF14,$DG14,$DH14)=0,"",AVERAGE($DF14,$DG14,$DH14)) | EV14: =IF(COUNT($DJ14,$DK14,$DL14)=0,"",AVERAGE($DJ14,$DK14,$DL14)) | EW14: =IF(OR($EU14="",$EV14=""),"",$EV14-$EU14) | EX14: =IF(COUNT($DM14,$DN14,$DO14)=0,"",AVERAGE($DM14,$DN14,$DO14)) | EY14: =IF(COUNT($DQ14,$DR14,$DS14)=0,"",AVERAGE($DQ14,$DR14,$DS14)) | EZ14: =IF(OR($EX14="",$EY14=""),"",$EY14-$EX14) | FA14: =IF(COUNT($EA14,$EB14,$EC14)=0,"",AVERAGE($EA14,$EB14,$EC14)) | FB14: =IF(COUNT($EE14,$EF14,$EG14)=0,"",AVERAGE($EE14,$EF14,$EG14)) | FC14: =IF(OR($FA14="",$FB14=""),"",$FB14-$FA14) | FD14: =IF(COUNT($EH14,$EI14,$EJ14)=0,"",AVERAGE($EH14,$EI14,$EJ14)) | FE14: =IF(COUNT($EL14,$EM14,$EN14)=0,"",AVERAGE($EL14,$EM14,$EN14)) | FF14: =IF(OR($FD14="",$FE14=""),"",$FE14-$FD14) | FG14: =IF(COUNT($DF14,$DG14,$DH14,$DJ14,$DK14,$DL14,$DM14,$DN14,$DO14,$DQ14,$DR14,$DS14)=12,"Yes","No") -> No | FH14: =IF(COUNT($EA14,$EB14,$EC14,$EE14,$EF14,$EG14,$EH14,$EI14,$EJ14,$EL14,$EM14,$EN14)=12,"Yes","No") -> No | FI14: =IF(AND($M14="Include",OR($FG14="Yes",$FH14="Yes")),"Ready","Not ready") -> Not ready
A15: TRT-0013 | B15: 24 | C15: Candidate treatment group | D15: 1 | E15: DATA - Innovation driven deals.xlsx | F15: cell medica acquires catapult therapy tcr from cell therapy catapult | G15: No | H15: No | I15: No | J15: 1 | K15: Not started | L15: Eligible - 100% | M15: Review | O15: 42906 | P15: 42906 | Q15: 2017 | R15: Q2 2017 | S15: Completed | T15: Cell Medica Acquires Catapult Therapy TCR from Cell Therapy Catapult | U15: Mergers & Acquisitions | V15: Acquisition | W15: 100% Acquisition | X15: United Kingdom | Y15: 100% Acquisition | AB15: Kuur Therapeutics Ltd | AC15: kuur therapeutics | AD15: Cell Medica TCR Ltd | AE15: cell medica tcr | AG15: n/a | AH15: Cell Medica Ltd, a developer of cellular immunotherapy for the treatment of cancer, has acquired Catapult Therapy TCR Limited, a developer of cell therapy for the treatment of acute myeloid leukaemia, from Cell Therapy Catapult Ltd, (Cell and Gene Therapy Catapult), a developer of cell and gene therapies. Catapult Therapy TCR is a company set up by Cell Therapy Catapult, University College London (UCL) Business and Imperial Innovations, and managed by Cell Therapy Catapult, for the development of the WT1 T cell receptor (TCR) cell therapy discovered through research at UCL and Imperial College London. The WT1-TCR cell therapy enhances the immune system to fight cancer by genetically engineering the patient’s T cells to target WT1, a tumour-associated antigen which is expressed in both solid tumours and blood cancers. Concurrently, Cell Medica entered into a collaboration agreement with Cell Therapy Catapult, to establish cell therapy manufacturing operations for Cell Medica at the GMP production facility recently built by Cell Therapy Catapult in Stevenage, UK. The collaboration will include transferring the current WT1-TCR cell therapy manufacturing process to Stevenage over the next twelve months while Cell Medica and Cell Therapy Catapult work to develop a commercial scale production process using advanced manufacturing techniques. Cell Medica will also evaluate the feasibility of manufacturing additional cell therapy products at the site. This transaction enables Cell Medica to create an effective treatment for patients with solid tumours. | AI15: This transaction enables Cell Medica to create an effective treatment for patients with solid tumours. | AL15: Unknown | AM15: Unknown | AS15: Kuur Therapeutics Ltd | AT15: Cell Medica TCR Ltd | AU15: Not reviewed | AV15: Not assessed | AW15: Unknown | AX15: Unknown | AY15: Unknown | AZ15: Unknown | BA15: Unknown | BB15: Unknown | BF15: Not collected | BG15: Not collected | BH15: Not defined | BI15: =IF($Q15="","",$Q15-3) -> 2014 | BJ15: =IF($Q15="","",$Q15-2) -> 2015 | BK15: =IF($Q15="","",$Q15-1) -> 2016 | BL15: =IF($Q15="","",$Q15+0) -> 2017 | BM15: =IF($Q15="","",$Q15+1) -> 2018 | BN15: =IF($Q15="","",$Q15+2) -> 2019 | BO15: =IF($Q15="","",$Q15+3) -> 2020 | EQ15: =IF(OR($EO15="",$EP15="",$EO15=0),"",$EP15/$EO15) | ES15: Unknown | ET15: Unknown | EU15: =IF(COUNT($DF15,$DG15,$DH15)=0,"",AVERAGE($DF15,$DG15,$DH15)) | EV15: =IF(COUNT($DJ15,$DK15,$DL15)=0,"",AVERAGE($DJ15,$DK15,$DL15)) | EW15: =IF(OR($EU15="",$EV15=""),"",$EV15-$EU15) | EX15: =IF(COUNT($DM15,$DN15,$DO15)=0,"",AVERAGE($DM15,$DN15,$DO15)) | EY15: =IF(COUNT($DQ15,$DR15,$DS15)=0,"",AVERAGE($DQ15,$DR15,$DS15)) | EZ15: =IF(OR($EX15="",$EY15=""),"",$EY15-$EX15) | FA15: =IF(COUNT($EA15,$EB15,$EC15)=0,"",AVERAGE($EA15,$EB15,$EC15)) | FB15: =IF(COUNT($EE15,$EF15,$EG15)=0,"",AVERAGE($EE15,$EF15,$EG15)) | FC15: =IF(OR($FA15="",$FB15=""),"",$FB15-$FA15) | FD15: =IF(COUNT($EH15,$EI15,$EJ15)=0,"",AVERAGE($EH15,$EI15,$EJ15)) | FE15: =IF(COUNT($EL15,$EM15,$EN15)=0,"",AVERAGE($EL15,$EM15,$EN15)) | FF15: =IF(OR($FD15="",$FE15=""),"",$FE15-$FD15) | FG15: =IF(COUNT($DF15,$DG15,$DH15,$DJ15,$DK15,$DL15,$DM15,$DN15,$DO15,$DQ15,$DR15,$DS15)=12,"Yes","No") -> No | FH15: =IF(COUNT($EA15,$EB15,$EC15,$EE15,$EF15,$EG15,$EH15,$EI15,$EJ15,$EL15,$EM15,$EN15)=12,"Yes","No") -> No | FI15: =IF(AND($M15="Include",OR($FG15="Yes",$FH15="Yes")),"Ready","Not ready") -> Not ready
A16: TRT-0014 | B16: 25 | C16: Candidate treatment group | D16: 1 | E16: DATA - Innovation driven deals.xlsx | F16: astellas pharma acquires ogeda for up to | G16: Yes | H16: No | I16: No | J16: 1 | K16: Not started | L16: Eligible - 100% | M16: Review | O16: 42828 | P16: 42871 | Q16: 2017 | R16: Q2 2017 | S16: Completed | T16: Astellas Pharma Acquires Ogeda for up to USD852 Million | U16: Mergers & Acquisitions | V16: Acquisition | W16: 100% Acquisition | X16: Belgium | Y16: 100% Acquisition | AA16: White & Case LLP , Jones Day | AB16: Astellas Pharma Inc | AC16: astellas pharma | AD16: Ogeda SA | AE16: ogeda | AF16: 852 | AG16: 852 | AH16: Astellas Pharma Inc., a pharmaceutical company, has completed the acquisition of Ogeda SA, a drug discovery company, for a cash consideration of up to EUR800 million (USD851.98 million). Under the agreement, Astellas Pharma paid up to a total of EUR800 million (USD851.98 million). Astellas Pharma will make an initial payment of EUR500 million (USD532.5 million) in consideration of 100% of the equity in Ogeda at the closing of the agreement. Then Ogeda shareholders will be eligible to receive an additional EUR300 million (USD319.49 million) with attainment of certain clinical development and regulatory milestones for fezolinetant. Following the transaction, Ogeda became a wholly owned subsidiary of Astellas Pharma. Fezolinetant, is a selective NK3 receptor antagonist, and the positive data from a Phase IIa study result for the non-hormonal treatment of menopause-related vasomotor symptoms (MR-VMS), announced in January 2017. This acquisition enables Astellas Pharma to expand its late stage pipeline and is expected to contribute to its mid-to-long term growth. Jones Day acted as legal advisor to Astellas Pharma and White & Case LLP acted as legal advisor to Ogedas for the agreement. Deal History: Announced: On April 3, 2017, Astellas Pharma entered into a definitive agreement to acquire Ogeda, for a cash consideration of up to EUR800 million (USD851.98 million). | AI16: This acquisition enables Astellas Pharma to expand its late stage pipeline and is expected to contribute to its mid-to-long term growth. | AL16: Unknown | AM16: Unknown | AS16: Astellas Pharma Inc | AT16: Ogeda SA | AU16: Not reviewed | AV16: Not assessed | AW16: Unknown | AX16: Unknown | AY16: Unknown | AZ16: Unknown | BA16: Unknown | BB16: Unknown | BF16: Not collected | BG16: Not collected | BH16: Not defined | BI16: =IF($Q16="","",$Q16-3) -> 2014 | BJ16: =IF($Q16="","",$Q16-2) -> 2015 | BK16: =IF($Q16="","",$Q16-1) -> 2016 | BL16: =IF($Q16="","",$Q16+0) -> 2017 | BM16: =IF($Q16="","",$Q16+1) -> 2018 | BN16: =IF($Q16="","",$Q16+2) -> 2019 | BO16: =IF($Q16="","",$Q16+3) -> 2020 | EQ16: =IF(OR($EO16="",$EP16="",$EO16=0),"",$EP16/$EO16) | ES16: Unknown | ET16: Unknown | EU16: =IF(COUNT($DF16,$DG16,$DH16)=0,"",AVERAGE($DF16,$DG16,$DH16)) | EV16: =IF(COUNT($DJ16,$DK16,$DL16)=0,"",AVERAGE($DJ16,$DK16,$DL16)) | EW16: =IF(OR($EU16="",$EV16=""),"",$EV16-$EU16) | EX16: =IF(COUNT($DM16,$DN16,$DO16)=0,"",AVERAGE($DM16,$DN16,$DO16)) | EY16: =IF(COUNT($DQ16,$DR16,$DS16)=0,"",AVERAGE($DQ16,$DR16,$DS16)) | EZ16: =IF(OR($EX16="",$EY16=""),"",$EY16-$EX16) | FA16: =IF(COUNT($EA16,$EB16,$EC16)=0,"",AVERAGE($EA16,$EB16,$EC16)) | FB16: =IF(COUNT($EE16,$EF16,$EG16)=0,"",AVERAGE($EE16,$EF16,$EG16)) | FC16: =IF(OR($FA16="",$FB16=""),"",$FB16-$FA16) | FD16: =IF(COUNT($EH16,$EI16,$EJ16)=0,"",AVERAGE($EH16,$EI16,$EJ16)) | FE16: =IF(COUNT($EL16,$EM16,$EN16)=0,"",AVERAGE($EL16,$EM16,$EN16)) | FF16: =IF(OR($FD16="",$FE16=""),"",$FE16-$FD16) | FG16: =IF(COUNT($DF16,$DG16,$DH16,$DJ16,$DK16,$DL16,$DM16,$DN16,$DO16,$DQ16,$DR16,$DS16)=12,"Yes","No") -> No | FH16: =IF(COUNT($EA16,$EB16,$EC16,$EE16,$EF16,$EG16,$EH16,$EI16,$EJ16,$EL16,$EM16,$EN16)=12,"Yes","No") -> No | FI16: =IF(AND($M16="Include",OR($FG16="Yes",$FH16="Yes")),"Ready","Not ready") -> Not ready
A17: TRT-0015 | B17: 26 | C17: Candidate treatment group | D17: 1 | E17: DATA - Innovation driven deals.xlsx | F17: boston scientific acquires symetis for | G17: Yes | H17: No | I17: No | J17: 1 | K17: Not started | L17: Eligible - 100% | M17: Review | O17: 42824 | P17: 42871 | Q17: 2017 | R17: Q1 2017 | S17: Completed | T17: Boston Scientific Acquires Symetis for USD435 Million | U17: Mergers & Acquisitions | V17: Acquisition | W17: 100% Acquisition | X17: Switzerland | Y17: 100% Acquisition | Z17: Vischer AG | AA17: Latham & Watkins LLP | AB17: Boston Scientific Corp | AC17: boston scientific | AD17: Symetis SA (Inactive) | AE17: symetis | AF17: 435 | AG17: 435 | AH17: Boston Scientific Corporation, a medical technology, has completed the acquisition Symetis SA, a medical technology company, for a purchase consideration of USD435 million in up-front cash. The Symetis portfolio includes the ACURATE tA and ACURATE neo/TF valve systems for use in the treatment of high-risk patients suffering from severe and symptomatic aortic valve stenosis, which are sold in Europe and in other geographies outside of the United States. Symetis is also developing the ACURATE neo/AS next generation valve system, currently in a clinical trial intended to serve as the basis for a future CE mark application. On an adjusted basis, the transaction is expected to be immaterial in 2017, slightly accretive in 2018, and increasingly accretive thereafter. The transaction is expected to be less accretive (or dilutive, as the case may be) on a GAAP basis, due to amortization expense and transaction and integration costs. This transaction enables Boston Scientific to expand treatments for patients with aortic valvular heart disease and strengthen its position in structural heart globally. Vischer AG acted as advisor to Symetis for the transaction. Deal History: Announced: On March 30, 2017, Boston Scientific entered into definitive agreement to acquire Symetis, for a purchase consideration of USD435 million in up-front cash. | AI17: This transaction enables Boston Scientific to expand treatments for patients with aortic valvular heart disease and strengthen its position in structural heart globally. | AL17: Unknown | AM17: Unknown | AS17: Boston Scientific Corp | AT17: Symetis SA (Inactive) | AU17: Not reviewed | AV17: Not assessed | AW17: Unknown | AX17: Unknown | AY17: Unknown | AZ17: Unknown | BA17: Unknown | BB17: Unknown | BF17: Not collected | BG17: Not collected | BH17: Not defined | BI17: =IF($Q17="","",$Q17-3) -> 2014 | BJ17: =IF($Q17="","",$Q17-2) -> 2015 | BK17: =IF($Q17="","",$Q17-1) -> 2016 | BL17: =IF($Q17="","",$Q17+0) -> 2017 | BM17: =IF($Q17="","",$Q17+1) -> 2018 | BN17: =IF($Q17="","",$Q17+2) -> 2019 | BO17: =IF($Q17="","",$Q17+3) -> 2020 | EQ17: =IF(OR($EO17="",$EP17="",$EO17=0),"",$EP17/$EO17) | ES17: Unknown | ET17: Unknown | EU17: =IF(COUNT($DF17,$DG17,$DH17)=0,"",AVERAGE($DF17,$DG17,$DH17)) | EV17: =IF(COUNT($DJ17,$DK17,$DL17)=0,"",AVERAGE($DJ17,$DK17,$DL17)) | EW17: =IF(OR($EU17="",$EV17=""),"",$EV17-$EU17) | EX17: =IF(COUNT($DM17,$DN17,$DO17)=0,"",AVERAGE($DM17,$DN17,$DO17)) | EY17: =IF(COUNT($DQ17,$DR17,$DS17)=0,"",AVERAGE($DQ17,$DR17,$DS17)) | EZ17: =IF(OR($EX17="",$EY17=""),"",$EY17-$EX17) | FA17: =IF(COUNT($EA17,$EB17,$EC17)=0,"",AVERAGE($EA17,$EB17,$EC17)) | FB17: =IF(COUNT($EE17,$EF17,$EG17)=0,"",AVERAGE($EE17,$EF17,$EG17)) | FC17: =IF(OR($FA17="",$FB17=""),"",$FB17-$FA17) | FD17: =IF(COUNT($EH17,$EI17,$EJ17)=0,"",AVERAGE($EH17,$EI17,$EJ17)) | FE17: =IF(COUNT($EL17,$EM17,$EN17)=0,"",AVERAGE($EL17,$EM17,$EN17)) | FF17: =IF(OR($FD17="",$FE17=""),"",$FE17-$FD17) | FG17: =IF(COUNT($DF17,$DG17,$DH17,$DJ17,$DK17,$DL17,$DM17,$DN17,$DO17,$DQ17,$DR17,$DS17)=12,"Yes","No") -> No | FH17: =IF(COUNT($EA17,$EB17,$EC17,$EE17,$EF17,$EG17,$EH17,$EI17,$EJ17,$EL17,$EM17,$EN17)=12,"Yes","No") -> No | FI17: =IF(AND($M17="Include",OR($FG17="Yes",$FH17="Yes")),"Ready","Not ready") -> Not ready
A18: TRT-0016 | B18: 27 | C18: Candidate treatment group | D18: 1 | E18: DATA - Innovation driven deals.xlsx | F18: biolinerx acquires agalimmune | G18: Yes | H18: No | I18: No | J18: 1 | K18: Not started | L18: Eligible - 100% | M18: Review | O18: 42817 | P18: 42817 | Q18: 2017 | R18: Q1 2017 | S18: Completed | T18: BioLineRx Acquires Agalimmune | U18: Mergers & Acquisitions | V18: Acquisition | W18: 100% Acquisition | X18: United Kingdom | Y18: 100% Acquisition | AA18: King & Wood Mallesons LLP | AB18: BioLineRx Ltd | AC18: biolinerx | AD18: Agalimmune Ltd | AE18: agalimmune | AF18: 6 | AG18: 6 | AH18: BioLineRx Ltd., a biopharmaceutical company focused on oncology and immunology, has acquired Agalimmune Ltd., a developer of anti-cancer immunotherapy, and its technology platform for a initial consideration of USD5.85 million, of which USD2.85 million is in cash and the remainder in the Company’s ADSs. Additional consideration may be due to Agalimmune shareholders based on certain development and commercial milestones, including future sales of Agalimmune products. The acquisition expands the Company’s pipeline with a number of assets, including Agalimmune’s primary asset, AGI-134, a novel immuno-oncology agent for various cancer indications at the near-clinical stage of development. Agalimmune also has a number of early-stage preclinical assets for future evaluation by the Company. Agalimmune’s lead compound, AGI-134 is a synthetic alpha-Gal immunotherapy in development for solid tumors. AGI-134 has completed numerous pre-clinical studies, demonstrating robust protection against the development of secondary tumors in a model of melanoma with a single dose only. Synergy has also been demonstrated in additional pre-clinical studies when combined with a PD-1 immune checkpoint inhibitor, offering the potential to broaden the utility of such immunotherapies, and improve the rate and duration of responses in multiple cancer types. AGI-134 is in near-clinical development and is expected to commence a first-in-man study in patients with solid tumors in the first half of 2018. This agreement enables BioLineRx to incorporate AGI-134 in its pipeline and strengthen its position in immuno-oncology. King & Wood Mallesons acted as legal advisor to Agalimmune for the transaction. | AI18: This agreement enables BioLineRx to incorporate AGI-134 in its pipeline and strengthen its position in immuno-oncology. | AL18: Unknown | AM18: Unknown | AS18: BioLineRx Ltd | AT18: Agalimmune Ltd | AU18: Not reviewed | AV18: Not assessed | AW18: Unknown | AX18: Unknown | AY18: Unknown | AZ18: Unknown | BA18: Unknown | BB18: Unknown | BF18: Not collected | BG18: Not collected | BH18: Not defined | BI18: =IF($Q18="","",$Q18-3) -> 2014 | BJ18: =IF($Q18="","",$Q18-2) -> 2015 | BK18: =IF($Q18="","",$Q18-1) -> 2016 | BL18: =IF($Q18="","",$Q18+0) -> 2017 | BM18: =IF($Q18="","",$Q18+1) -> 2018 | BN18: =IF($Q18="","",$Q18+2) -> 2019 | BO18: =IF($Q18="","",$Q18+3) -> 2020 | EQ18: =IF(OR($EO18="",$EP18="",$EO18=0),"",$EP18/$EO18) | ES18: Unknown | ET18: Unknown | EU18: =IF(COUNT($DF18,$DG18,$DH18)=0,"",AVERAGE($DF18,$DG18,$DH18)) | EV18: =IF(COUNT($DJ18,$DK18,$DL18)=0,"",AVERAGE($DJ18,$DK18,$DL18)) | EW18: =IF(OR($EU18="",$EV18=""),"",$EV18-$EU18) | EX18: =IF(COUNT($DM18,$DN18,$DO18)=0,"",AVERAGE($DM18,$DN18,$DO18)) | EY18: =IF(COUNT($DQ18,$DR18,$DS18)=0,"",AVERAGE($DQ18,$DR18,$DS18)) | EZ18: =IF(OR($EX18="",$EY18=""),"",$EY18-$EX18) | FA18: =IF(COUNT($EA18,$EB18,$EC18)=0,"",AVERAGE($EA18,$EB18,$EC18)) | FB18: =IF(COUNT($EE18,$EF18,$EG18)=0,"",AVERAGE($EE18,$EF18,$EG18)) | FC18: =IF(OR($FA18="",$FB18=""),"",$FB18-$FA18) | FD18: =IF(COUNT($EH18,$EI18,$EJ18)=0,"",AVERAGE($EH18,$EI18,$EJ18)) | FE18: =IF(COUNT($EL18,$EM18,$EN18)=0,"",AVERAGE($EL18,$EM18,$EN18)) | FF18: =IF(OR($FD18="",$FE18=""),"",$FE18-$FD18) | FG18: =IF(COUNT($DF18,$DG18,$DH18,$DJ18,$DK18,$DL18,$DM18,$DN18,$DO18,$DQ18,$DR18,$DS18)=12,"Yes","No") -> No | FH18: =IF(COUNT($EA18,$EB18,$EC18,$EE18,$EF18,$EG18,$EH18,$EI18,$EJ18,$EL18,$EM18,$EN18)=12,"Yes","No") -> No | FI18: =IF(AND($M18="Include",OR($FG18="Yes",$FH18="Yes")),"Ready","Not ready") -> Not ready
A19: TRT-0017 | B19: 28 | C19: Candidate treatment group | D19: 1 | E19: DATA - Innovation driven deals.xlsx | F19: mediolanum farmaceutici acquires therabel pharma gienne | G19: No | H19: No | I19: No | J19: 1 | K19: Not started | L19: Exclude - minority | M19: Review | O19: 42783 | P19: 42796 | Q19: 2017 | R19: Q1 2017 | S19: Completed | T19: Mediolanum Farmaceutici Acquires Therabel Pharma Gienne | U19: Mergers & Acquisitions | V19: Acquisition | W19: Minority Acquisition | X19: Italy | Y19: Minority Acquisition | Z19: Ernst & Young Global Ltd | AA19: NCTM Studio Legale Associato | AB19: Mediolanum farmaceutici SpA | AC19: mediolanum farmaceutici | AD19: Therabel Pharma SA | AE19: therabel pharma | AG19: n/a | AH19: Mediolanum Farmaceutici, an Italian pharmaceutical company, acquires Therabel Pharma Gienne, a pharmaceutical company. Ernst & Young acted as financial advisor and NCTM acted as legal advisor of Mediolanum Group. Deal Hisory: Announced: February, 17, 2017, Mediolanum Farmaceutici entered into an agreement to acquire Therabel Pharma Gienne. | AL19: Unknown | AM19: Unknown | AS19: Mediolanum farmaceutici SpA | AT19: Therabel Pharma SA | AU19: Not reviewed | AV19: Not assessed | AW19: Unknown | AX19: Unknown | AY19: Unknown | AZ19: Unknown | BA19: Unknown | BB19: Unknown | BF19: Not collected | BG19: Not collected | BH19: Not defined | BI19: =IF($Q19="","",$Q19-3) -> 2014 | BJ19: =IF($Q19="","",$Q19-2) -> 2015 | BK19: =IF($Q19="","",$Q19-1) -> 2016 | BL19: =IF($Q19="","",$Q19+0) -> 2017 | BM19: =IF($Q19="","",$Q19+1) -> 2018 | BN19: =IF($Q19="","",$Q19+2) -> 2019 | BO19: =IF($Q19="","",$Q19+3) -> 2020 | EQ19: =IF(OR($EO19="",$EP19="",$EO19=0),"",$EP19/$EO19) | ES19: Unknown | ET19: Unknown | EU19: =IF(COUNT($DF19,$DG19,$DH19)=0,"",AVERAGE($DF19,$DG19,$DH19)) | EV19: =IF(COUNT($DJ19,$DK19,$DL19)=0,"",AVERAGE($DJ19,$DK19,$DL19)) | EW19: =IF(OR($EU19="",$EV19=""),"",$EV19-$EU19) | EX19: =IF(COUNT($DM19,$DN19,$DO19)=0,"",AVERAGE($DM19,$DN19,$DO19)) | EY19: =IF(COUNT($DQ19,$DR19,$DS19)=0,"",AVERAGE($DQ19,$DR19,$DS19)) | EZ19: =IF(OR($EX19="",$EY19=""),"",$EY19-$EX19) | FA19: =IF(COUNT($EA19,$EB19,$EC19)=0,"",AVERAGE($EA19,$EB19,$EC19)) | FB19: =IF(COUNT($EE19,$EF19,$EG19)=0,"",AVERAGE($EE19,$EF19,$EG19)) | FC19: =IF(OR($FA19="",$FB19=""),"",$FB19-$FA19) | FD19: =IF(COUNT($EH19,$EI19,$EJ19)=0,"",AVERAGE($EH19,$EI19,$EJ19)) | FE19: =IF(COUNT($EL19,$EM19,$EN19)=0,"",AVERAGE($EL19,$EM19,$EN19)) | FF19: =IF(OR($FD19="",$FE19=""),"",$FE19-$FD19) | FG19: =IF(COUNT($DF19,$DG19,$DH19,$DJ19,$DK19,$DL19,$DM19,$DN19,$DO19,$DQ19,$DR19,$DS19)=12,"Yes","No") -> No | FH19: =IF(COUNT($EA19,$EB19,$EC19,$EE19,$EF19,$EG19,$EH19,$EI19,$EJ19,$EL19,$EM19,$EN19)=12,"Yes","No") -> No | FI19: =IF(AND($M19="Include",OR($FG19="Yes",$FH19="Yes")),"Ready","Not ready") -> Not ready
A20: TRT-0018 | B20: 29 | C20: Candidate treatment group | D20: 1 | E20: DATA - Innovation driven deals.xlsx | F20: agile pharma acquires generis farmaceutica from magnum capital partners for | G20: Yes | H20: No | I20: No | J20: 1 | K20: Not started | L20: Eligible - 100% | M20: Review | O20: 42742 | P20: 42853 | Q20: 2017 | R20: Q1 2017 | S20: Completed | T20: Agile Pharma Acquires Generis Farmaceutica from Magnum Capital Partners for USD142.8 Million | U20: Mergers & Acquisitions | V20: Acquisition | W20: 100% Acquisition | X20: Portugal | Y20: 100% Acquisition | AB20: Agile Pharma BV | AC20: agile pharma | AD20: Generis Pharmaceuticals SA | AE20: generis pharmaceuticals | AF20: 143 | AG20: 143 | AH20: Agile Pharma BV, a pharmaceutical company and wholly-owned subsidiary of Aurobindo Pharma Ltd., has acquired Generis Farmaceutica, S.A., a manufacturer and supplier of pharmaceutical products, and its subsidiaries from Magnum Capital Partners Limited, a private equity firm, for a purchase consideration of EUR135 million (USD142.78 million), in cash. Generis Farmaceutica subsidiaries includes Mer Medicamentos, Lda., Generis Phar, Unipessoal Lda., Farma APS – Promocao de Medicamentos, Unipessoal Lda., and Generis MZ, Lda. The acquisition includes Generis Farmaceutica's manufacturing facility in Amadora, Portugal which has a capacity to produce 1.2 billion tablets/capsules/sachets annually. This transaction enables Agile Pharma to expand its businesses portfolio in Portuguese market. Deal History: Announced: On January 7, 2017, Agile Pharma entered into a binding agreement to acquire Generis Farmaceutica from Magnum Capital Partners for a purchase consideration of EUR135 million (USD142.78 million), in cash. Rumor: On November 3, 2016, Aurobindo Pharma intended to acquire Generis Farmaceutica, according to people familiar with the matter. The transaction is expected to be valued at approximately USD200 million. | AI20: This transaction enables Aurobindo Pharma to expands its businesses portfolio in Portuguese market. | AL20: Unknown | AM20: Unknown | AS20: Agile Pharma BV | AT20: Generis Pharmaceuticals SA | AU20: Not reviewed | AV20: Not assessed | AW20: Unknown | AX20: Unknown | AY20: Unknown | AZ20: Unknown | BA20: Unknown | BB20: Unknown | BF20: Not collected | BG20: Not collected | BH20: Not defined | BI20: =IF($Q20="","",$Q20-3) -> 2014 | BJ20: =IF($Q20="","",$Q20-2) -> 2015 | BK20: =IF($Q20="","",$Q20-1) -> 2016 | BL20: =IF($Q20="","",$Q20+0) -> 2017 | BM20: =IF($Q20="","",$Q20+1) -> 2018 | BN20: =IF($Q20="","",$Q20+2) -> 2019 | BO20: =IF($Q20="","",$Q20+3) -> 2020 | EQ20: =IF(OR($EO20="",$EP20="",$EO20=0),"",$EP20/$EO20) | ES20: Unknown | ET20: Unknown | EU20: =IF(COUNT($DF20,$DG20,$DH20)=0,"",AVERAGE($DF20,$DG20,$DH20)) | EV20: =IF(COUNT($DJ20,$DK20,$DL20)=0,"",AVERAGE($DJ20,$DK20,$DL20)) | EW20: =IF(OR($EU20="",$EV20=""),"",$EV20-$EU20) | EX20: =IF(COUNT($DM20,$DN20,$DO20)=0,"",AVERAGE($DM20,$DN20,$DO20)) | EY20: =IF(COUNT($DQ20,$DR20,$DS20)=0,"",AVERAGE($DQ20,$DR20,$DS20)) | EZ20: =IF(OR($EX20="",$EY20=""),"",$EY20-$EX20) | FA20: =IF(COUNT($EA20,$EB20,$EC20)=0,"",AVERAGE($EA20,$EB20,$EC20)) | FB20: =IF(COUNT($EE20,$EF20,$EG20)=0,"",AVERAGE($EE20,$EF20,$EG20)) | FC20: =IF(OR($FA20="",$FB20=""),"",$FB20-$FA20) | FD20: =IF(COUNT($EH20,$EI20,$EJ20)=0,"",AVERAGE($EH20,$EI20,$EJ20)) | FE20: =IF(COUNT($EL20,$EM20,$EN20)=0,"",AVERAGE($EL20,$EM20,$EN20)) | FF20: =IF(OR($FD20="",$FE20=""),"",$FE20-$FD20) | FG20: =IF(COUNT($DF20,$DG20,$DH20,$DJ20,$DK20,$DL20,$DM20,$DN20,$DO20,$DQ20,$DR20,$DS20)=12,"Yes","No") -> No | FH20: =IF(COUNT($EA20,$EB20,$EC20,$EE20,$EF20,$EG20,$EH20,$EI20,$EJ20,$EL20,$EM20,$EN20)=12,"Yes","No") -> No | FI20: =IF(AND($M20="Include",OR($FG20="Yes",$FH20="Yes")),"Ready","Not ready") -> Not ready
A21: TRT-0019 | B21: 30 | C21: Candidate treatment group | D21: 1 | E21: DATA - Innovation driven deals.xlsx | F21: genticel merges with genkyotex | G21: Yes | H21: No | I21: No | J21: 1 | K21: Not started | L21: Review - merger | M21: Review | O21: 42726 | P21: 42794 | Q21: 2017 | R21: Q4 2016 | S21: Completed | T21: Genticel Merges with GenKyoTex | U21: Mergers & Acquisitions | V21: Merger | X21: France , Switzerland | Z21: Jones Day | AA21: Paul Hastings LLP | AB21: Calliditas Therapeutics France SAS | AC21: calliditas therapeutics france | AD21: Calliditas Therapeutics France SAS; Calliditas Therapeutics France SAS | AE21: calliditas therapeutics france calliditas therapeutics france | AF21: 156 | AG21: 156 | AH21: Genticel SA, a biotechnology company, has merged with GenKyoTex SA, a developer of small molecule therapeutics. Pursuant to the transaction, Genticel changed its name to Genkyotex; and the combined company will create a European group with a pipeline of first-in-class NOX inhibitors in fibrosis and inflammatory pain. In conjunction with the transaction, Elias Papatheodorou, CEO of Genkyotex became the CEO of the group. Under the terms of the transaction, the contribution by all the GenKyoTex shareholders to Genticel of the 5,262,133 ordinary shares they hold in GenKyoTex represent 100% of its share capital and voting rights; and the issuance by Genticel of 62,279,951 new shares to GenKyoTex’s shareholders in remuneration of the contribution of their shares. These shareholders thus received 11.8355 Genticel shares for each GenKyoTex share contributed. The exchange parity was agreed between Genticel and GenKyoTex’s shareholders on the basis of a real value of EUR120 million (USD124.94 million) for GenKyoTex and EUR30 million (USD31.24 million) for Genticel, as foreseen in the contribution agreement. As a result, GenKyoTex’s former shareholders now hold 80% of the share capital and voting rights of Genkyotex. Admission to trading on the Euronext Paris and Euronext Brussels regulated markets of the new shares issued by the company in remuneration of the contribution in kind will become effective on March 2, 2017. The shares listed on these markets will trade under the name Genkyotex with ticker ‘GKTX’ from March 2, 2017, as soon as trading begins on the Euronext markets in Paris and Brussels. This transaction enables Genticel and GenKyoTex to complete both phase II study in primary biliary cholangitis (PBC) with GKT831 and first Phase I study with GKT771. Jones Day acted as advisor to Genticel for the transaction. Deal History: Announced: On December 22, 2016, Genticel agreed to merge with GenKyoTex. | AI21: This transaction enables GenKyoTex and Genticel to complete both phase II study in primary biliary cholangitis (PBC) with GKT831 and first Phase I study with GKT771. | AL21: Unknown | AM21: Unknown | AS21: Calliditas Therapeutics France SAS | AT21: Calliditas Therapeutics France SAS; Calliditas Therapeutics France SAS | AU21: Not reviewed | AV21: Not assessed | AW21: Unknown | AX21: Unknown | AY21: Unknown | AZ21: Unknown | BA21: Unknown | BB21: Unknown | BF21: Not collected | BG21: Not collected | BH21: Not defined | BI21: =IF($Q21="","",$Q21-3) -> 2014 | BJ21: =IF($Q21="","",$Q21-2) -> 2015 | BK21: =IF($Q21="","",$Q21-1) -> 2016 | BL21: =IF($Q21="","",$Q21+0) -> 2017 | BM21: =IF($Q21="","",$Q21+1) -> 2018 | BN21: =IF($Q21="","",$Q21+2) -> 2019 | BO21: =IF($Q21="","",$Q21+3) -> 2020 | EQ21: =IF(OR($EO21="",$EP21="",$EO21=0),"",$EP21/$EO21) | ES21: Unknown | ET21: Unknown | EU21: =IF(COUNT($DF21,$DG21,$DH21)=0,"",AVERAGE($DF21,$DG21,$DH21)) | EV21: =IF(COUNT($DJ21,$DK21,$DL21)=0,"",AVERAGE($DJ21,$DK21,$DL21)) | EW21: =IF(OR($EU21="",$EV21=""),"",$EV21-$EU21) | EX21: =IF(COUNT($DM21,$DN21,$DO21)=0,"",AVERAGE($DM21,$DN21,$DO21)) | EY21: =IF(COUNT($DQ21,$DR21,$DS21)=0,"",AVERAGE($DQ21,$DR21,$DS21)) | EZ21: =IF(OR($EX21="",$EY21=""),"",$EY21-$EX21) | FA21: =IF(COUNT($EA21,$EB21,$EC21)=0,"",AVERAGE($EA21,$EB21,$EC21)) | FB21: =IF(COUNT($EE21,$EF21,$EG21)=0,"",AVERAGE($EE21,$EF21,$EG21)) | FC21: =IF(OR($FA21="",$FB21=""),"",$FB21-$FA21) | FD21: =IF(COUNT($EH21,$EI21,$EJ21)=0,"",AVERAGE($EH21,$EI21,$EJ21)) | FE21: =IF(COUNT($EL21,$EM21,$EN21)=0,"",AVERAGE($EL21,$EM21,$EN21)) | FF21: =IF(OR($FD21="",$FE21=""),"",$FE21-$FD21) | FG21: =IF(COUNT($DF21,$DG21,$DH21,$DJ21,$DK21,$DL21,$DM21,$DN21,$DO21,$DQ21,$DR21,$DS21)=12,"Yes","No") -> No | FH21: =IF(COUNT($EA21,$EB21,$EC21,$EE21,$EF21,$EG21,$EH21,$EI21,$EJ21,$EL21,$EM21,$EN21)=12,"Yes","No") -> No | FI21: =IF(AND($M21="Include",OR($FG21="Yes",$FH21="Yes")),"Ready","Not ready") -> Not ready
A22: TRT-0020 | B22: 31 | C22: Candidate treatment group | D22: 1 | E22: DATA - Innovation driven deals.xlsx | F22: biogaia acquires additional 9 stake in metabogen for | G22: Yes | H22: No | I22: Yes | J22: 2 | K22: Not started | L22: Exclude - minority | M22: Review | O22: 42704 | P22: 42704 | Q22: 2016 | R22: Q4 2016 | S22: Completed | T22: BioGaia Acquires Additional 9% Stake in MetaboGen for USD0.43 Million | U22: Mergers & Acquisitions | V22: Acquisition | W22: Minority Acquisition | X22: Sweden | Y22: Minority Acquisition | AB22: BioGaia AB | AC22: biogaia ab | AD22: MetaboGen AB | AE22: metabogen ab | AF22: 0 | AG22: 0 | AH22: BioGaia AB, a biotechnology company, has acquired additional 9% stake in MetaboGen AB, a research company, for a consideration of SEK4 million (USD0.43 million). In total BioGaia acquired 36% stake in MetaboGen. Earlier, on December 31, 2014, BioGaia agreed to acquire 35% stake in MetaboGen, for a purchase consideration of SEK12 million (USD1.6 million). Pursuant to the transaction, the investment will be made over a two year period and will then give BioGaia 35% of the share capital of the company. On December 31, 2016, BioGaia acquired 15% stake in MetaboGen, for a consideration of SEK4 million (USD0.54 million). On December 1, 2015, BioGaia acquired additional 12% stake in MetaboGen, for a consideration of SEK4 million (USD0.46 million). This acquisition enables BioGaia to strengthen its business and develop the next-generation of probiotic products using new technology. | AI22: This acquisition enables BioGaia to strengthen its business and develop the next-generation of probiotic products using new technology. | AL22: Unknown | AM22: Unknown | AS22: BioGaia AB | AT22: MetaboGen AB | AU22: Not reviewed | AV22: Not assessed | AW22: Unknown | AX22: Unknown | AY22: Unknown | AZ22: Unknown | BA22: Unknown | BB22: Unknown | BF22: Not collected | BG22: Not collected | BH22: Not defined | BI22: =IF($Q22="","",$Q22-3) -> 2013 | BJ22: =IF($Q22="","",$Q22-2) -> 2014 | BK22: =IF($Q22="","",$Q22-1) -> 2015 | BL22: =IF($Q22="","",$Q22+0) -> 2016 | BM22: =IF($Q22="","",$Q22+1) -> 2017 | BN22: =IF($Q22="","",$Q22+2) -> 2018 | BO22: =IF($Q22="","",$Q22+3) -> 2019 | EQ22: =IF(OR($EO22="",$EP22="",$EO22=0),"",$EP22/$EO22) | ES22: Unknown | ET22: Unknown | EU22: =IF(COUNT($DF22,$DG22,$DH22)=0,"",AVERAGE($DF22,$DG22,$DH22)) | EV22: =IF(COUNT($DJ22,$DK22,$DL22)=0,"",AVERAGE($DJ22,$DK22,$DL22)) | EW22: =IF(OR($EU22="",$EV22=""),"",$EV22-$EU22) | EX22: =IF(COUNT($DM22,$DN22,$DO22)=0,"",AVERAGE($DM22,$DN22,$DO22)) | EY22: =IF(COUNT($DQ22,$DR22,$DS22)=0,"",AVERAGE($DQ22,$DR22,$DS22)) | EZ22: =IF(OR($EX22="",$EY22=""),"",$EY22-$EX22) | FA22: =IF(COUNT($EA22,$EB22,$EC22)=0,"",AVERAGE($EA22,$EB22,$EC22)) | FB22: =IF(COUNT($EE22,$EF22,$EG22)=0,"",AVERAGE($EE22,$EF22,$EG22)) | FC22: =IF(OR($FA22="",$FB22=""),"",$FB22-$FA22) | FD22: =IF(COUNT($EH22,$EI22,$EJ22)=0,"",AVERAGE($EH22,$EI22,$EJ22)) | FE22: =IF(COUNT($EL22,$EM22,$EN22)=0,"",AVERAGE($EL22,$EM22,$EN22)) | FF22: =IF(OR($FD22="",$FE22=""),"",$FE22-$FD22) | FG22: =IF(COUNT($DF22,$DG22,$DH22,$DJ22,$DK22,$DL22,$DM22,$DN22,$DO22,$DQ22,$DR22,$DS22)=12,"Yes","No") -> No | FH22: =IF(COUNT($EA22,$EB22,$EC22,$EE22,$EF22,$EG22,$EH22,$EI22,$EJ22,$EL22,$EM22,$EN22)=12,"Yes","No") -> No | FI22: =IF(AND($M22="Include",OR($FG22="Yes",$FH22="Yes")),"Ready","Not ready") -> Not ready
A23: TRT-0021 | B23: 32 | C23: Candidate treatment group | D23: 1 | E23: DATA - Innovation driven deals.xlsx | F23: macarthys laboratories martindale pharma acquires viridian pharma | G23: Yes | H23: No | I23: No | J23: 1 | K23: Not started | L23: Review - majority | M23: Review | O23: 42562 | P23: 42562 | Q23: 2016 | R23: Q3 2016 | S23: Completed | T23: Macarthys Laboratories (Martindale Pharma) acquires Viridian Pharma | U23: Mergers & Acquisitions | V23: Acquisition | W23: Majority Acquisition | X23: United Kingdom | Y23: Majority Acquisition | AB23: Martindale Pharma | AC23: martindale pharma | AD23: Viridian Pharma Ltd | AE23: viridian pharma | AG23: n/a | AH23: Macarthys Laboratories Limited (trading as Martindale Pharma), a specialty pharmaceutical company, has acquired Viridian Pharma Limited, a developer and marketer of niche pharmaceutical products. Both the companies are based in the UK. _x000D_Following the transaction, Viridian Pharma will be combined with Martindale Pharma’s existing business. | AI23: According to Martindale Pharma, “This acquisition is part of the company’s strategy to expand its product portfolio and actively support further growth of its hospital-initiated medicines product range.” | AL23: Unknown | AM23: Unknown | AS23: Martindale Pharma | AT23: Viridian Pharma Ltd | AU23: Not reviewed | AV23: Not assessed | AW23: Unknown | AX23: Unknown | AY23: Unknown | AZ23: Unknown | BA23: Unknown | BB23: Unknown | BF23: Not collected | BG23: Not collected | BH23: Not defined | BI23: =IF($Q23="","",$Q23-3) -> 2013 | BJ23: =IF($Q23="","",$Q23-2) -> 2014 | BK23: =IF($Q23="","",$Q23-1) -> 2015 | BL23: =IF($Q23="","",$Q23+0) -> 2016 | BM23: =IF($Q23="","",$Q23+1) -> 2017 | BN23: =IF($Q23="","",$Q23+2) -> 2018 | BO23: =IF($Q23="","",$Q23+3) -> 2019 | EQ23: =IF(OR($EO23="",$EP23="",$EO23=0),"",$EP23/$EO23) | ES23: Unknown | ET23: Unknown | EU23: =IF(COUNT($DF23,$DG23,$DH23)=0,"",AVERAGE($DF23,$DG23,$DH23)) | EV23: =IF(COUNT($DJ23,$DK23,$DL23)=0,"",AVERAGE($DJ23,$DK23,$DL23)) | EW23: =IF(OR($EU23="",$EV23=""),"",$EV23-$EU23) | EX23: =IF(COUNT($DM23,$DN23,$DO23)=0,"",AVERAGE($DM23,$DN23,$DO23)) | EY23: =IF(COUNT($DQ23,$DR23,$DS23)=0,"",AVERAGE($DQ23,$DR23,$DS23)) | EZ23: =IF(OR($EX23="",$EY23=""),"",$EY23-$EX23) | FA23: =IF(COUNT($EA23,$EB23,$EC23)=0,"",AVERAGE($EA23,$EB23,$EC23)) | FB23: =IF(COUNT($EE23,$EF23,$EG23)=0,"",AVERAGE($EE23,$EF23,$EG23)) | FC23: =IF(OR($FA23="",$FB23=""),"",$FB23-$FA23) | FD23: =IF(COUNT($EH23,$EI23,$EJ23)=0,"",AVERAGE($EH23,$EI23,$EJ23)) | FE23: =IF(COUNT($EL23,$EM23,$EN23)=0,"",AVERAGE($EL23,$EM23,$EN23)) | FF23: =IF(OR($FD23="",$FE23=""),"",$FE23-$FD23) | FG23: =IF(COUNT($DF23,$DG23,$DH23,$DJ23,$DK23,$DL23,$DM23,$DN23,$DO23,$DQ23,$DR23,$DS23)=12,"Yes","No") -> No | FH23: =IF(COUNT($EA23,$EB23,$EC23,$EE23,$EF23,$EG23,$EH23,$EI23,$EJ23,$EL23,$EM23,$EN23)=12,"Yes","No") -> No | FI23: =IF(AND($M23="Include",OR($FG23="Yes",$FH23="Yes")),"Ready","Not ready") -> Not ready
A24: TRT-0022 | B24: 33 | C24: Candidate treatment group | D24: 1 | E24: DATA - Innovation driven deals.xlsx | F24: carbylan therapeutics acquires kalvista pharma | G24: Yes | H24: No | I24: No | J24: 1 | K24: Not started | L24: Eligible - 100% | M24: Review | O24: 42536 | P24: 42696 | Q24: 2016 | R24: Q2 2016 | S24: Completed | T24: Carbylan Therapeutics Acquires KalVista Pharma | U24: Mergers & Acquisitions | V24: Acquisition | W24: 100% Acquisition | X24: United Kingdom | Y24: 100% Acquisition | Z24: Wedbush PacGrow Life Sciences , Jefferies LLC | AA24: Fenwick & West LLP , Cooley LLP , Latham & Watkins LLP | AB24: Kalvista Pharmaceuticals Inc | AC24: kalvista pharmaceuticals | AD24: Kalvista Pharmaceuticals Ltd | AE24: kalvista pharmaceuticals | AG24: n/a | AH24: Carbylan Therapeutics, Inc., a pharmaceutical company, has completed the acquisition of KalVista Pharmaceuticals Ltd., a pharmaceutical company. Under the terms, Carbylan Therapeutics issued new shares of its common stock to KalVista Pharma shareholders. Following the transaction, Carbylan Therapeutics changed its name to KalVista Pharmaceuticals, Inc. The company will commence trading on November 22, 2016 on the NASDAQ Stock Market under the symbol 'KALV'. Upon the closing of the transaction, existing KalVista Pharma equity holders owned approximately 81% of the combined company, and existing Carbylan stockholders owned approximately 19%, each on a fully-diluted basis. As part of the transaction, the designated equity holders and KalVista Pharma's shareholder each entered into a lock-up agreement with Carbylan Therapeutics pursuant to which such parties have agreed, except in limited circumstances, not to sell or transfer, or engage in swap or similar transactions with respect to, shares of Carbylan Therapeutics’ common stock, including, as applicable, shares received in connection with the transaction, for a period of 180 days following the closing of the transaction. The total cash balance, net of debt and expected transaction costs, of the combined company upon the closing of the transaction is expected to be minimum of USD35 million and maximum of USD40 million, which is expected to be sufficient to allow the combined company to achieve meaningful clinical data. Following the transaction, KalVista Pharma will become a wholly owned subsidiary of Carbylan Therapeutics. The transaction has been unanimously approved by the boards of directors of both companies. Carbylan Therapeutics' three largest shareholders, Interwest Partners, LLC, Alta Partners and Vivo Capital, who hold approximately 50% of its voting shares, have entered into agreements in support of the proposed transaction. KalVista Pharma’s existing shareholders, which have unanimously agreed to the proposed transaction, include Longwood Fund, Novo A/S, RA Capital Management, SV Life Sciences and Venrock. This transaction enables KalVista Pharma to continue the development of its plasma kallikrein inhibitor platform, and advance its programs in hereditary angioedema (HAE) and diabetic macular edema (DME), bringing much-needed treatments to patients. Wedbush PacGrow Life Sciences acted as advisor, and Latham & Watkins LLP acted as legal advisor to Carbylan Therapeutics; while Jefferies LLC acted as advisor, and Fenwick & West LLP and Cooley LLP acted as legal advisor to KalVista Pharma, for the transaction. Deal History: Announced: On June 15, 2016, Carbylan Therapeutics entered into a definitive share purchase agreement to acquire KalVista Pharma. | AI24: This transaction enables KalVista Pharma to continue the development of its plasma kallikrein inhibitor platform, and advance its programs in hereditary angioedema (HAE) and diabetic macular edema (DME), bringing much-needed treatments to patients. | AL24: Unknown | AM24: Unknown | AS24: Kalvista Pharmaceuticals Inc | AT24: Kalvista Pharmaceuticals Ltd | AU24: Not reviewed | AV24: Not assessed | AW24: Unknown | AX24: Unknown | AY24: Unknown | AZ24: Unknown | BA24: Unknown | BB24: Unknown | BF24: Not collected | BG24: Not collected | BH24: Not defined | BI24: =IF($Q24="","",$Q24-3) -> 2013 | BJ24: =IF($Q24="","",$Q24-2) -> 2014 | BK24: =IF($Q24="","",$Q24-1) -> 2015 | BL24: =IF($Q24="","",$Q24+0) -> 2016 | BM24: =IF($Q24="","",$Q24+1) -> 2017 | BN24: =IF($Q24="","",$Q24+2) -> 2018 | BO24: =IF($Q24="","",$Q24+3) -> 2019 | EQ24: =IF(OR($EO24="",$EP24="",$EO24=0),"",$EP24/$EO24) | ES24: Unknown | ET24: Unknown | EU24: =IF(COUNT($DF24,$DG24,$DH24)=0,"",AVERAGE($DF24,$DG24,$DH24)) | EV24: =IF(COUNT($DJ24,$DK24,$DL24)=0,"",AVERAGE($DJ24,$DK24,$DL24)) | EW24: =IF(OR($EU24="",$EV24=""),"",$EV24-$EU24) | EX24: =IF(COUNT($DM24,$DN24,$DO24)=0,"",AVERAGE($DM24,$DN24,$DO24)) | EY24: =IF(COUNT($DQ24,$DR24,$DS24)=0,"",AVERAGE($DQ24,$DR24,$DS24)) | EZ24: =IF(OR($EX24="",$EY24=""),"",$EY24-$EX24) | FA24: =IF(COUNT($EA24,$EB24,$EC24)=0,"",AVERAGE($EA24,$EB24,$EC24)) | FB24: =IF(COUNT($EE24,$EF24,$EG24)=0,"",AVERAGE($EE24,$EF24,$EG24)) | FC24: =IF(OR($FA24="",$FB24=""),"",$FB24-$FA24) | FD24: =IF(COUNT($EH24,$EI24,$EJ24)=0,"",AVERAGE($EH24,$EI24,$EJ24)) | FE24: =IF(COUNT($EL24,$EM24,$EN24)=0,"",AVERAGE($EL24,$EM24,$EN24)) | FF24: =IF(OR($FD24="",$FE24=""),"",$FE24-$FD24) | FG24: =IF(COUNT($DF24,$DG24,$DH24,$DJ24,$DK24,$DL24,$DM24,$DN24,$DO24,$DQ24,$DR24,$DS24)=12,"Yes","No") -> No | FH24: =IF(COUNT($EA24,$EB24,$EC24,$EE24,$EF24,$EG24,$EH24,$EI24,$EJ24,$EL24,$EM24,$EN24)=12,"Yes","No") -> No | FI24: =IF(AND($M24="Include",OR($FG24="Yes",$FH24="Yes")),"Ready","Not ready") -> Not ready
A25: TRT-0023 | B25: 34 | C25: Candidate treatment group | D25: 1 | E25: DATA - Innovation driven deals.xlsx | F25: albany molecular research acquires 100 stake of prime european therapeuticals euticals | G25: Yes | H25: No | I25: No | J25: 1 | K25: Not started | L25: Eligible - 100% | M25: Review | O25: 42495 | P25: 42562 | Q25: 2016 | R25: Q2 2016 | S25: Completed | T25: Albany Molecular Research acquires 100% stake of Prime European Therapeuticals (Euticals) | U25: Mergers & Acquisitions | V25: Acquisition | W25: 100% Acquisition | X25: Italy | Y25: 100% Acquisition | Z25: Nomura Holdings Inc , Lincoln International LLC | AA25: LCA Studio Legale , Chiomenti Studio Legale , Debevoise & Plimpton LLP , Goodwin Procter LLP | AB25: Albany Molecular Research, Inc. | AC25: albany molecular research | AD25: Euticals SpA | AE25: euticals | AF25: 358 | AG25: 358 | AH25: Albany Molecular Research, Inc. (AMRI) has acquired all outstanding shares of Prime European Therapeuticals S.p.A. (also known as Euticals S.p.A.), an Italy-based chemical company focused on active pharmaceutical ingredients (APIs), custom synthesis and fine chemicals projects and products, from Lauro Cinquantesette, S.p.A for approximately $358 million, consisting of shares of AMRI common stock, cash, and a seller note. _x000D_ AMRI is a US-based provider of contract research and manufacturing services to the pharmaceutical and biotechnology industries, while Lauro is an Italy-based acquisition vehicle of Clessidra Capital Partners II and Mandarin Capital Partner SCA SICAR. _x000D_ AMRI financed the transaction through the issuance of approximately 7.1 million shares of AMRI common stock, seller notes totaling EUR55 million, and the remainder in cash. _x000D_ Announcement (May 5, 2016): _x000D_ AMRI has signed a definitive agreement to acquire all outstanding shares of Euticals from Lauro for approximately $358 million, consisting of shares of AMRI common stock, cash, and a seller note. _x000D_ AMRI intends to fund the transaction through the issuance of approximately 7 million shares of its common stock; a seller note of $63 million; and the remainder in cash. _x000D_ AMRI has entered into debt financing commitments with JPMorgan Chase & Co. and Barclays Bank PLC for amounts that are expected to be sufficient to provide funds necessary to consummate the transaction. _x000D_ Pursuant to the transaction, the 7 million shares of AMRI common stock to be issued in connection with the transaction will be offered and sold outside the US to Lauro. _x000D_ Euticals reported a revenue of $245 million and an earnings before interest, taxes, depreciation and amortization (EBITDA) of $27 million respectively for the year ended December 31, 2015. _x000D_ Euticals' full year 2016 revenue is forecast to be between $245 million and $255 million, with adjusted EBITDA1 of between $34 million and $38 million, implying a purchase price multiple, prior to anticipated synergies, of approximately 9.9 times 2016 adjusted EBITDA at the midpoint of the range and excluding transaction related costs or purchase accounting impacts. AMRI's 2017 pro forma revenue expected to exceed $750 million, with 2017 adjusted EBITDA margins of 20%. _x000D_ Nomura Holdings, Inc. is acting as financial advisor, while Goodwin Procter LLP and LCA Studio Legale are acting as legal advisors to AMRI. Lincoln International LLC is acting as financial advisor, while Chiomenti Studio Legale and Debevoise & Plimpton LLP are acting as legal advisors to Lauro. | AI25: The transaction will provide AMRI an established custom synthesis presence in Europe and will further build on its capability in complex APIs, positioning AMRI as a preeminent provider of contract research, development and manufacturing services to the pharmaceutical industry._x000D_ _x000D_ It will expand AMRI's capabilities in multiple areas: sterile API, steroids, generics, fermentation, controlled substances and monobactams._x000D_ _x000D_ It will also provide an opportunity to AMRI to enter into Euticals’s technologies and products, including certain tetracyclines, monobactams, sterile and fermented APIs and controlled substances and to further expand its presence in the European community. | AL25: Unknown | AM25: Unknown | AS25: Albany Molecular Research, Inc. | AT25: Euticals SpA | AU25: Not reviewed | AV25: Not assessed | AW25: Unknown | AX25: Unknown | AY25: Unknown | AZ25: Unknown | BA25: Unknown | BB25: Unknown | BF25: Not collected | BG25: Not collected | BH25: Not defined | BI25: =IF($Q25="","",$Q25-3) -> 2013 | BJ25: =IF($Q25="","",$Q25-2) -> 2014 | BK25: =IF($Q25="","",$Q25-1) -> 2015 | BL25: =IF($Q25="","",$Q25+0) -> 2016 | BM25: =IF($Q25="","",$Q25+1) -> 2017 | BN25: =IF($Q25="","",$Q25+2) -> 2018 | BO25: =IF($Q25="","",$Q25+3) -> 2019 | EQ25: =IF(OR($EO25="",$EP25="",$EO25=0),"",$EP25/$EO25) | ES25: Unknown | ET25: Unknown | EU25: =IF(COUNT($DF25,$DG25,$DH25)=0,"",AVERAGE($DF25,$DG25,$DH25)) | EV25: =IF(COUNT($DJ25,$DK25,$DL25)=0,"",AVERAGE($DJ25,$DK25,$DL25)) | EW25: =IF(OR($EU25="",$EV25=""),"",$EV25-$EU25) | EX25: =IF(COUNT($DM25,$DN25,$DO25)=0,"",AVERAGE($DM25,$DN25,$DO25)) | EY25: =IF(COUNT($DQ25,$DR25,$DS25)=0,"",AVERAGE($DQ25,$DR25,$DS25)) | EZ25: =IF(OR($EX25="",$EY25=""),"",$EY25-$EX25) | FA25: =IF(COUNT($EA25,$EB25,$EC25)=0,"",AVERAGE($EA25,$EB25,$EC25)) | FB25: =IF(COUNT($EE25,$EF25,$EG25)=0,"",AVERAGE($EE25,$EF25,$EG25)) | FC25: =IF(OR($FA25="",$FB25=""),"",$FB25-$FA25) | FD25: =IF(COUNT($EH25,$EI25,$EJ25)=0,"",AVERAGE($EH25,$EI25,$EJ25)) | FE25: =IF(COUNT($EL25,$EM25,$EN25)=0,"",AVERAGE($EL25,$EM25,$EN25)) | FF25: =IF(OR($FD25="",$FE25=""),"",$FE25-$FD25) | FG25: =IF(COUNT($DF25,$DG25,$DH25,$DJ25,$DK25,$DL25,$DM25,$DN25,$DO25,$DQ25,$DR25,$DS25)=12,"Yes","No") -> No | FH25: =IF(COUNT($EA25,$EB25,$EC25,$EE25,$EF25,$EG25,$EH25,$EI25,$EJ25,$EL25,$EM25,$EN25)=12,"Yes","No") -> No | FI25: =IF(AND($M25="Include",OR($FG25="Yes",$FH25="Yes")),"Ready","Not ready") -> Not ready
A26: TRT-0024 | B26: 35 | C26: Candidate treatment group | D26: 1 | E26: DATA - Innovation driven deals.xlsx | F26: vectura group acquires 100 stake in skyepharma | G26: Yes | H26: No | I26: Yes | J26: 2 | K26: Not started | L26: Eligible - 100% | M26: Review | O26: 42445 | P26: 42531 | Q26: 2016 | R26: Q1 2016 | S26: Completed | T26: Vectura Group acquires 100% stake in SkyePharma | U26: Mergers & Acquisitions | V26: Acquisition | W26: 100% Acquisition | X26: United Kingdom | Y26: 100% Acquisition | Z26: N M Rothschild & Sons Limited (Inactive) , N M Rothschild & Sons Limited (Inactive) , N M Rothschild & Sons Limited (Inactive) , Singer Capital Markets Ltd , Lazard & Co Ltd , Lazard & Co Ltd , Lazard & Co Ltd , J.P. Morgan Cazenove Ltd (Inactive) , J.P. Morgan Cazenove Ltd (Inactive) , J.P. Morgan Cazenove Ltd (Inactive) , Peel Hunt LLP | AB26: Vectura Group Limited | AC26: vectura | AD26: Skyepharma PLC | AE26: skyepharma | AF26: 627 | AG26: 627 | AH26: Vectura Group plc, a developer of pharmaceutical therapies for the treatment of airways-related diseases, has acquired the entire issued and to be issued ordinary share capital of Skyepharma Plc, a specialist drug delivery company developing oral and inhalation products, by way of a scheme of arrangement for approximately GBP4.10 per Skyepharma share, or approximately GBP441.3 million. Both the companies are based in the UK. _x000D_Announcement (March 16, 2016): _x000D_Vectura has signed an agreement to acquire the entire issued and to be issued ordinary share capital of Skyepharma by way of a scheme of arrangement for approximately GBP4.10 per Skyepharma share, or approximately GBP441.3 million. _x000D_Under the terms of the transaction, Skyepharma shareholders will be entitled to receive 2.7977 new Vectura shares for every Skyepharma share. _x000D_Based on the closing price of GBP1.46 per Vectura share on March 15, 2016, the consideration under the terms of the transaction represents a value of GBP4.10 per Skyepharma share, or approximately GBP441.3 million in aggregate, representing: a premium of approximately 13.6% to the 90 trading day volume weighted average price of GBP3.61 per Skyepharma share on March 15, 2016; and a premium of approximately 4.2% to the closing price of GBP3.93 per Skyepharma share on March 15, 2016. _x000D_There will be a partial cash alternative of a maximum amount of GBP70 million pursuant to which Skyepharma shareholders can elect to receive cash instead of some or all of the new Vectura shares to which they would otherwise be entitled under the transaction (subject to scale-back in accordance with the terms of the partial cash alternative). The maximum amount of cash available under the partial cash alternative of GBP70 million equates to 15.9% of the total value of the consideration offered to Skyepharma shareholders under the terms of the transaction, based on the closing price of GBP1.46 per Vectura share on March 15, 2016. _x000D_The transaction (excluding the effect of the partial cash alternative) will result in Skyepharma shareholders owning approximately 41.75% of the enlarged group on a fully diluted basis. If the GBP70 million available under the partial cash alternative is paid in full, the transaction will result in Skyepharma shareholders owning approximately 37.62% of the Enlarged Group on a fully diluted basis. _x000D_Based on closing prices as of March 15, 2016, the enlarged group would have had a pro-forma market capitalization of GBP1,014.3 million and generated pro-forma combined revenues of GBP153.9 million and pro-forma combined EBITDA of GBP50.5 million based on the last reported full-year results for both companies. _x000D_ Vectura has received support for the transaction from: the Skyepharma directors who hold Skyepharma shares and who in aggregate hold 0.39% of the issued ordinary share capital of Skyepharma as at March 15, 2016 (being the last business day prior to the date of the announcement); and HBM Healthcare Investments, Ltd., which holds approximately 28.5% of the issued ordinary share capital of Skyepharma as at March 15, 2016 (being the last business day prior to the date of the announcement). _x000D_ Such Skyepharma directors and HBM have irrevocably undertaken to support the scheme. Frank Condella and Thomas Werner have undertaken not to elect to receive the partial cash alternative in respect of their Skyepharma shares and HBM will elect to receive the partial cash alternative in respect of 15.9% of the consideration due to them. _x000D_The transaction is expected to close in the third quarter of 2016. _x000D_J.P. Morgan Cazenove, N M Rothschild & Sons Limited and Peel Hunt LLP are acting as financial advisors, while Citigate Dewe Rogerson is acting as public relations (PR) advisor to Vectura. _x000D_ Lazard & Co., Limited and N+1 Singer are acting as financial advisors, while FTI Consulting is acting as PR advisor to Skyepharma. | AI26: The transaction will combine the complementary Vectura and Skyepharma businesses to create airways-related specialty business. _x000D_ _x000D_ Vectura and Skyepharma's complementary inhaled formulation, development regulatory and device capabilities (dry powder inhalers (DPI), pressurized metered dose inhalers (pMDI) and smart nebulisers) will provide a series of enhanced platforms to accelerate growth in the inhaled respiratory market along with providing a broader product and development portfolio._x000D_ _x000D_ The transaction will allow Vectura and Skyepharma to develop and commercialize its own products and progressively build a specialty commercial capability targeting the airways market, with the US as a priority. | AL26: Unknown | AM26: Unknown | AS26: Vectura Group Limited | AT26: Skyepharma PLC | AU26: Not reviewed | AV26: Not assessed | AW26: Unknown | AX26: Unknown | AY26: Unknown | AZ26: Unknown | BA26: Unknown | BB26: Unknown | BF26: Not collected | BG26: Not collected | BH26: Not defined | BI26: =IF($Q26="","",$Q26-3) -> 2013 | BJ26: =IF($Q26="","",$Q26-2) -> 2014 | BK26: =IF($Q26="","",$Q26-1) -> 2015 | BL26: =IF($Q26="","",$Q26+0) -> 2016 | BM26: =IF($Q26="","",$Q26+1) -> 2017 | BN26: =IF($Q26="","",$Q26+2) -> 2018 | BO26: =IF($Q26="","",$Q26+3) -> 2019 | EQ26: =IF(OR($EO26="",$EP26="",$EO26=0),"",$EP26/$EO26) | ES26: Unknown | ET26: Unknown | EU26: =IF(COUNT($DF26,$DG26,$DH26)=0,"",AVERAGE($DF26,$DG26,$DH26)) | EV26: =IF(COUNT($DJ26,$DK26,$DL26)=0,"",AVERAGE($DJ26,$DK26,$DL26)) | EW26: =IF(OR($EU26="",$EV26=""),"",$EV26-$EU26) | EX26: =IF(COUNT($DM26,$DN26,$DO26)=0,"",AVERAGE($DM26,$DN26,$DO26)) | EY26: =IF(COUNT($DQ26,$DR26,$DS26)=0,"",AVERAGE($DQ26,$DR26,$DS26)) | EZ26: =IF(OR($EX26="",$EY26=""),"",$EY26-$EX26) | FA26: =IF(COUNT($EA26,$EB26,$EC26)=0,"",AVERAGE($EA26,$EB26,$EC26)) | FB26: =IF(COUNT($EE26,$EF26,$EG26)=0,"",AVERAGE($EE26,$EF26,$EG26)) | FC26: =IF(OR($FA26="",$FB26=""),"",$FB26-$FA26) | FD26: =IF(COUNT($EH26,$EI26,$EJ26)=0,"",AVERAGE($EH26,$EI26,$EJ26)) | FE26: =IF(COUNT($EL26,$EM26,$EN26)=0,"",AVERAGE($EL26,$EM26,$EN26)) | FF26: =IF(OR($FD26="",$FE26=""),"",$FE26-$FD26) | FG26: =IF(COUNT($DF26,$DG26,$DH26,$DJ26,$DK26,$DL26,$DM26,$DN26,$DO26,$DQ26,$DR26,$DS26)=12,"Yes","No") -> No | FH26: =IF(COUNT($EA26,$EB26,$EC26,$EE26,$EF26,$EG26,$EH26,$EI26,$EJ26,$EL26,$EM26,$EN26)=12,"Yes","No") -> No | FI26: =IF(AND($M26="Include",OR($FG26="Yes",$FH26="Yes")),"Ready","Not ready") -> Not ready
A27: TRT-0025 | B27: 36 | C27: Candidate treatment group | D27: 1 | E27: DATA - Innovation driven deals.xlsx | F27: skyepharma merges with vectura | G27: Yes | H27: No | I27: Yes | J27: 2 | K27: Not started | L27: Review - merger | M27: Review | O27: 42445 | P27: 42531 | Q27: 2016 | R27: Q1 2016 | S27: Completed | T27: SkyePharma Merges with Vectura | U27: Mergers & Acquisitions | V27: Merger | X27: United Kingdom | Z27: Lazard & Co Ltd , J.P. Morgan Cazenove Ltd (Inactive) , N M Rothschild & Sons Ltd | AB27: Vectura Group Ltd | AC27: vectura | AD27: SkyePharma Ltd; Vectura Group Ltd | AE27: skyepharma vectura | AF27: 627 | AG27: 627 | AH27: SkyePharma PLC, a provider of oral and inhalation pharmaceutical products, has merged with Vectura Group plc, a provider of drugs for the treatment of bronchopulmonary diseases. The transaction is valued at GBP4.1 (USD5.83) per SkyePharma share or approximately GBP441.3 million (USD627.45 million), in shares. Following the transaction, the combined company will be Vectura Group. The purchase consideration represents a premium of approximately 4.2% to the closing price of GBP3.93 (USD5.55) per Skyepharma share on March 15, 2016 and a premium of approximately 13.6% to the 90 trading day volume weighted average price (VWAP) of GBP3.61 (USD5.1) per Skyepharma share on March 15, 2016. Pursuant to the transaction, SkyePharma shareholders are entitled to receive 2.7977 new shares for each share held, valuing SkyePharma at GBP441.3 million (USD627.45 million). Alternatively, SkyePharma shareholders have an option to receive a part of the offer instead of some or all of the new Vectura shares. If GBP70 million (USD99.53 million) available under the cash alternative is paid in full, SkyePharma shareholders would own about 37.62% of the combined company and an all-stock transaction would result in SkyePharma shareholders owning about 41.75% of the combined company. In addtion, Skyepharma shareholders who validly elect to receive the partial cash alternative for up to a basic entitlement of GBP0.23 (USD0.33) in cash and 0.8414 of a new Vectura share for every new Vectura share to which they would otherwise be entitled under the merger, will receive the full amount of cash for which they have elected. Assuming all Skyepharma shareholders elect for their basic entitlement under the partial cash alternative in respect of all of the new Vectura shares to which they would otherwise be entitled under the merger, a Skyepharma shareholder would receive GBP0.65 (USD0.92) in cash and 2.3539 new Vectura shares per Skyepharma share representing consideration of, in aggregate, GBP0.41 (USD0.58) per Skyepharma share. Following the transaction, Skyepharma will operate as a wholly-owned subsidiary of Vectura. As part of the consideration, Vectura entered into a new five year revolving loan facility with HSBC Bank plc for GBP50 million (USD71.09 million) with the option to extend to GBP75 million (USD106.64 million). Under the terms of the transaction, new Vectura shares will be issued as consideration. The cash payable pursuant to the terms of the partial cash alternative will be funded from Vectura's existing cash resources, together with the proceeds of GBP50 million (USD71.09 million) from the revolving loan facility with HSBC Bank plc which are available to Vectura for the purposes of financing the transaction. As part of the transaction, James Ward-Lilley, CEO of Vectura, will join as CEO of the enlarged group. The executive directors of enlarged group consist of Andrew Derodra, CFO of Skyepharma, and Trevor Phillips, COO of Vectura. Bruno Angelici, chairman of Vectura, will join as the chairman of the enlarged group. In addition, Andrew Oakley, CFO of Vectura, will leave the board of directors of Vectura on terms to be agreed and Peter Grant, CEO of Skyepharma, will leave board of directors of Skyepharma on terms to be agreed. Vectura will appoint Frank Condella, chairman of Skyepharma, as the vice-chairman of the enlarged group, and Thomas Werner, a non-executive Skyepharma director, as a non-executive director on the enlarged group board. Andrew Derodra, CFO of Skyepharma , will become the CFO of the enlarged group. This transaction enables Vectura and SkyePharma to focus on respiratory drug development. J.P. Morgan Cazenove Limited and N M Rothschild and Sons Limited acted as joint financial advisors to Vectura, while Lazard & Co., Limited acted as financial advisor to SkyePharma. Deal History: Announced: On March 16, 2016, SkyePharma entered into an agreement to merge with Vectura. The transaction is valued at GBP4.1 (USD5.83) per SkyePharma share or approximately GBP441.3 million (USD627.45 million), in shares. | AI27: This transaction enables Vectura and SkyePharma to focus on respiratory drug development. | AL27: Unknown | AM27: Unknown | AS27: Vectura Group Ltd | AT27: SkyePharma Ltd; Vectura Group Ltd | AU27: Not reviewed | AV27: Not assessed | AW27: Unknown | AX27: Unknown | AY27: Unknown | AZ27: Unknown | BA27: Unknown | BB27: Unknown | BF27: Not collected | BG27: Not collected | BH27: Not defined | BI27: =IF($Q27="","",$Q27-3) -> 2013 | BJ27: =IF($Q27="","",$Q27-2) -> 2014 | BK27: =IF($Q27="","",$Q27-1) -> 2015 | BL27: =IF($Q27="","",$Q27+0) -> 2016 | BM27: =IF($Q27="","",$Q27+1) -> 2017 | BN27: =IF($Q27="","",$Q27+2) -> 2018 | BO27: =IF($Q27="","",$Q27+3) -> 2019 | EQ27: =IF(OR($EO27="",$EP27="",$EO27=0),"",$EP27/$EO27) | ES27: Unknown | ET27: Unknown | EU27: =IF(COUNT($DF27,$DG27,$DH27)=0,"",AVERAGE($DF27,$DG27,$DH27)) | EV27: =IF(COUNT($DJ27,$DK27,$DL27)=0,"",AVERAGE($DJ27,$DK27,$DL27)) | EW27: =IF(OR($EU27="",$EV27=""),"",$EV27-$EU27) | EX27: =IF(COUNT($DM27,$DN27,$DO27)=0,"",AVERAGE($DM27,$DN27,$DO27)) | EY27: =IF(COUNT($DQ27,$DR27,$DS27)=0,"",AVERAGE($DQ27,$DR27,$DS27)) | EZ27: =IF(OR($EX27="",$EY27=""),"",$EY27-$EX27) | FA27: =IF(COUNT($EA27,$EB27,$EC27)=0,"",AVERAGE($EA27,$EB27,$EC27)) | FB27: =IF(COUNT($EE27,$EF27,$EG27)=0,"",AVERAGE($EE27,$EF27,$EG27)) | FC27: =IF(OR($FA27="",$FB27=""),"",$FB27-$FA27) | FD27: =IF(COUNT($EH27,$EI27,$EJ27)=0,"",AVERAGE($EH27,$EI27,$EJ27)) | FE27: =IF(COUNT($EL27,$EM27,$EN27)=0,"",AVERAGE($EL27,$EM27,$EN27)) | FF27: =IF(OR($FD27="",$FE27=""),"",$FE27-$FD27) | FG27: =IF(COUNT($DF27,$DG27,$DH27,$DJ27,$DK27,$DL27,$DM27,$DN27,$DO27,$DQ27,$DR27,$DS27)=12,"Yes","No") -> No | FH27: =IF(COUNT($EA27,$EB27,$EC27,$EE27,$EF27,$EG27,$EH27,$EI27,$EJ27,$EL27,$EM27,$EN27)=12,"Yes","No") -> No | FI27: =IF(AND($M27="Include",OR($FG27="Yes",$FH27="Yes")),"Ready","Not ready") -> Not ready
A28: TRT-0026 | B28: 37 | C28: Candidate treatment group | D28: 1 | E28: DATA - Innovation driven deals.xlsx | F28: therametrics merges with relief therapeutics | G28: Yes | H28: No | I28: No | J28: 1 | K28: Not started | L28: Review - merger | M28: Review | O28: 42359 | P28: 42569 | Q28: 2016 | R28: Q4 2015 | S28: Completed | T28: Therametrics Merges with Relief Therapeutics | U28: Mergers & Acquisitions | V28: Merger | X28: Switzerland | Z28: ACXIT Capital Partners | AA28: Bar & Karrer AG , CPV Partners , Froriep & Renggli | AB28: Relief Therapeutics Holding AG; Sonnet BioTherapeutics CH SA | AC28: relief therapeutics sonnet biotherapeutics ch | AD28: THERAMetrics holding AG (Inactive); Sonnet BioTherapeutics CH SA | AE28: therametrics sonnet biotherapeutics ch | AG28: n/a | AH28: Therametrics holding AG (formerly mondoBIOTECH holding AG), a provider of drugs for rare diseases, has merged with Relief Therapeutics S.A., a biotechnology company. Following the transaction, the combined entity changed its name from Therametrics holding AG to Relief Therapeutics Holding AG, Relief Therapeutics become the majority owners of the combined company. The business combination was carried out by way of 5,750 Therametrics shares for each outstanding share of Relief Therapeutics SA common stock. As a result, the company issued 1,196,937,250 new shares against contribution in kind of 208,163 shares of Relief Therapeutics SA. Concurrently, all 1,936,627,375 Relief Therapeutics Holding shares are listed and freely tradable on the SIX Swiss Exchange under the International Reporting Standard, under the ticker symbol of 'RLF'. In addition, Relief Therapeutics Holding announced that a CHF3.3 million (USD3.32 million) shareholder loan with all accrued interest has been mandatorily converted, with effect as of completion of the business combination with Relief Therapeutics SA, into shares of the company. Thereby, 84,906,473 new shares of Relief Therapeutics Holding have been issued out of conditional capital. This transaction enables the combined company to advance the possibility of demonstrating the potential of Low Dose IL-6 to treat neuropathies. ACXIT Capital Partners acted as sole financial advisor, Bar & Karrer Rechtsanwalte and Froriep & Renggli acted as legal advisors to Therametrics and CPV Partners (Geneva) acted as legal advisor to Relief Therapeutics for the transaction. Deal History: Announced: On December 21, 2015, Therametrics and Relief Therapeutics entered into a binding agreement to combine their businesses by way of an exchange of Relief Therapeutics’ shares for new Therametrics shares, subject to shareholder approval and other customary conditions. | AI28: This transaction enables the combined company to advance the possibility of demonstrating the potential of Low Dose IL-6 to treat neuropathies. | AL28: Unknown | AM28: Unknown | AS28: Relief Therapeutics Holding AG; Sonnet BioTherapeutics CH SA | AT28: THERAMetrics holding AG (Inactive); Sonnet BioTherapeutics CH SA | AU28: Not reviewed | AV28: Not assessed | AW28: Unknown | AX28: Unknown | AY28: Unknown | AZ28: Unknown | BA28: Unknown | BB28: Unknown | BF28: Not collected | BG28: Not collected | BH28: Not defined | BI28: =IF($Q28="","",$Q28-3) -> 2013 | BJ28: =IF($Q28="","",$Q28-2) -> 2014 | BK28: =IF($Q28="","",$Q28-1) -> 2015 | BL28: =IF($Q28="","",$Q28+0) -> 2016 | BM28: =IF($Q28="","",$Q28+1) -> 2017 | BN28: =IF($Q28="","",$Q28+2) -> 2018 | BO28: =IF($Q28="","",$Q28+3) -> 2019 | EQ28: =IF(OR($EO28="",$EP28="",$EO28=0),"",$EP28/$EO28) | ES28: Unknown | ET28: Unknown | EU28: =IF(COUNT($DF28,$DG28,$DH28)=0,"",AVERAGE($DF28,$DG28,$DH28)) | EV28: =IF(COUNT($DJ28,$DK28,$DL28)=0,"",AVERAGE($DJ28,$DK28,$DL28)) | EW28: =IF(OR($EU28="",$EV28=""),"",$EV28-$EU28) | EX28: =IF(COUNT($DM28,$DN28,$DO28)=0,"",AVERAGE($DM28,$DN28,$DO28)) | EY28: =IF(COUNT($DQ28,$DR28,$DS28)=0,"",AVERAGE($DQ28,$DR28,$DS28)) | EZ28: =IF(OR($EX28="",$EY28=""),"",$EY28-$EX28) | FA28: =IF(COUNT($EA28,$EB28,$EC28)=0,"",AVERAGE($EA28,$EB28,$EC28)) | FB28: =IF(COUNT($EE28,$EF28,$EG28)=0,"",AVERAGE($EE28,$EF28,$EG28)) | FC28: =IF(OR($FA28="",$FB28=""),"",$FB28-$FA28) | FD28: =IF(COUNT($EH28,$EI28,$EJ28)=0,"",AVERAGE($EH28,$EI28,$EJ28)) | FE28: =IF(COUNT($EL28,$EM28,$EN28)=0,"",AVERAGE($EL28,$EM28,$EN28)) | FF28: =IF(OR($FD28="",$FE28=""),"",$FE28-$FD28) | FG28: =IF(COUNT($DF28,$DG28,$DH28,$DJ28,$DK28,$DL28,$DM28,$DN28,$DO28,$DQ28,$DR28,$DS28)=12,"Yes","No") -> No | FH28: =IF(COUNT($EA28,$EB28,$EC28,$EE28,$EF28,$EG28,$EH28,$EI28,$EJ28,$EL28,$EM28,$EN28)=12,"Yes","No") -> No | FI28: =IF(AND($M28="Include",OR($FG28="Yes",$FH28="Yes")),"Ready","Not ready") -> Not ready
A29: TRT-0027 | B29: 38 | C29: Candidate treatment group | D29: 1 | E29: DATA - Innovation driven deals.xlsx | F29: biogaia acquires additional 12 stake in metabogen for | G29: Yes | H29: No | I29: Yes | J29: 2 | K29: Not started | L29: Exclude - minority | M29: Review | O29: 42339 | P29: 42339 | Q29: 2015 | R29: Q4 2015 | S29: Completed | T29: BioGaia Acquires Additional 12% Stake in MetaboGen for USD0.5 Million | U29: Mergers & Acquisitions | V29: Acquisition | W29: Minority Acquisition | X29: Sweden | Y29: Minority Acquisition | AB29: BioGaia AB | AC29: biogaia ab | AD29: MetaboGen AB | AE29: metabogen ab | AF29: 0 | AG29: 0 | AH29: BioGaia AB, a biotechnology company, has acquired additional 12% stake in MetaboGen AB, a research company, for a consideration of SEK4 million (USD0.46 million). In total BioGaia acquired 27% stake in MetaboGen. Earlier, on December 31, 2014, BioGaia agreed to acquire 35% stake in MetaboGen, for a purchase consideration of SEK12 million (USD1.6 million). Pursuant to the transaction, the investment will be made over a two year period and will then give BioGaia 35% of the share capital of the company. On December 31, 2016, BioGaia acquired 15% stake in MetaboGen, for a consideration of SEK4 million (USD0.54 million). This acquisition enables BioGaia to strengthen its business and develop the next-generation of probiotic products using new technology. | AI29: This acquisition enables BioGaia to strengthen its business and develop the next-generation of probiotic products using new technology. | AL29: Unknown | AM29: Unknown | AS29: BioGaia AB | AT29: MetaboGen AB | AU29: Not reviewed | AV29: Not assessed | AW29: Unknown | AX29: Unknown | AY29: Unknown | AZ29: Unknown | BA29: Unknown | BB29: Unknown | BF29: Not collected | BG29: Not collected | BH29: Not defined | BI29: =IF($Q29="","",$Q29-3) -> 2012 | BJ29: =IF($Q29="","",$Q29-2) -> 2013 | BK29: =IF($Q29="","",$Q29-1) -> 2014 | BL29: =IF($Q29="","",$Q29+0) -> 2015 | BM29: =IF($Q29="","",$Q29+1) -> 2016 | BN29: =IF($Q29="","",$Q29+2) -> 2017 | BO29: =IF($Q29="","",$Q29+3) -> 2018 | EQ29: =IF(OR($EO29="",$EP29="",$EO29=0),"",$EP29/$EO29) | ES29: Unknown | ET29: Unknown | EU29: =IF(COUNT($DF29,$DG29,$DH29)=0,"",AVERAGE($DF29,$DG29,$DH29)) | EV29: =IF(COUNT($DJ29,$DK29,$DL29)=0,"",AVERAGE($DJ29,$DK29,$DL29)) | EW29: =IF(OR($EU29="",$EV29=""),"",$EV29-$EU29) | EX29: =IF(COUNT($DM29,$DN29,$DO29)=0,"",AVERAGE($DM29,$DN29,$DO29)) | EY29: =IF(COUNT($DQ29,$DR29,$DS29)=0,"",AVERAGE($DQ29,$DR29,$DS29)) | EZ29: =IF(OR($EX29="",$EY29=""),"",$EY29-$EX29) | FA29: =IF(COUNT($EA29,$EB29,$EC29)=0,"",AVERAGE($EA29,$EB29,$EC29)) | FB29: =IF(COUNT($EE29,$EF29,$EG29)=0,"",AVERAGE($EE29,$EF29,$EG29)) | FC29: =IF(OR($FA29="",$FB29=""),"",$FB29-$FA29) | FD29: =IF(COUNT($EH29,$EI29,$EJ29)=0,"",AVERAGE($EH29,$EI29,$EJ29)) | FE29: =IF(COUNT($EL29,$EM29,$EN29)=0,"",AVERAGE($EL29,$EM29,$EN29)) | FF29: =IF(OR($FD29="",$FE29=""),"",$FE29-$FD29) | FG29: =IF(COUNT($DF29,$DG29,$DH29,$DJ29,$DK29,$DL29,$DM29,$DN29,$DO29,$DQ29,$DR29,$DS29)=12,"Yes","No") -> No | FH29: =IF(COUNT($EA29,$EB29,$EC29,$EE29,$EF29,$EG29,$EH29,$EI29,$EJ29,$EL29,$EM29,$EN29)=12,"Yes","No") -> No | FI29: =IF(AND($M29="Include",OR($FG29="Yes",$FH29="Yes")),"Ready","Not ready") -> Not ready
A30: TRT-0028 | B30: 39 | C30: Candidate treatment group | D30: 1 | E30: DATA - Innovation driven deals.xlsx | F30: aduro biotech acquires bionovion holding | G30: Yes | H30: No | I30: No | J30: 1 | K30: Not started | L30: Eligible - 100% | M30: Review | O30: 42271 | P30: 42307 | Q30: 2015 | R30: Q3 2015 | S30: Completed | T30: Aduro BioTech acquires BioNovion Holding | U30: Mergers & Acquisitions | V30: Acquisition | W30: 100% Acquisition | X30: The Netherlands | Y30: 100% Acquisition | AA30: Van Campen & Partners NV , Van Campen & Partners NV , Van Campen & Partners NV | AB30: Chinook Therapeutics Inc | AC30: chinook therapeutics | AD30: BioNovion Holding B.V. | AE30: bionovion b v | AF30: 32 | AG30: 32 | AH30: Aduro BioTech, Inc., a US-based cancer immunotherapy company, has acquired all of the issued and outstanding shares of BioNovion Holding B.V., a Netherlands-based monoclonal antibody discovery and development company. _x000D_ Announcement (September 24, 2015): _x000D_Aduro has entered into a definitive agreement to acquire BioNovion. _x000D_ Under the terms of the agreement, Aduro will acquire BioNovion for EUR14.5 million in cash and EUR14.5 million in stock. _x000D_Following the transaction, Aduro plans to maintain BioNovion's current 24-person operations as a subsidiary of Aduro. _x000D_ Van Campen Liem is acting as legal advisor to Aduro. _x000D_The transaction is expected to complete in October 2015. | AI30: The transaction will strengthen and expand Aduro's immunotherapy capabilities to now encompass monoclonal antibodies, including preclinical assets that inhibit clinically validated immune checkpoint pathways. | AL30: Unknown | AM30: Yes | AN30: KDNY US | AS30: Chinook Therapeutics Inc | AT30: BioNovion Holding B.V. | AU30: Not reviewed | AV30: Not assessed | AW30: Lens.org acquirer-side patent export imported; target patent export not supplied. | AX30: Unknown | AY30: Unknown | AZ30: Unknown | BA30: Unknown | BB30: Unknown | BE30: EUR | BF30: Partial | BG30: Partial event window — 4/7 years covered | BH30: Includes Chinook Therapeutics and former name Aduro BioTech; obvious unrelated Chinook entities excluded. | BI30: 2012 | BJ30: 2013 | BK30: 2014 | BL30: 2015 | BM30: 2016 | BN30: 2017 | BO30: 2018 | BQ30: 0.6236 | BR30: 10.0952 | BS30: 65.7915 | BT30: 45.8136 | BU30: 15.2911 | BV30: 12.7858 | BX30: -10.9476 | BY30: -14.4148 | BZ30: -12.2281 | CA30: -64.9613 | CB30: -94.4247 | CC30: -82.5163 | CF30: -12.8284 | CG30: -35.3474 | CH30: -82.3942 | CI30: -81.4833 | CJ30: -80.812 | CL30: 7.1651 | CM30: 104.514 | CN30: 443.4244 | CO30: 415.8633 | CP30: 370.2612 | CQ30: 312.176 | CS30: 9.4198 | CT30: 0 | CU30: 0 | CV30: 0 | CW30: 0 | CX30: 0 | CZ30: 8.0488 | DA30: 17.7286 | DB30: 52.8728 | DC30: 79.2936 | DD30: 79.2826 | DE30: 64.2686 | DH30: -24.9578 | DI30: -12.8916 | DJ30: -19.8054 | DK30: -20.7896 | DL30: -23.7611 | DN30: -1755.5556 | DO30: -142.7889 | DP30: -18.5862 | DQ30: -141.7948 | DR30: -617.5126 | DS30: -671.8367 | DU30: 131.4676 | DV30: 0 | DW30: 0 | DX30: 0 | DY30: 0 | DZ30: 0 | ED30: 2 | EE30: 1 | EF30: 2 | EG30: 1 | EK30: 3 | EL30: 0 | EM30: 0 | EN30: 0 | EQ30: =IF(OR($EO30="",$EP30="",$EO30=0),"",$EP30/$EO30) | ES30: No | ET30: No | EU30: =IF(COUNT($DF30,$DG30,$DH30)=0,"",AVERAGE($DF30,$DG30,$DH30)) -> -24.9578 | EV30: =IF(COUNT($DJ30,$DK30,$DL30)=0,"",AVERAGE($DJ30,$DK30,$DL30)) -> -21.452033 | EW30: =IF(OR($EU30="",$EV30=""),"",$EV30-$EU30) -> 3.5057667 | EX30: =IF(COUNT($DM30,$DN30,$DO30)=0,"",AVERAGE($DM30,$DN30,$DO30)) -> -949.17225 | EY30: =IF(COUNT($DQ30,$DR30,$DS30)=0,"",AVERAGE($DQ30,$DR30,$DS30)) -> -477.04803 | EZ30: =IF(OR($EX30="",$EY30=""),"",$EY30-$EX30) -> 472.12422 | FA30: =IF(COUNT($EA30,$EB30,$EC30)=0,"",AVERAGE($EA30,$EB30,$EC30)) | FB30: =IF(COUNT($EE30,$EF30,$EG30)=0,"",AVERAGE($EE30,$EF30,$EG30)) -> 1.3333333 | FC30: =IF(OR($FA30="",$FB30=""),"",$FB30-$FA30) | FD30: =IF(COUNT($EH30,$EI30,$EJ30)=0,"",AVERAGE($EH30,$EI30,$EJ30)) | FE30: =IF(COUNT($EL30,$EM30,$EN30)=0,"",AVERAGE($EL30,$EM30,$EN30)) -> 0 | FF30: =IF(OR($FD30="",$FE30=""),"",$FE30-$FD30) | FG30: =IF(COUNT($DF30,$DG30,$DH30,$DJ30,$DK30,$DL30,$DM30,$DN30,$DO30,$DQ30,$DR30,$DS30)=12,"Yes","No") -> No | FH30: =IF(COUNT($EA30,$EB30,$EC30,$EE30,$EF30,$EG30,$EH30,$EI30,$EJ30,$EL30,$EM30,$EN30)=12,"Yes","No") -> No | FI30: =IF(AND($M30="Include",OR($FG30="Yes",$FH30="Yes")),"Ready","Not ready") -> Not ready
A31: TRT-0029 | B31: 40 | C31: Candidate treatment group | D31: 1 | E31: DATA - Innovation driven deals.xlsx | F31: ares allergy stallergenes and greer labs merge | G31: Yes | H31: No | I31: No | J31: 1 | K31: Not started | L31: Review - merger | M31: Review | O31: 42255 | P31: 42255 | Q31: 2015 | R31: Q3 2015 | S31: Completed | T31: Ares Allergy, Stallergenes and Greer Labs Merge | U31: Mergers & Acquisitions | V31: Merger | X31: France , United Kingdom , United States | AB31: Stallergenes Greer Ltd | AC31: stallergenes greer | AD31: Greer Laboratories Inc; Stallergenes SA; Stallergenes Greer Ltd | AE31: greer laboratories stallergenes stallergenes greer | AG31: n/a | AH31: Ares Allergy Holdings plc, a healthcare company, Stallergenes SA, a biopharmaceutical company, and Greer Laboratories Inc., a developer of allergy immunotherapy, have merged. Under the transaction, Ares Allergy, Stallergenes and Greer Labs will join their forces to strengthen its allergy immunotherapy; and combines sales of EUR312.5 million (USD344 million) in 2014 and 1,434 employees. The merger was approved by the shareholders of Stallergenes and Ares Allergy. Following the transaction, Ares Allergy changed its name to Stallergenes Greer plc. The exchange ratio that was approved by the Stallergenes shareholders provides for the issuance of one new Ares Allergy share for each existing Stallergenes share (excluding treasury shares) held on September 8, 2015. Trading in Stallergenes shares on Euronext Paris was suspended after the stock exchange closed on September 7, 2015. Ares Allergy shares will be admitted to trading on the Euronext Paris regulated market on September 8, 2015, and settlement and delivery of the shares will take place on September 10, 2015. This transaction enables Ares Allergy to develop and market allergy immunotherapy treatments. | AI31: This transaction enables Ares Allergy to develop and market allergy immunotherapy treatments. | AL31: Unknown | AM31: Unknown | AS31: Stallergenes Greer Ltd | AT31: Greer Laboratories Inc; Stallergenes SA; Stallergenes Greer Ltd | AU31: Not reviewed | AV31: Not assessed | AW31: Unknown | AX31: Unknown | AY31: Unknown | AZ31: Unknown | BA31: Unknown | BB31: Unknown | BF31: Not collected | BG31: Not collected | BH31: Not defined | BI31: =IF($Q31="","",$Q31-3) -> 2012 | BJ31: =IF($Q31="","",$Q31-2) -> 2013 | BK31: =IF($Q31="","",$Q31-1) -> 2014 | BL31: =IF($Q31="","",$Q31+0) -> 2015 | BM31: =IF($Q31="","",$Q31+1) -> 2016 | BN31: =IF($Q31="","",$Q31+2) -> 2017 | BO31: =IF($Q31="","",$Q31+3) -> 2018 | EQ31: =IF(OR($EO31="",$EP31="",$EO31=0),"",$EP31/$EO31) | ES31: Unknown | ET31: Unknown | EU31: =IF(COUNT($DF31,$DG31,$DH31)=0,"",AVERAGE($DF31,$DG31,$DH31)) | EV31: =IF(COUNT($DJ31,$DK31,$DL31)=0,"",AVERAGE($DJ31,$DK31,$DL31)) | EW31: =IF(OR($EU31="",$EV31=""),"",$EV31-$EU31) | EX31: =IF(COUNT($DM31,$DN31,$DO31)=0,"",AVERAGE($DM31,$DN31,$DO31)) | EY31: =IF(COUNT($DQ31,$DR31,$DS31)=0,"",AVERAGE($DQ31,$DR31,$DS31)) | EZ31: =IF(OR($EX31="",$EY31=""),"",$EY31-$EX31) | FA31: =IF(COUNT($EA31,$EB31,$EC31)=0,"",AVERAGE($EA31,$EB31,$EC31)) | FB31: =IF(COUNT($EE31,$EF31,$EG31)=0,"",AVERAGE($EE31,$EF31,$EG31)) | FC31: =IF(OR($FA31="",$FB31=""),"",$FB31-$FA31) | FD31: =IF(COUNT($EH31,$EI31,$EJ31)=0,"",AVERAGE($EH31,$EI31,$EJ31)) | FE31: =IF(COUNT($EL31,$EM31,$EN31)=0,"",AVERAGE($EL31,$EM31,$EN31)) | FF31: =IF(OR($FD31="",$FE31=""),"",$FE31-$FD31) | FG31: =IF(COUNT($DF31,$DG31,$DH31,$DJ31,$DK31,$DL31,$DM31,$DN31,$DO31,$DQ31,$DR31,$DS31)=12,"Yes","No") -> No | FH31: =IF(COUNT($EA31,$EB31,$EC31,$EE31,$EF31,$EG31,$EH31,$EI31,$EJ31,$EL31,$EM31,$EN31)=12,"Yes","No") -> No | FI31: =IF(AND($M31="Include",OR($FG31="Yes",$FH31="Yes")),"Ready","Not ready") -> Not ready
A32: TRT-0030 | B32: 41 | C32: Candidate treatment group | D32: 1 | E32: DATA - Innovation driven deals.xlsx | F32: stada arzneimittel acquires sciotec diagnostic technologies for | G32: Yes | H32: No | I32: No | J32: 1 | K32: Not started | L32: Eligible - 100% | M32: Review | O32: 42242 | P32: 42242 | Q32: 2015 | R32: Q3 2015 | S32: Completed | T32: STADA Arzneimittel Acquires SCIOTEC Diagnostic Technologies for USD19.8 Million | U32: Mergers & Acquisitions | V32: Acquisition | W32: 100% Acquisition | X32: Austria | Y32: 100% Acquisition | AB32: Stada Arzneimittel AG | AC32: stada arzneimittel | AD32: SCIOTEC Diagnostic Technologies GmbH | AE32: sciotec diagnostic technologies | AF32: 20 | AG32: 20 | AH32: STADA Arzneimittel AG, a pharmaceutical company, has acquired SCIOTEC Diagnostic Technologies GmbH, a company engaged in developing, manufactureing, and marketing diagnostic kits, health systems, nutritional supplements and cosmetics, from a number of private owners, a sales company as well as an investment company, for purchase consideration of EUR17.2 million (USD19.8 million) in cash. The transaction includes acquisition of SCIOTEC Diagnostic Technologies' relevant sales structures, that is primarily focused on the development and marketing of prescription-free OTC products against enzymatic food intolerances (histamine, fructose and lactose intolerance) and take over of its 17 employees. Sales expectations for the products acquired within the scope of the transaction for 2015 are approximately EUR5.8 million (USD6.68 million), whereby the current sales are, for the most part, generated in equal parts in Germany and Austria as well as about 20% internationally through distributors. This transaction enables STADA Arzneimittel to expand its branded product activities into the area of food intolerances in order to position appropriately in the lucrative market with strong global growth. | AI32: This transaction enables STADA Arzneimittel to expand its branded product activities into the area of food intolerances in order to position appropriately in the lucrative market with strong global growth. | AL32: Unknown | AM32: Unknown | AS32: Stada Arzneimittel AG | AT32: SCIOTEC Diagnostic Technologies GmbH | AU32: Not reviewed | AV32: Not assessed | AW32: Unknown | AX32: Unknown | AY32: Unknown | AZ32: Unknown | BA32: Unknown | BB32: Unknown | BF32: Not collected | BG32: Not collected | BH32: Not defined | BI32: =IF($Q32="","",$Q32-3) -> 2012 | BJ32: =IF($Q32="","",$Q32-2) -> 2013 | BK32: =IF($Q32="","",$Q32-1) -> 2014 | BL32: =IF($Q32="","",$Q32+0) -> 2015 | BM32: =IF($Q32="","",$Q32+1) -> 2016 | BN32: =IF($Q32="","",$Q32+2) -> 2017 | BO32: =IF($Q32="","",$Q32+3) -> 2018 | EQ32: =IF(OR($EO32="",$EP32="",$EO32=0),"",$EP32/$EO32) | ES32: Unknown | ET32: Unknown | EU32: =IF(COUNT($DF32,$DG32,$DH32)=0,"",AVERAGE($DF32,$DG32,$DH32)) | EV32: =IF(COUNT($DJ32,$DK32,$DL32)=0,"",AVERAGE($DJ32,$DK32,$DL32)) | EW32: =IF(OR($EU32="",$EV32=""),"",$EV32-$EU32) | EX32: =IF(COUNT($DM32,$DN32,$DO32)=0,"",AVERAGE($DM32,$DN32,$DO32)) | EY32: =IF(COUNT($DQ32,$DR32,$DS32)=0,"",AVERAGE($DQ32,$DR32,$DS32)) | EZ32: =IF(OR($EX32="",$EY32=""),"",$EY32-$EX32) | FA32: =IF(COUNT($EA32,$EB32,$EC32)=0,"",AVERAGE($EA32,$EB32,$EC32)) | FB32: =IF(COUNT($EE32,$EF32,$EG32)=0,"",AVERAGE($EE32,$EF32,$EG32)) | FC32: =IF(OR($FA32="",$FB32=""),"",$FB32-$FA32) | FD32: =IF(COUNT($EH32,$EI32,$EJ32)=0,"",AVERAGE($EH32,$EI32,$EJ32)) | FE32: =IF(COUNT($EL32,$EM32,$EN32)=0,"",AVERAGE($EL32,$EM32,$EN32)) | FF32: =IF(OR($FD32="",$FE32=""),"",$FE32-$FD32) | FG32: =IF(COUNT($DF32,$DG32,$DH32,$DJ32,$DK32,$DL32,$DM32,$DN32,$DO32,$DQ32,$DR32,$DS32)=12,"Yes","No") -> No | FH32: =IF(COUNT($EA32,$EB32,$EC32,$EE32,$EF32,$EG32,$EH32,$EI32,$EJ32,$EL32,$EM32,$EN32)=12,"Yes","No") -> No | FI32: =IF(AND($M32="Include",OR($FG32="Yes",$FH32="Yes")),"Ready","Not ready") -> Not ready
A33: TRT-0031 | B33: 42 | C33: Candidate treatment group | D33: 1 | E33: DATA - Innovation driven deals.xlsx | F33: tigenix acquires coretherapix | G33: Yes | H33: No | I33: No | J33: 1 | K33: Not started | L33: Review - majority | M33: Review | O33: 42215 | P33: 42216 | Q33: 2015 | R33: Q3 2015 | S33: Completed | T33: TiGenix acquires Coretherapix | U33: Mergers & Acquisitions | V33: Acquisition | W33: Majority Acquisition | X33: Spain | Y33: Majority Acquisition | AB33: TiGenix NV | AC33: tigenix | AD33: Coretherapix SLU | AE33: coretherapix slu | AF33: 7 | AG33: 7 | AH33: TiGenix N.V., a Belgium-based cell therapy company, has acquired Coretherapix S.L., a cardiology-focused cell therapy company, from Genetrix S.L., a biotechnology company. Coretherapix and Genetrix are based in Spain. _x000D_Announcement (July 30, 2015): _x000D_TiGenix has agreed to acquire Coretherapix from Genetrix. _x000D_The consideration includes an upfront payment of approximately EUR1.2 million in cash and approximately EUR5.5 million in new TiGenix shares. Additionally, Genetrix may receive up to EUR15 million in new TiGenix shares depending on the results of the ongoing clinical trial of Coretherapix. _x000D_Based on and subject to future sales milestones, Genetrix may receive in addition up to EUR245 million plus certain percentages of the direct net sales of the first product, or certain percentages of any third party royalties and sales milestones for the first product. Sales milestones start when annual net sales reach EUR150 million and the last one will be payable once annual net sales are above EUR750 million. Also, Genetrix will receive a EUR25 million milestone payment per additional product reaching the market. The new shares to be issued on closing of the transaction will be subject to lock-up undertakings for up to 12 months, part of which will be gradually released from the lock-up over the 12-months period. _x000D_ The transaction is expected to be closed on July 31, 2015. | AI33: The acquisition will allow TiGenix to expand its pipeline into cardiology indications. | AL33: Unknown | AM33: Unknown | AS33: TiGenix NV | AT33: Coretherapix SLU | AU33: Not reviewed | AV33: Not assessed | AW33: Unknown | AX33: Unknown | AY33: Unknown | AZ33: Unknown | BA33: Unknown | BB33: Unknown | BF33: Not collected | BG33: Not collected | BH33: Not defined | BI33: =IF($Q33="","",$Q33-3) -> 2012 | BJ33: =IF($Q33="","",$Q33-2) -> 2013 | BK33: =IF($Q33="","",$Q33-1) -> 2014 | BL33: =IF($Q33="","",$Q33+0) -> 2015 | BM33: =IF($Q33="","",$Q33+1) -> 2016 | BN33: =IF($Q33="","",$Q33+2) -> 2017 | BO33: =IF($Q33="","",$Q33+3) -> 2018 | EQ33: =IF(OR($EO33="",$EP33="",$EO33=0),"",$EP33/$EO33) | ES33: Unknown | ET33: Unknown | EU33: =IF(COUNT($DF33,$DG33,$DH33)=0,"",AVERAGE($DF33,$DG33,$DH33)) | EV33: =IF(COUNT($DJ33,$DK33,$DL33)=0,"",AVERAGE($DJ33,$DK33,$DL33)) | EW33: =IF(OR($EU33="",$EV33=""),"",$EV33-$EU33) | EX33: =IF(COUNT($DM33,$DN33,$DO33)=0,"",AVERAGE($DM33,$DN33,$DO33)) | EY33: =IF(COUNT($DQ33,$DR33,$DS33)=0,"",AVERAGE($DQ33,$DR33,$DS33)) | EZ33: =IF(OR($EX33="",$EY33=""),"",$EY33-$EX33) | FA33: =IF(COUNT($EA33,$EB33,$EC33)=0,"",AVERAGE($EA33,$EB33,$EC33)) | FB33: =IF(COUNT($EE33,$EF33,$EG33)=0,"",AVERAGE($EE33,$EF33,$EG33)) | FC33: =IF(OR($FA33="",$FB33=""),"",$FB33-$FA33) | FD33: =IF(COUNT($EH33,$EI33,$EJ33)=0,"",AVERAGE($EH33,$EI33,$EJ33)) | FE33: =IF(COUNT($EL33,$EM33,$EN33)=0,"",AVERAGE($EL33,$EM33,$EN33)) | FF33: =IF(OR($FD33="",$FE33=""),"",$FE33-$FD33) | FG33: =IF(COUNT($DF33,$DG33,$DH33,$DJ33,$DK33,$DL33,$DM33,$DN33,$DO33,$DQ33,$DR33,$DS33)=12,"Yes","No") -> No | FH33: =IF(COUNT($EA33,$EB33,$EC33,$EE33,$EF33,$EG33,$EH33,$EI33,$EJ33,$EL33,$EM33,$EN33)=12,"Yes","No") -> No | FI33: =IF(AND($M33="Include",OR($FG33="Yes",$FH33="Yes")),"Ready","Not ready") -> Not ready
A34: TRT-0032 | B34: 43 | C34: Candidate treatment group | D34: 1 | E34: DATA - Innovation driven deals.xlsx | F34: auspex pharma acquires imphar | G34: Yes | H34: No | I34: No | J34: 1 | K34: Not started | L34: Eligible - 100% | M34: Review | O34: 42015 | P34: 42369 | Q34: 2015 | R34: Q1 2015 | S34: Completed | T34: Auspex Pharma Acquires Imphar | U34: Mergers & Acquisitions | V34: Acquisition | W34: 100% Acquisition | X34: Germany | Y34: 100% Acquisition | AB34: Auspex Pharmaceuticals Inc | AC34: auspex pharmaceuticals | AD34: imphar AG | AE34: imphar | AG34: n/a | AH34: Auspex Pharmaceuticals, Inc., a biopharmaceutical company, has acquired Imphar AG, a drug development company. Through the acquisition, Auspex Pharma acquired the remaining rights to SD-1077, and related intellectual property rights. Earlier, In July 2014, Auspex Pharma entered into an agreement with Imphar, to further develop SD-1077, a deuterium containing levodopa. At the time the agreement, Auspex Pharma determined that it held a variable interest in the development partner’s intellectual property assets and the related potential future product candidates these assets may produce. This transaction enables Auspex Pharma to accelerate SD-1077 clinical development for the patients living with Parkinson's disease around the world. Deal History: Announced: On January 11, 2015, Auspex Pharma agreed to acquire Imphar. | AI34: This transaction enables Auspex Pharma to accelerate SD-1077 clinical development for the patients living with Parkinson's disease around the world. | AL34: Unknown | AM34: Unknown | AS34: Auspex Pharmaceuticals Inc | AT34: imphar AG | AU34: Not reviewed | AV34: Not assessed | AW34: Unknown | AX34: Unknown | AY34: Unknown | AZ34: Unknown | BA34: Unknown | BB34: Unknown | BF34: Not collected | BG34: Not collected | BH34: Not defined | BI34: =IF($Q34="","",$Q34-3) -> 2012 | BJ34: =IF($Q34="","",$Q34-2) -> 2013 | BK34: =IF($Q34="","",$Q34-1) -> 2014 | BL34: =IF($Q34="","",$Q34+0) -> 2015 | BM34: =IF($Q34="","",$Q34+1) -> 2016 | BN34: =IF($Q34="","",$Q34+2) -> 2017 | BO34: =IF($Q34="","",$Q34+3) -> 2018 | EQ34: =IF(OR($EO34="",$EP34="",$EO34=0),"",$EP34/$EO34) | ES34: Unknown | ET34: Unknown | EU34: =IF(COUNT($DF34,$DG34,$DH34)=0,"",AVERAGE($DF34,$DG34,$DH34)) | EV34: =IF(COUNT($DJ34,$DK34,$DL34)=0,"",AVERAGE($DJ34,$DK34,$DL34)) | EW34: =IF(OR($EU34="",$EV34=""),"",$EV34-$EU34) | EX34: =IF(COUNT($DM34,$DN34,$DO34)=0,"",AVERAGE($DM34,$DN34,$DO34)) | EY34: =IF(COUNT($DQ34,$DR34,$DS34)=0,"",AVERAGE($DQ34,$DR34,$DS34)) | EZ34: =IF(OR($EX34="",$EY34=""),"",$EY34-$EX34) | FA34: =IF(COUNT($EA34,$EB34,$EC34)=0,"",AVERAGE($EA34,$EB34,$EC34)) | FB34: =IF(COUNT($EE34,$EF34,$EG34)=0,"",AVERAGE($EE34,$EF34,$EG34)) | FC34: =IF(OR($FA34="",$FB34=""),"",$FB34-$FA34) | FD34: =IF(COUNT($EH34,$EI34,$EJ34)=0,"",AVERAGE($EH34,$EI34,$EJ34)) | FE34: =IF(COUNT($EL34,$EM34,$EN34)=0,"",AVERAGE($EL34,$EM34,$EN34)) | FF34: =IF(OR($FD34="",$FE34=""),"",$FE34-$FD34) | FG34: =IF(COUNT($DF34,$DG34,$DH34,$DJ34,$DK34,$DL34,$DM34,$DN34,$DO34,$DQ34,$DR34,$DS34)=12,"Yes","No") -> No | FH34: =IF(COUNT($EA34,$EB34,$EC34,$EE34,$EF34,$EG34,$EH34,$EI34,$EJ34,$EL34,$EM34,$EN34)=12,"Yes","No") -> No | FI34: =IF(AND($M34="Include",OR($FG34="Yes",$FH34="Yes")),"Ready","Not ready") -> Not ready
A35: TRT-0033 | B35: 44 | C35: Candidate treatment group | D35: 1 | E35: DATA - Innovation driven deals.xlsx | F35: cadila pharma sweden acquires biochromix newco | G35: Yes | H35: No | I35: No | J35: 1 | K35: Not started | L35: Eligible - 100% | M35: Review | O35: 41914 | P35: 41914 | Q35: 2014 | R35: Q4 2014 | S35: Completed | T35: Cadila Pharma Sweden Acquires BioChromix NewCo | U35: Mergers & Acquisitions | V35: Acquisition | W35: 100% Acquisition | X35: Sweden | Y35: 100% Acquisition | AB35: Cadila Pharmaceuticals Sweden AB | AC35: cadila pharmaceuticals sweden ab | AD35: BioChromix NewCo AB | AE35: biochromix newco ab | AG35: n/a | AH35: Cadila Pharmaceuticals Ltd, an India-based leading research-driven pharmaceutical companies, has announced the acquisition of Swedish BioChromix NewCo AB through its subsidiary Cadila Pharmaceuticals Sverige AB. The subsidiary has recently been established to investigate and facilitate business interactions between Cadila Pharmaceuticals Ltd and potential collaborators, academic groups, etc. BioChromix NewCo AB develops new and innovative treatments against diseases involving misfolded proteins, which are believed to be central in the development of certain neurodegenerative diseases. BioChromix NewCo's unique substance class is believed to selectively bind to, neutralize and eliminate soluble, toxic protein oligomers, protofibrils and soluble aggregates that are believed to contribute to the neurodegenerative process in several diseases that affect the nervous system. Cadila Pharmaceuticals will continue the preclinical and clinical development of the drug candidates developed by BioChromix NewCo. According to the agreement, development is to be based on milestones and will be carried out at Cadila Pharmaceuticals' state-of-the-art research facility in Ahmedabad, India. Cadila Pharmaceuticals Ltd. has all the resources necessary to take the project to the clinical phase and on to the market. "The acquisition makes it possible to take the project, which was previously carried out by BioChromix NewCo, forward with significant resources. Cadila's expertise in drug development, together with BioChromix NewCo's scientific know-how in its field, provides an excellent platform for the further development of these unique drug candidates Provided that the development is successful, opportunities are created to enter into valuable commercial agreements in important geographic markets such as the USA and Europe," says Dr. Peter Åsberg, outgoing CEO of BioChromix NewCo under the proposed name change to CPL BCX PHARMA AB. "There is a lot of promising research going on around the world, especially in Europe, which complements our research portfolio in pharmaceuticals. The acquisition of BioChromix NewCo, through our Swedish subsidiary, is a step towards establishing new domestic solutions at our own high-class facility for the treatment of neurodegenerative diseases. This is an area of ??therapy that is of great importance to us," comments Dr. Rajiv I. Modi, Chairman and CEO of Cadila Pharmaceuticals. "Going from the discovery electronic polymers interact with misfolded proteins in the university laboratory to medical innovation is a long step. The intellectual capital found in BioChromix NewCo was created through the transfer of university projects to the small development companies BioChromix AB and BioChromix Pharma AB. Cadila Pharmaceuticals' acquisition of BioChromix NewCo means that this knowledge is now transferred to an organization that can take the project to the clinic. I hope that it will ultimately lead to new treatments that can slow the progression of the disease and create a future benefit for patients suffering from these neurodegenerative diseases," says Olle Inganäs , one of the founders of BioChromix NewCo and professor at Linköping University. Formerly BioChromix AB is part of UIC Alumni and has received advanced business development support through UIC's program UIC Business Accelerator . | AI35: The acquisition of BioChromix NewCo, through Cadila's Swedish subsidiary, is a step towards establishing new domestic solutions at Cadila's own high-class facility for the treatment of neurodegenerative diseases. | AL35: Unknown | AM35: Unknown | AS35: Cadila Pharmaceuticals Sweden AB | AT35: BioChromix NewCo AB | AU35: Not reviewed | AV35: Not assessed | AW35: Unknown | AX35: Unknown | AY35: Unknown | AZ35: Unknown | BA35: Unknown | BB35: Unknown | BF35: Not collected | BG35: Not collected | BH35: Not defined | BI35: =IF($Q35="","",$Q35-3) -> 2011 | BJ35: =IF($Q35="","",$Q35-2) -> 2012 | BK35: =IF($Q35="","",$Q35-1) -> 2013 | BL35: =IF($Q35="","",$Q35+0) -> 2014 | BM35: =IF($Q35="","",$Q35+1) -> 2015 | BN35: =IF($Q35="","",$Q35+2) -> 2016 | BO35: =IF($Q35="","",$Q35+3) -> 2017 | EQ35: =IF(OR($EO35="",$EP35="",$EO35=0),"",$EP35/$EO35) | ES35: Unknown | ET35: Unknown | EU35: =IF(COUNT($DF35,$DG35,$DH35)=0,"",AVERAGE($DF35,$DG35,$DH35)) | EV35: =IF(COUNT($DJ35,$DK35,$DL35)=0,"",AVERAGE($DJ35,$DK35,$DL35)) | EW35: =IF(OR($EU35="",$EV35=""),"",$EV35-$EU35) | EX35: =IF(COUNT($DM35,$DN35,$DO35)=0,"",AVERAGE($DM35,$DN35,$DO35)) | EY35: =IF(COUNT($DQ35,$DR35,$DS35)=0,"",AVERAGE($DQ35,$DR35,$DS35)) | EZ35: =IF(OR($EX35="",$EY35=""),"",$EY35-$EX35) | FA35: =IF(COUNT($EA35,$EB35,$EC35)=0,"",AVERAGE($EA35,$EB35,$EC35)) | FB35: =IF(COUNT($EE35,$EF35,$EG35)=0,"",AVERAGE($EE35,$EF35,$EG35)) | FC35: =IF(OR($FA35="",$FB35=""),"",$FB35-$FA35) | FD35: =IF(COUNT($EH35,$EI35,$EJ35)=0,"",AVERAGE($EH35,$EI35,$EJ35)) | FE35: =IF(COUNT($EL35,$EM35,$EN35)=0,"",AVERAGE($EL35,$EM35,$EN35)) | FF35: =IF(OR($FD35="",$FE35=""),"",$FE35-$FD35) | FG35: =IF(COUNT($DF35,$DG35,$DH35,$DJ35,$DK35,$DL35,$DM35,$DN35,$DO35,$DQ35,$DR35,$DS35)=12,"Yes","No") -> No | FH35: =IF(COUNT($EA35,$EB35,$EC35,$EE35,$EF35,$EG35,$EH35,$EI35,$EJ35,$EL35,$EM35,$EN35)=12,"Yes","No") -> No | FI35: =IF(AND($M35="Include",OR($FG35="Yes",$FH35="Yes")),"Ready","Not ready") -> Not ready
A36: TRT-0034 | B36: 45 | C36: Candidate treatment group | D36: 1 | E36: DATA - Innovation driven deals.xlsx | F36: nicox acquires 100 stake in doliage | G36: Yes | H36: No | I36: No | J36: 1 | K36: Not started | L36: Eligible - 100% | M36: Review | O36: 41898 | P36: 41908 | Q36: 2014 | R36: Q3 2014 | S36: Completed | T36: Nicox acquires 100% stake in Doliage | U36: Mergers & Acquisitions | V36: Acquisition | W36: 100% Acquisition | X36: France | Y36: 100% Acquisition | Z36: Michel Dyens & Co | AB36: Nicox SA | AC36: nicox | AD36: Doliage | AE36: doliage | AF36: 6 | AG36: 6 | AH36: Nicox SA, a biopharmaceutical company, has agreed to acquire 100% stake in Doliage, a pharmaceutical company, in exchange for newly-issued Nicox shares for a total value of EUR5 million. Both the companies are based in France. _x000D_ Announcement (September 16, 2014): _x000D_ Nicox has agreed to acquire 100% stake in Doliage for EUR5 million. _x000D_ The number of shares to be issued would be based on the volume-weighted average closing price of Nicox shares during a 20 trading day period preceding the execution of the agreement. _x000D_Doliage generated sales of EUR2.6 million with an EBITDA of EUR0.36 million for the fiscal year ending on September 30, 2013. _x000D_ Michel Dyens & Co. is acting as financial advisor to Nicox. The transaction is expected to close in October 2014. | AI36: The transaction will add ophthalmic product portfolio and will complement Nicox's existing commercial infrastructure in France with further upside potential in some export markets such as Southern Europe and North Africa. | AL36: Unknown | AM36: Yes | AN36: ALCOX FP | AS36: Nicox SA | AT36: Doliage | AU36: Not reviewed | AV36: Not assessed | AW36: Lens.org acquirer-side patent export imported; target patent export not supplied. | AX36: Unknown | AY36: Unknown | AZ36: Unknown | BA36: Unknown | BB36: Unknown | BE36: EUR | BF36: Partial | BG36: Complete event window — provisional | BH36: Includes Nicox entities and Aciex Therapeutics as a pre-existing subsidiary/affiliate alias. | BI36: 2011 | BJ36: 2012 | BK36: 2013 | BL36: 2014 | BM36: 2015 | BN36: 2016 | BO36: 2017 | BP36: 0 | BQ36: 7.614 | BR36: 0.436 | BS36: 5.982 | BT36: 0.067 | BU36: 0.016 | BV36: 15.08 | BW36: -13.184 | BX36: -6.619 | BY36: -14.224 | BZ36: -20.921 | CA36: -19.639 | CB36: -6.929 | CC36: -17.534 | CD36: -16.635 | CE36: -10.247 | CF36: -18.145 | CG36: -23.158 | CH36: -27.939 | CI36: -19.035 | CJ36: -3.618 | CK36: 95.829 | CL36: 84.147 | CM36: 72.178 | CN36: 150.041 | CO36: 163.348 | CP36: 148.748 | CQ36: 152.252 | CR36: 0.082 | CS36: 0.157 | CT36: 0.152 | CU36: 16.538 | CV36: 3.941 | CW36: 0.985 | CX36: 0.05 | CY36: 8.998 | CZ36: 6.471 | DA36: 3.685 | DB36: 4.432 | DC36: 6.159 | DD36: 12.168 | DE36: 9.75 | DF36: -15.9369 | DG36: -11.3871 | DH36: -23.2145 | DI36: -20.8425 | DJ36: -17.8302 | DK36: -12.1982 | DL36: -2.404 | DN36: -114.8805 | DO36: -2537.844 | DP36: -360.5316 | DQ36: -30931.343 | DR36: -48650 | DS36: -122.7984 | DT36: 0.0856 | DU36: 0.1866 | DV36: 0.2106 | DW36: 11.0223 | DX36: 2.4126 | DY36: 0.6622 | DZ36: 0.0328 | EA36: 2 | EB36: 3 | EC36: 4 | ED36: 3 | EE36: 2 | EF36: 1 | EG36: 0 | EH36: 8 | EI36: 7 | EJ36: 1 | EK36: 0 | EL36: 0 | EM36: 0 | EN36: 0 | EO36: 9 | EQ36: =IF(OR($EO36="",$EP36="",$EO36=0),"",$EP36/$EO36) | ES36: No | ET36: No | EU36: =IF(COUNT($DF36,$DG36,$DH36)=0,"",AVERAGE($DF36,$DG36,$DH36)) -> -16.846167 | EV36: =IF(COUNT($DJ36,$DK36,$DL36)=0,"",AVERAGE($DJ36,$DK36,$DL36)) -> -10.8108 | EW36: =IF(OR($EU36="",$EV36=""),"",$EV36-$EU36) -> 6.0353667 | EX36: =IF(COUNT($DM36,$DN36,$DO36)=0,"",AVERAGE($DM36,$DN36,$DO36)) -> -1326.3623 | EY36: =IF(COUNT($DQ36,$DR36,$DS36)=0,"",AVERAGE($DQ36,$DR36,$DS36)) -> -26568.047 | EZ36: =IF(OR($EX36="",$EY36=""),"",$EY36-$EX36) -> -25241.685 | FA36: =IF(COUNT($EA36,$EB36,$EC36)=0,"",AVERAGE($EA36,$EB36,$EC36)) -> 3 | FB36: =IF(COUNT($EE36,$EF36,$EG36)=0,"",AVERAGE($EE36,$EF36,$EG36)) -> 1 | FC36: =IF(OR($FA36="",$FB36=""),"",$FB36-$FA36) -> -2 | FD36: =IF(COUNT($EH36,$EI36,$EJ36)=0,"",AVERAGE($EH36,$EI36,$EJ36)) -> 5.3333333 | FE36: =IF(COUNT($EL36,$EM36,$EN36)=0,"",AVERAGE($EL36,$EM36,$EN36)) -> 0 | FF36: =IF(OR($FD36="",$FE36=""),"",$FE36-$FD36) -> -5.3333333 | FG36: =IF(COUNT($DF36,$DG36,$DH36,$DJ36,$DK36,$DL36,$DM36,$DN36,$DO36,$DQ36,$DR36,$DS36)=12,"Yes","No") -> No | FH36: =IF(COUNT($EA36,$EB36,$EC36,$EE36,$EF36,$EG36,$EH36,$EI36,$EJ36,$EL36,$EM36,$EN36)=12,"Yes","No") -> Yes | FI36: =IF(AND($M36="Include",OR($FG36="Yes",$FH36="Yes")),"Ready","Not ready") -> Not ready
A37: TRT-0035 | B37: 46 | C37: Candidate treatment group | D37: 1 | E37: DATA - Innovation driven deals.xlsx | F37: productlife group acquires kohne pharma | G37: Yes | H37: No | I37: No | J37: 1 | K37: Not started | L37: Review - majority | M37: Review | O37: 41687 | P37: 41687 | Q37: 2014 | R37: Q1 2014 | S37: Completed | T37: ProductLife Group acquires Kohne Pharma | U37: Mergers & Acquisitions | V37: Acquisition | W37: Majority Acquisition | X37: France , Germany | Y37: Majority Acquisition | AB37: ProductLife Group | AC37: productlife | AD37: Kohne Pharma GmbH | AE37: kohne pharma | AG37: n/a | AH37: ProductLife Group (PLG), a France-based provider of life sciences consulting and outsourcing services, has acquired Kohne Pharma GmbH, a Germany-based regulatory and pharmacovigilance services provider. _x000D_ Pursuant to the transaction, Kohne Pharma will retain its brand and will be known as Kohne Pharma, a PLG company. Kohne's safety and regulatory functions will be managed, operated and aligned with the pan-European PLG functions. | AI37: The acquisition will allow PLG to grow its regulatory services and expand its existing pharmacovigilance and safety services business across Germany._x000D_ _x000D_ The acquisition will also allow PLG to increase its local presence in Germany and support its continued commitment to smart outsourcing. | AL37: Unknown | AM37: Unknown | AS37: ProductLife Group | AT37: Kohne Pharma GmbH | AU37: Not reviewed | AV37: Not assessed | AW37: Unknown | AX37: Unknown | AY37: Unknown | AZ37: Unknown | BA37: Unknown | BB37: Unknown | BF37: Not collected | BG37: Not collected | BH37: Not defined | BI37: =IF($Q37="","",$Q37-3) -> 2011 | BJ37: =IF($Q37="","",$Q37-2) -> 2012 | BK37: =IF($Q37="","",$Q37-1) -> 2013 | BL37: =IF($Q37="","",$Q37+0) -> 2014 | BM37: =IF($Q37="","",$Q37+1) -> 2015 | BN37: =IF($Q37="","",$Q37+2) -> 2016 | BO37: =IF($Q37="","",$Q37+3) -> 2017 | EQ37: =IF(OR($EO37="",$EP37="",$EO37=0),"",$EP37/$EO37) | ES37: Unknown | ET37: Unknown | EU37: =IF(COUNT($DF37,$DG37,$DH37)=0,"",AVERAGE($DF37,$DG37,$DH37)) | EV37: =IF(COUNT($DJ37,$DK37,$DL37)=0,"",AVERAGE($DJ37,$DK37,$DL37)) | EW37: =IF(OR($EU37="",$EV37=""),"",$EV37-$EU37) | EX37: =IF(COUNT($DM37,$DN37,$DO37)=0,"",AVERAGE($DM37,$DN37,$DO37)) | EY37: =IF(COUNT($DQ37,$DR37,$DS37)=0,"",AVERAGE($DQ37,$DR37,$DS37)) | EZ37: =IF(OR($EX37="",$EY37=""),"",$EY37-$EX37) | FA37: =IF(COUNT($EA37,$EB37,$EC37)=0,"",AVERAGE($EA37,$EB37,$EC37)) | FB37: =IF(COUNT($EE37,$EF37,$EG37)=0,"",AVERAGE($EE37,$EF37,$EG37)) | FC37: =IF(OR($FA37="",$FB37=""),"",$FB37-$FA37) | FD37: =IF(COUNT($EH37,$EI37,$EJ37)=0,"",AVERAGE($EH37,$EI37,$EJ37)) | FE37: =IF(COUNT($EL37,$EM37,$EN37)=0,"",AVERAGE($EL37,$EM37,$EN37)) | FF37: =IF(OR($FD37="",$FE37=""),"",$FE37-$FD37) | FG37: =IF(COUNT($DF37,$DG37,$DH37,$DJ37,$DK37,$DL37,$DM37,$DN37,$DO37,$DQ37,$DR37,$DS37)=12,"Yes","No") -> No | FH37: =IF(COUNT($EA37,$EB37,$EC37,$EE37,$EF37,$EG37,$EH37,$EI37,$EJ37,$EL37,$EM37,$EN37)=12,"Yes","No") -> No | FI37: =IF(AND($M37="Include",OR($FG37="Yes",$FH37="Yes")),"Ready","Not ready") -> Not ready
A38: TRT-0036 | B38: 47 | C38: Candidate treatment group | D38: 1 | E38: DATA - Innovation driven deals.xlsx | F38: cardiome pharma acquires correvio | G38: Yes | H38: No | I38: No | J38: 1 | K38: Not started | L38: Eligible - 100% | M38: Review | O38: 41596 | P38: 41596 | Q38: 2013 | R38: Q4 2013 | S38: Completed | T38: Cardiome Pharma acquires Correvio | U38: Mergers & Acquisitions | V38: Acquisition | W38: 100% Acquisition | X38: Switzerland | Y38: 100% Acquisition | AB38: Correvio Pharma Corp. | AC38: correvio pharma | AD38: Correvio International Sarl | AE38: correvio international sarl | AF38: 23 | AG38: 23 | AH38: Cardiome Pharma Corp., a Canada-based biopharmaceutical company, has acquired Correvio International Sarl, a Switzerland-based pharmaceutical company. _x000D_ Under the terms of the agreement, Cardiome has acquired 100% of Correvio through the purchase of a combination of assets and shares of its subsidiaries in exchange for 19.9% of Cardiome's outstanding shares and a deferred cash consideration of $12 million. The total transaction is valued at approximately $23 million. _x000D_ The deferred cash consideration will be repaid monthly at an amount equal to 10% of cash receipts from product sales and any applicable interest accrued at 10% compounded annually. The adjusted deferred cash consideration must be repaid in full by December 1, 2019. | AI38: The acquisition will provide Cardiome Pharma with an operational European platform, global distribution, complementary products and the financial flexibility required to launch its product BRINAVESS(TM). | AL38: Unknown | AM38: Unknown | AS38: Correvio Pharma Corp. | AT38: Correvio International Sarl | AU38: Not reviewed | AV38: Not assessed | AW38: Unknown | AX38: Unknown | AY38: Unknown | AZ38: Unknown | BA38: Unknown | BB38: Unknown | BF38: Not collected | BG38: Not collected | BH38: Not defined | BI38: =IF($Q38="","",$Q38-3) -> 2010 | BJ38: =IF($Q38="","",$Q38-2) -> 2011 | BK38: =IF($Q38="","",$Q38-1) -> 2012 | BL38: =IF($Q38="","",$Q38+0) -> 2013 | BM38: =IF($Q38="","",$Q38+1) -> 2014 | BN38: =IF($Q38="","",$Q38+2) -> 2015 | BO38: =IF($Q38="","",$Q38+3) -> 2016 | EQ38: =IF(OR($EO38="",$EP38="",$EO38=0),"",$EP38/$EO38) | ES38: Unknown | ET38: Unknown | EU38: =IF(COUNT($DF38,$DG38,$DH38)=0,"",AVERAGE($DF38,$DG38,$DH38)) | EV38: =IF(COUNT($DJ38,$DK38,$DL38)=0,"",AVERAGE($DJ38,$DK38,$DL38)) | EW38: =IF(OR($EU38="",$EV38=""),"",$EV38-$EU38) | EX38: =IF(COUNT($DM38,$DN38,$DO38)=0,"",AVERAGE($DM38,$DN38,$DO38)) | EY38: =IF(COUNT($DQ38,$DR38,$DS38)=0,"",AVERAGE($DQ38,$DR38,$DS38)) | EZ38: =IF(OR($EX38="",$EY38=""),"",$EY38-$EX38) | FA38: =IF(COUNT($EA38,$EB38,$EC38)=0,"",AVERAGE($EA38,$EB38,$EC38)) | FB38: =IF(COUNT($EE38,$EF38,$EG38)=0,"",AVERAGE($EE38,$EF38,$EG38)) | FC38: =IF(OR($FA38="",$FB38=""),"",$FB38-$FA38) | FD38: =IF(COUNT($EH38,$EI38,$EJ38)=0,"",AVERAGE($EH38,$EI38,$EJ38)) | FE38: =IF(COUNT($EL38,$EM38,$EN38)=0,"",AVERAGE($EL38,$EM38,$EN38)) | FF38: =IF(OR($FD38="",$FE38=""),"",$FE38-$FD38) | FG38: =IF(COUNT($DF38,$DG38,$DH38,$DJ38,$DK38,$DL38,$DM38,$DN38,$DO38,$DQ38,$DR38,$DS38)=12,"Yes","No") -> No | FH38: =IF(COUNT($EA38,$EB38,$EC38,$EE38,$EF38,$EG38,$EH38,$EI38,$EJ38,$EL38,$EM38,$EN38)=12,"Yes","No") -> No | FI38: =IF(AND($M38="Include",OR($FG38="Yes",$FH38="Yes")),"Ready","Not ready") -> Not ready
A39: TRT-0037 | B39: 48 | C39: Candidate treatment group | D39: 1 | E39: DATA - Innovation driven deals.xlsx | F39: polytherics acquires antitope | G39: No | H39: No | I39: No | J39: 1 | K39: Not started | L39: Eligible - 100% | M39: Review | O39: 41481 | P39: 41481 | Q39: 2013 | R39: Q3 2013 | S39: Completed | T39: PolyTherics acquires Antitope | U39: Mergers & Acquisitions | V39: Acquisition | W39: 100% Acquisition | X39: United Kingdom | Y39: 100% Acquisition | AB39: Abzena UK Ltd | AC39: abzena uk | AD39: Antitope Ltd | AE39: antitope | AG39: n/a | AH39: PolyTherics Limited, a provider of technologies and services for the development of biopharmaceutical products, has acquired Antitope Limited, a biotechnology company. Both the companies are based in the UK. _x000D_ As part of the consideration, PolyTherics is issuing new shares up to an aggregate value of GBP13.5 million to fund the transaction and to provide working capital for the enlarged group. Imperial Innovations led the investment with further funds provided by Invesco Perpetual, Mercia Fund Management and Advantage Enterprise & Innovation Fund. _x000D_ Pursuant to the transaction, Antitope will operate as a wholly-owned subsidiary of PolyTherics. | AI39: The transaction will allow PolyTherics to expand its drug development service offerings. | AL39: Unknown | AM39: Unknown | AS39: Abzena UK Ltd | AT39: Antitope Ltd | AU39: Not reviewed | AV39: Not assessed | AW39: Unknown | AX39: Unknown | AY39: Unknown | AZ39: Unknown | BA39: Unknown | BB39: Unknown | BF39: Not collected | BG39: Not collected | BH39: Not defined | BI39: =IF($Q39="","",$Q39-3) -> 2010 | BJ39: =IF($Q39="","",$Q39-2) -> 2011 | BK39: =IF($Q39="","",$Q39-1) -> 2012 | BL39: =IF($Q39="","",$Q39+0) -> 2013 | BM39: =IF($Q39="","",$Q39+1) -> 2014 | BN39: =IF($Q39="","",$Q39+2) -> 2015 | BO39: =IF($Q39="","",$Q39+3) -> 2016 | EQ39: =IF(OR($EO39="",$EP39="",$EO39=0),"",$EP39/$EO39) | ES39: Unknown | ET39: Unknown | EU39: =IF(COUNT($DF39,$DG39,$DH39)=0,"",AVERAGE($DF39,$DG39,$DH39)) | EV39: =IF(COUNT($DJ39,$DK39,$DL39)=0,"",AVERAGE($DJ39,$DK39,$DL39)) | EW39: =IF(OR($EU39="",$EV39=""),"",$EV39-$EU39) | EX39: =IF(COUNT($DM39,$DN39,$DO39)=0,"",AVERAGE($DM39,$DN39,$DO39)) | EY39: =IF(COUNT($DQ39,$DR39,$DS39)=0,"",AVERAGE($DQ39,$DR39,$DS39)) | EZ39: =IF(OR($EX39="",$EY39=""),"",$EY39-$EX39) | FA39: =IF(COUNT($EA39,$EB39,$EC39)=0,"",AVERAGE($EA39,$EB39,$EC39)) | FB39: =IF(COUNT($EE39,$EF39,$EG39)=0,"",AVERAGE($EE39,$EF39,$EG39)) | FC39: =IF(OR($FA39="",$FB39=""),"",$FB39-$FA39) | FD39: =IF(COUNT($EH39,$EI39,$EJ39)=0,"",AVERAGE($EH39,$EI39,$EJ39)) | FE39: =IF(COUNT($EL39,$EM39,$EN39)=0,"",AVERAGE($EL39,$EM39,$EN39)) | FF39: =IF(OR($FD39="",$FE39=""),"",$FE39-$FD39) | FG39: =IF(COUNT($DF39,$DG39,$DH39,$DJ39,$DK39,$DL39,$DM39,$DN39,$DO39,$DQ39,$DR39,$DS39)=12,"Yes","No") -> No | FH39: =IF(COUNT($EA39,$EB39,$EC39,$EE39,$EF39,$EG39,$EH39,$EI39,$EJ39,$EL39,$EM39,$EN39)=12,"Yes","No") -> No | FI39: =IF(AND($M39="Include",OR($FG39="Yes",$FH39="Yes")),"Ready","Not ready") -> Not ready
A40: TRT-0038 | B40: 49 | C40: Candidate treatment group | D40: 1 | E40: DATA - Innovation driven deals.xlsx | F40: glaxosmithkline acquires okairos | G40: Yes | H40: No | I40: No | J40: 1 | K40: Not started | L40: Review - majority | M40: Review | O40: 41423 | P40: 41423 | Q40: 2013 | R40: Q2 2013 | S40: Completed | T40: GlaxoSmithKline acquires Okairos | U40: Mergers & Acquisitions | V40: Acquisition | W40: Majority Acquisition | X40: Italy | Y40: Majority Acquisition | AB40: GSK plc. | AC40: gsk | AD40: ReiThera Srl | AE40: reithera | AF40: 325 | AG40: 325 | AH40: GlaxoSmithKline plc (GSK), a UK-based pharmaceutical, biologics, vaccines and consumer healthcare company, has acquired Okairos AG, a Switzerland-based developer of vaccine platform technologies, for $325 million in cash. _x000D_The transaction also includes a small number of early stage assets. _x000D_Under the terms of the transaction, GSK will take full ownership of Okairos and thus assume ownership of early stage assets for diseases such as respiratory syncytial virus (RSV), hepatitis C virus (HCV), malaria, tuberculosis, ebola and HIV, supplementing Okairos’ existing vaccines pipeline. _x000D_Earlier, Okairos had secured funding from BioMedPartners AG, Boehringer Ingelheim Venture Fund, Life Science Partners (LSP), Novartis Venture Funds and Versant Ventures, Inc. | AI40: Okairos’ novel vaccine platform technology will enhance GSK’s development of new prophylactic vaccines (designed to prevent infection) as well as new classes of therapeutic vaccines (designed to treat infection or disease). _x000D_ _x000D_ Okairos’ technology complements GSK’s existing vaccine technology and expertise and will enable GSK to continue its work developing the next generation of vaccines. | AL40: Unknown | AM40: Yes | AN40: GSK LN | AS40: GSK plc. | AT40: ReiThera Srl | AU40: Not reviewed | AV40: Not assessed | AW40: Lens.org acquirer-side patent export imported; target patent export not supplied. | AX40: Unknown | AY40: Unknown | AZ40: Unknown | BA40: Unknown | BB40: Unknown | BE40: EUR | BF40: Complete | BG40: Partial event window — 6/7 years covered; limited subsidiary scope | BH40: Export is concentrated on GSK Consumer Healthcare/Haleon and may not represent the full GSK pharmaceutical group. | BI40: 2010 | BJ40: 2011 | BK40: 2012 | BL40: 2013 | BM40: 2014 | BN40: 2015 | BO40: 2016 | BP40: 33112.481 | BQ40: 31564.125 | BR40: 32595.19 | BS40: 31221.028 | BT40: 28547.647 | BU40: 32954.971 | BV40: 34143.306 | BW40: 6050.5618 | BX40: 9666.2034 | BY40: 9646.2327 | BZ40: 8845.0745 | CA40: 7446.5109 | CB40: 7646.7434 | CC40: 9044.8114 | CD40: 1905.6704 | CE40: 6063.4191 | CF40: 5548.2487 | CG40: 6403.2261 | CH40: 3419.8607 | CI40: 11601.671 | CJ40: 1116.5225 | CK40: 49259.908 | CL40: 49159.701 | CM40: 51052.088 | CN40: 50561.801 | CO40: 52345.722 | CP40: 72471.32 | CQ40: 69152.834 | CR40: 17613.654 | CS40: 17831.76 | CT40: 22524.898 | CU40: 21919.405 | CV40: 24187.893 | CW40: 22552.539 | CX40: 21993.226 | CY40: 4623.0584 | CZ40: 4396.8721 | DA40: 4419.854 | DB40: 4119.2203 | DC40: 3952.1975 | DD40: 4321.3537 | DE40: 4295.9181 | DF40: 3.8405 | DG40: 12.6299 | DH40: 10.8986 | DI40: 13.0099 | DJ40: 6.6621 | DK40: 17.9007 | DL40: 1.6209 | DM40: 13.5355 | DN40: 28.5975 | DO40: 27.8499 | DP40: 26.6704 | DQ40: 15.5568 | DR40: 43.3432 | DS40: 9.5055 | DT40: 35.7566 | DU40: 36.2731 | DV40: 44.1214 | DW40: 43.3517 | DX40: 46.208 | DY40: 31.1193 | DZ40: 31.8038 | EB40: 1 | EC40: 0 | ED40: 7 | EE40: 1 | EF40: 2 | EG40: 6 | EI40: 0 | EJ40: 0 | EK40: 37 | EL40: 0 | EM40: 1 | EN40: 18 | EQ40: =IF(OR($EO40="",$EP40="",$EO40=0),"",$EP40/$EO40) | ES40: No | ET40: No | EU40: =IF(COUNT($DF40,$DG40,$DH40)=0,"",AVERAGE($DF40,$DG40,$DH40)) -> 9.123 | EV40: =IF(COUNT($DJ40,$DK40,$DL40)=0,"",AVERAGE($DJ40,$DK40,$DL40)) -> 8.7279 | EW40: =IF(OR($EU40="",$EV40=""),"",$EV40-$EU40) -> -0.3951 | EX40: =IF(COUNT($DM40,$DN40,$DO40)=0,"",AVERAGE($DM40,$DN40,$DO40)) -> 23.327633 | EY40: =IF(COUNT($DQ40,$DR40,$DS40)=0,"",AVERAGE($DQ40,$DR40,$DS40)) -> 22.801833 | EZ40: =IF(OR($EX40="",$EY40=""),"",$EY40-$EX40) -> -0.5258 | FA40: =IF(COUNT($EA40,$EB40,$EC40)=0,"",AVERAGE($EA40,$EB40,$EC40)) -> 0.5 | FB40: =IF(COUNT($EE40,$EF40,$EG40)=0,"",AVERAGE($EE40,$EF40,$EG40)) -> 3 | FC40: =IF(OR($FA40="",$FB40=""),"",$FB40-$FA40) -> 2.5 | FD40: =IF(COUNT($EH40,$EI40,$EJ40)=0,"",AVERAGE($EH40,$EI40,$EJ40)) -> 0 | FE40: =IF(COUNT($EL40,$EM40,$EN40)=0,"",AVERAGE($EL40,$EM40,$EN40)) -> 6.3333333 | FF40: =IF(OR($FD40="",$FE40=""),"",$FE40-$FD40) -> 6.3333333 | FG40: =IF(COUNT($DF40,$DG40,$DH40,$DJ40,$DK40,$DL40,$DM40,$DN40,$DO40,$DQ40,$DR40,$DS40)=12,"Yes","No") -> Yes | FH40: =IF(COUNT($EA40,$EB40,$EC40,$EE40,$EF40,$EG40,$EH40,$EI40,$EJ40,$EL40,$EM40,$EN40)=12,"Yes","No") -> No | FI40: =IF(AND($M40="Include",OR($FG40="Yes",$FH40="Yes")),"Ready","Not ready") -> Not ready
A41: TRT-0039 | B41: 50 | C41: Candidate treatment group | D41: 1 | E41: DATA - Innovation driven deals.xlsx | F41: eurofins scientific acquires aros applied biotechnology | G41: Yes | H41: No | I41: No | J41: 1 | K41: Not started | L41: Review - majority | M41: Review | O41: 41326 | P41: 41326 | Q41: 2013 | R41: Q1 2013 | S41: Completed | T41: Eurofins Scientific acquires AROS Applied Biotechnology | U41: Mergers & Acquisitions | V41: Acquisition | W41: Majority Acquisition | X41: Denmark | Y41: Majority Acquisition | AB41: Eurofins Scientific SE | AC41: eurofins scientific | AD41: AROS Applied Biotechnology AS | AE41: aros applied biotechnology | AG41: n/a | AH41: Eurofins Scientific S.A., a Belgium-based provider of food, environment and pharmaceutical product testing services, has acquired AROS Applied Biotechnology AS (AROS), a Denmark-based contract research organization providing service to the pharmaceutical industry and universities. _x000D_ AROS generated revenues of about EUR10 million. | AI41: The transaction will reinforce Eurofins' position as a testing provider to the pharmaceutical industry, and expands its genomic services footprint into the Nordic region. It also complements Eurofins' technological platform with additional capabilities in genotyping and expression profiling. The acquisition also allows Eurofin to further expand its share by leveraging its increased scale._x000D_ _x000D_ The acquisition will also provide AROS access to a broader portfolio of genomic services to further strengthen its position as a genomic service provider in markets. | AL41: Unknown | AM41: Yes | AN41: ERF FP | AS41: Eurofins Scientific SE | AT41: AROS Applied Biotechnology AS | AU41: Not reviewed | AV41: Not assessed | AW41: Lens.org acquirer-side patent export imported; target patent export not supplied. | AX41: Unknown | AY41: Unknown | AZ41: Unknown | BA41: Unknown | BB41: Unknown | BE41: EUR | BF41: Complete | BG41: Insufficient event-window coverage | BH41: Single family matched through owner field; event-window coverage is not established. | BI41: 2010 | BJ41: 2011 | BK41: 2012 | BL41: 2013 | BM41: 2014 | BN41: 2015 | BO41: 2016 | BP41: 680.333 | BQ41: 828.934 | BR41: 1043.963 | BS41: 1225.572 | BT41: 1410.227 | BU41: 1950.074 | BV41: 2536.608 | BW41: 61.971 | BX41: 91.366 | BY41: 124.738 | BZ41: 151.279 | CA41: 174.39 | CB41: 235.358 | CC41: 317.946 | CD41: 23.4 | CE41: 55.407 | CF41: 65.924 | CG41: 72.18 | CH41: 79.104 | CI41: 87.316 | CJ41: 173.997 | CK41: 736.161 | CL41: 1074.575 | CM41: 1159.096 | CN41: 1497.016 | CO41: 1873.19 | CP41: 3699.833 | CQ41: 4129.415 | CR41: 276.718 | CS41: 434.677 | CT41: 435.119 | CU41: 684.103 | CV41: 710.232 | CW41: 1710.033 | CX41: 1383.878 | DD41: 0 | DE41: 0 | DF41: 13.1527 | DG41: 13.426 | DH41: 5.9027493 | DI41: 5.4350118 | DJ41: 4.6943125 | DK41: 3.1335238 | DL41: 4.4447947 | DM41: 108.0344 | DN41: 108.3867 | DO41: 11.948508 | DP41: 12.343542 | DQ41: 12.366094 | DR41: 12.069183 | DS41: 12.534298 | DT41: 37.589332 | DU41: 40.451062 | DV41: 37.539514 | DW41: 45.697775 | DX41: 37.915641 | DY41: 46.219194 | DZ41: 33.512689 | EQ41: =IF(OR($EO41="",$EP41="",$EO41=0),"",$EP41/$EO41) | ES41: No | ET41: No | EU41: =IF(COUNT($DF41,$DG41,$DH41)=0,"",AVERAGE($DF41,$DG41,$DH41)) -> 10.82715 | EV41: =IF(COUNT($DJ41,$DK41,$DL41)=0,"",AVERAGE($DJ41,$DK41,$DL41)) -> 4.090877 | EW41: =IF(OR($EU41="",$EV41=""),"",$EV41-$EU41) -> -6.7362728 | EX41: =IF(COUNT($DM41,$DN41,$DO41)=0,"",AVERAGE($DM41,$DN41,$DO41)) -> 76.123203 | EY41: =IF(COUNT($DQ41,$DR41,$DS41)=0,"",AVERAGE($DQ41,$DR41,$DS41)) -> 12.323192 | EZ41: =IF(OR($EX41="",$EY41=""),"",$EY41-$EX41) -> -63.800011 | FA41: =IF(COUNT($EA41,$EB41,$EC41)=0,"",AVERAGE($EA41,$EB41,$EC41)) | FB41: =IF(COUNT($EE41,$EF41,$EG41)=0,"",AVERAGE($EE41,$EF41,$EG41)) | FC41: =IF(OR($FA41="",$FB41=""),"",$FB41-$FA41) | FD41: =IF(COUNT($EH41,$EI41,$EJ41)=0,"",AVERAGE($EH41,$EI41,$EJ41)) | FE41: =IF(COUNT($EL41,$EM41,$EN41)=0,"",AVERAGE($EL41,$EM41,$EN41)) | FF41: =IF(OR($FD41="",$FE41=""),"",$FE41-$FD41) | FG41: =IF(COUNT($DF41,$DG41,$DH41,$DJ41,$DK41,$DL41,$DM41,$DN41,$DO41,$DQ41,$DR41,$DS41)=12,"Yes","No") -> Yes | FH41: =IF(COUNT($EA41,$EB41,$EC41,$EE41,$EF41,$EG41,$EH41,$EI41,$EJ41,$EL41,$EM41,$EN41)=12,"Yes","No") -> No | FI41: =IF(AND($M41="Include",OR($FG41="Yes",$FH41="Yes")),"Ready","Not ready") -> Not ready
A42: TRT-0040 | B42: 51 | C42: Candidate treatment group | D42: 1 | E42: DATA - Innovation driven deals.xlsx | F42: alvogen acquires labormed pharma | G42: Yes | H42: No | I42: No | J42: 1 | K42: Not started | L42: Review - majority | M42: Review | O42: 41289 | P42: 41274 | Q42: 2012 | R42: Q1 2013 | S42: Completed | T42: Alvogen acquires LaborMed Pharma | U42: Mergers & Acquisitions | V42: Acquisition | W42: Majority Acquisition | X42: Romania | Y42: Majority Acquisition | AB42: Alvogen Inc | AC42: alvogen | AD42: LaborMed Pharma SA | AE42: labormed pharma | AG42: n/a | AH42: Alvogen, Inc., a US-based specialty generics company, has acquired LaborMed Pharma SA, a Romania-based company engaged in the manufacturing and sales of generic medicines. | AI42: According to Alvogen, the transaction creates a powerful platform from which to drive further revenue growth in the Romanian market, as well as in other Central and Eastern European markets. It also represents a significant milestone in Alvogen’s strategy to become one of the leading companies in the global generic pharmaceutical sector._x000D_ _x000D_ Through this acquisition, both Alvogen and Labormed will benefit from the increased scale, portfolio and geographic reach of the enlarged group._x000D_ _x000D_ The acquisition also brings Alvogen considerable product and marketing synergies and positions it to take advantage of further opportunities in the CEE pharmaceutical market. | AL42: Unknown | AM42: Unknown | AS42: Alvogen Inc | AT42: LaborMed Pharma SA | AU42: Not reviewed | AV42: Not assessed | AW42: Unknown | AX42: Unknown | AY42: Unknown | AZ42: Unknown | BA42: Unknown | BB42: Unknown | BF42: Not collected | BG42: Not collected | BH42: Not defined | BI42: =IF($Q42="","",$Q42-3) -> 2009 | BJ42: =IF($Q42="","",$Q42-2) -> 2010 | BK42: =IF($Q42="","",$Q42-1) -> 2011 | BL42: =IF($Q42="","",$Q42+0) -> 2012 | BM42: =IF($Q42="","",$Q42+1) -> 2013 | BN42: =IF($Q42="","",$Q42+2) -> 2014 | BO42: =IF($Q42="","",$Q42+3) -> 2015 | EQ42: =IF(OR($EO42="",$EP42="",$EO42=0),"",$EP42/$EO42) | ES42: Unknown | ET42: Unknown | EU42: =IF(COUNT($DF42,$DG42,$DH42)=0,"",AVERAGE($DF42,$DG42,$DH42)) | EV42: =IF(COUNT($DJ42,$DK42,$DL42)=0,"",AVERAGE($DJ42,$DK42,$DL42)) | EW42: =IF(OR($EU42="",$EV42=""),"",$EV42-$EU42) | EX42: =IF(COUNT($DM42,$DN42,$DO42)=0,"",AVERAGE($DM42,$DN42,$DO42)) | EY42: =IF(COUNT($DQ42,$DR42,$DS42)=0,"",AVERAGE($DQ42,$DR42,$DS42)) | EZ42: =IF(OR($EX42="",$EY42=""),"",$EY42-$EX42) | FA42: =IF(COUNT($EA42,$EB42,$EC42)=0,"",AVERAGE($EA42,$EB42,$EC42)) | FB42: =IF(COUNT($EE42,$EF42,$EG42)=0,"",AVERAGE($EE42,$EF42,$EG42)) | FC42: =IF(OR($FA42="",$FB42=""),"",$FB42-$FA42) | FD42: =IF(COUNT($EH42,$EI42,$EJ42)=0,"",AVERAGE($EH42,$EI42,$EJ42)) | FE42: =IF(COUNT($EL42,$EM42,$EN42)=0,"",AVERAGE($EL42,$EM42,$EN42)) | FF42: =IF(OR($FD42="",$FE42=""),"",$FE42-$FD42) | FG42: =IF(COUNT($DF42,$DG42,$DH42,$DJ42,$DK42,$DL42,$DM42,$DN42,$DO42,$DQ42,$DR42,$DS42)=12,"Yes","No") -> No | FH42: =IF(COUNT($EA42,$EB42,$EC42,$EE42,$EF42,$EG42,$EH42,$EI42,$EJ42,$EL42,$EM42,$EN42)=12,"Yes","No") -> No | FI42: =IF(AND($M42="Include",OR($FG42="Yes",$FH42="Yes")),"Ready","Not ready") -> Not ready
A43: TRT-0041 | B43: 52 | C43: Candidate treatment group | D43: 1 | E43: DATA - Innovation driven deals.xlsx | F43: enara acquires angels care services | G43: Yes | H43: No | I43: No | J43: 1 | K43: Not started | L43: Review - majority | M43: Review | O43: 41110 | P43: 41110 | Q43: 2012 | R43: Q3 2012 | S43: Completed | T43: Enara acquires Angels Care Services | U43: Mergers & Acquisitions | V43: Acquisition | W43: Majority Acquisition | X43: United Kingdom | Y43: Majority Acquisition | AB43: Enara Limited | AC43: enara | AD43: Angel Care Services UK Ltd | AE43: angel care services uk | AG43: n/a | AH43: Enara Limited, a provider of home care services, has acquired Angels Care Services Limited (Angels). Both the companies are based in the UK. _x000D_ Angels a provider of homecare services to the elderly and those suffering from conditions such as Alzheimers and other forms of dementia. _x000D_ Concurrently, Enara has also acquired Training and Care Solutions Essex Limited, Extracare Limited and Home Comforts (South) Limited. | AI43: The acquisition will allow Enara to enhance its service offering and geographical coverage. | AL43: Unknown | AM43: Unknown | AS43: Enara Limited | AT43: Angel Care Services UK Ltd | AU43: Not reviewed | AV43: Not assessed | AW43: Unknown | AX43: Unknown | AY43: Unknown | AZ43: Unknown | BA43: Unknown | BB43: Unknown | BF43: Not collected | BG43: Not collected | BH43: Not defined | BI43: =IF($Q43="","",$Q43-3) -> 2009 | BJ43: =IF($Q43="","",$Q43-2) -> 2010 | BK43: =IF($Q43="","",$Q43-1) -> 2011 | BL43: =IF($Q43="","",$Q43+0) -> 2012 | BM43: =IF($Q43="","",$Q43+1) -> 2013 | BN43: =IF($Q43="","",$Q43+2) -> 2014 | BO43: =IF($Q43="","",$Q43+3) -> 2015 | EQ43: =IF(OR($EO43="",$EP43="",$EO43=0),"",$EP43/$EO43) | ES43: Unknown | ET43: Unknown | EU43: =IF(COUNT($DF43,$DG43,$DH43)=0,"",AVERAGE($DF43,$DG43,$DH43)) | EV43: =IF(COUNT($DJ43,$DK43,$DL43)=0,"",AVERAGE($DJ43,$DK43,$DL43)) | EW43: =IF(OR($EU43="",$EV43=""),"",$EV43-$EU43) | EX43: =IF(COUNT($DM43,$DN43,$DO43)=0,"",AVERAGE($DM43,$DN43,$DO43)) | EY43: =IF(COUNT($DQ43,$DR43,$DS43)=0,"",AVERAGE($DQ43,$DR43,$DS43)) | EZ43: =IF(OR($EX43="",$EY43=""),"",$EY43-$EX43) | FA43: =IF(COUNT($EA43,$EB43,$EC43)=0,"",AVERAGE($EA43,$EB43,$EC43)) | FB43: =IF(COUNT($EE43,$EF43,$EG43)=0,"",AVERAGE($EE43,$EF43,$EG43)) | FC43: =IF(OR($FA43="",$FB43=""),"",$FB43-$FA43) | FD43: =IF(COUNT($EH43,$EI43,$EJ43)=0,"",AVERAGE($EH43,$EI43,$EJ43)) | FE43: =IF(COUNT($EL43,$EM43,$EN43)=0,"",AVERAGE($EL43,$EM43,$EN43)) | FF43: =IF(OR($FD43="",$FE43=""),"",$FE43-$FD43) | FG43: =IF(COUNT($DF43,$DG43,$DH43,$DJ43,$DK43,$DL43,$DM43,$DN43,$DO43,$DQ43,$DR43,$DS43)=12,"Yes","No") -> No | FH43: =IF(COUNT($EA43,$EB43,$EC43,$EE43,$EF43,$EG43,$EH43,$EI43,$EJ43,$EL43,$EM43,$EN43)=12,"Yes","No") -> No | FI43: =IF(AND($M43="Include",OR($FG43="Yes",$FH43="Yes")),"Ready","Not ready") -> Not ready
A44: TRT-0042 | B44: 53 | C44: Candidate treatment group | D44: 1 | E44: DATA - Innovation driven deals.xlsx | F44: agilent technologies acquires 100 stake in dako | G44: Yes | H44: No | I44: No | J44: 1 | K44: Not started | L44: Eligible - 100% | M44: Review | O44: 41046 | P44: 41081 | Q44: 2012 | R44: Q2 2012 | S44: Completed | T44: Agilent Technologies acquires 100% stake in Dako | U44: Mergers & Acquisitions | V44: Acquisition | W44: 100% Acquisition | X44: Denmark | Y44: 100% Acquisition | Z44: Credit Suisse Securities USA LLC , Goldman Sachs International | AA44: Accura Advokatpartnerselskab , Cleary Gottlieb Steen & Hamilton LLP , Davis Polk & Wardwell LLP , Kromann Reumert , Kromann Reumert | AB44: Agilent Technologies, Inc. | AC44: agilent technologies | AD44: Dako A/S | AE44: dako a s | AF44: 2200 | AG44: 2200 | AH44: Agilent Technologies Inc., a US-based measurement company engaged in providing bio-analytical and electronic measurement solutions, has acquired 100% stake in Dako A/S, a Denmark-based cancer diagnostic company, from EQT V Limited. _x000D_ EQT V is a UK-based equity fund managed by private equity fund manager EQT Funds Management Limited. _x000D_Announcement (May 17, 2012): _x000D_ Agilent has entered into a definitive agreement to acquire Dako from EQT V for a cash consideration of $2,200 million. _x000D_ _x000D_For the year ending 2010, Dako had generated annual revenue of approximately $340 million with approximately 1,000 employees. _x000D_Credit Suisse Securities (USA) LLC is acting as financial advisor, while Kromann Reumert and Cleary Gottlieb Steen & Hamilton, LLP are acting as legal advisors to Agilent. Goldman Sachs International is acting as financial advisor, while Davis Polk & Wardwell LLP and Accura Advokataktieselskab are acting as legal advisors to EQT V. _x000D_ The acquisition is expected to close within the next 60 days. | AI44: The transaction will strategically complement Agilent’s research technologies and will accelerate growth in diagnostic markets._x000D_ _x000D_ The acquisition will allow Agilent to strengthen its position in life sciences, with a focus on product development to help in the fight against cancer._x000D_ _x000D_ The addition of Dako and its portfolio will help Agilent accelerate its growth in several rapidly expanding areas of diagnostics, as well as strengthen its existing offerings. | AL44: Unknown | AM44: Unknown | AS44: Agilent Technologies, Inc. | AT44: Dako A/S | AU44: Not reviewed | AV44: Not assessed | AW44: Unknown | AX44: Unknown | AY44: Unknown | AZ44: Unknown | BA44: Unknown | BB44: Unknown | BF44: Not collected | BG44: Not collected | BH44: Not defined | BI44: =IF($Q44="","",$Q44-3) -> 2009 | BJ44: =IF($Q44="","",$Q44-2) -> 2010 | BK44: =IF($Q44="","",$Q44-1) -> 2011 | BL44: =IF($Q44="","",$Q44+0) -> 2012 | BM44: =IF($Q44="","",$Q44+1) -> 2013 | BN44: =IF($Q44="","",$Q44+2) -> 2014 | BO44: =IF($Q44="","",$Q44+3) -> 2015 | EQ44: =IF(OR($EO44="",$EP44="",$EO44=0),"",$EP44/$EO44) | ES44: Unknown | ET44: Unknown | EU44: =IF(COUNT($DF44,$DG44,$DH44)=0,"",AVERAGE($DF44,$DG44,$DH44)) | EV44: =IF(COUNT($DJ44,$DK44,$DL44)=0,"",AVERAGE($DJ44,$DK44,$DL44)) | EW44: =IF(OR($EU44="",$EV44=""),"",$EV44-$EU44) | EX44: =IF(COUNT($DM44,$DN44,$DO44)=0,"",AVERAGE($DM44,$DN44,$DO44)) | EY44: =IF(COUNT($DQ44,$DR44,$DS44)=0,"",AVERAGE($DQ44,$DR44,$DS44)) | EZ44: =IF(OR($EX44="",$EY44=""),"",$EY44-$EX44) | FA44: =IF(COUNT($EA44,$EB44,$EC44)=0,"",AVERAGE($EA44,$EB44,$EC44)) | FB44: =IF(COUNT($EE44,$EF44,$EG44)=0,"",AVERAGE($EE44,$EF44,$EG44)) | FC44: =IF(OR($FA44="",$FB44=""),"",$FB44-$FA44) | FD44: =IF(COUNT($EH44,$EI44,$EJ44)=0,"",AVERAGE($EH44,$EI44,$EJ44)) | FE44: =IF(COUNT($EL44,$EM44,$EN44)=0,"",AVERAGE($EL44,$EM44,$EN44)) | FF44: =IF(OR($FD44="",$FE44=""),"",$FE44-$FD44) | FG44: =IF(COUNT($DF44,$DG44,$DH44,$DJ44,$DK44,$DL44,$DM44,$DN44,$DO44,$DQ44,$DR44,$DS44)=12,"Yes","No") -> No | FH44: =IF(COUNT($EA44,$EB44,$EC44,$EE44,$EF44,$EG44,$EH44,$EI44,$EJ44,$EL44,$EM44,$EN44)=12,"Yes","No") -> No | FI44: =IF(AND($M44="Include",OR($FG44="Yes",$FH44="Yes")),"Ready","Not ready") -> Not ready
A45: TRT-0043 | B45: 253 | C45: User-designated treatment group (reclassified) | D45: 1 | E45: DATA non-innovation deals.xlsx | F45: midatech acquires q chip | G45: No | H45: No | I45: No | J45: 1 | K45: In progress | L45: Review - majority | M45: Review | O45: 41981 | P45: 41981 | Q45: 2014 | R45: Q4 2014 | S45: Completed | T45: Midatech acquires Q Chip | U45: Mergers & Acquisitions | V45: Acquisition | W45: Majority Acquisition | X45: United Kingdom | Y45: Majority Acquisition | Z45: Panmure Gordon (UK) Ltd , BDO LLP | AA45: Geldards LLP , Brown Rudnick LLP , Theobald Associates | AB45: Biodexa Ltd | AC45: biodexa ltd | AD45: Q Chip, Ltd. | AE45: q chip ltd | AG45: n/a | AH45: Midatech, Ltd., a clinical stage biotechnology company engaged in design, synthesis and manufacturing of nanomedicines, has acquired Q Chip, Ltd. (Q Chip), a bio-pharmaceutical company that develops sustained-release drug formulations for cancer and other diseases, and its subsidiaries. Both the companies are based in the UK. <br /><br />_x000D_Q Chip was backed by Finance Wales Investments, Ltd., Disruptive Capital Finance LLP (formerly Curzon Park Capital, Ltd.) and individual investors including an angel syndicate including both Simon Turton and Ken Powell. <br /><br />_x000D_ Panmure Gordon (UK) Limited and BDO LLP acted as financial advisors, while Brown Rudnick, LLP acted a legal advisor to Midatech. Theobald Associates and Geldards LLP acted as legal advisors to Q Chip. | AI45: The transaction will enable Midatech to add programs in cancer and ophthalmology based on the sustained release platform to its portfolio in cancer, diabetes and neuroscience. | AL45: Unknown | AM45: Yes | AN45: BDRX LN | AQ45: Biodexa Ltd | AR45: Q Chip, Ltd. | AS45: Biodexa Ltd | AT45: Q Chip, Ltd. | AU45: Not reviewed | AV45: Not assessed | AW45: Unknown | AX45: Unknown | AY45: Unknown | AZ45: Unknown | BA45: Unknown | BB45: Unknown | BC45: Moved into the treatment workbook at the user's instruction. Innovation classification and control-transfer eligibility still require manual validation. | BE45: EUR | BF45: Partial | BG45: Not collected | BH45: Not defined | BI45: 2011 | BJ45: 2012 | BK45: 2013 | BL45: 2014 | BM45: 2015 | BN45: 2016 | BO45: 2017 | BP45: 0 | BQ45: 0 | BR45: 0.1732 | BS45: 0.1948 | BT45: 1.8941 | BU45: 8.4755 | BV45: 8.6742 | BW45: -4.4787 | BX45: -4.9427 | BY45: -5.2995 | BZ45: -10.7497 | CA45: -14.5055 | CB45: -23.4347 | CC45: -18.369 | CD45: -4.7173 | CE45: -4.9255 | CF45: -4.8107 | CG45: -10.947 | CH45: -13.9118 | CI45: -24.6835 | CJ45: -18.3393 | CK45: 6.4058 | CL45: 2.7335 | CM45: 6.216 | CN45: 60.0873 | CO45: 86.8379 | CP45: 66.3531 | CQ45: 55.3739 | CR45: 5.8733 | CS45: 6.7075 | CT45: 4.0451 | CU45: 2.5483 | CV45: 2.6441 | CW45: 2.5259 | CX45: 7.3638 | CY45: 1.5582 | CZ45: 2.036 | DA45: 2.2675 | DB45: 6.7491 | DC45: 8.1551 | DD45: 8.1829 | DE45: 11.6276 | DF45: -73.641075 | DG45: -105.4661 | DH45: -110.453 | DI45: -34.0375 | DJ45: -18.245 | DK45: -33.4001 | DL45: -30.3343 | DO45: -3060.5442 | DP45: -6170.0637 | DQ45: -939.4909 | DR45: -441.3549 | DS45: -231.8636 | DT45: 91.6869 | DU45: 245.385 | DV45: 65.0754 | DW45: 4.241 | DX45: 3.0449 | DY45: 3.8067 | DZ45: 13.2984 | EQ45: =IF(OR($EO45="",$EP45="",$EO45=0),"",$EP45/$EO45) | ES45: Unknown | ET45: Unknown | EU45: =IF(COUNT($DF45,$DG45,$DH45)=0,"",AVERAGE($DF45,$DG45,$DH45)) -> -96.520058 | EV45: =IF(COUNT($DJ45,$DK45,$DL45)=0,"",AVERAGE($DJ45,$DK45,$DL45)) -> -27.326467 | EW45: =IF(OR($EU45="",$EV45=""),"",$EV45-$EU45) -> 69.193592 | EX45: =IF(COUNT($DM45,$DN45,$DO45)=0,"",AVERAGE($DM45,$DN45,$DO45)) -> -3060.5442 | EY45: =IF(COUNT($DQ45,$DR45,$DS45)=0,"",AVERAGE($DQ45,$DR45,$DS45)) -> -537.5698 | EZ45: =IF(OR($EX45="",$EY45=""),"",$EY45-$EX45) -> 2522.9744 | FA45: =IF(COUNT($EA45,$EB45,$EC45)=0,"",AVERAGE($EA45,$EB45,$EC45)) | FB45: =IF(COUNT($EE45,$EF45,$EG45)=0,"",AVERAGE($EE45,$EF45,$EG45)) | FC45: =IF(OR($FA45="",$FB45=""),"",$FB45-$FA45) | FD45: =IF(COUNT($EH45,$EI45,$EJ45)=0,"",AVERAGE($EH45,$EI45,$EJ45)) | FE45: =IF(COUNT($EL45,$EM45,$EN45)=0,"",AVERAGE($EL45,$EM45,$EN45)) | FF45: =IF(OR($FD45="",$FE45=""),"",$FE45-$FD45) | FG45: =IF(COUNT($DF45,$DG45,$DH45,$DJ45,$DK45,$DL45,$DM45,$DN45,$DO45,$DQ45,$DR45,$DS45)=12,"Yes","No") -> No | FH45: =IF(COUNT($EA45,$EB45,$EC45,$EE45,$EF45,$EG45,$EH45,$EI45,$EJ45,$EL45,$EM45,$EN45)=12,"Yes","No") -> No | FI45: =IF(AND($M45="Include",OR($FG45="Yes",$FH45="Yes")),"Ready","Not ready") -> Not ready
A46: TRT-0044 | B46: 39 | C46: User-designated treatment group (reclassified) | D46: 1 | E46: DATA non-innovation deals.xlsx | F46: esteve pharma acquires riemser pharma from ardian | G46: No | H46: No | I46: No | J46: 1 | K46: In progress | L46: Eligible - 100% | M46: Review | O46: 43838 | P46: 43868 | Q46: 2020 | R46: Q1 2020 | S46: Completed | T46: Esteve Pharma Acquires Riemser Pharma from Ardian | U46: Mergers & Acquisitions | V46: Acquisition | W46: 100% Acquisition | X46: Germany | Y46: 100% Acquisition | Z46: Rothschild & Co SCA , PricewaterhouseCoopers International Ltd , Ernst & Young Global Ltd | AA46: NOVACOS Rechtsanwalte , Hogan Lovells International LLP , Willkie Farr & Gallagher LLP | AB46: Esteve Pharmaceuticals SA | AC46: esteve pharmaceuticals sa | AD46: ESTEVE Pharmaceuticals GmbH | AE46: esteve pharmaceuticals gmbh | AG46: n/a | AH46: Esteve Pharmaceuticals SA, a pharmaceutical company, has acquired 100% of the shares in Riemser Pharma GmbH, a pharmaceutical company from Ardian, an investment company.<br /><br />The product portfolio of Riemser comprises the three main therapy areas oncology, neurology and niche therapies. Riemser operates a pharmaceutical production facility in Germany and is represented in four of the five most important European countries with a company headquarters or a subsidiary: Germany, Great Britain, France and Spain. RIEMSER generates around 80% of its sales with products for clinical use, especially specialty pharmaceuticals and a wide range of medicinal products for therapeutic niche areas.<br /><br />Through the acquisition, Esteve is also expanding its access to the hospital market.<br /><br />This acquisition will enable Esteve Pharma to accelerate its transformation into a specialty pharma company.<br /><br />Deal History: On January 8, 2020, Esteve Pharmaceuticals SA, has entered into an agreement to acquire 100% of the shares in Riemser Pharma GmbH, a pharmaceutical company from Ardian, an investment company. | AI46: This acquisition will enable Esteve Pharma to accelerate its transformation into a specialty pharma company. | AL46: Unknown | AM46: Yes | AN46: 0646926D SM | AQ46: Esteve Pharmaceuticals SA | AR46: ESTEVE Pharmaceuticals GmbH | AS46: Esteve Pharmaceuticals SA | AT46: ESTEVE Pharmaceuticals GmbH | AU46: Not reviewed | AV46: Not assessed | AW46: Lens.org acquirer-side patent export imported; target patent export not supplied. | AX46: Unknown | AY46: Unknown | AZ46: Unknown | BA46: Unknown | BB46: Unknown | BC46: Moved into the treatment workbook at the user's instruction. Innovation classification and control-transfer eligibility still require manual validation. | BE46: EUR | BF46: Partial | BG46: Partial event window — 5/7 years covered | BH46: Applicant/owner aliases for Esteve Pharmaceuticals and Laboratorios del Dr. Esteve. | BI46: 2017 | BJ46: 2018 | BK46: 2019 | BL46: 2020 | BM46: 2021 | BN46: 2022 | BO46: 2023 | BW46: 19.8088 | BX46: 12.6743 | BY46: 166.8558 | BZ46: -23.2304 | CA46: 46.584 | CK46: 458.8717 | CL46: 538.6484 | CM46: 890.9543 | CN46: 851.7258 | CO46: 779.869 | CR46: 0 | CS46: 17.1185 | CT46: 23.5852 | CU46: 30.0069 | CV46: 0.021 | DF46: 4.4884 | DG46: 3.2539 | DH46: 23.6081 | DI46: 7.5956 | DJ46: 5.2352 | DM46: 91.1781 | DN46: 76.1274 | DO46: 95.7042 | DP46: -357.3914 | DQ46: 85.7143 | DT46: 0 | DU46: 3.178 | DV46: 2.6472 | DW46: 3.5231 | DX46: 0.0027 | EA46: 8 | EB46: 5 | EC46: 3 | ED46: 1 | EE46: 1 | EH46: 0 | EI46: 0 | EJ46: 0 | EK46: 0 | EL46: 0 | EO46: 16 | EQ46: =IF(OR($EO46="",$EP46="",$EO46=0),"",$EP46/$EO46) | ES46: No | ET46: No | EU46: =IF(COUNT($DF46,$DG46,$DH46)=0,"",AVERAGE($DF46,$DG46,$DH46)) -> 10.450133 | EV46: =IF(COUNT($DJ46,$DK46,$DL46)=0,"",AVERAGE($DJ46,$DK46,$DL46)) -> 5.2352 | EW46: =IF(OR($EU46="",$EV46=""),"",$EV46-$EU46) -> -5.2149333 | EX46: =IF(COUNT($DM46,$DN46,$DO46)=0,"",AVERAGE($DM46,$DN46,$DO46)) -> 87.6699 | EY46: =IF(COUNT($DQ46,$DR46,$DS46)=0,"",AVERAGE($DQ46,$DR46,$DS46)) -> 85.7143 | EZ46: =IF(OR($EX46="",$EY46=""),"",$EY46-$EX46) -> -1.9556 | FA46: =IF(COUNT($EA46,$EB46,$EC46)=0,"",AVERAGE($EA46,$EB46,$EC46)) -> 5.3333333 | FB46: =IF(COUNT($EE46,$EF46,$EG46)=0,"",AVERAGE($EE46,$EF46,$EG46)) -> 1 | FC46: =IF(OR($FA46="",$FB46=""),"",$FB46-$FA46) -> -4.3333333 | FD46: =IF(COUNT($EH46,$EI46,$EJ46)=0,"",AVERAGE($EH46,$EI46,$EJ46)) -> 0 | FE46: =IF(COUNT($EL46,$EM46,$EN46)=0,"",AVERAGE($EL46,$EM46,$EN46)) -> 0 | FF46: =IF(OR($FD46="",$FE46=""),"",$FE46-$FD46) -> 0 | FG46: =IF(COUNT($DF46,$DG46,$DH46,$DJ46,$DK46,$DL46,$DM46,$DN46,$DO46,$DQ46,$DR46,$DS46)=12,"Yes","No") -> No | FH46: =IF(COUNT($EA46,$EB46,$EC46,$EE46,$EF46,$EG46,$EH46,$EI46,$EJ46,$EL46,$EM46,$EN46)=12,"Yes","No") -> No | FI46: =IF(AND($M46="Include",OR($FG46="Yes",$FH46="Yes")),"Ready","Not ready") -> Not ready
A47: TRT-0045 | B47: 299 | C47: User-designated treatment group (reclassified) | D47: 1 | E47: DATA non-innovation deals.xlsx | F47: shire acquires premacure | G47: No | H47: No | I47: No | J47: 1 | K47: In progress | L47: Review - majority | M47: Review | O47: 41345 | P47: 41345 | Q47: 2013 | R47: Q1 2013 | S47: Completed | T47: Shire acquires Premacure | U47: Mergers & Acquisitions | V47: Acquisition | W47: Majority Acquisition | X47: Sweden | Y47: Majority Acquisition | Z47: Bank of America Corp | AA47: Mannheimer Swartling Advokatbyra AB , Mannheimer Swartling Advokatbyra AB | AB47: Shire plc (Inactive) | AC47: shire plc inactive | AD47: Premacure AB | AE47: premacure ab | AG47: n/a | AH47: Shire plc, a UK-based biopharmaceutical company, has acquired Premacure AB, a Sweden-based biotechnology company developing a protein replacement therapy.<br /><br />_x000D_Bank of America Merrill Lynch acted as financial advisor and Mannheimer Swartling Advokatbyra AB acted as legal advisor to Shire. | AI47: The acquisition expands Shire’s therapies to patients with rare disorders._x000D_ _x000D_ The acquisition allows Shire HGT to enter a new therapeutic area, neonatology, maintaining its focus on developing novel therapies for the treatment of diseases with high unmet medical need. _x000D_ _x000D_ With the acquisition, Shire HGT will continue the ongoing Phase II study, the primary goal of which is to restore the IGF-1 levels in the preterm infant to those found during normal in utero development. | AL47: Unknown | AM47: Yes | AN47: SHP LN | AQ47: Shire plc (Inactive) | AR47: Premacure AB | AS47: Shire plc (Inactive) | AT47: Premacure AB | AU47: Not reviewed | AV47: Not assessed | AW47: Lens.org acquirer-side patent export imported; target patent export not supplied. | AX47: Unknown | AY47: Unknown | AZ47: Unknown | BA47: Unknown | BB47: Unknown | BC47: Moved into the treatment workbook at the user's instruction. Innovation classification and control-transfer eligibility still require manual validation. | BE47: USD | BF47: Complete | BG47: Partial event window — 6/7 years covered | BH47: Applicant/owner aliases containing Shire; later Takeda-only records excluded unless Shire appears. | BI47: 2010 | BJ47: 2011 | BK47: 2012 | BL47: 2013 | BM47: 2014 | BN47: 2015 | BO47: 2016 | BP47: 3471.1 | BQ47: 4263.4 | BR47: 4681.2 | BS47: 4934.3 | BT47: 6022.1 | BU47: 6416.7 | BV47: 11396.6 | BW47: 794.1 | BX47: 1109.2 | BY47: 949.2 | BZ47: 1733.5 | CA47: 1698 | CB47: 1419.5 | CC47: 962.9 | CD47: 588 | CE47: 865 | CF47: 745.4 | CG47: 665.1 | CH47: 3405.5 | CI47: 1303.4 | CJ47: 327.4 | CK47: 5387.6 | CL47: 6380.2 | CM47: 7317.2 | CN47: 8323 | CO47: 13632.1 | CP47: 16609.8 | CQ47: 67035.4 | CR47: 1107.9 | CS47: 1100 | CT47: 1100 | CU47: 0 | CV47: 850 | CW47: 1581.4 | CX47: 22967.8 | CY47: 661.5 | CZ47: 754.7 | DA47: 894.3 | DB47: 913.5 | DC47: 762.7 | DD47: 905.8 | DE47: 1430.9 | DF47: 11.75 | DG47: 14.7 | DH47: 10.88 | DI47: 8.51 | DJ47: 31.02 | DK47: 8.62 | DL47: 0.78 | DM47: 22.88 | DN47: 26.02 | DO47: 20.28 | DP47: 35.13 | DQ47: 28.2 | DR47: 22.12 | DS47: 8.45 | DT47: 20.5639 | DU47: 17.2408 | DV47: 15.0331 | DW47: 0 | DX47: 6.2353 | DY47: 9.5209 | DZ47: 34.2622 | EB47: 15 | EC47: 13 | ED47: 23 | EE47: 18 | EF47: 8 | EG47: 6 | EI47: 159 | EJ47: 241 | EK47: 416 | EL47: 245 | EM47: 20 | EN47: 22 | EQ47: =IF(OR($EO47="",$EP47="",$EO47=0),"",$EP47/$EO47) | ES47: No | ET47: No | EU47: =IF(COUNT($DF47,$DG47,$DH47)=0,"",AVERAGE($DF47,$DG47,$DH47)) -> 12.443333 | EV47: =IF(COUNT($DJ47,$DK47,$DL47)=0,"",AVERAGE($DJ47,$DK47,$DL47)) -> 13.473333 | EW47: =IF(OR($EU47="",$EV47=""),"",$EV47-$EU47) -> 1.03 | EX47: =IF(COUNT($DM47,$DN47,$DO47)=0,"",AVERAGE($DM47,$DN47,$DO47)) -> 23.06 | EY47: =IF(COUNT($DQ47,$DR47,$DS47)=0,"",AVERAGE($DQ47,$DR47,$DS47)) -> 19.59 | EZ47: =IF(OR($EX47="",$EY47=""),"",$EY47-$EX47) -> -3.47 | FA47: =IF(COUNT($EA47,$EB47,$EC47)=0,"",AVERAGE($EA47,$EB47,$EC47)) -> 14 | FB47: =IF(COUNT($EE47,$EF47,$EG47)=0,"",AVERAGE($EE47,$EF47,$EG47)) -> 10.666667 | FC47: =IF(OR($FA47="",$FB47=""),"",$FB47-$FA47) -> -3.3333333 | FD47: =IF(COUNT($EH47,$EI47,$EJ47)=0,"",AVERAGE($EH47,$EI47,$EJ47)) -> 200 | FE47: =IF(COUNT($EL47,$EM47,$EN47)=0,"",AVERAGE($EL47,$EM47,$EN47)) -> 95.666667 | FF47: =IF(OR($FD47="",$FE47=""),"",$FE47-$FD47) -> -104.33333 | FG47: =IF(COUNT($DF47,$DG47,$DH47,$DJ47,$DK47,$DL47,$DM47,$DN47,$DO47,$DQ47,$DR47,$DS47)=12,"Yes","No") -> Yes | FH47: =IF(COUNT($EA47,$EB47,$EC47,$EE47,$EF47,$EG47,$EH47,$EI47,$EJ47,$EL47,$EM47,$EN47)=12,"Yes","No") -> No | FI47: =IF(AND($M47="Include",OR($FG47="Yes",$FH47="Yes")),"Ready","Not ready") -> Not ready

Sheet Panel_DiD
